Workbook

Sheet 01 Preliminaries
A1: Item Code | B1: Item Name | C1: Item Details | D1: Additional Information | E1: UOM | F1: Quantity | G1: Unit Price | H1: Total Price In Figure
A2: P1 | B2: Preliminary and General Requirements Tender Drawings | C2: Notes | D2: All items will be priced individually. Any item not priced hereunder will be deemed to be included in the Contractors Tender. | E2: Item | F2: 0 | G2: 0 | H2: =F2*G2 -> 0
A3: P2 | B3: Preliminary and General Requirements Tender Drawings | C3: Tender Drawings | D3: The Tender Drawings are listed in Volume 4 Tender Drawings. | E3: Item | F3: 1 | G3: 0 | H3: =F3*G3 -> 0
A4: P3 | B4: Preliminary and General Requirements Conditions of Contract | C4: Conditions of Contract | D4: The Conditions of Contract shall be those contained within the Sultanate of Oman Standard Documents for Building and Civil Engineering Works prepared and issued by the Ministry of Finance Muscat. | E4: Item | F4: 1 | G4: 0 | H4: =F4*G4 -> 0
A5: P4 | B5: Preliminary and General Requirements Conditions of Contract | C5: Conditions of Contract | D5: The Contractor shall allow for complying in all respect with the Conditions of Contract. | E5: Item | F5: 1 | G5: 0 | H5: =F5*G5 -> 0
A6: P5 | B6: Preliminary and General Requirements Contractors Administration Arrangements | C6: Drawings | D6: The Contractor shall be responsible for checking all drawings and schedule etc. supplied by the Engineer. In the event of any discrepancy being found between such drawings and schedules etc. or if the Contractor considers that additional detail drawings are required then in either case the Contractor shall report such discrepancy to the Engineer for instruction or apply in writing for such detail drawings at least 28 days before the materials and components necessary for the works are to be placed on order by the Contractor. | E6: Item | F6: 1 | G6: 0 | H6: =F6*G6 -> 0
A7: P6 | B7: Preliminary and General Requirements Contractors Administration Arrangements | C7: Drawings | D7: The Contractor shall ascertain from the drawings or otherwise any holes recesses plugs etc. which may be required in time to form these as the work proceeds. No extra payments will be allowed for cuttings or forming such holes subsequently. | E7: Item | F7: 1 | G7: 0 | H7: =F7*G7 -> 0
A8: P7 | B8: Preliminary and General Requirements Contractors Administration Arrangements | C8: Drawings | D8: The Contractor will prepare at his own cost detailed working and shop drawings that may require supplementary to the construction drawings furnished by the Engineer. | E8: Item | F8: 1 | G8: 0 | H8: =F8*G8 -> 0
A9: P8 | B9: Preliminary and General Requirements Contractors Administration Arrangements | C9: Drawings | D9: The detail and working drawing for civil and building works shall be prepared by the contractor supplement the construction drawings furnished by the Engineer will include Reinforcement details and Other drawings. | E9: Item | F9: 1 | G9: 10500 | H9: =F9*G9 -> 10500
A10: P9 | B10: Preliminary and General Requirements Contractors Administration Arrangements | C10: Drawings | D10: The detail and working drawing for civil and building works shall be prepared by the contractor supplement the construction drawings furnished by the Engineer will include the Drawings and details of foundation for equipment machinery and technical installation. | E10: Item | F10: 1 | G10: 10500 | H10: =F10*G10 -> 10500
A11: P10 | B11: Preliminary and General Requirements Contractors Administration Arrangements | C11: Drawings | D11: Such drawing and detail will depend on the type and make of the equipment offered and will include in particular foundations etc. for the standby power generators chiller and radiators transformers ventilation and airconditioning equipment etc. Construction details as required. | E11: Item | F11: 1 | G11: 0 | H11: =F11*G11 -> 0
A12: P11 | B12: Preliminary and General Requirements Contractors Administration Arrangements | C12: Drawings | D12: No drawing etc. prepared by the Contractor shall be used in the works before the Engineer has approved it. | E12: Item | F12: 1 | G12: 0 | H12: =F12*G12 -> 0
A13: P12 | B13: Preliminary and General Requirements Contractors Administration Arrangements | C13: Drawings | D13: The Contractor shall submit to the Engineer for his approval two copies of all his detail working or shop drawings and related documents produced by him for use in construction work. Any changes or modifications considered necessary by the Engineer shall be made at no extra cost to the Employer. | E13: Item | F13: 1 | G13: 0 | H13: =F13*G13 -> 0
... A50: P49 | B50: Preliminary and General Requirements Contractors Administration Arrangements | C50: Site Transportation | D50: Provide all necessary vehicles and other site transport etc. with all consumables store etc. as described for small plant and tools etc. | E50: Item | F50: 1 | G50: 0 | H50: =F50*G50 -> 0
A51: P50 | B51: Preliminary and General Requirements Employer Facilities | C51: Temporary Office | D51: Provide erect furnish equip maintain and remove three month after completion of the Contract fully serviced furnished and equipped airconditioned offices and a conference room for the exclusive use of the Engineer all as described in General Requirement of the Architectural Specification. | E51: Item | F51: 1 | G51: 0 | H51: =F51*G51 -> 0 | I51: =SUM(H2:H51) -> 24150
A52: P51 | B52: Preliminary and General Requirements Employer Facilities | C52: Temporary Office | D52: The offices shall be provided and maintained throughout the period of the Contract. | E52: Item | F52: 1 | G52: 0 | H52: =F52*G52 -> 0
A53: P52 | B53: Preliminary and General Requirements Employer Facilities | C53: Temporary Office | D53: The Contractor shall be responsible for providing security power water drainage safety helmets safety boots daily cleaning car parking and other facilities to the Engineers offices. | E53: Item | F53: 1 | G53: 0 | H53: =F53*G53 -> 0
A54: P53 | B54: Preliminary and General Requirements Employer Facilities | C54: Temporary Office | D54: The Contractor shall be responsible during the continuance of the Contract for satisfactorily maintain and security of the offices and for all plans documents and paper and other articles contained there in. | E54: Item | F54: 1 | G54: 0 | H54: =F54*G54 -> 0
A55: P54 | B55: Preliminary and General Requirements Employer Facilities | C55: Telephone for the Engineer and Employer | D55: Allow for providing the Engineers site office with an independent telephone service until removal of office and for paying all charges incurred by the Engineers staff for business calls concerning the project within the Sultanate of Oman. | E55: Item | F55: 1 | G55: 1050 | H55: =F55*G55 -> 1050
A56: P55 | B56: Preliminary and General Requirements Employer Facilities | C56: Attendance on the Engineer | D56: Provide attendance and assistance to the Engineer all as described in the Specification. | E56: Item | F56: 1 | G56: 0 | H56: =F56*G56 -> 0
A57: P56 | B57: Preliminary and General Requirements Employer Facilities | C57: Surveying and other equipment | D57: The Contractor shall provide to the Engineer for his exclusive use all survey equipment and electrical test equipment as described in the Specification. | E57: Item | F57: 1 | G57: 1575 | H57: =F57*G57 -> 1575
A58: P57 | B58: Preliminary and General Requirements Employer Facilities | C58: Mobilisation | D58: The Engineer may issue the notice to proceed at any time within the period of validity of the tender. After the date of the notice to proceed the Contractor shall have a period of 120 days to complete mobilisation and to be completely prepared for the work. After the mobilisation is complete the work shall be carried out in accordance with the requirements of this Contract. | E58: Item | F58: 1 | G58: 0 | H58: =F58*G58 -> 0
A59: P58 | B59: Preliminary and General Requirements Employer Facilities | C59: Programme and Order of Works | D59: Within 14 days of receipt of an order to commence the Works the Contractor shall submit to the Engineer a detailed programme in respect of all works contained in the scope of works including temporary works and services. | E59: Item | F59: 1 | G59: 0 | H59: =F59*G59 -> 0
A60: P59 | B60: Preliminary and General Requirements Employer Facilities | C60: Programme and Order of Works | D60: Within 21 days of receipt of an order to commence the Works the Contractor shall submit to the Engineer a detailed programme in respect of all trades separately for each building section and external works and services together with the target dates for receipt of information required to enable the Contractor to comply with this programme. | E60: Item | F60: 1 | G60: 0 | H60: =F60*G60 -> 0
A61: P60 | B61: Preliminary and General Requirements Employer Facilities | C61: Programme and Order of Works | D61: In addition the Contractor shall at the same time submit to the Engineer a detailed schedule of items and information that he requires instruction upon for early ordering schedules. | E61: Item | F61: 1 | G61: 0 | H61: =F61*G61 -> 0
A62: P61 | B62: Preliminary and General Requirements Employer Facilities | C62: Coordination | D62: The Contractors attention is drawn to the fact that he shall be entirely responsible for the coordination of all works carried out by both his own workmen and the workmen of SubContractors and shall be responsible for ensuring that all SubContractors shop andor working drawings are submitted to the Engineer for approval in such time as not to prejudice the expeditious execution of the Works in accordance with the Contractors programme. | E62: Item | F62: 1 | G62: 0 | H62: =F62*G62 -> 0
A63: P62 | B63: Preliminary and General Requirements Employer Facilities | C63: Reports | D63: Provide and maintain daily reports and delivery records for inspection by the Engineer. Such reports must give details of number and category of labour force list of plant list of material deliveries work planned and work carried out climatic conditions high and low temperature and any other information required by the Engineer. | E63: Item | F63: 1 | G63: 0 | H63: =F63*G63 -> 0
... A100: P99 | B100: Preliminary and General Requirements | C100: Sundry ItemsSite Survey and Grid of Levels | D100: Before commencing excavation or site levelling operations the Contractor shall conduct a coordinated site survey witnessed by the Engineer related to a bench mark referred to in the Contract document and shall prepare a site plan showing a grid of levels at 5 m centres to the proposed site the Contractor shall provide the Engineer with one transparency and two copies of the site survey plan. | E100: Item | F100: 1 | G100: 0 | H100: =F100*G100 -> 0
A101: P100 | B101: Preliminary and General Requirements | C101: Sundry ItemsSite Survey and Grid of Levels | D101: The Contractor shall conduct similar site survey after site levelling operations and external works have been completed and provide drawings as above. | E101: Item | F101: 1 | G101: 0 | H101: =F101*G101 -> 0 | I101: =SUM(H52:H101) -> 44730
A102: P101 | B102: Preliminary and General Requirements | C102: Sundry ItemsCopies of Orders | D102: Provide the Engineers Representative with a copy of all orders for the supply of such materials or goods required in connection with the Works as the Engineers Representative may specify. | E102: Item | F102: 1 | G102: 0 | H102: =F102*G102 -> 0
A103: P102 | B103: Preliminary and General Requirements | C103: Sundry ItemsWorking Drawings | D103: Allow for preparing and submission to the Engineer of all working drawings and operation and maintenance instructions as detailed in the specification if these costs are not specifically measured elsewhere in the relevant sections of this document. | E103: Item | F103: 1 | G103: 0 | H103: =F103*G103 -> 0
A104: P103 | B104: Preliminary and General Requirements | C104: Sundry ItemsWorking Drawings | D104: Upon completion of the works submit two sets of diskettes Autocad R12 later two transparencies and four copies of all drawings duly marked AsBuilt clearly defining all locations depths shapes and dimensions of all permanent works executed. | E104: Item | F104: 1 | G104: 0 | H104: =F104*G104 -> 0
A105: P104 | B105: Preliminary and General Requirements | C105: Sundry ItemsTraining of Employers Personnel | D105: During the execution of the Works the Contractor shall provide such assistance as may be necessary for the instruction and training of personnel appointed by the Employer. | E105: Item | F105: 1 | G105: 0 | H105: =F105*G105 -> 0
A106: P105 | B106: Preliminary and General Requirements | C106: Sundry ItemsTraining of Employers Personnel | D106: The Contractor shall provide all necessary instruction material for this purpose such as manuals booklets pamphlets drawings sketches models pictures photoscolour slides films etc. This instruction material shall become the property of the Employer. | E106: Item | F106: 1 | G106: 0 | H106: =F106*G106 -> 0
A107: P106 | B107: Preliminary and General Requirements | C107: Sundry ItemsDirect Contractors | D107: The Tenderers attention is drawn to the fact that the Employer may appoint other Contractors to carry out certain items of Specialist Works in accordance with Clause 31 of the Conditions of Contract. | E107: Item | F107: 1 | G107: 0 | H107: =F107*G107 -> 0
A108: P107 | B108: Preliminary and General Requirements Performance Bond Advance Payment Bond and Insurance Certificate | C108: Performance Bond | D108: The Contractor will be required to provide Performance Bond all in accordance with Clause 4.2 of the Conditions of Contract. | E108: Item | F108: 1 | G108: 0 | H108: =F108*G108 -> 0
A109: P108 | B109: Preliminary and General Requirements Performance Bond Advance Payment Bond and Insurance Certificate | C109: Insurance | D109: The Contractor will be required to provide all Insurances in accordance with the Conditions of Contract. | E109: Item | F109: 1 | G109: 0 | H109: =F109*G109 -> 0
A110: P109 | B110: Preliminary and General Requirements Performance Bond Advance Payment Bond and Insurance Certificate | C110: Insurance Declaration | D110: On signing the Contract the Contractor shall obtain from his Insurance Company and lodge with the Engineer a declaration that the insurance provided is strictly in accordance with all relevant Clause in the Conditions of Contract. This shall also include insurance against damage of any kind to existing buildings which may arise as a result of the building operations. | E110: Item | F110: 1 | G110: 0 | H110: =F110*G110 -> 0
A111: P110 | B111: Preliminary and General Requirements Performance Bond Advance Payment Bond and Insurance Certificate | C111: Advance Payment Bond | D111: The Contractor will be required to provide an Advance Payment Bond all in accordance with Clause 14.2 of Conditions of Contract. | E111: Item | F111: 1 | G111: 0 | H111: =F111*G111 -> 0
A112: P111 | B112: Preliminary and General Requirements Temporary Facilities. | C112: Refer Provisional SumTemporary Houses | D112: The Contractor will be required to provide temporary houses Caravan for the resident while working in the Construction and also during Maintenance Works and refix inside houses after work finish as outside extra rooms for them. Every caravan will be around 65m2 and will include and not be limited to 2 rooms a hall a kitchen and two toilets The structure to use steel structure painted with anticorrosion paint with isolated walls and roof aluminum sandwich panels 50 mm thickness from 2 sheets 0.7 mm thickness and foam of 45 kgm3 density internal ceramic floor and walls for toiles and kitchen to be ceramic all sanitary fixture for toilet and kitchen sink and cabinet sewage electrical and water connection to be done in the temporary place and will be finally done again after move to internal new and maintained houses foundation for caravan and 3 steps omani marble in final place fixing also 4 AC are included design of caravan to be done by the contractor approved by clientconsultant beforedelivery the caravans will be under project defects notification period for one year. | E112: item | F112: 1 | G112: 124800 | H112: =F112*G112 -> 124800
A113: P112 | B113: Preliminary and General Requirements CCTV Control. | C113: CCTV | D113: The Contractor will be required to provide CCTV to monitor and maintain the work activity at site while working in the Construction Works also during Maintenance Works. | E113: Item | F113: 1 | G113: 0 | H113: =F113*G113 -> 0
A114: P113 | B114: Preliminary and General Requirements Temporary Facilities. | C114: External Temporary Building | D114: The Contractor should follow maintenance works for the External Building for the Existing 32 Housing while working in the Construction Works also during Maintenance Works. | E114: Item | F114: 1 | G114: 0 | H114: =F114*G114 -> 0
A115: P114 | B115: Preliminary and General Requirements EngineerEmployer Facilities | C115: Facilities for Engineers Employers | D115: The Contractor shall provide erect maintain and remove on completion all necessary Engineers accommodation Employers accommodation common kitchen with dining hall including food for all time to the EngineersEmployers sanitary accommodation and other facilities all by the Contractor expenses and link together with all associated water drainage electrical lighting and power airconditioning telephone mobile phones 4nos with recharge cards 30rial new furniture washing equipment and maintenance the same until the Completion of Project as per details in prim documents. | E115: Item | F115: 1 | G115: 25200 | H115: =F115*G115 -> 25200
A116: P115 | B116: Preliminary and General Requirements Contractors Administration Arrangements | C116: Site Transportation for Engineers Employers | D116: Provide necessary 4x4 vehicles 2nos in excellent condition for consultantclient staff transportation and pickup vehicle 2nos for site transport etc. with all consumables fuel etc. as described for small plant and tools for regular maintenance etc as per details in prim documents. | E116: Item | F116: 1 | G116: 8700 | H116: =F116*G116 -> 8700 | I116: =SUM(H102:H116) -> 158700
A117: TOTAL PRELIMINARIES | G117: =SUM(H2:H116) -> 227580

Sheet 02 Dayworks
A1: Item Code | B1: Item Name | C1: Item Details | D1: Additional Information | E1: UOM | F1: Quantity | G1: Unit Price | H1: Total Price In Figure
A2: D1 | B2: Daywork Schedule | C2: Day Work | D2: The Contractor may be required to execute certain works on the basis of day works. | E2: Item | F2: 1 | G2: 0 | H2: =F2*G2 -> 0
A3: D2 | B3: Daywork Schedule | C3: Day Work | D3: The Contractor shall keep an accurate record of time spent and materials and plant and used on each separate instruction given. Day work sheets are to be numbered and are to describe fully the instructions to which they refer and they are to be fully summarized fully priced and submitted to the Engineer for signature. The submission of such day work sheets does not necessarily mean that the work will be valued under Clause 13.5 of the Conditions of Contract or that any payment is in fact due. | E3: Item | F3: 1 | G3: 0 | H3: =F3*G3 -> 0
A4: D3 | B4: Daywork Schedule | C4: Labour 1. The Tenderer shall give the rates herein required for labourers and craftsmen against each item stated. 2.The rates are to be comprehensive and include | D4: Wages and all costs payments and charges including pensions annual and public holidays traveling time expenses fares and transport guaranteed time nonproductive time and other expenses in connection with overtime incentive and bonus payments dirty money and danger money and other disbursements arising from employment of labour including redundancy payment reduced working hours during Ramadhan all associated costs if labourers imported form other countries and workmens compensation insurance gratuity and all terminal benefits as per Oman labour Laws. | E4: Item | F4: 1 | G4: 0 | H4: =F4*G4 -> 0
A5: D4 | B5: Daywork Schedule | C5: Labour 1. The Tenderer shall give the rates herein required for labourers and craftsmen against each item stated. 2.The rates are to be comprehensive and include | D5: Charges incurred in respect of site and office supervision including foreman�s time and extra emoluments paid to foreman and leading craftsmen and gangers. | E5: Item | F5: 1 | G5: 0 | H5: =F5*G5 -> 0
A6: D5 | B6: Daywork Schedule | C6: Labour 1. The Tenderer shall give the rates herein required for labourers and craftsmen against each item stated. 2.The rates are to be comprehensive and include | D6: Site and Head Office overhead charges such as rent rates insurances electricity fuel water printing stationery postage telephone charges motor car expenses renewals maintenance and depreciation of premises machinery plant and the like. | E6: Item | F6: 1 | G6: 0 | H6: =F6*G6 -> 0
A7: D6 | B7: Daywork Schedule | C7: Labour 1. The Tenderer shall give the rates herein required for labourers and craftsmen against each item stated. 2.The rates are to be comprehensive and include | D7: Profit | E7: Item | F7: 1 | G7: 0 | H7: =F7*G7 -> 0
A8: D7 | B8: Daywork Schedule | C8: Materials | D8: Materials used in day works to be charged at invoice cost. All discounts are to be allowed to the Ministry of Health. Invoices are to be made available to the Engineer at the time the relevant day work sheets are submitted. | E8: Item | F8: 1 | G8: 0 | H8: =F8*G8 -> 0
A9: D8 | B9: Daywork Schedule | C9: Materials | D9: The Contractor is to allow for additional percentage he requires to be added to the invoice cost of materials to cover for ordering taking delivery paying all insurances in transit landing charges dues custom duties Municipality tax and all other charges loading and transporting to the site taking into store storing as may be required and all other charges and profit. | E9: Item | F9: 1 | G9: 0 | H9: =F9*G9 -> 0
A10: D9 | B10: Daywork Schedule | C10: Plant 1. The Contractor shall give here the rates he requires for plant and machinery 2. The rates are to be comprehensive and include | D10: Mobilization and demobilization costs | E10: Item | F10: 1 | G10: 0 | H10: =F10*G10 -> 0
A11: D10 | B11: Daywork Schedule | C11: Plant 1. The Contractor shall give here the rates he requires for plant and machinery 2. The rates are to be comprehensive and include | D11: Fuel oil lubricants and all other consumable stores. | E11: Item | F11: 1 | G11: 0 | H11: =F11*G11 -> 0
A12: D11 | B12: Daywork Schedule | C12: Plant 1. The Contractor shall give here the rates he requires for plant and machinery 2. The rates are to be comprehensive and include | D12: Servicing repairs and replacements. | E12: Item | F12: 1 | G12: 0 | H12: =F12*G12 -> 0
A13: D12 | B13: Daywork Schedule | C13: Plant 1. The Contractor shall give here the rates he requires for plant and machinery 2. The rates are to be comprehensive and include | D13: Site and Head Office overhead charges as previously defined. | E13: Item | F13: 1 | G13: 0 | H13: =F13*G13 -> 0
... A50: D49 | B50: Daywork Schedule | C50: Plant | D50: Roller 4 tonne | E50: Hr | F50: 25 | G50: 42 | H50: =F50*G50 -> 1050
A51: D50 | B51: Daywork Schedule | C51: Plant | D51: Welding set 300 A including electrodes | E51: Hr | F51: 25 | G51: 31.5 | H51: =F51*G51 -> 787.5 | I51: =SUM(H2:H51) -> 24675
A52: D51 | B52: Daywork Schedule | C52: Plant | D52: Oxy acetylene cutting set including electrodes | E52: Hr | F52: 25 | G52: 31.5 | H52: =F52*G52 -> 787.5
A53: D52 | B53: Daywork Schedule | C53: Plant | D53: 2 inch Water pump 5 hp | E53: Hr | F53: 30 | G53: 26.25 | H53: =F53*G53 -> 787.5
A54: D53 | B54: Daywork Schedule | C54: Plant | D54: 4 inch Water pump 10 hp | E54: Hr | F54: 30 | G54: 36.75 | H54: =F54*G54 -> 1102.5
A55: D54 | B55: Daywork Schedule | C55: Employee Staff | D55: Project Manager | E55: Hr | F55: 200 | G55: 42 | H55: =F55*G55 -> 8400
A56: D55 | B56: Daywork Schedule | C56: Employee Staff | D56: Resident Project Engineer | E56: Hr | F56: 200 | G56: 26.25 | H56: =F56*G56 -> 5250
A57: D56 | B57: Daywork Schedule | C57: Employee Staff | D57: Resident Civil Material Engineer | E57: Hr | F57: 200 | G57: 26.25 | H57: =F57*G57 -> 5250
A58: D57 | B58: Daywork Schedule | C58: Employee Staff | D58: Resident Electrical Engineer | E58: Hr | F58: 200 | G58: 26.25 | H58: =F58*G58 -> 5250
A59: D58 | B59: Daywork Schedule | C59: Employee Staff | D59: Resident Mechanical Engineer | E59: Hr | F59: 200 | G59: 26.25 | H59: =F59*G59 -> 5250
A60: D59 | B60: Daywork Schedule | C60: Employee Staff | D60: Resident Architecture Engineer Omani | E60: Hr | F60: 200 | G60: 26.25 | H60: =F60*G60 -> 5250
A61: D60 | B61: Daywork Schedule | C61: Employee Staff | D61: Resident Quantity Surveyor | E61: Hr | F61: 200 | G61: 26.25 | H61: =F61*G61 -> 5250
A62: D61 | B62: Daywork Schedule | C62: Employee Staff | D62: Resident Draftsman Omani | E62: Hr | F62: 200 | G62: 26.25 | H62: =F62*G62 -> 5250
A63: D62 | B63: Daywork Schedule | C63: Employee Staff | D63: Resident QA QC | E63: Hr | F63: 200 | G63: 26.25 | H63: =F63*G63 -> 5250
... A100: P99 | B100: Preliminary and General Requirements | C100: Sundry ItemsSite Survey and Grid of Levels | D100: Before commencing excavation or site levelling operations the Contractor shall conduct a coordinated site survey witnessed by the Engineer related to a bench mark referred to in the Contract document and shall prepare a site plan showing a grid of levels at 5 m centres to the proposed site the Contractor shall provide the Engineer with one transparency and two copies of the site survey plan. | E100: Item | F100: 1 | G100: 0 | H100: =F100*G100 -> 0
A101: P100 | B101: Preliminary and General Requirements | C101: Sundry ItemsSite Survey and Grid of Levels | D101: The Contractor shall conduct similar site survey after site levelling operations and external works have been completed and provide drawings as above. | E101: Item | F101: 1 | G101: 0 | H101: =F101*G101 -> 0 | I101: =SUM(H52:H101) -> 63577.5
A102: P101 | B102: Preliminary and General Requirements | C102: Sundry ItemsCopies of Orders | D102: Provide the Engineers Representative with a copy of all orders for the supply of such materials or goods required in connection with the Works as the Engineers Representative may specify. | E102: Item | F102: 1 | G102: 0 | H102: =F102*G102 -> 0
A103: P102 | B103: Preliminary and General Requirements | C103: Sundry ItemsWorking Drawings | D103: Allow for preparing and submission to the Engineer of all working drawings and operation and maintenance instructions as detailed in the specification if these costs are not specifically measured elsewhere in the relevant sections of this document. | E103: Item | F103: 1 | G103: 0 | H103: =F103*G103 -> 0
A104: P103 | B104: Preliminary and General Requirements | C104: Sundry ItemsWorking Drawings | D104: Upon completion of the works submit two sets of diskettes Autocad R12 later two transparencies and four copies of all drawings duly marked AsBuilt clearly defining all locations depths shapes and dimensions of all permanent works executed. | E104: Item | F104: 1 | G104: 0 | H104: =F104*G104 -> 0
A105: P104 | B105: Preliminary and General Requirements | C105: Sundry ItemsTraining of Employers Personnel | D105: During the execution of the Works the Contractor shall provide such assistance as may be necessary for the instruction and training of personnel appointed by the Employer. | E105: Item | F105: 1 | G105: 0 | H105: =F105*G105 -> 0
A106: P105 | B106: Preliminary and General Requirements | C106: Sundry ItemsTraining of Employers Personnel | D106: The Contractor shall provide all necessary instruction material for this purpose such as manuals booklets pamphlets drawings sketches models pictures photoscolour slides films etc. This instruction material shall become the property of the Employer. | E106: Item | F106: 1 | G106: 0 | H106: =F106*G106 -> 0
A107: P106 | B107: Preliminary and General Requirements | C107: Sundry ItemsDirect Contractors | D107: The Tenderers attention is drawn to the fact that the Employer may appoint other Contractors to carry out certain items of Specialist Works in accordance with Clause 31 of the Conditions of Contract. | E107: Item | F107: 1 | G107: 0 | H107: =F107*G107 -> 0
A108: P107 | B108: Preliminary and General Requirements Performance Bond Advance Payment Bond and Insurance Certificate | C108: Performance Bond | D108: The Contractor will be required to provide Performance Bond all in accordance with Clause 4.2 of the Conditions of Contract. | E108: Item | F108: 1 | G108: 0 | H108: =F108*G108 -> 0
A109: P108 | B109: Preliminary and General Requirements Performance Bond Advance Payment Bond and Insurance Certificate | C109: Insurance | D109: The Contractor will be required to provide all Insurances in accordance with the Conditions of Contract. | E109: Item | F109: 1 | G109: 0 | H109: =F109*G109 -> 0
A110: P109 | B110: Preliminary and General Requirements Performance Bond Advance Payment Bond and Insurance Certificate | C110: Insurance Declaration | D110: On signing the Contract the Contractor shall obtain from his Insurance Company and lodge with the Engineer a declaration that the insurance provided is strictly in accordance with all relevant Clause in the Conditions of Contract. This shall also include insurance against damage of any kind to existing buildings which may arise as a result of the building operations. | E110: Item | F110: 1 | G110: 0 | H110: =F110*G110 -> 0
A111: P110 | B111: Preliminary and General Requirements Performance Bond Advance Payment Bond and Insurance Certificate | C111: Advance Payment Bond | D111: The Contractor will be required to provide an Advance Payment Bond all in accordance with Clause 14.2 of Conditions of Contract. | E111: Item | F111: 1 | G111: 0 | H111: =F111*G111 -> 0
A112: P111 | B112: Preliminary and General Requirements Temporary Facilities. | C112: Refer Provisional SumTemporary Houses | D112: The Contractor will be required to provide temporary houses Caravan for the resident while working in the Construction and also during Maintenance Works and refix inside houses after work finish as outside extra rooms for them. Every caravan will be around 65m2 and will include and not be limited to 2 rooms a hall a kitchen and two toilets The structure to use steel structure painted with anticorrosion paint with isolated walls and roof aluminum sandwich panels 50 mm thickness from 2 sheets 0.7 mm thickness and foam of 45 kgm3 density internal ceramic floor and walls for toiles and kitchen to be ceramic all sanitary fixture for toilet and kitchen sink and cabinet sewage electrical and water connection to be done in the temporary place and will be finally done again after move to internal new and maintained houses foundation for caravan and 3 steps omani marble in final place fixing also 4 AC are included design of caravan to be done by the contractor approved by clientconsultant beforedelivery the caravans will be under project defects notification period for one year. | E112: item | F112: 0 | G112: 0 | H112: =F112*G112 -> 0
A113: P112 | B113: Preliminary and General Requirements CCTV Control. | C113: CCTV | D113: The Contractor will be required to provide CCTV to monitor and maintain the work activity at site while working in the Construction Works also during Maintenance Works. | E113: Item | F113: 1 | G113: 0 | H113: =F113*G113 -> 0
... A115: P114 | B115: Preliminary and General Requirements EngineerEmployer Facilities | C115: Facilities for EngineersEmployers | D115: The Contractor shall provide erect maintain and remove on completion all necessary Engineers accommodation Employers accommodation common kitchen with dining hall including food for all time to the EngineersEmployers sanitary accommodation and other facilities all by the Contractor expenses and link together with all associated water drainage electrical lighting and power airconditioning telephone mobile phones 4nos with recharge cards 30rial new furniture washing equipment and maintenance the same until the Completion of Project as per details in prim documents. | E115: Item | F115: 1 | G115: 0 | H115: =F115*G115 -> 0
A116: P115 | B116: Preliminary and General Requirements Contractors Administration Arrangements | C116: Site Transportation for EngineersEmployers | D116: Provide necessary 4x4 vehicles 2nos in excellent condition for consultantclient staff transportation and pickup vehicle 2nos for site transport etc. with all consumables fuel etc. as described for small plant and tools for regular maintenance etc as per details in prim documents. | E116: Item | F116: 1 | G116: 0 | H116: =F116*G116 -> 0 | I116: =SUM(H102:H116) -> 0
A117: TOTAL DAYWORKS | G117: =SUM(H2:H116) -> 88252.5

Sheet 03 Housing Units
A1: Item Code | B1: Item Name | C1: Item Details | D1: Additional Information | E1: UOM | F1: Quantity | G1: Unit Price | H1: Total Price In Figure | I1: =SUM(H2:H22) -> 947257
A2: C1 | B2: General Works | C2: Demolishing and Clearing the Construction Area | D2: Demolishing the complete building and removing the debris from the Construction Site as per EngineerEmployer Instruction including cart away from the Project Site up to OGL | E2: NO | F2: 20 | G2: 2520 | H2: =F2*G2 -> 50400
A3: C2 | B3: Substructure Works | C3: Site Clearance | D3: This shall include removing vegetation undergrowth bushes hedges trees other temporary buildings structures or the like all complete to clean the full plot. | E3: NO | F3: 20 | G3: 52.5 | H3: =F3*G3 -> 1050
A4: C3 | B4: Substructure Works | C4: Earth work and Excavation | D4: Bulk Excavation to receive foundations in any kind of soil including hard soil and rock earth sport underground surface or running water from whatever source if any for the new foundation building area including removal of old buildings foundations cleaning the site and removing all debris not suitable for backfilling from the project area to the damp yard contractor to prepare all areas to receive new foundation safely as per drawings and soil report. | E4: M3 | F4: 15000 | G4: 0.77 | H4: =F4*G4 -> 11550
A5: C4 | B5: Substructure Works | C5: Filling | D5: Approved imported granular fill material compacted in layers in making up levels under floors | E5: M3 | F5: 4000 | G5: 0.525 | H5: =F5*G5 -> 2100
A6: C5 | B6: Substructure Works | C6: Filling | D6: Approved imported fill material compacted in layers to raise the levels | E6: M3 | F6: 15000 | G6: 0.525 | H6: =F6*G6 -> 7875
A7: C6 | B7: Substructure Works | C7: Filling | D7: Approved selected excavated material backfilled into excavations | E7: M3 | F7: 6000 | G7: 0.525 | H7: =F7*G7 -> 3150
A8: C7 | B8: Substructure Works | C8: Filling | D8: 200 mm thick well compacted hardcore filling under floors | E8: M3 | F8: 1040 | G8: 0.455 | H8: =F8*G8 -> 473.2 | I8: =H5+H6+H7+H8 -> 13598.2 | J8: 13598.2
A9: C8 | B9: Substructure Works | C9: Anti termite treatment | D9: Anti termite treatment to surfaces of ground or filling applied strictly in accordance with the manufacturers printed instructions including digging trenches backfilling etc. as required by the manufacturer and the provision of guarantee valid for 10 years | E9: M2 | F9: 6200 | G9: 1.524 | H9: =F9*G9 -> 9448.8
A10: C9 | B10: Substructure Works | C10: Poured Concrete Plain insitu concrete poured Ordinary Portland Cement OPC Concrete Grade C15 all in accordance with Drawings and Specifications and including Formwork to give as struck finish. Providing and erecting formwork including all necessary staging centering shuttering supports cross bracing deshuttering carefully making good the damaged surfaces wherever necessary all complete as specified and as directed by the Engineer all in accordance with the Drawings and Specifications | D10: Blinding upto 100 mm thickness | E10: M3 | F10: 300 | G10: 63 | H10: =F10*G10 -> 18900 | I10: =H10+H11+H12+H13+H14 -> 245700 | J10: concrete work
A11: C10 | B11: Substructure Works | C11: Reinforced insitu concrete poured vibrated Sulphate Resistent Cement OPC Concrete Grade C30 all in accordance with Drawings and Specifications and including Reinforcement High yield strength deformed bars conforming to BS 4449 Grade 460 including cutting bending binding binding wire cover blocks tests and all necessary fixing accessories all in accordance with the Drawings and Specifications and including Formwork to give as struck finish. Providing and erecting formwork including all necessary staging centering shuttering supports cross bracing deshuttering carefully making good the damaged surfaces wherever necessary all complete as specified and as directed by the Engineer all in accordance with the Drawings and Specifications | D11: Footings | E11: M3 | F11: 800 | G11: 94.5 | H11: =F11*G11 -> 75600
A12: C11 | B12: Substructure Works | C12: Reinforced insitu concrete poured vibrated Sulphate Resistent Cement OPC Concrete Grade C30 all in accordance with Drawings and Specifications and including Reinforcement High yield strength deformed bars conforming to BS 4449 Grade 460 including cutting bending binding binding wire cover blocks tests and all necessary fixing accessories all in accordance with the Drawings and Specifications and including Formwork to give as struck finish. Providing and erecting formwork including all necessary staging centering shuttering supports cross bracing deshuttering carefully making good the damaged surfaces wherever necessary all complete as specified and as directed by the Engineer all in accordance with the Drawings and Specifications | D12: Plinth beams | E12: M3 | F12: 600 | G12: 94.5 | H12: =F12*G12 -> 56700
A13: C12 | B13: Substructure Works | C13: Reinforced insitu concrete poured vibrated Sulphate Resistent Cement OPC Concrete Grade C30 all in accordance with Drawings and Specifications and including Reinforcement High yield strength deformed bars conforming to BS 4449 Grade 460 including cutting bending binding binding wire cover blocks tests and all necessary fixing accessories all in accordance with the Drawings and Specifications and including Steel fabric reinforcement A 393 BRC mesh in two layers. All complete in accordance with the Drawings and Specifications and including Formwork to give as struck finish. Providing and erecting formwork including all necessary staging centering shuttering supports cross bracing deshuttering carefully making good the damaged surfaces wherever necessary all complete as specified and as directed by the Engineer all in accordance with the Drawings and Specifications | D13: Beds Slabs Grade slabs upto 120 mm thickness | E13: M3 | F13: 800 | G13: 94.5 | H13: =F13*G13 -> 75600 | I13: 75600
A14: C13 | B14: Substructure Works | C14: Reinforced insitu concrete poured vibrated ordinary Portland Cement OPC Concrete Grade C40 all in accordance with Drawings and Specifications and including Reinforcement High yield strength deformed bars conforming to BS 4449 Grade 460 including cutting bending binding binding wire cover blocks tests and all necessary fixing accessories all in accordance with the Drawings and Specifications and including Formwork to give as struck finish. Providing and erecting formwork including all necessary staging centering shuttering supports cross bracing deshuttering carefully making good the damaged surfaces wherever necessary all complete as specified and as directed by the Engineer all in accordance with the Drawings and Specifications | D14: Substructure columns | E14: M3 | F14: 200 | G14: 94.5 | H14: =F14*G14 -> 18900
A15: C14 | B15: Substructure Works | C15: Sundries Concrete and Block work Protection | D15: Polythene sheet gauge 1200 all in accordance with Drawings and Specifications to surfaces of structural members in contact with soil | E15: M2 | F15: 8400 | G15: 2 | H15: =F15*G15 -> 16800
A16: C15 | B16: Substructure Works | C16: Sundries Bitumenous Paint | D16: Bitumenous Paint 3 coat to the surfaces of concrete | E16: M2 | F16: 10000 | G16: 0.546 | H16: =F16*G16 -> 5460
A17: C16 | B17: Substructure Works | C17: Sundries Bitumenous Sheet | D17: Bitumenous Sheet to the surfaces of concrete | E17: M2 | F17: 5200 | G17: 5.25 | H17: =F17*G17 -> 27300 | J17: 27300
A18: C17 | B18: Substructure Works | C18: Sundries Block work Protection including Bitumenous Paint and Bitumenous Sheet | D18: Protection to concrete masonryblock work in contact with soil 3 coats of approved bituminous paint bituminous sheet and including flexible board all in accordance with Drawings and Specifications to surfaces of block work in contact with soil. | E18: M2 | F18: 22000 | G18: 21 | H18: =F18*G18 -> 462000 | J18: =462000+H19 -> 565950
A19: C18 | B19: Substructure Works | C19: Concrete solid block work 10.5N per mm2 compressive strength cement and sand mortar 1to3 with and including stiffener columns and stiffener beams as required all in accordance with Drawings and Specifications | D19: 200mm thick walls | E19: M2 | F19: 11000 | G19: 9.45 | H19: =F19*G19 -> 103950 | I19: 103950
A20: C19 | B20: Substructure Works | C20: The Contractor should read and quote as per the supply laying and all works are included and required approval and commissioning as per contract standards should be under the Contractor scope of work including required charges also including DNP scope and guarantees for material. | D20: Important Note | E20: Item | F20: 0 | G20: 0 | H20: =F20*G20 -> 0
A21: C20 | B21: Substructure Works | C21: The Contractor is adviced to complete the project as per the drawing boq and specification also need to complete if anything missing in the drawing but mentioned in the boq and specification and viceversa. Should the Tenderer fail to insert any item here it will be deemed that this lump sum price for the tender includes all items and no subsequent claim for any additional items will be entertained | D21: Important Note | E21: Item | F21: 0 | G21: 0 | H21: =F21*G21 -> 0
A22: C21 | B22: Substructure Works | C22: The Contractor is to detail below any additional items with quantities and rates not previously included to complete the build up of the lump sum tender price for this section of the works. Should the Tenderer fail to insert any item here it will be deemed that this lump sum price for the tender includes all items and no subsequent claim for any additional items will be entertained | D22: Important Note | E22: Item | F22: 0 | G22: 0 | H22: =F22*G22 -> 0
A23: C22 | B23: Superstructure Works Concrete Works | C23: Poured Concrete Reinforced insitu concrete poured vibrated Ordinary Portland Cement OPC concrete grade C30 all in accordance with the Drawings and Specifications and including Reinforcement High yield strength deformed bars conforming to BS 4449 Grade 460 including cutting bending binding binding wire cover blocks tests and all necessary fixing accessories all in accordance with the Drawings and Specifications and including Formwork to give as struck finish. Providing and erecting formwork including all necessary staging centering shuttering supports cross bracing deshuttering carefully making good the damaged surfaces wherever necessary all complete as specified and as directed by the Engineer all in accordance with the Drawings and Specifications | D23: Suspended slabs waist slabs landingsstair etc. not exceeding 200 mm thickness | E23: M3 | F23: 1400 | G23: 10.08 | H23: =F23*G23 -> 14112
A24: C23 | B24: Superstructure Works Concrete Works | C24: Poured Concrete Reinforced insitu concrete poured vibrated Ordinary Portland Cement OPC Concrete Grade C30 all in accordance with the Drawings and Specifications and including Reinforcement High yield strength deformed bars conforming to BS 4449 Grade 460 including cutting bending binding binding wire cover blocks tests and all necessary fixing accessories all in accordance with the Drawings and Specifications and including Formwork to give as struck finish. Providing and erecting formwork including all necessary staging centering shuttering supports cross bracing deshuttering carefully making good the damaged surfaces wherever necessary all complete as specified and as directed by the Engineer all in accordance with the Drawings and Specifications | D24: Columns | E24: M3 | F24: 380 | G24: 13.153 | H24: =F24*G24 -> 4998.14
A25: C24 | B25: Superstructure Works Concrete Works | C25: Poured Concrete Reinforced insitu concrete poured vibrated Ordinary Portland Cement OPC Concrete Grade C30 all in accordance with the Drawings and Specifications and including Reinforcement High yield strength deformed bars conforming to BS 4449 Grade 460 including cutting bending binding binding wire cover blocks tests and all necessary fixing accessories all in accordance with the Drawings and Specifications and including Formwork to give as struck finish. Providing and erecting formwork including all necessary staging centering shuttering supports cross bracing deshuttering carefully making good the damaged surfaces wherever necessary all complete as specified and as directed by the Engineer all in accordance with the Drawings and Specifications | D25: Beams | E25: M3 | F25: 650 | G25: 8.53 | H25: =F25*G25 -> 5544.5
A26: C25 | B26: Superstructure Works Concrete Works | C26: Poured Concrete Reinforced insitu concrete poured vibrated Ordinary Portland Cement OPC Concrete Grade C30 all in accordance with the Drawings and Specifications and including Reinforcement High yield strength deformed bars conforming to BS 4449 Grade 460 including cutting bending binding binding wire cover blocks tests and all necessary fixing accessories all in accordance with the Drawings and Specifications and including Formwork to give as struck finish. Providing and erecting formwork including all necessary staging centering shuttering supports cross bracing deshuttering carefully making good the damaged surfaces wherever necessary all complete as specified and as directed by the Engineer all in accordance with the Drawings and Specifications | D26: Ramp | E26: M3 | F26: 200 | G26: 1.26 | H26: =F26*G26 -> 252
A27: C26 | B27: Superstructure Works Concrete Works | C27: Sundries | D27: GRC Mesh in the Duct 300 X 400 refer to the Architectural Drawing. | E27: NO | F27: 20 | G27: 21 | H27: =F27*G27 -> 420 | I27: =H27+H28+H29 -> 1260 | J27: GRC MESH
A28: C27 | B28: Superstructure Works Concrete Works | C28: Sundries | D28: GRC Mesh in the Duct 300 X 500 refer to the Architectural Drawing. | E28: NO | F28: 20 | G28: 21 | H28: =F28*G28 -> 420
A29: C28 | B29: Superstructure Works Concrete Works | C29: Sundries | D29: GRC Mesh in the Duct 300 X 1000 refer to the Architectural Drawing. | E29: NO | F29: 20 | G29: 21 | H29: =F29*G29 -> 420
A30: C29 | B30: Superstructure Works Concrete Works | C30: Sundries | D30: Planter box including excavation backfilling disposals blinding solid blockwork waterproofing plaster all complete of various size | E30: No | F30: 100 | G30: 47.25 | H30: =F30*G30 -> 4725 | I30: =H30 -> 4725 | J30: PLANTER BOX
A31: C30 | B31: Superstructure Works Masonry | C31: Internal Walls Ordinary Portland cement concrete blocks 7.5N per mm2 compressive strength cement and sand mortar 1to3 with and including stiffener columns and stiffener beams as required all in accordance with the Drawings and Specifications | D31: 200mm thick walls | E31: M2 | F31: 17400 | G31: 15 | H31: =F31*G31 -> 261000 | I31: =H31 -> 261000 | J31: BLOCK WORK
A32: C31 | B32: Superstructure Works Masonry | C32: Sunken Slab Waterproofing | D32: Providing and applying Sunken Slab Waterproof course with bituminous paint and bituminous membrane conforming to BSto6398 in horizontal joints laid strictly in compliance with approved manufacturers printed instructions and as directed by Engineer. | E32: M2 | F32: 700 | G32: 3.6 | H32: =F32*G32 -> 2520 | I32: =H32+H33+H34+H35+H36+H37 -> 37905 | J32: WATER PROOFING
B33: Superstructure Works Masonry | C33: Roof Slab Waterproofing THERMAL AND MOISTURE PROTECTION COVERINGS AND LININGS | D33: Combo roof treatment for thermal and moisture protection for open terraces by an approved expert agency complete with thermal and moisture resistant layers UV protection layer leveling course separation layers top finishes skirting with 250mm high etc. ensuring smooth runoff and with minimum 25 years of warranty. | E33: Item | F33: 1 | G33: 15750 | H33: =F33*G33 -> 15750
A34: C33 | B34: Superstructure Works Thermal and Moisture Protection | C34: Backgrounds and Finishes Roof screed light weight concrete screed 1000 kg per m3 minimum 50 mm thick to a maximum of 125 mm thick | D34: 50 mm minimum bed laid on concrete to falls and cross falls | E34: M2 | F34: 5600 | G34: 1.05 | H34: =F34*G34 -> 5880
A35: C34 | B35: Superstructure Works Thermal and Moisture Protection | C35: 4 mm thick torch applied acrylic polypropylene modified bitumen membrane with non woven polyester reinforcement and polyethylene film waterproof membrane including primer to roofs as per the manufacturer printed instructions complete as specified. Contractor to allow for 10 years guarantee and 24 hours flood test. | D35: To roof decks 4mm thick on flat surface laid to falls and cross falls | E35: M2 | F35: 5600 | G35: 1.05 | H35: =F35*G35 -> 5880
A36: C35 | B36: Superstructure Works Thermal and Moisture Protection | C36: Skirting 300 mm girth including turning into groove | D36: In up standsdrops and around plinths minimum 300 mm high including dressing over fillet grooves sealant tantalized batten etc. complete to roof deck | E36: M | F36: 1900 | G36: 1.05 | H36: =F36*G36 -> 1995
A37: C36 | B37: Superstructure Works Thermal and Moisture Protection | C37: Insulation Extruded high density polystyrene foam board insulation with rigid closed cell structure all in accordance with the specifications and drawings in external | D37: to roof decks 50 mm thick laid on concrete spot bonded to waterproofing | E37: M2 | F37: 5600 | G37: 1.05 | H37: =F37*G37 -> 5880
A38: C37 | B38: Superstructure Works Thermal and Moisture Protection | C38: Roof Finishes | D38: 300 x 300 x 30 mm white cement tiles bedded on and including cement mortar screed to falls and cross falls jointed in cement mortar movements joints etc. complete to roof | E38: M2 | F38: 5600 | G38: 4.2 | H38: =F38*G38 -> 23520
A39: C38 | B39: Superstructure Works Thermal and Moisture Protection | C39: Roof Finishes | D39: 100 x 30 mm white cement skirting to upstands | E39: M | F39: 1900 | G39: 3.15 | H39: =F39*G39 -> 5985
A40: C39 | B40: Superstructure Works Thermal and Moisture Protection | C40: Roof Sundries | D40: Allow for Providing dressing around 110mm 83mm UPVC rainwater outlets roof duct gargoyle extract fan soil and vent pipe | E40: NO | F40: 20 | G40: 78.75 | H40: =F40*G40 -> 1575
A41: C40 | B41: Superstructure Works Thermal and Moisture Protection | C41: Roof Sundries | D41: Allow for gun applied sealant to seal the joints and groove as applicable and as specified. | E41: NO | F41: 20 | G41: 26.25 | H41: =F41*G41 -> 525
A42: C41 | B42: Superstructure Works Metal Works | C42: WPC Pergola | D42: Supply fabricate and install of WPC Pergola as per the approved Construction Drawing and refer to the Architectural Drawing for a highquality WPC Pergola waterproof and antimoisture. The Contractor should submit a detailed drawing of pergola approval 10 years guarantee.. | E42: NO | F42: 19 | G42: 210 | H42: =F42*G42 -> 3990
A43: C42 | B43: Superstructure Works Metal Works | C43: Staircase hand rail | D43: Stainless steel handrail as shown in the Architectural drawing shop drawings with full sections details to be approved before supply. Note to all stainless steel material shall be of 316 grade. | E43: M | F43: 200 | G43: 26.25 | H43: =F43*G43 -> 5250
A44: C43 | B44: Superstructure Works Metal Works | C44: CAT Ladder | D44: Supply and install a 3800mm high CAT steel Ladder as specified and detailed on the drawing with anticorrelation epoxy pain. | E44: No | F44: 20 | G44: 152.25 | H44: =F44*G44 -> 3045
A45: C44 | B45: Superstructure Works Doors and Windows | C45: Wood Doors Note | D45: 1 All timber and veneers shall be well conditioned seasoned dried vacuum treated and preservative treated all as specified | E45: Item | F45: 1 | G45: 0 | H45: =F45*G45 -> 0 | I45: =SUM(H45:H66) -> 194881.96 | J45: DOORS
A46: C45 | B46: Superstructure Works Doors and Windows | C46: Wood Doors Note | D46: 2 Prepare the surface prime and apply two under coats and two finishing coats of high gloss enamel paint of approved quality make and shade for shutter and frame | E46: Item | F46: 1 | G46: 0 | H46: =F46*G46 -> 0
A47: C46 | B47: Superstructure Works Doors and Windows | C47: Wood Doors Note | D47: 3 All hardwood timber shall be best quality Meranti | E47: Item | F47: 0 | G47: 0 | H47: =F47*G47 -> 0
A48: C47 | B48: Superstructure Works Doors and Windows | C48: Wood Doors Note | D48: 4 Sizes stated are structural opening sizes | E48: Item | F48: 0 | G48: 0 | H48: =F48*G48 -> 0 | I48: =H49+H50+H51+H52+H53+H54 -> 97652 | J48: WOODEN DOORS
A49: C48 | B49: Superstructure Works Doors and Windows | C49: Wood Doors Door comprising profiled heads jambs frames subframes architraves beadings mouldings plinth block ply linings infill panels mastic and other pointing fixings neoprene seal master lining and all ancillary items including fixing of ironmongery and final decoration for a complete installation all as specified and as detailed on drawing including required reinforcement cement concrete lintels and including Supply and fix ironmongery as specified in schedule and approved fixed to hardwood including paint All locks shall be under master key system as detailed on drawing Note All stainless steel fittings shall be of 316 grade | D49: Type D1 double leaf overall size 1800x2400mm high | E49: No | F49: 20 | G49: 892.5 | H49: =F49*G49 -> 17850 | I49: =H55+H56+H57+H58+H59+H60 -> 68565 | J49: WPC DOORS
A50: C49 | B50: Superstructure Works Doors and Windows | C50: Wood Doors Door comprising profiled heads jambs frames subframes architraves beadings mouldings plinth block ply linings infill panels mastic and other pointing fixings neoprene seal master lining and all ancillary items including fixing of ironmongery and final decoration for a complete installation all as specified and as detailed on drawing including required reinforcement cement concrete lintels and including Supply and fix ironmongery as specified in schedule and approved fixed to hardwood including paint All locks shall be under master key system as detailed on drawing Note All stainless steel fittings shall be of 316 grade | D50: Type D2 single leaf overall size 1000x2400mm high | E50: No | F50: 20 | G50: 262.5 | H50: =F50*G50 -> 5250
A51: C50 | B51: Superstructure Works Doors and Windows | C51: Wood Doors Door comprising profiled heads jambs frames subframes architraves beadings mouldings plinth block ply linings infill panels mastic and other pointing fixings neoprene seal master lining and all ancillary items including fixing of ironmongery and final decoration for a complete installation all as specified and as detailed on drawing including required reinforcement cement concrete lintels and including Supply and fix ironmongery as specified in schedule and approved fixed to hardwood including paint All locks shall be under master key system as detailed on drawing Note All stainless steel fittings shall be of 316 grade | D51: Type D3 single leaf overall size 1000x2100mm high | E51: No | F51: 160 | G51: 229.7 | H51: =F51*G51 -> 36752 | I51: =SUM(H2:H51) -> 1380795.6 | J51: =I51-1380795.64 -> 0
A52: C51 | B52: Superstructure Works Doors and Windows | C52: Wood Doors Door comprising profiled heads jambs frames subframes architraves beadings mouldings plinth block ply linings infill panels mastic and other pointing fixings neoprene seal master lining and all ancillary items including fixing of ironmongery and final decoration for a complete installation all as specified and as detailed on drawing including required reinforcement cement concrete lintels and including Supply and fix ironmongery as specified in schedule and approved fixed to hardwood including paint All locks shall be under master key system as detailed on drawing Note All stainless steel fittings shall be of 316 grade | D52: Type D4 single leaf overall size 800x2100mm high | E52: No | F52: 100 | G52: 220.5 | H52: =F52*G52 -> 22050
A53: C52 | B53: Superstructure Works Doors and Windows | C53: Wood Doors Door comprising profiled heads jambs frames subframes architraves beadings mouldings plinth block ply linings infill panels mastic and other pointing fixings neoprene seal master lining and all ancillary items including fixing of ironmongery and final decoration for a complete installation all as specified and as detailed on drawing including required reinforcement cement concrete lintels and including Supply and fix ironmongery as specified in schedule and approved fixed to hardwood including paint All locks shall be under master key system as detailed on drawing Note All stainless steel fittings shall be of 316 grade | D53: Type D5 single leaf overall size 1000x2100mm high | E53: No | F53: 40 | G53: 262.5 | H53: =F53*G53 -> 10500
A54: C53 | B54: Superstructure Works Doors and Windows | C54: Wood Doors Door comprising profiled heads jambs frames subframes architraves beadings mouldings plinth block ply linings infill panels mastic and other pointing fixings neoprene seal master lining and all ancillary items including fixing of ironmongery and final decoration for a complete installation all as specified and as detailed on drawing including required reinforcement cement concrete lintels and including Supply and fix ironmongery as specified in schedule and approved fixed to hardwood including paint All locks shall be under master key system as detailed on drawing Note All stainless steel fittings shall be of 316 grade | D54: Type D6 single leaf overall size 1000x2400mm high | E54: No | F54: 40 | G54: 131.25 | H54: =F54*G54 -> 5250
A55: C54 | B55: Superstructure Works Doors and Windows | C55: WPC Solid Core Doors Door comprising profiled heads jambs frames subframes architraves beadings mouldings plinth block ply linings infill panels mastic and other pointing fixings neoprene seal master lining and all ancillary items including fixing of ironmongery and final decoration for a complete installation all as specified and as detailed on drawing including required reinforcement cement concrete lintels and including Supply and fix ironmongery as specified in schedule and approved fixed to hardwood including paint All locks shall be under master key system as detailed on drawing Note All stainless steel fittings shall be of 316 grade. | D55: Type D1 double leaf overall size 1800x2400mm high | E55: Item | F55: 1 | G55: 9135 | H55: =F55*G55 -> 9135
A56: C55 | B56: Superstructure Works Doors and Windows | C56: WPC Solid Core Doors Door comprising profiled heads jambs frames subframes architraves beadings mouldings plinth block ply linings infill panels mastic and other pointing fixings neoprene seal master lining and all ancillary items including fixing of ironmongery and final decoration for a complete installation all as specified and as detailed on drawing including required reinforcement cement concrete lintels and including Supply and fix ironmongery as specified in schedule and approved fixed to hardwood including paint All locks shall be under master key system as detailed on drawing Note All stainless steel fittings shall be of 316 grade. | D56: Type D2 single leaf overall size 1000x2400mm high | E56: Item | F56: 1 | G56: 4410 | H56: =F56*G56 -> 4410
A57: C56 | B57: Superstructure Works Doors and Windows | C57: WPC Solid Core Doors Door comprising profiled heads jambs frames subframes architraves beadings mouldings plinth block ply linings infill panels mastic and other pointing fixings neoprene seal master lining and all ancillary items including fixing of ironmongery and final decoration for a complete installation all as specified and as detailed on drawing including required reinforcement cement concrete lintels and including Supply and fix ironmongery as specified in schedule and approved fixed to hardwood including paint All locks shall be under master key system as detailed on drawing Note All stainless steel fittings shall be of 316 grade. | D57: Type D3 single leaf overall size 1000x2100mm high | E57: Item | F57: 1 | G57: 26460 | H57: =F57*G57 -> 26460
A58: C57 | B58: Superstructure Works Doors and Windows | C58: WPC Solid Core Doors Door comprising profiled heads jambs frames subframes architraves beadings mouldings plinth block ply linings infill panels mastic and other pointing fixings neoprene seal master lining and all ancillary items including fixing of ironmongery and final decoration for a complete installation all as specified and as detailed on drawing including required reinforcement cement concrete lintels and including Supply and fix ironmongery as specified in schedule and approved fixed to hardwood including paint All locks shall be under master key system as detailed on drawing Note All stainless steel fittings shall be of 316 grade. | D58: Type D4 single leaf overall size 800x2100mm high | E58: Item | F58: 1 | G58: 15750 | H58: =F58*G58 -> 15750
A59: C58 | B59: Superstructure Works Doors and Windows | C59: WPC Solid Core Doors Door comprising profiled heads jambs frames subframes architraves beadings mouldings plinth block ply linings infill panels mastic and other pointing fixings neoprene seal master lining and all ancillary items including fixing of ironmongery and final decoration for a complete installation all as specified and as detailed on drawing including required reinforcement cement concrete lintels and including Supply and fix ironmongery as specified in schedule and approved fixed to hardwood including paint All locks shall be under master key system as detailed on drawing Note All stainless steel fittings shall be of 316 grade. | D59: Type D5 single leaf overall size 1000x2100mm high | E59: Item | F59: 1 | G59: 8400 | H59: =F59*G59 -> 8400
A60: C59 | B60: Superstructure Works Doors and Windows | C60: WPC Solid Core Doors Door comprising profiled heads jambs frames subframes architraves beadings mouldings plinth block ply linings infill panels mastic and other pointing fixings neoprene seal master lining and all ancillary items including fixing of ironmongery and final decoration for a complete installation all as specified and as detailed on drawing including required reinforcement cement concrete lintels and including Supply and fix ironmongery as specified in schedule and approved fixed to hardwood including paint All locks shall be under master key system as detailed on drawing Note All stainless steel fittings shall be of 316 grade. | D60: Type D6 single leaf overall size 1000x2400mm high | E60: Item | F60: 1 | G60: 4410 | H60: =F60*G60 -> 4410
A61: C60 | B61: Superstructure Works Doors and Windows | C61: Ironmongery Supply and fix of ironmongery with and including all necessary fixing accessories and screws to match all in accordance with the specifications and drawings to wood doors | D61: Allow for grand master key and master key system | E61: No | F61: 20 | G61: 31.5 | H61: =F61*G61 -> 630 | I61: =H61 -> 630 | J61: IRON MONGRY
A62: C61 | B62: Superstructure Works Doors and Windows | C62: UPVC windows window sets complete with all necessary ironmongery as specified including fixing to blockwork or concrete and mastic pointing all around all as specified and detailed on drawing and including required reinforcement cement concrete lintels | D62: Type W1 overall size 2000 x 1300mm high | E62: No | F62: 160 | G62: 68.906 | H62: =F62*G62 -> 11024.96 | I62: =H62+H63+H64+H65+H66 -> 28034.96 | J62: UPVC DOORS
A63: C62 | B63: Superstructure Works Doors and Windows | C63: UPVC windows window sets complete with all necessary ironmongery as specified including fixing to blockwork or concrete and mastic pointing all around all as specified and detailed on drawing and including required reinforcement cement concrete lintels | D63: Type W2 overall size 1200 x 900mm high | E63: No | F63: 20 | G63: 47.25 | H63: =F63*G63 -> 945
A64: C63 | B64: Superstructure Works Doors and Windows | C64: UPVC windows window sets complete with all necessary ironmongery as specified including fixing to blockwork or concrete and mastic pointing all around all as specified and detailed on drawing and including required reinforcement cement concrete lintels | D64: Type W3 overall size 600 x 1300mm high | E64: No | F64: 60 | G64: 78.75 | H64: =F64*G64 -> 4725
A65: C64 | B65: Superstructure Works Doors and Windows | C65: UPVC windows window sets complete with all necessary ironmongery as specified including fixing to blockwork or concrete and mastic pointing all around all as specified and detailed on drawing and including required reinforcement cement concrete lintels | D65: Type W4 overall size 1000 x 3700mm high | E65: No | F65: 20 | G65: 94.5 | H65: =F65*G65 -> 1890
A66: C65 | B66: Superstructure Works Doors and Windows | C66: UPVC ventilator ventilator sets complete with all necessary ironmongery as specified including fixing to blockwork or concrete and mastic pointing all around all as specified and detailed on drawing and including required reinforcement cement concrete lintels | D66: Type V overall size 600 x 600mm high | E66: No | F66: 100 | G66: 94.5 | H66: =F66*G66 -> 9450
A67: C66 | B67: Superstructure Works Finishes | C67: Backgrounds Plaster cement and sand 1to3 internal To walls and columns on concrete block base internal including stainsteel mesh butterfly angle between the concrete column and block work. | D67: to receive internal painting | E67: M2 | F67: 16200 | G67: 2.385 | H67: =F67*G67 -> 38637
A68: C67 | B68: Superstructure Works Finishes | C68: Backgrounds Plaster cement and sand 1to4 external To walls and columns on concrete block base external including stainsteel mesh butterfly angle between the concrete column and block work. | D68: to receive external painting | E68: M2 | F68: 14000 | G68: 2.07 | H68: =F68*G68 -> 28980
A69: C68 | B69: Superstructure Works Finishes | C69: Allow for laying of Marble Threshold as per the specifications drawings and to approval of the Engineer. | D69: Internal Floor Tile | E69: No | F69: 20 | G69: 945 | H69: =F69*G69 -> 18900 | J69: FLOOR TILES
A70: C69 | B70: Superstructure Works Finishes | C70: Floor Tilesto FF1 Ceramic floor tiles laid on screed grouted with waterproof coloured compatible mortar to manufacturers specificationinstruction; internally | D70: 600 x 600 x 8 mm AntiSlip tiling to floor | E70: M2 | F70: 3700 | G70: 4.086 | H70: =F70*G70 -> 15118.2 | I70: =H70+H71+H72+H78+H84+H85 -> 61318.4 | J70: ANTI SLIPS
A71: C70 | B71: Superstructure Works Finishes | C71: Floor Tilesto FF2 Ceramic floor tiles laid on screed grouted with waterproof coloured compatible mortar to manufacturers specificationinstruction; internally | D71: 600 x 600 x 8 mm AntiSlip tiling to floor | E71: M2 | F71: 550 | G71: 4.582 | H71: =F71*G71 -> 2520.1 | I71: =H73+H77+H74+H79 -> 8365 | J71: STAIRCASE STEPS
A72: C71 | B72: Superstructure Works Finishes | C72: Floor Tilesto FF3 Ceramic floor tiles laid on screed grouted with waterproof coloured compatible mortar to manufacturers specificationinstruction; internally | D72: 600 x 600 x 8 mm AntiSlip tiling to floor | E72: M2 | F72: 600 | G72: 6.3 | H72: =F72*G72 -> 3780 | I72: =H78+H84+H85+H94 -> 43470.1 | J72: CERAMIC TILES
A73: C72 | B73: Superstructure Works Finishes | C73: Floor Tilesto FF4 30mm tk. Granite laid on screed grouted with waterproof coloured compatible mortar to manufacturers specificationinstruction; internally | D73: 30mm thick Granite for Staircase and Steps | E73: M2 | F73: 600 | G73: 5.6 | H73: =F73*G73 -> 3360 | J73: INTERNAL PAINT
A74: C73 | B74: Superstructure Works Finishes | C74: Floor Tilesto FF5 20mm tk. Granite laid on screed grouted with waterproof coloured compatible mortar to manufacturers specificationinstruction; internally | D74: 20mm tk. Granite Tiles alternative bands of rough smooth coping both sides | E74: M2 | F74: 500 | G74: 2.52 | H74: =F74*G74 -> 1260 | J74: EXTERNAL PAINT
A75: C74 | B75: Superstructure Works Finishes | C75: Floor Tilesto FF6 80mm tk. Interlock tiles laid on screed grouted with waterproof coloured compatible mortar to manufacturers specificationinstruction; internally | D75: 80mm tk. Heavy Duty Interlock Tile | E75: M2 | F75: 4000 | G75: 1.47 | H75: =F75*G75 -> 5880
A76: C75 | B76: Superstructure Works Finishes | C76: Floor Tilesto FF7 Porcelain tiles laid on screed grouted with waterproof coloured compatible mortar to manufacturers specificationinstruction; internally | D76: Porcelain Tiles 600 X 600 X 20 | E76: M2 | F76: 800 | G76: 16.275 | H76: =F76*G76 -> 13020
A77: C76 | B77: Superstructure Works Finishes | C77: Floor Tilesto FF9 Granite tiles laid on screed grouted with waterproof coloured compatible mortar to manufacturers specificationinstruction; internally | D77: 30mm thick Granite for Entrance floor and Staircase and Steps | E77: M2 | F77: 200 | G77: 14 | H77: =F77*G77 -> 2800
A78: C77 | B78: Superstructure Works Finishes | C78: Skirting Tilesto FF1 Ceramic tiles laid on screed grouted with waterproof coloured compatible mortar to manufacturers specificationinstruction; internally | D78: Ceramic Tiles 600 X 150 X 8 Anti Slip | E78: M | F78: 3800 | G78: 1.658 | H78: =F78*G78 -> 6300.4
A79: C78 | B79: Superstructure Works Finishes | C79: Skirting Tilesto FF4 30mm tk. Granite laid on screed grouted with waterproof coloured compatible mortar to manufacturers specificationinstruction; internally | D79: 30mm thick Granite for Staircase and Steps | E79: M | F79: 200 | G79: 4.725 | H79: =F79*G79 -> 945
A80: C79 | B80: Superstructure Works Finishes | C80: Allow for construction of Decorative projection weather coat stoneshield with 10 years garantee as per the specifications drawings and to approval of the Engineer | D80: External Elevation | E80: No | F80: 20 | G80: 47.25 | H80: =F80*G80 -> 945
A81: C80 | B81: Superstructure Works Finishes | C81: Allow for construction of Decorative projection weather coat stoneshield with 10 years garantee as per the specifications drawings and to approval of the Engineer | D81: F1F2 External Elevation | E81: M2 | F81: 11600 | G81: 1.72 | H81: =F81*G81 -> 19952 | I81: =H81+H82+H80 -> 22157 | J81: EXTERNAL ELEVATION
A82: C81 | B82: Superstructure Works Finishes | C82: Allow for construction of Decorative projection as per the specifications drawings and to approval of the Engineer | D82: F3 External Elevation | E82: Item | F82: 2400 | G82: 0.525 | H82: =F82*G82 -> 1260
A83: C82 | B83: Superstructure Works Finishes | C83: Wall Finishes FF1 Painting and decorating Eligance marble paint finish internal | D83: Smooth Plaster Painting Anti Fungal and Water Resistance | E83: M2 | F83: 12200 | G83: 2.479 | H83: =F83*G83 -> 30243.8 | I83: =H83+H86+H87+H88+H89 -> 70666.6 | J83: INTERNAL PAINT
A84: C83 | B84: Superstructure Works Finishes | C84: Wall Finishes FF2 Ceramic Tiles 600 X 200 X 8 Anti Slip | D84: Ceramic Tiles 600 X 200 X 20 Anti Slip | E84: M2 | F84: 1700 | G84: 4.941 | H84: =F84*G84 -> 8399.7
A85: C84 | B85: Superstructure Works Finishes | C85: Wall Finishes FF3 Ceramic Tiles 600 X 200 X 8 Anti Slip | D85: Ceramic Tiles 600 X 200 X 20 Anti Slip | E85: M2 | F85: 3600 | G85: 7 | H85: =F85*G85 -> 25200
A86: C85 | B86: Superstructure Works Finishes | C86: Ceilings Finishes FF1 Painting and decoratingEligance marble paint finish internal | D86: Smooth Plaster Painting Anti Fungal and Water Resistance | E86: M2 | F86: 3700 | G86: 7.15 | H86: =F86*G86 -> 26455
A87: C86 | B87: Superstructure Works Finishes | C87: Ceilings Finishes FF2 Smooth Plaster PaintingEligance marble paint finish Anti Fungal and Water Resistance | D87: Smooth Plaster Painting Anti Fungal and Water Resistance | E87: M2 | F87: 550 | G87: 7.636 | H87: =F87*G87 -> 4199.8
A88: C87 | B88: Superstructure Works Finishes | C88: Ceilings Finishes FF3 Smooth Plaster Painting Eligance marble paint finish Anti Fungal and Water Resistance | D88: Smooth Plaster Painting Anti Fungal and Water Resistance | E88: M2 | F88: 600 | G88: 8.4 | H88: =F88*G88 -> 5040
A89: C88 | B89: Superstructure Works Finishes | C89: Ceilings Finishes FF4 Smooth Plaster Painting Eligance marble paint finish Anti Fungal and Water Resistance | D89: Smooth Plaster Painting Anti Fungal and Water Resistance | E89: M2 | F89: 600 | G89: 7.88 | H89: =F89*G89 -> 4728
A90: C89 | B90: Superstructure Works Finishes | C90: Allow for supply fabricate and installation of Gas Cyclinder Stage as per the specifications drawings and to approval of the Engineer. | D90: Gas Cylinder Stage | E90: No | F90: 20 | G90: 36.75 | H90: =F90*G90 -> 735
A91: C90 | B91: Superstructure Works Finishes | C91: Allow for corecut remove and smooth finish as per the specifications drawings and to approval of the Engineer. | D91: Drain Open to connect Sewage Tanker to the Holding Tank size 550 X 400mm | E91: No | F91: 20 | G91: 42 | H91: =F91*G91 -> 840 | I91: =H91+H92+H93 -> 2730
A92: C91 | B92: Superstructure Works Finishes | C92: Allow for supply fabricate and installation of water point protection as per the specifications drawings and to approval of the Engineer. | D92: Water point protection | E92: No | F92: 20 | G92: 47.25 | H92: =F92*G92 -> 945
A93: C92 | B93: Superstructure Works Finishes | C93: Allow for supply fabricate and installation of Meter Panel protection as per the specifications drawings and to approval of the Engineer. | D93: Meter Panel protection | E93: No | F93: 20 | G93: 47.25 | H93: =F93*G93 -> 945
A94: C93 | B94: Superstructure Works Finishes | C94: Allow for supply fabricate and installation of Kitchen Stage including Stage Concrete Stage Korean Top and Stage Area Ceramic Wall Tile as per the specifications drawings and to approval of the Engineer. | D94: Kitchen Stage Concrete Korean Top Ceramic Wall Tiles | E94: No | F94: 20 | G94: 178.5 | H94: =F94*G94 -> 3570
A95: C94 | B95: Superstructure Works Finishes | C95: Allow for supply fabricate and installation of Kitchen Hood Range including Aluminum Kitchen Cabinet above and Aluminum Kitchen Cabinet below all as per the specifications drawings and to approval of the Engineer. | D95: Kitchen Hood Range Cabinet above and below Cabinet. | E95: No | F95: 20 | G95: 189 | H95: =F95*G95 -> 3780
A96: C95 | B96: Superstructure Works Finishes | C96: The Contractor should read and quote as per the supply laying and all works are included and required approval commissioning as per contract standards should be under the Contractor scope of work including required charges also including DNP scope and guarantees for material. | D96: Important Note | E96: Item | F96: 0 | G96: 0 | H96: =F96*G96 -> 0
A97: C96 | B97: Superstructure Works Finishes | C97: The Contractor is adviced to complete the project as per the drawing boq and specification also need to complete if anything missing in the drawing but mentioned in the boqspecification and viceversa. Should the Tenderer fail to insert any item here it will be deemed that this lump sum price for the tender includes all items and no subsequent claim for any additional items will be entertained | D97: Important Note | E97: Item | F97: 0 | G97: 0 | H97: =F97*G97 -> 0
A98: C97 | B98: Superstructure Works Finishes | C98: The Contractor is to detail below any additional items with quantities and rates not previously included to complete the build up of the lump sum tender price for this section of the works. Should the Tenderer fail to insert any item here it will be deemed that this lump sum price for the tender includes all items and no subsequent claim for any additional items will be entertained | D98: Important Note | E98: Item | F98: 0 | G98: 0 | H98: =F98*G98 -> 0
A99: P1 | B99: Sanitary Installation | C99: UPVC pipes to BS 4514 1983 and BS 4660 1973 including all joints and accessories and brackets | D99: UPVC drain pipes to BS 4514 1983 and BS 4660 1973 including all joints with ring seals fittings and accessories in the running length. | E99: Item | F99: 0 | G99: 0 | H99: =F99*G99 -> 0 | I99: =H100+H101+H102+H103+H104+H105+H106+H107+H108+H109+H111+H112+H113+H114+H115+H116+H117+H118+H119+H120+H121+H122+H123+H124 -> 46576.86 | J99: sanitary installations
A100: P2 | B100: Sanitary Installation | C100: UPVC pipes to BS 4514 1983 and BS 4660 1973 including all joints and accessories and brackets | D100: 160mm diamater | E100: M | F100: 1120 | G100: 6.975 | H100: =F100*G100 -> 7812
...

Sheet 04  External Works
A1: Item Code | B1: Item Name | C1: Item Details | D1: Additional Information | E1: UOM | F1: Quantity | G1: Unit Price In Figure | H1: Total Price In Figure
A2: EW1 | B2: External Works General Site Works | C2: Site Preparation | D2: Allow for setting out grading trimming including clearing loose boulders vegetation stones and the like all trees bushes shrubs and undergrowth grub up all roots and burn or remove from site as directed by the Engineer. | E2: Item | F2: 1 | G2: 0 | H2: =F2*G2 -> 0
A3: EW2 | B3: External Works General Site Works | C3: Boundary wall | D3: Allow for the Contractor to prepare RCC foundation column block work plastering and painting as per the Architectural Drawing and as per Engineer Employer Instruction to complete the Boundary Wall. | E3: M | F3: 1775 | G3: 2.1 | H3: =F3*G3 -> 3727.5
A4: EW3 | B4: External Works General Site Works | C4: Wicket Gate | D4: Allow for the Contractor to supply fabricate and installation of single leaf Wicket Gate as per the Architectural Drawing and follow as per Engineer Employer Instructions including anti corrotion epoxy paint. | E4: no | F4: 20 | G4: 105 | H4: =F4*G4 -> 2100
A5: EW4 | B5: External Works General Site Works | C5: Car Entrance Gate | D5: Allow for the Contractor to supply fabricate and installation of single leaf Car Entrance Gate as per the Architectural Drawing and follow as per Engineer Employer Instructions including anti corrotion epoxy paint | E5: no | F5: 20 | G5: 141.75 | H5: =F5*G5 -> 2835
A6: EW5 | B6: External Works General Site Works | C6: Entrance Gate ont only | D6: Allow for the Contractor to supply fabricate and installation of Wicket Gate solid WPC with 10 years garantee as per the Architectural Drawing and follow as per Engineer Employer Instructions including anti corrotion epoxy paint. | E6: Item | F6: 0 | G6: 0 | H6: =F6*G6 -> 0
A7: EW6 | B7: External Works General Site Works | C7: Wicket Gate | D7: Single leaf Wicket Gate solid WPC | E7: Item | F7: 1 | G7: 0 | H7: =F7*G7 -> 0
A8: EW7 | B8: External Works General Site Works | C8: Car Entrance Gate | D8: Single leaf Car Entrance Gate soild WPC | E8: Item | F8: 1 | G8: 0 | H8: =F8*G8 -> 0
A9: EW8 | B9: External Works General Site Works | C9: Entrance Concrete Paver | D9: Allow for the Contractor to prepare Concrete Paver as per the Architectural Drawing and place at the House Main Entrance. | E9: No | F9: 100 | G9: 5.25 | H9: =F9*G9 -> 525
A10: EW9 | B10: External Works General Site Works | C10: Interlock Tile | D10: Allow for connection Asphalt road to the site from the main drawing as per approval | E10: M2 | F10: 13550 | G10: 1.05 | H10: =F10*G10 -> 14227.5
A11: EW10 | B11: External Works General Site Works | C11: Curb Stone | D11: Allow for connection Asphalt road to the site from the main drawing as per approval | E11: M | F11: 1400 | G11: 2.1 | H11: =F11*G11 -> 2940
A12: EW11 | B12: External Works General Site Works | C12: Design and Build Shaded Car Parking of 20 numbers with Solar Panel Canopy | D12: Allow for the Contractor to design and build the Shaded Car Park for houses with Solar Panel Canopy as per Engineer Employer Instruction. | E12: no | F12: 20 | G12: 105 | H12: =F12*G12 -> 2100 | I12: STORM WATER BILL
A13: TOTAL EXTERNAL WORKS AND EXTERNAL SERVICES | G13: =SUM(H2:H12) -> 28455 | I13: =G13+'06 Storm Water'!G44 -> 28455

Sheet 05 Existing Housing Units-29
A1: Item Code | B1: Item Name | C1: Item Details | D1: Additional Information | E1: UOM | F1: Quantity | G1: Unit Price In Figure | H1: Total Price In Figure | I1: demolishing team | J1: Concret Team | K1: helper | L1: Masen | M1: Tielman | N1: draftsman | O1: Painter | P1: electrician | Q1: plumper | R1: steel man | S1: carpenter | T1: AC tec | U1: welder | V1: doorman | W1: windoman | X1: SS work | Y1: Solar | Z1: TV Dish
A2: EX1 | B2: External Works Lump sum | C2: Site Clearance | D2: Which shall include removing vegetation undergrowth bushes hedges trees or the like all complete item also Removal and disposal of surplus excavated material including providing suitable tip to the dumping yard or as specified and directed by the Engineer or local authorities.. | E2: Item | F2: 29 | G2: 304.5 | H2: =F2*G2 -> 8830.5 | I2: Yes | AA2: =SUM(H2:H9) -> 119059.5 | AB2: demolitios
A3: EX2 | B3: External Works Lump sum | C3: Demolishing | D3: demolishing all the structures and stores inside the boundary wall by preparing a sketch for each house and submitting to clients engineer and getting the written approval for demolishing and shifting the disposal material to damp yard including foundations of structres. | E3: Item | F3: 29 | G3: 514.5 | H3: =F3*G3 -> 14920.5 | I3: Yes | N3: Yes | AA3: =SUM(H2:H18) -> 452152.05 | AB3: till super structure
A4: EX3 | B4: External Works Lump sum | C4: Demolishing Rebuild | D4: demolishing and rebuilding as per the Same Specifications the gates columns damaged boundary wall damaged manholes damaged Holding Tanks damaged Sock Pits and change the cover to be GRP type Heavy duty and any other elements must be demolished to modified or rebuilt as per main scope all of this including and not limited to Excavation in any type of soil Disposal of surplus material filling by imported fill material compacted in layers waterproof concrete reinforcements joints block works polythene sheets anti termite manholes cover plastering PVC Pipes and any necessary work to finish the work in functional condition. | E4: Item | F4: 29 | G4: 619.5 | H4: =F4*G4 -> 17965.5 | I4: Yes | J4: Yes | L4: Yes | Q4: Yes
A5: EX4 | B5: External Works Lump sum | C5: boundary wall | D5: the contractor has to remove and demolish any damaged or unsafe parts of the wall and rebuild it with the same height after filling any cracks space between concreet and blockwork with non shirenkage filler with SS mesh between concrete and blocks and to remove all the paint or cladding and re paint again with external paint weather coat stoneshield with prime coat with 10 years garantee .all of this including and not limitted to to 200mm thick walls Polythene sheet gauge 1000 Waterproofing with two bitumen coats and membrane 4mm to surfaces of concreteProtection to concretemasonryblock work in contact with soil 3 coats approved bituminous paintExpansion joint | E5: Item | F5: 29 | G5: 619.5 | H5: =F5*G5 -> 17965.5 | I5: Yes | L5: Yes | O5: Yes
A6: EX5 | B6: External Works Lump sum | C6: GI gates | D6: remove the existing gates and supply and fix new gates GI and painted with marine paint as per the site conditions with warranty for the paint and gates for 10 years | E6: Item | F6: 29 | G6: 724.5 | H6: =F6*G6 -> 21010.5
A7: EX6 | B7: External Works Lump sum | C7: Pea Gravel around the house and inside the boundary wall | D7: the contractor has fill the full area with pea gravel with size between 20mm to 50mm max with depth 100 mm around the house detecting from it the manholes and holding tanks and sock pit only but it must be under the new caravans | E7: Item | F7: 29 | G7: 829.5 | H7: =F7*G7 -> 24055.5 | K7: Yes
A8: EX7 | B8: External Works Lump sum | C8: Dewatering | D8: Allow for keeping excavations free from underground surface or running water from whatever source | E8: Item | F8: 29 | G8: 252 | H8: =F8*G8 -> 7308 | Q8: Yes
A9: EX8 | B9: External Works Lump sum | C9: Gas Cylinder Room | D9: Contractor has to built a Gas Cylinder Room with RCC base and block work with height 1.5 m with concrete top slab with suitable foundation and safety gate that powder coated and painted with marine paint with warranty 10 years. | E9: Item | F9: 29 | G9: 241.5 | H9: =F9*G9 -> 7003.5 | L9: Yes
A10: C1 | B10: Super Structure Works Lump sum | C10: Demolishing the Existing staircase slab and reconstract it with Poured Concrete Reinforced insitu concrete poured vibrated Ordinary Portland Cement OPC concrete grade C35 all in accordance with the Drawings and Specifications including but not limited formwork reinforcement additives movement joints construction joints joint filler curing compounds surface finishes water stop wherever necessary concrete tests and any other accessories and ancillary work required to complete the work. | D10: RCC slabs RCC beams RCC Columns landingsstair etc. not exceeding 200 mm thickness at staircase head rooms. | E10: Item | F10: 29 | G10: 262.5 | H10: =F10*G10 -> 7612.5 | I10: Yes | J10: Yes | L10: Yes | O10: Yes | P10: Yes | R10: Yes | S10: Yes
A11: C2 | B11: Superstructure Works Thermal and Moisture Protection | C11: Removing Roof tiles and screed and waterproofing with cleaning the surfaces closing any cracks with chemical sealants and making the surface ready for receiving the new waterproofing. | D11: Demolishing the existing roof finish with waterproof and disposal the material and make the surface ready for receiving the new waterproofing | E11: Item | F11: 29 | G11: 1995 | H11: =F11*G11 -> 57855 | I11: Yes
A12: C3 | B12: Superstructure Works Thermal and Moisture Protection | C12: Roof screed lightweight concrete screed 1000 kgm3 minimum 50 mm thick to a maximum of 125 mm thick and Waterproofing with two bitumen coats and 4 mm thick torch applied acrylic polypropylene modified bitumen membrane with nonwoven polyester reinforcement and polyethylene film waterproof membrane including primer to roofs as per the manufacturer printed instructions complete as specified. Contractor to allow for 10 years guarantee and 24 hours flood test | D12: To roof decksRoof screed lightweight concrete screed 1000 kgm3 minimum 50 mm thick to a maximum of 125 mm thick and Waterproofing with two bitumen coats and 4mm thick membrane on flat surface laid to falls and cross falls | E12: Item | F12: 29 | G12: 3150 | H12: =F12*G12 -> 91350 | J12: Yes | L12: Yes
A13: C4 | B13: Superstructure Works Thermal and Moisture Protection | C13: Skirting 300 mm girth including turning into groove | D13: In up standsdrops and around parapet minimum 300 mm high including dressing over fillet grooves sealant tantalized batten etc. complete to roof deck | E13: Item | F13: 29 | G13: 1890 | H13: =F13*G13 -> 54810 | J13: Yes | L13: Yes
A14: C5 | B14: Superstructure Works Thermal and Moisture Protection | C14: Insulation Extruded high density polystyrene foam board insulation with rigid closed cell structure all in accordance with the specifications and drawings external | D14: to roof decks 50 mm thick laid on concrete spot bonded to waterproofing | E14: Item | F14: 29 | G14: 514.5 | H14: =F14*G14 -> 14920.5
A15: C6 | B15: Superstructure Works Thermal and Moisture Protection | C15: Roof Finishes | D15: Supply and fix 300 x 300 x 25 mm terrazzo tiles bedded on and including cement mortar screed to falls and cross falls jointed in cement mortar movements joints etc. complete to roof | E15: Item | F15: 29 | G15: 1995 | H15: =F15*G15 -> 57855 | M15: Yes
A16: C7 | B16: Superstructure Works Thermal and Moisture Protection | C16: Roof Finishes | D16: Supply and fix 100x20 mm terrazzo skirting to upstands | E16: Item | F16: 29 | G16: 892.5 | H16: =F16*G16 -> 25882.5 | M16: Yes | AA16: =H16+H13 -> 80692.5
A17: C8 | B17: Superstructure Works Thermal and Moisture Protection | C17: Roof Sundries | D17: Allow for Providing dressing around 110mm83mm UPVC rainwater outlets roof duct gargoyle extract fan soil and vent pipe | E17: Item | F17: 29 | G17: 481.95 | H17: =F17*G17 -> 13976.55 | M17: Yes | Q17: Yes
A18: C9 | B18: Superstructure Works Thermal and Moisture Protection | C18: Roof Sundries | D18: For parapet Allow for gun applied sealant to seal the joints and groove as applicable and as specified. | E18: Item | F18: 29 | G18: 304.5 | H18: =F18*G18 -> 8830.5 | M18: Yes
A19: C10 | B19: Superstructure Works Metal Works | C19: Staircase handrail | D19: Removing the old handrails and replacing them with 316 St.st handrails including supply and fix as per exixting desin hand rail in new houses drawings. | E19: Item | F19: 29 | G19: 1575 | H19: =F19*G19 -> 45675 | I19: Yes | X19: Yes | AA19: =H19+H20 -> 53287.5
A20: C11 | B20: Superstructure Works Metal Works | C20: galvanized steel cat Ladder | D20: Supply and install galvanized steel cat Ladder as specified and detailed on the drawingas per exixting desin hand rail in new houses drawings. | E20: Item | F20: 29 | G20: 262.5 | H20: =F20*G20 -> 7612.5 | U20: Yes
A21: C12 | B21: Superstructure Works Doors and Windows | C21: Wood Doors All Types and Size of doors including the main entrance door comprising profiled heads jambs frames subframes architraves beadings moldings plinth block ply linings infill panels mastic and other pointing fixings neoprene seal master lining and all ancillary items including fixing of ironmongery and final decoration for a complete installation ironmongery as specified in schedule and approved; fixed to hardwood All locks shall be 3 sets of keys Note to all stainless steel fittings shall be of 316 grade | D21: 1remove the Old doors and maintain the frame if possible and supply and fix wooden door with the same existing size and specification and new accessories.item include and not limited to maintain the existing frame and paint. | E21: Item | F21: 29 | G21: 9975 | H21: =F21*G21 -> 289275 | V21: Yes | AA21: =H21+H22+H23 -> 639450 | AB21: doors and windows
A22: C13 | B22: Superstructure Works Doors | C22: UPVC Doors | D22: The contractor to Replace all Wooden Doors for Toilets and Roof to be UPVC and to respect the following to: 1 Door sizes stated are structural opening size 2 Tenderers shall strictly follow the door size as per site conditions prior to pricing this section. No additional payments will be entertained due to failure or and misunderstanding by the tenderer. 3 Rate shall include for supply and fixing of new all necessary ironmongery as specified 4 Roof doors shall be airtight rubbersealed and weather resistant 5 Rate shall include final finishing and final decoration as per the specification drawings and schedule and to the approval of the Engineer | E22: Item | F22: 29 | G22: 3675.000 | H22: =F22*G22 -> 106575 | V22: Yes
A23: C14 | B23: Superstructure Works for Windows | C23: Aluminium windows | D23: The contractor is to Maintain the existing Aluminum Windows for and to respect the following to: 1 Windows sizes stated are structural opening size 2 Contractor shall strictly follow the Windows size as per site conditions prior to pricing this section. No additional payments will be entertained due to failure or and misunderstanding by the contractor. 3 Rate shall include for supply and fixing of new all necessary ironmongery as specified 4 Windows shall be airtight rubbersealed and weather resistant. 5 Rate shall include final finishing and final decoration as per the specification drawings and schedule and to the approval of the Engineer 6 The exterior glass is to be replaced with new 6 mm Reflected Glass and 6 mm smokey glass for toilets complete systems including all stiffeners fasteners sealants jointing and material thickness as required to form highquality systems in accordance with specifications. 7 Contractor to replace the Insect mesh to be aluminum type not metal. 8 the contractor is to replace any Aluminum section that could be totally damaged and can not be rectified. | E23: Item | F23: 29 | G23: 8400.000 | H23: =F23*G23 -> 243600 | W23: Yes
A24: C15 | B24: Superstructure Works Finishes | C24: Entrance Flooring | D24: Demolishing entrance flooring preparing the surface to receive marble tiles and supplying and fixing marble tiles for landing and stairs Tread and raiser for steps also skirting included with the same material.with supplying and fixing | E24: Item | F24: 29 | G24: 430.500 | H24: =F24*G24 -> 12484.5 | I24: Yes | M24: Yes
A25: C16 | B25: Superstructure Works Finishes | C25: Salah and Majles flooring | D25: Demolishing salah and Majles flooring preparing the surface to receive porcelain tiles and supplying and fixing porcelain tiles matching with existing floors also skirting included with the same material.with supplying and fixing | E25: Item | F25: 29 | G25: 472.500 | H25: =F25*G25 -> 13702.5 | I25: Yes | M25: Yes
A26: C17 | B26: Superstructure Works Finishes | C26: Kitchen and toilets flooring | D26: Demolishing Kitchen and toilets flooring preparing the surface to receive antislip ceramic tiles and supplying and fixing antislip ceramic tiles matching with existing floors.with supplying and fixing | E26: Item | F26: 29 | G26: 367.500 | H26: =F26*G26 -> 10657.5 | I26: Yes | M26: Yes
A27: C18 | B27: Superstructure Works Finishes | C27: Stairs Landing and steps | D27: Demolishing Stairs flooring preparing the surface to receive marble tiles and supplying and fixing marble tiles for landing and stairs Tread and raiser for steps also skirting included with the same material.with supplying and fixing | E27: Item | F27: 29 | G27: 682.500 | H27: =F27*G27 -> 19792.5 | I27: Yes | M27: Yes
A28: C19 | B28: Superstructure Works Finishes | C28: Internal Wall Finishes Scrap the existing paint repair the cracks fill the cracks and put SS mesh between concrete and block work and over the MEP pipes including PVC corner beads and expanded metal lath angle beads and plaster stops as specified. including decorative around the windows with internal Backgrounds Plaster cement and sand 1to3 internal To walls and columns on concrete block base internal for the damaged areas to receive INTERNAL Paint to walls of approved color over a coat of waterbased primer including preparation of surface by thorough cleaning and wetting and applying POP Gypsum powder putty as per manufacturer�s specification fully to give an even shade before painting and curing as per manufacturers specifications and as directed the paint should be antifungal growth and weather resistance. | D28: Prepare prime and apply one coat of primer and 2 coats of approved quality and color Painting and decoratingEligance marble paint with 10 years garantee all as specifiedto internally | E28: Item | F28: 29 | G28: 1260.000 | H28: =F28*G28 -> 36540 | L28: Yes | O28: Yes
A29: C20 | B29: Superstructure Works Finishes | C29: External Wall Finishes Scrap the existing paint repair the cracks fill the cracks and put SS mesh between concrete and block work and over the MEP pipes including PVC corner beads and expanded metal lath angle beads and plaster stops as specified. including decorative around the windows with internal Backgrounds Plaster cement and sand 1to3 External To walls and columns on concrete block base External for the damaged areas to receive three coats of heavy texture EXTERNAL walls and columns design and windows concrete frame and all mentioned areas at tender drawings of approved color over a coat of waterbased primer including preparation of surface by thorough cleaning and wetting and applying POP Gypsum powder putty as per manufacturer�s specification fully to give an even shade before painting and curing as per manufacturers specifications and as directed the paint should be antifungal growth and weather resistance | D29: Prepare prime and apply 3 coats of approved quality and color Decorative projection weather coat stoneshield with 10 years garantee as per the specificationsto Externally | E29: Item | F29: 29 | G29: 787.500 | H29: =F29*G29 -> 22837.5 | L29: Yes | O29: Yes
A30: C21 | B30: Superstructure Works Finishes | C30: Toilets and Kitchen wall Ceramic tiles | D30: Demolishing Kitchen and toilets walls tiles preparing the surface to receive glossy ceramic tiles with supplying and fixing | E30: Item | F30: 29 | G30: 735.000 | H30: =F30*G30 -> 21315 | I30: Yes | M30: Yes
A31: C22 | B31: Superstructure Works Finishes | C31: Ceilings Finishes Scrap the existing paint repair the cracks fill the cracks Painting and decorating internal Paint to walls of approved color over a coat of waterbased primer including preparation of surface by thorough cleaning and wetting and applying POP Gypsum powder putty as per manufacturer�s specification fully to give an even shade before painting and curing as per manufacturers specifications and as directed the paint should be antifungal growth and weather resistance. | D31: One coat Primertwo coats putty Three coats of Fenomastic Silk paint or equivalent on cement sand plaster. Colour as per Approval of Engineer | E31: Item | F31: 29 | G31: 945.000 | H31: =F31*G31 -> 27405 | L31: Yes | O31: Yes
A32: C23 | B32: Superstructure Works Finishes | C32: External Wall Finishes supply and fix Crazy Natural Stone with height 1.5 meter from external FFL | D32: Supply and fix Crazy Natural Stone or marble with a height 1.5 meters from External FFL | E32: Item | F32: 29 | G32: 1522.500 | H32: =F32*G32 -> 44152.5 | M32: Yes
A33: C24 | B33: Superstructure Works Finishes | C33: Remove the Existing and Allow for supply fabricate and installation of Kitchen Stage including Stage Concrete Stage Korean Top and Stage Area Ceramic Wall Tile as per the specifications drawings and to approval of the Engineer. | D33: Kitchen Stage Concrete Korean Top Ceramic Wall Tiles | E33: Item | F33: 29 | G33: 84.000 | H33: =F33*G33 -> 2436 | I33: Yes | L33: Yes | W33: Yes
A34: C25 | B34: Superstructure Works Finishes | C34: Remove the Existing and Allow for supply fabricate and installation of Kitchen Hood Range including Aluminum Kitchen Cabinet above and Aluminum Kitchen Cabinet below all as per the specifications drawings and to approval of the Engineer. | D34: Kitchen Hood Range Cabinet above and below Cabinet. | E34: Item | F34: 29 | G34: 84.000 | H34: =F34*G34 -> 2436 | I34: Yes | W34: Yes
A35: P1 | B35: Sanitary Installation | C35: The Contractor must remove all sanitary that were fixed | D35: The Contractor must remove all sanitary that were fixed at toilets and kitchens including but not limited to Wash basins EWC Mixers toilet accessories st st sink floor trap covers towel rails tissue holder �.. Etc and store it to handover to the client in clients storages. | E35: Item | F35: 29 | G35: 95.550 | H35: =F35*G35 -> 2770.95 | I35: Yes | Q35: Yes | AA35: =SUM(H35:H49) -> 7825.65 | AB35: SANITARY WARE ND INSTALLATION
A36: P2 | B36: Sanitary Installation | C36: UPVC pipes to BS 45141983 and BS 4660 1973 including all joints accessories and brackets | D36: Supply and install Vent cowl with weathering apron 75 mm diameter | E36: Item | F36: 29 | G36: 12.6 | H36: =F36*G36 -> 365.4 | Q36: Yes
A37: P3 | B37: Sanitary Installation | C37: Floor Drain trap | D37: Supply and install 110 mm diameter Floor Trap with 150 X 150 mm SS grating Cover including all UPVC and PVC pipes for water supply and drain with fittings and flexible pipes | E37: Item | F37: 29 | G37: 11.55 | H37: =F37*G37 -> 334.95 | Q37: Yes
A38: P4 | B38: Sanitary Installation | C38: Gully Trap | D38: Supply and install 300 mm x 300 mm gully trap of approx. 300 mm depth set in concrete Grade 30 Nmm� joints to drain pipes complete with 300 mm x 300 mm medium duty cast iron cover and frame. including all UPVC and PVC pipes for water supply and drain with fittings and flexible pipes | E38: Item | F38: 29 | G38: 12.6 | H38: =F38*G38 -> 365.4 | Q38: Yes
A39: P5 | B39: Sanitary Wares and Fittings | C39: Semi pedestal wash basin | D39: Supply and install 650 mm x 475 mm vitreous china white wash basin with semi pedestal center tap hole overflow and bottle trap. including all UPVC and PVC pipes for water supply and drain with fittings and flexible pipes including all UPVC and PVC pipes for water supply and drain with fittings and flexible pipes | E39: Item | F39: 29 | G39: 12.6 | H39: =F39*G39 -> 365.4 | Q39: Yes
A40: P6 | B40: Sanitary Wares and Fittings | C40: Stainless Steel Sink | D40: Supply and install 1000 mm x 550 mm stainless steel sink single bowl single drainer with drainboard to BS 1244 complete with 2 piece tubular P trap chain plug waste brackets. including all UPVC and PVC pipes for water supply and drain with fittings and flexible pipes | E40: Item | F40: 29 | G40: 23.1 | H40: =F40*G40 -> 669.9 | Q40: Yes
A41: P7 | B41: Sanitary Wares and Fittings | C41: European Water Closet | D41: Supply and install 400 mm x 685 mm vitreous china white concealed tank wall hung mounted EWC squatting pan built in wall toilet dual flush 3L6L concealed cistern and heavy duty auto closed seat and cover including all UPVC and PVC pipes for water supply and drain with fittings and flexible pipes | E41: Item | F41: 29 | G41: 13.65 | H41: =F41*G41 -> 395.85 | Q41: Yes
A42: P8 | B42: Sanitary Wares and Fittings | C42: shower tray | D42: Supply and install white glazed shower tray size 70x70 with the necessary fittings and plumbing darins including all UPVC and PVC pipes for water supply and drain with fittings and flexible pipes | E42: Item | F42: 29 | G42: 12.6 | H42: =F42*G42 -> 365.4 | Q42: Yes
A43: P9 | B43: Sanitary Wares and Fittings | C43: Ablution Faucet | D43: Chromium plated approved ablution faucet with angle valve hose and spray unit. including all UPVC and PVC pipes for water supply and drain with fittings and flexible pipes | E43: Item | F43: 29 | G43: 13.65 | H43: =F43*G43 -> 395.85 | Q43: Yes
A44: P10 | B44: Sanitary Wares and Fittings | C44: shower Mixer | D44: Single lever chrome plated shower mixer including Rainshower rail set with its hand shower. including all UPVC and PVC pipes for water supply and drain with fittings and flexible pipes | E44: Item | F44: 29 | G44: 12.6 | H44: =F44*G44 -> 365.4 | Q44: Yes
A45: P11 | B45: Sanitary Wares and Fittings | C45: Wash Basin Mixer | D45: Single lever chrome plated wash basin mixer including pop up waste. including all UPVC and PVC pipes for water supply and drain with fittings and flexible pipes | E45: Item | F45: 29 | G45: 9.45 | H45: =F45*G45 -> 274.05 | Q45: Yes
A46: P12 | B46: Sanitary Wares and Fittings | C46: Sink Mixer | D46: Single lever chrome plated Sink mixer. including all UPVC and PVC pipes for water supply and drain with fittings and flexible pipes | E46: Item | F46: 29 | G46: 9.45 | H46: =F46*G46 -> 274.05 | Q46: Yes
A47: P13 | B47: Sanitary Wares and Fittings | C47: Toilet tissue holder | D47: Recessed type stainless steel Toilet tissue dispenser holder with stainless steel hood. | E47: Item | F47: 29 | G47: 9.45 | H47: =F47*G47 -> 274.05 | Q47: Yes
... A49: P15 | B49: Sanitary Wares and Fittings | C49: Mirror | D49: 450 x 600 mm mirror 6 mm thick bevel edged plywood backing fixed with chromium plated dome headed screws | E49: Item | F49: 29 | G49: 12.6 | H49: =F49*G49 -> 365.4 | Q49: Yes
A50: P16 | B50: Water Supply | C50: Polypropylene random copolymer pipe | D50: contractor to check the pressure of the cold and hot water at each house and to replace the damaged or leacked pipes after removing the tiles floor wall and refix the tiles again with similar or with new the Polypropylene random copolymer pipes and fittings cold and hot water connections to international standard ISOto EN ISO 15874 to 2003 and DIN 80777 8078 including up stand and brackets exposed insulation as per Specificationall the pipes as per the original sizes. | E50: Item | F50: 29 | G50: 8.4 | H50: =F50*G50 -> 243.6 | Q50: Yes | AA50: =H50+H51+H52+H53+H54+H55+H56 -> 4952.85 | AB50: water supply
A51: P17 | B51: Water Supply | C51: Cold and Hot water Valves | D51: Supply and install the following Isolating valves to BS 5154 series B bronze wedge gate pattern screwed joints with adaptor to pipes etc. wherever shown in drawings and or specified and as approved by the Engineer.all the Valves as per the original sizes. | E51: Item | F51: 29 | G51: 9.45 | H51: =F51*G51 -> 274.05 | Q51: Yes
A52: P18 | B52: Water Supply | C52: The Contractor must remove all Equipment and Accessories that were fixed | D52: The Contractor must remove all Equipment and accessories that were fixed at houses including but not limited to GRP Water Tanks water Heater �.. Etc and store it to hand over to the client in the clients storage. | E52: Item | F52: 32 | G52: 8.4 | H52: =F52*G52 -> 268.8 | P52: Yes | Q52: Yes
A53: P19 | B53: Water Supply | C53: Water Tank | D53: Supply and install 400US gallon capacity GRP type water storage tank with foundation epoxy coated frame ball valve overflows etc. to approval | E53: Item | F53: 32 | G53: 47.25 | H53: =F53*G53 -> 1512 | Q53: Yes
A54: P20 | B54: Water Supply | C54: Water Heater | D54: Supply and install 50 liter capacity horizontal type copper tank high level wall mounted electrical water heater including all connections and fixing. | E54: Item | F54: 32 | G54: 27.3 | H54: =F54*G54 -> 873.6 | Q54: Yes
A55: P21 | B55: Rain Water Installation | C55: Rain Water UPVC Pipeswith outlet | D55: remove the existing and Supply and install UPVC pipes to BS 4514 1983 including all joints fittings accessories connections and brackets | E55: Item | F55: 32 | G55: 29.4 | H55: =F55*G55 -> 940.8 | Q55: Yes
A56: P22 | B56: Rain Water Installation | C56: TAP AND ABLUTION FAUCET | D56: Construct a 60x120x40 Ablution base by Solid Block with RCC base and finished from all side with anti slip ceramic including the mixer subject to the engineers and client approval | E56: Item | F56: 32 | G56: 26.25 | H56: =F56*G56 -> 840 | L56: Yes | Q56: Yes
A57: M1 | B57: Air Conditioning and Ventilation Installation | C57: The Contractor must remove all Equipment and Accessories that were fixed | D57: The Contractor must remove all Equipment and accessories that were fixed at houses including but not limited to AC units indoor outdoor�.. Etc and store it to hand over to the client in the clients storage. | E57: Item | F57: 32 | G57: 23.1 | H57: =F57*G57 -> 739.2 | I57: Yes | P57: Yes | AA57: =H57+H58+H59+H60+H61 -> 17875.2 | AB57: AC
A58: M2 | B58: Air Conditioning and Ventilation Installation | C58: High level Wall mounted Split AC with DX unit replacing the box type at walls | D58: Contractor ro remove the existing AC at walls and to close the walls and make plaster with st st mesh and painting after that to fix 18000 BTUHR capacity highlevel wall mounted split type air conditioner including connection to electrical outlet and concrete base foundation and AC drain pipes to gully trap. | E58: Item | F58: 32 | G58: 21 | H58: =F58*G58 -> 672 | L58: Yes | P58: Yes | Q58: Yes | T58: Yes
A59: M3 | B59: Air Conditioning and Ventilation Installation | C59: High level Wall mounted Split AC with DX unit for Kitchen | D59: 18000 BTUHR capacity highlevel wall mounted split type air conditioner including connection to electrical outlet and concrete base foundation and AC drain pipes to gully trap. | E59: Item | F59: 32 | G59: 220.5 | H59: =F59*G59 -> 7056 | L59: Yes | P59: Yes | Q59: Yes | T59: Yes
A60: M4 | B60: Air Conditioning and Ventilation Installation | C60: High level Wall mounted Split AC with DX unit for salah and majles | D60: 30000 BTUHR capacity highlevel wall mounted split type air conditioner including connection to electrical outlet and concrete base foundation and AC drain pipes to gully trap. | E60: Item | F60: 32 | G60: 252 | H60: =F60*G60 -> 8064 | L60: Yes | P60: Yes | Q60: Yes | T60: Yes
A61: M5 | B61: Air Conditioning and Ventilation Installation | C61: Ventilating Fans | D61: remove the existing and Supply and install test and commission ventilating fan 6 and 8 with electrically operated louvers as specified on the drawings complete with all mounting requirements flexible connections electrical connections support backdraft dampers auto changeover controller all in accordance with the specification | E61: Item | F61: 32 | G61: 42 | H61: =F61*G61 -> 1344 | P61: Yes
A62: E1 | B62: Electrical Engineering Installation | C62: Distribution Board | D62: the Contractor must check the Power supply distribution copper cable with earth continuity cable Rate should cover related accessories jointing glanding earthing tag termination legs PVA shrowds and cable tag for interconnecting cables cable trays cable identification cable route marker from substation to the switches and sockets and in between subboards and distribution panels and change any defected item to have the system working in functional conditions | E62: Item | F62: 32 | G62: 42 | H62: =F62*G62 -> 1344 | P62: Yes | AA62: =SUM(H62:H91) -> 47006.4 | AB62: ELECTRICAL
A63: E2 | B63: Electrical Engineering Installation | C63: Contractor to provide full Solar system | D63: The contractor to Design and Provide the solar system including all materials and supply and fix it to be compatible with the MCCP and DBs at the houses and get the approvals from the ClientEngineer before executing any work | E63: Item | F63: 32 | G63: 0 | H63: =F63*G63 -> 0 | P63: Yes | Y63: Yes
A64: E3 | B64: Electrical Engineering Installation | C64: Sub Main Distribution Board | D64: the Contractor to replace the existing with new weatherproof GRP IP 65 Main or Sub Main Distribution panel board including MCCBs supports earthing cable glands Ammeters Voltmeters internal wiring interconnection and labels as per drawings and specification | E64: Item | F64: 32 | G64: 48.3 | H64: =F64*G64 -> 1545.6 | P64: Yes
A65: E4 | B65: Electrical Engineering Installation | C65: Sub Main Distribution Board | D65: The contractor to replace the existing DBs with new weatherproof GRP IP 65 for all the DBs at the houses. | E65: Item | F65: 32 | G65: 57.75 | H65: =F65*G65 -> 1848 | P65: Yes
A66: E5 | B66: Electrical Engineering Installation | C66: Sub Main Distribution Board | D66: The contractor to add a new DB for the New Caravans to be weatherproof GRP IP 65 . | E66: Item | F66: 32 | G66: 56.7 | H66: =F66*G66 -> 1814.4 | P66: Yes
A67: E6 | B67: Electrical Engineering Installation | C67: Small Power Accessories removing | D67: the Contractor to replace the existing with new switches and sockets and the existing to be handover to client at his storage at end of the project. | E67: Item | F67: 32 | G67: 6.3 | H67: =F67*G67 -> 201.6 | P67: Yes
A68: E7 | B68: Electrical Engineering Installation | C68: Small Power Accessories Installation | D68: the Contractor to replace the existing with new 13A DP single switched socket outlet | E68: Item | F68: 32 | G68: 47.25 | H68: =F68*G68 -> 1512 | P68: Yes
A69: E8 | B69: Electrical Engineering Installation | C69: Small Power Accessories Installation | D69: the Contractor to replace the existing with new 13A DP twin switched socket outlet | E69: Item | F69: 32 | G69: 10.5 | H69: =F69*G69 -> 336 | P69: Yes
A70: E9 | B70: Electrical Engineering Installation | C70: Small Power Accessories Installation | D70: the Contractor to replace the existing with new 13A DP single gang weatherproof switch socket outlet | E70: Item | F70: 32 | G70: 11.55 | H70: =F70*G70 -> 369.6 | P70: Yes
A71: E10 | B71: Electrical Engineering Installation | C71: Small Power Accessories Installation | D71: the Contractor to replace the existing with new 20A Dp switch outlet | E71: Item | F71: 32 | G71: 577.5 | H71: =F71*G71 -> 18480 | P71: Yes
A72: E11 | B72: Electrical Engineering Installation | C72: Small Power Accessories Installation | D72: the Contractor to replace the existing with new two way two gang | E72: Item | F72: 32 | G72: 25.2 | H72: =F72*G72 -> 806.4 | P72: Yes
A73: E12 | B73: Electrical Engineering Installation | C73: Small Power Accessories Installation | D73: the Contractor to replace the existing regulator for the ceiling fans | E73: Item | F73: 32 | G73: 27.3 | H73: =F73*G73 -> 873.6 | P73: Yes
A74: E13 | B74: Electrical Engineering Installation | C74: Small Power Lighting Fixture removing | D74: the Contractor to replace the existing with new Lighting Fixture inside and out side and celing fans such as including lamps electronic ballasts control gearwirescables and all necessary accessories and the existing to be handover to client at his storage at end of the project. | E74: Item | F74: 32 | G74: 26.25 | H74: =F74*G74 -> 840 | P74: Yes
A75: E14 | B75: Electrical Engineering Installation | C75: Lighting Fixture | D75: Supply install connect test and commissioning of the following lighting fixtures including lamps electronic ballasts control gearwirescables and all necessary accessories complete as specified and as shown on the drawingsto | E75: Item | F75: 32 | G75: 157.5 | H75: =F75*G75 -> 5040 | P75: Yes
... A88: E27 | B88: Electrical Engineering Installation | C88: Earthing Installation | D88: Supply install NEW Earthing system including 16 mm dia. high conductivity solid copper rod electrodes with drive head assemblies and Earthing clamps for earth pits Earthing of exposed pipe work sanitary fittings and equipment all as required including 300 x 300 x 400 mm deep internally earth pit earth wires as per specification and drawings complete with 300 mm x 300 mm medium duty double seal cast iron cover and frame. | E88: Item | F88: 32 | G88: 26.25 | H88: =F88*G88 -> 840 | P88: Yes
A89: E28 | B89: Electrical Engineering Installation | C89: TV Points and Dish Installation | D89: Supply install NEW TV Satellite system all Data Cable with the dish above the roof and the concrete base and to connect it to the existing TV points all in functional conditions. | E89: Item | F89: 32 | G89: 47.25 | H89: =F89*G89 -> 1512 | P89: Yes | Z89: Yes
A90: G1 | B90: Sundrie | C90: Sundrie Items | D90: Any other works not specifically enumerated under the works in this bill but indicated in the drawings or required to complete the work in manner of respect to handover the project in working and safe conditions to the residents specification or needed to complete the work. | E90: Item | F90: 32 | G90: 47.25 | H90: =F90*G90 -> 1512
A91: G2 | B91: Sundrie | C91: Sundrie Items | D91: if any works was miss matching with any part of this tender documents the contractor must raise his queries during tender period and by submitting the offer the contractor confirming that every points was clear for him and confirming that is included at his price and no variation will be accepted | E91: Item | F91: 32 | G91: 47.25 | H91: =F91*G91 -> 1512
A92: TOTAL EXISTING HOUSING UNITS 29 NOS | G92: =SUM(H2:H91) -> 1436308.7 | H92: =SUM(H2:H91) -> 1436308.7

Sheet 06 Storm Water
A1: Item Code | B1: Item Name | C1: Item Details | D1: Additional Information | E1: UOM | F1: Quantity | G1: Unit Price In Figure | H1: Total Price In Figure
A2: PSW1 | B2: 1 Conditions of Contract | C2: Flood Protection and Strom Water Drainage Systems. Note | D2: The contractor is deemed to have carefully studied and understood and taken into account the provisions and requirements of the General Conditions of Contract. The rates and prices stated in the Bill of Quantities shall include for all costs of compliance with the conditions. Reconstruct the new flood protection system as per the specification and drawing and not allowed to remove or demolish the existing system before constructing the new system. | E2: Item | F2: 0 | G2: 0 | H2: =F2*G2 -> 0 | I2: =SUM(H2:H25) -> 232396.5
A3: PSW2 | B3: Conditions of Contract | C3: Flood Protection and Strom Water Drainage Systems.Note | D3: The contractor must refer to Oman Highway Design Standards 2017 for Specifications and Details. | E3: Item | F3: 0 | G3: 0 | H3: =F3*G3 -> 0
A4: PSW2 | B4: 2 Earthwork | C4: Earthwork Excavation .Note | D4: All the Levels taken from Architecture Zero Level and the Contractor must submit the Quantities based on approved topographical survey. | E4: Item | F4: 0 | G4: 0 | H4: =F4*G4 -> 0
A5: PSW3 | B5: Earthwork | C5: Earthwork Excavation .Note | D5: Rate to include for excavation for all leads & lift loading unloading & double handling where required necessary equipments tools & plants dressing the excavation to proper level and grade as required dumping the soil in the designated area approved by the Authorities taking necessary precautions to prevent any spillages or spoiling of the premises public roads during removal & transporting the soil all consumables including protecting the sides of excavation as per the the nature of site soil condition and safety of excavation etc complete as directed. | E5: Item | F5: 0 | G5: 0 | H5: =F5*G5 -> 0
A6: PSW4 | B6: Earthwork | C6: Excavation for Structures Trenches | D6: Unclassified structural excavation Depth 0 to required depth as per drawings Excavation by mechanical means using excavators JCB Porcelains etc. in soil any type to the required level for foundation excavation. Including soft rock and hard rock and any remaining material or elements for the existing building. Dispose of excavated material offsite by mechanical means as directed to the approval of the Client and consultant. Disposal is not measured separately mass excavation must be done. | E6: m3 | F6: 111780 | G6: 1.05 | H6: =F6*G6 -> 117369 | I6: 117369
A7: PSW5 | B7: Earthwork | C7: Backfilling for Structures trenches . Note | D7: Rate shall include for loading unloading transportation hire and fuel charges for tools and plants employed and other incidental charges etc. complete and as directed. | E7: Item | F7: 0 | G7: 0 | H7: =F7*G7 -> 0
A8: PSW6 | B8: Earthwork | C8: Backfilling for Structures trenches.Note | D8: Supplying and filling in foundations and the area wherever required below ground level with the approved by Consultant material brought from outside other approved filling materials like river sand in layers not exceeding 150 mm thickness including mixing spreading levelling watering and consolidating each layer with power hand roller of required capacity to obtain required proctor density as per specification etc. all complete and as directed. | E8: Item | F8: 0 | G8: 0 | H8: =F8*G8 -> 0
A9: PSW7 | B9: Earthwork | C9: Backfilling for Structures trenches.Note | D9: Approved imported fill material in making up level compacted in layers planting and execute pit including but not limited to: | E9: Item | F9: 0 | G9: 0 | H9: =F9*G9 -> 0
A10: PSW8 | B10: Earthwork | C10: Backfilling for Structures trenches | D10: Backfilling | E10: m3 | F10: 38975 | G10: 0.525 | H10: =F10*G10 -> 20461.875 | I10: 20461.875
A11: PSW9 | B11: Earthwork | C11: Earthwork for Pipe Trenches | D11: Trench excavation and backfilling Depth 0 to 2m | E11: m3 | F11: 9180 | G11: 0.7 | H11: =F11*G11 -> 6426 | I11: =H11+H12+H13+H14 -> 49919.625
A12: PSW10 | B12: Earthwork | C12: Earthwork for Pipe Trenches | D12: Trench excavation and backfilling 2m to 3m | E12: m3 | F12: 12615 | G12: 1.575 | H12: =F12*G12 -> 19868.625
A13: PSW11 | B13: Earthwork | C13: Earthwork for Pipe Trenches | D13: Trench excavation and backfilling 3m to 4m | E13: m3 | F13: 3090 | G13: 2.1 | H13: =F13*G13 -> 6489
A14: PSW12 | B14: Earthwork | C14: Earthwork for Pipe Trenches | D14: Trench excavation and backfilling Depth more than 4m | E14: m3 | F14: 4080 | G14: 4.2 | H14: =F14*G14 -> 17136
A15: PSW13 | B15: 3 Granular Subbase Aggregate Base Course and Stabilized Base Courses. | C15: Redesign and Construction of Asphalt Road to be suitable for Erection of Culvert with all necessary drawings details… | D15: Aggregate Base Course Class B | E15: m3 | F15: 1500 | G15: 2.1 | H15: =F15*G15 -> 3150 | I15: 3150
A16: PSW14 | B16: 4 Bituminous Pavement | C16: Redesign and Construction of Asphalt Road to be suitable for Erection of Culvert with all necessary drawings details… | D16: Bituminous Prime Coat Application rate 1.5 KgSq.m | E16: m3 | F16: 4050 | G16: 2.1 | H16: =F16*G16 -> 8505 | I16: 8505
A17: PSW15 | B17: Asphalt Road | C17: Redesign and Construction of Asphalt Road to be suitable for Erection of Culvert with all necessary drawings details… | D17: Bituminous Wearing Course Class B | E17: m3 | F17: 280 | G17: 12.6 | H17: =F17*G17 -> 3528 | I17: 3528
A18: PSW16 | B18: 5 Concrete and Concrete Structures | C18: Construction of Box culvert N2 Size 2x1.5m concrete class 30 with reinforcement as per HDS 2017 including wing wall foundations bituminous paint excavation backfilling and as directed by Engineer | D18: Concrete Materials and Mixes Note | E18: Item | F18: 0 | G18: 0 | H18: =F18*G18 -> 0
A19: PSW17 | B19: Concrete and Concrete Structures | C19: Construction of Box culvert N2 Size 2x1.5m concrete class 30 with reinforcement as per HDS 2017 including wing wall foundations bituminous paint excavation backfilling and as directed by Engineer | D19: Concrete Class 15 in foundations. | E19: m3 | F19: 130 | G19: 13.65 | H19: =F19*G19 -> 1774.5 | I19: 1774.5
A20: PSW18 | B20: Concrete and Concrete Structures | C20: Construction of Box culvert N2 Size 2x1.5m concrete class 30 with reinforcement as per HDS 2017 including wing wall foundations bituminous paint excavation backfilling and as directed by Engineer | D20: Concrete Class 35 in box culverts wing walls apron slab retaining walls and debris foundations. | E20: m3 | F20: 375 | G20: 12.6 | H20: =F20*G20 -> 4725 | I20: 4725
A21: PSW19 | B21: Concrete and Concrete Structures | C21: Construction of Box culvert N2 Size 2x1.5m concrete class 30 with reinforcement as per HDS 2017 including wing wall foundations bituminous paint excavation backfilling and as directed by Engineer | D21: Reinforcing Steel Note | E21: Item | F21: 0 | G21: 0 | H21: =F21*G21 -> 0
A22: PSW20 | B22: Concrete and Concrete Structures | C22: Construction of Box culvert N2 Size 2x1.5m concrete class 30 with reinforcement as per HDS 2017 including wing wall foundations bituminous paint excavation backfilling and as directed by Engineer | D22: High tensile steel bar factory epoxy coated reinforcement of any diameter | E22: Ton | F22: 55 | G22: 94.5 | H22: =F22*G22 -> 5197.5 | I22: 5197.5
A23: PSW21 | B23: Concrete and Concrete Structures | C23: Construction of Box culvert N2 Size 2x1.5m concrete class 30 with reinforcement as per HDS 2017 including wing wall foundations bituminous paint excavation backfilling and as directed by Engineer | D23: Waterproofing for Structures Note | E23: Item | F23: 0 | G23: 0 | H23: =F23*G23 -> 0
A24: PSW22 | B24: Concrete and Concrete Structures | C24: Construction of Box culvert N2 Size 2x1.5m concrete class 30 with reinforcement as per HDS 2017 including wing wall foundations bituminous paint excavation backfilling and as directed by Engineer | D24: Tar or bituminous paint Type II 2 coats for surfaces in contact with earth in all structures | E24: m2 | F24: 1420 | G24: 1.05 | H24: =F24*G24 -> 1491 | I24: 1491
A25: PSW23 | B25: Concrete and Concrete Structures | C25: Construction of Box culvert N2 Size 2x1.5m concrete class 30 with reinforcement as per HDS 2017 including wing wall foundations bituminous paint excavation backfilling and as directed by Engineer | D25: Membrane Waterproofing Geotextile 4mm thickness | E25: m2 | F25: 15500 | G25: 1.05 | H25: =F25*G25 -> 16275
A26: PSW24 | B26: Drainage | C26: Storm Sewer | D26: Item includes and not limited to 200mm aggregateSand bed and aggregatesand surrounding 200 mm of pipe crown fixing with approved slop and concrete fixing for pipe fron middel end and crawn testing flexable joint rocker piece giotextile membrane surrounding including proper reinstatement with concrete or interlock or asphalt above the compacted surface in the existing route or new route etc. | E26: Item | F26: 0 | G26: 0 | H26: =F26*G26 -> 0 | I26: =SUM(H26:H43) -> 33278.175
A27: PSW25 | B27: Drainage | C27: Storm Sewer | D27: Storm Sewer GRP Diameter 300mm | E27: m | F27: 315 | G27: 3.15 | H27: =F27*G27 -> 992.25
A28: PSW26 | B28: Drainage | C28: Storm Sewer | D28: Storm Sewer GRP Diameter 400mm | E28: m | F28: 1270 | G28: 2.1 | H28: =F28*G28 -> 2667
A29: PSW27 | B29: Drainage | C29: Storm Sewer | D29: Storm Sewer GRP Diameter 500mm | E29: m | F29: 345 | G29: 1.575 | H29: =F29*G29 -> 543.375
A30: PSW28 | B30: Drainage | C30: Storm Sewer | D30: Storm Sewer R.C Diameter 600mm | E30: m | F30: 865 | G30: 1.575 | H30: =F30*G30 -> 1362.375
A31: PSW29 | B31: Drainage | C31: Storm Sewer | D31: Storm Sewer R.C Diameter 700mm | E31: m | F31: 1090 | G31: 2.1 | H31: =F31*G31 -> 2289
A32: PSW30 | B32: Drainage | C32: Storm Sewer | D32: Storm Sewer R.C Diameter 800mm | E32: m | F32: 460 | G32: 2.1 | H32: =F32*G32 -> 966
A33: PSW31 | B33: Drainage | C33: Storm Sewer | D33: Storm Sewer R.C Diameter 900mm | E33: m | F33: 130 | G33: 3.15 | H33: =F33*G33 -> 409.5
A34: PSW32 | B34: Drainage | C34: Storm Sewer | D34: Storm Sewer R.C Diameter 1200mm | E34: m | F34: 490 | G34: 3.15 | H34: =F34*G34 -> 1543.5
A35: PSW33 | B35: Drainage | C35: Manholes Inlets and Chambers Note | D35: Item includes MH double seal cover DI heavy duty with lock water proofing and as per detailed drawings Note | E35: Item | F35: 0 | G35: 0 | H35: =F35*G35 -> 0
A36: PSW34 | B36: Drainage | C36: Manholes Inlets and Chambers | D36: R.C Manholes Chamber Ring Dia. 1200mm Type A | E36: No | F36: 48 | G36: 3.15 | H36: =F36*G36 -> 151.2
A37: PSW35 | B37: Drainage | C37: Manholes Inlets and Chambers | D37: R.C Manholes Chamber Ring Dia. 1500mm Type A | E37: No | F37: 21 | G37: 4.2 | H37: =F37*G37 -> 88.2
A38: PSW36 | B38: Drainage | C38: Manholes Inlets and Chambers | D38: R.C Manholes Chamber Ring Dia. 2000mm Type A | E38: No | F38: 9 | G38: 4.2 | H38: =F38*G38 -> 37.8
... A43: PSW41 | B43: Slope Protection and Stabilization | C43: Existing Dyke Improvement: | D43: Remove the existing dyke use the suitable backfilling and compact in the new place in layers as per Oman specifications shift not suitable existing backfilling materials to damp yard etc. | E43: Item | F43: 1 | G43: 52.5 | H43: =F43*G43 -> 52.5
A44: TOTAL PROTECTION AND STORM WATER DRAINAGE SYSTEM | H44: =SUM(H2:H43) -> 265674.67

Sheet 07  Housing Units 3 Nos
A1: Item Code | B1: Item Name | C1: Item Details | D1: Additional Information | E1: UOM | F1: Quantity | G1: Unit Price In Figure | H1: Total Price In Figure
A2: C1 | B2: General Works | C2: Demolishing and Clearing the Construction Area. | D2: Demolishing the complete buildings up to foundations and removing the debris from the Construction Site as per Engineer/Employer Instruction (including cart-away from the Project Site) | E2: LS | F2: 1 | G2: 2000 | H2: =F2*G2 -> 2000
A3: C2 | B3: Substructure Works | C3: Site Clearance | D3: This shall include removing vegetation, undergrowth, bushes, hedges, trees, other temporary buildings, structures,... or the like all complete to clean the full plot. | E3: LS | F3: 1 | G3: 1000 | H3: =F3*G3 -> 1000
A4: C3 | B4: Substructure Works | C4: Earth work and Excavation | D4: Bulk Excavation to receive foundations in any kind of soil including hard soil and rock, earth sport, underground, surface or running water from whatever source if any, for the new foundation building area including removal of old buildings' foundations, cleaning the site, and removing all debris (not suitable for backfilling) from the project area to the damp yard, contractor to prepare all areas to receive new foundation safely as per drawings and soil report | E4: M3 | F4: 350 | G4: 0.8 | H4: =F4*G4 -> 280
A5: C4 | B5: Substructure Works | C5: Filling | D5: Approved imported granular fill material compacted in layers in making up levels in the excavation area of the demolished buildings from foundation level up to levels on site plan. | E5: M3 | F5: 400 | G5: 0.5 | H5: =F5*G5 -> 200
A6: C5 | B6: Substructure Works | C6: Filling | D6: Approved imported fill material compacted in layers to raise the levels | E6: M3 | F6: 200 | G6: 0.5 | H6: =F6*G6 -> 100
A7: C6 | B7: Substructure Works | C7: Filling | D7: Approved, selected excavated material backfilled into excavations | E7: M3 | F7: 350 | G7: 0.5 | H7: =F7*G7 -> 175
A8: C7 | B8: Substructure Works | C8: Filling | D8: 200 mm thick well compacted hardcore filling under floors | E8: M3 | F8: 35 | G8: 0.5 | H8: =F8*G8 -> 17.5
A9: C8 | B9: Substructure Works | C9: Anti-termite treatment | D9: Anti-termite treatment to surfaces of ground or filling applied strictly in accordance with the manufacturers printed instructions including digging trenches, backfilling, etc. as required by the manufacturer and the provision of guarantee valid for 10 years | E9: M2 | F9: 150 | G9: 1.5 | H9: =F9*G9 -> 225
A10: C9 | B10: Substructure Works | C10: Poured Concrete - Plain insitu concrete, poured ordinary Portland Cement (OPC), concrete grade (C15), all in accordance with Drawings and Specifications and including Formwork to give (as struck) finish - Providing and erecting formwork including all necessary staging, centering, shuttering, supports, cross bracing, de-shuttering carefully, making good the damaged surfaces wherever necessary, all complete as specified and as directed by the Engineer all in accordance with the Drawings and Specifications | D10: Blinding upto 100 mm thickness for the full area under the boundary of foundation. | E10: M3 | F10: 17.5 | G10: 45 | H10: =F10*G10 -> 787.5
A11: C10 | B11: Substructure Works | C11: Reinforced insitu concrete, poured vibrated Sulphate Resistent Cement (OPC), concrete grade (C30), all in accordance with Drawings and Specifications and including Reinforcement - High yield strength deformed bars, conforming to BS 4449 (grade 460) including cutting, bending, binding, binding wire, cover blocks, tests and all necessary fixing accessories, all in accordance with the Drawings and Specifications and including Formwork to give (as struck) finish - Providing and erecting formwork including all necessary staging, centering, shuttering, supports, cross bracing, de-shuttering carefully, making good the damaged surfaces wherever necessary, all complete as specified and as directed by the Engineer all in accordance with the Drawings and Specifications | D11: Footings | E11: M3 | F11: 45 | G11: 50 | H11: =F11*G11 -> 2250
A12: C11 | B12: Substructure Works | C12: Reinforced insitu concrete, poured vibrated Sulphate Resistent Cement (OPC), concrete grade (C30), all in accordance with Drawings and Specifications and including Reinforcement - High yield strength deformed bars, conforming to BS 4449 (grade 460) including cutting, bending, binding, binding wire, cover blocks, tests and all necessary fixing accessories, all in accordance with the Drawings and Specifications and including Formwork to give (as struck) finish - Providing and erecting formwork including all necessary staging, centering, shuttering, supports, cross bracing, de-shuttering carefully, making good the damaged surfaces wherever necessary, all complete as specified and as directed by the Engineer all in accordance with the Drawings and Specifications | D12: Plinth beams | E12: M3 | F12: 14 | G12: 50 | H12: =F12*G12 -> 700
A13: C12 | B13: Substructure Works | C13: Reinforced insitu concrete, poured vibrated Sulphate Resistent Cement (OPC), concrete grade (C30), all in accordance with Drawings and Specifications and including Reinforcement - High yield strength deformed bars, conforming to BS 4449 (grade 460) including cutting, bending, binding, binding wire, cover blocks, tests and all necessary fixing accessories, all in accordance with the Drawings and Specifications and including Steel fabric reinforcement, A-393 BRC mesh in two layers. All complete in accordance with the Drawings and Specifications and including Formwork to give (as struck) finish - Providing and erecting formwork including all necessary staging, centering, shuttering, supports, cross bracing, de-shuttering carefully, making good the damaged surfaces wherever necessary, all complete as specified and as directed by the Engineer all in accordance with the Drawings and Specifications | D13: Beds (Slabs, Grade slabs) upto 200 mm thickness | E13: M3 | F13: 30 | G13: 50 | H13: =F13*G13 -> 1500
... A50: C49 | B50: Superstructure Works Doors and Windows | C50: WPC Solid Core Doors -Door comprising profiled heads, jambs, frames, subframes, architraves, beadings, moldings, plinth block, ply linings, infill panels, mastic and other pointing, fixings, neoprene seal master lining and all ancillary items including fixing of ironmongery and final decoration for a complete installation all as specified and as detailed on drawing including required reinforcement cement concrete lintels and including Supply and fix ironmongery as specified in schedule and approved; fixed to hardcore, including paint and 10 years guarantee (All locks shall be under master key system) as detailed on drawing Note: all stainless steel fittings shall be of 316-grade | D50: Type D2, single leaf, overall size 1000x2500mm high | E50: Item | F50: 1 | G50: 400 | H50: =F50*G50 -> 400
A51: C50 | B51: Superstructure Works Doors and Windows | C51: WPC Solid Core Doors -Door comprising profiled heads, jambs, frames, subframes, architraves, beadings, moldings, plinth block, ply linings, infill panels, mastic and other pointing, fixings, neoprene seal master lining and all ancillary items including fixing of ironmongery and final decoration for a complete installation all as specified and as detailed on drawing including required reinforcement cement concrete lintels and including Supply and fix ironmongery as specified in schedule and approved; fixed to hardcore, including paint and 10 years guarantee (All locks shall be under master key system) as detailed on drawing Note: all stainless steel fittings shall be of 316-grade | D51: Type D3, single leaf, overall size 1000x2100mm high | E51: Item | F51: 1 | G51: 400 | H51: =F51*G51 -> 400 | I51: =SUM(H2:H51) -> 25875
A52: C51 | B52: Superstructure Works Doors and Windows | C52: WPC Solid Core Doors -Door comprising profiled heads, jambs, frames, subframes, architraves, beadings, moldings, plinth block, ply linings, infill panels, mastic and other pointing, fixings, neoprene seal master lining and all ancillary items including fixing of ironmongery and final decoration for a complete installation all as specified and as detailed on drawing including required reinforcement cement concrete lintels and including Supply and fix ironmongery as specified in schedule and approved; fixed to hardcore, including paint and 10 years guarantee (All locks shall be under master key system) as detailed on drawing Note: all stainless steel fittings shall be of 316-grade | D52: Type D4, single leaf overall size 800x2100mm high | E52: Item | F52: 1 | G52: 400 | H52: =F52*G52 -> 400
A53: C52 | B53: Superstructure Works Doors and Windows | C53: WPC Solid Core Doors -Door comprising profiled heads, jambs, frames, subframes, architraves, beadings, moldings, plinth block, ply linings, infill panels, mastic and other pointing, fixings, neoprene seal master lining and all ancillary items including fixing of ironmongery and final decoration for a complete installation all as specified and as detailed on drawing including required reinforcement cement concrete lintels and including Supply and fix ironmongery as specified in schedule and approved; fixed to hardcore, including paint and 10 years guarantee (All locks shall be under master key system) as detailed on drawing Note: all stainless steel fittings shall be of 316-grade | D53: Type D5, single leaf overall size 1000x2100mm high | E53: Item | F53: 1 | G53: 400 | H53: =F53*G53 -> 400
A54: C53 | B54: Superstructure Works Doors and Windows | C54: WPC Solid Core Doors -Door comprising profiled heads, jambs, frames, subframes, architraves, beadings, moldings, plinth block, ply linings, infill panels, mastic and other pointing, fixings, neoprene seal master lining and all ancillary items including fixing of ironmongery and final decoration for a complete installation all as specified and as detailed on drawing including required reinforcement cement concrete lintels and including Supply and fix ironmongery as specified in schedule and approved; fixed to hardcore, including paint and 10 years guarantee (All locks shall be under master key system) as detailed on drawing Note: all stainless steel fittings shall be of 316-grade | D54: Type D6, single leaf overall size 1000x2400mm high | E54: Item | F54: 1 | G54: 400 | H54: =F54*G54 -> 400
A55: C54 | B55: Superstructure Works Doors and Windows | C55: Ironmongery - Supply and fix of ironmongery, with and including all necessary fixing accessories and screws to match, all in accordance with the specifications and drawings - to wood doors | D55: Allow for grand master key and master key system | E55: Item | F55: 1 | G55: 100 | H55: =F55*G55 -> 100
A56: C55 | B56: Superstructure Works Doors and Windows | C56: UPVC windows -window sets complete with all necessary ironmongery as specified, including fixing to blockwork or concrete and mastic pointing all around, all as specified and detailed on drawing and including required reinforcement cement concrete lintels | D56: Type W1, overall size 2000 x 1300mm high | E56: No | F56: 13 | G56: 50 | H56: =F56*G56 -> 650
A57: C56 | B57: Superstructure Works Doors and Windows | C57: UPVC windows -window sets complete with all necessary ironmongery as specified, including fixing to blockwork or concrete and mastic pointing all around, all as specified and detailed on drawing and including required reinforcement cement concrete lintels | D57: Type W2, overall size 1200 x 900mm high, | E57: No | F57: 1 | G57: 50 | H57: =F57*G57 -> 50
A58: C57 | B58: Superstructure Works Doors and Windows | C58: UPVC ventilator -ventilator sets complete with all necessary ironmongery as specified, including fixing to blockwork or concrete and mastic pointing all around, all as specified and detailed on drawing and including required reinforcement cement concrete lintels | D58: Type V, overall size 600 x 600mm high | E58: No | F58: 2 | G58: 50 | H58: =F58*G58 -> 100
A59: C58 | B59: Superstructure Works Finishes | C59: Backgrounds - Plaster, cement and sand (1:3), internal - To walls and columns, on concrete block base, internal including stainsteel mesh, butterfly angle between the concrete column and block work. | D59: to receive internal painting | E59: M2 | F59: 600 | G59: 1 | H59: =F59*G59 -> 600
A60: C59 | B60: Superstructure Works Finishes | C60: Backgrounds - Plaster, cement and sand (1:4), external - To walls and columns, on concrete block base, external including stainsteel mesh, butterfly angle between the concrete column and block work. | D60: to receive external painting | E60: M2 | F60: 480 | G60: 1.5 | H60: =F60*G60 -> 720
A61: C60 | B61: Superstructure Works Finishes | C61: Allow for laying of Marble Threshold as per the specifications, drawings and to approval of the Engineer. | D61: Internal Floor Tile | E61: NO | F61: 1 | G61: 500 | H61: =F61*G61 -> 500
A62: C61 | B62: Superstructure Works Finishes | C62: Floor Tiles: FF1 Ceramic floor tiles laid on screed grouted with waterproof coloured compatible mortar to manufacturers specification/instruction; internally | D62: 600 x 600 x 8 mm Anti-Slip tiling to floor | E62: M2 | F62: 85 | G62: 3 | H62: =F62*G62 -> 255
A63: C62 | B63: Superstructure Works Finishes | C63: Floor Tiles: FF2 Ceramic floor tiles laid on screed grouted with waterproof coloured compatible mortar to manufacturers specification/instruction; internally | D63: 600 x 600 x 8 mm Anti-Slip tiling to floor | E63: M2 | F63: 12 | G63: 3 | H63: =F63*G63 -> 36
... A100: P2 | B100: Sanitary Installation | C100: ditto | D100: 160mm diamater | E100: M | F100: 40 | G100: 10 | H100: =F100*G100 -> 400
A101: P3 | B101: Sanitary Installation | C101: ditto | D101: 110mm diamater | E101: M | F101: 6 | G101: 8 | H101: =F101*G101 -> 48 | I101: =SUM(H52:H101) -> 29616
A102: P4 | B102: Sanitary Installation | C102: ditto | D102: 82mm diameter | E102: M | F102: 7 | G102: 8 | H102: =F102*G102 -> 56
A103: P5 | B103: Sanitary Installation | C103: ditto | D103: 50mm diameter | E103: M | F103: 8 | G103: 8 | H103: =F103*G103 -> 64
A104: P6 | B104: Sanitary Installation | C104: ditto | D104: 42mm diameter | E104: M | F104: 8 | G104: 8 | H104: =F104*G104 -> 64
A105: P7 | B105: Sanitary Installation | C105: vent cowl | D105: Vent cowl with weathering apron 50mm diameter | E105: No | F105: 2 | G105: 8 | H105: =F105*G105 -> 16
A106: P8 | B106: Sanitary Installation | C106: Floor Drain trap | D106: Floor Trap with 150 X 150 mm SS grating Cover | E106: No | F106: 3 | G106: 25 | H106: =F106*G106 -> 75
A107: P9 | B107: Sanitary Installation | C107: Gully Trap | D107: 300 mm and 300 mm gully trap of approximate 300 mm depth set in concrete Grade 30 Nmm� joints to drain pipes complete with 300 mm and 300 mm medium duty cast iron cover and frame. | E107: No | F107: 2 | G107: 30 | H107: =F107*G107 -> 60
A108: P10 | B108: Grease Trap | C108: Grease Trap | D108: 300 mm and 300 mm grease trap of approximate 300 mm depth set in concrete Grade 30 Nmm� joints to drain pipes complete with 300 mm and 300 mm medium duty cast iron cover and frame. | E108: No | F108: 1 | G108: 30 | H108: =F108*G108 -> 30
A109: P11 | B109: Sanitary Installation | C109: Inspection Chambers | D109: Manhole size 600 and 600 mm internally upto 1.24m deep to invert | E109: No | F109: 7 | G109: 180 | H109: =F109*G109 -> 1260
A110: P12 | B110: Sanitary Installation | C110: Manhole Cover | D110: 600 and 600 mm medium duty double seal cast iron manhole cover and frame. | E110: No | F110: 7 | G110: 110 | H110: =F110*G110 -> 770
A111: P13 | B111: Sanitary Installation | C111: Holding tank with soak pit | D111: Reinforced concrete grade 30 N mm2 holding tank size 4000 and 2000 and 2500 mm deep internally with concrete grade 15 N mm2 and 100mm thick blinding and 250mm thick concrete base slab and 200mm thick concrete wall and roof slab and including reinforcement and formwork and rendering and step irons and 3 coats of bitumen paint and 2 layer of 1000 gauge polythene sheet and excavation and dewatering backfilling and disposal of surplus excavated materials and 600 and 600 mm heavy duty double seal ductile iron cover and frame and Precast concrete soak pit size 2000 mm diameter and 2500 mm deep internally including reinforcement and excavation and dewatering and backfilling and disposal of surplus excavated materials 600 and 600 mm heavy duty ductile iron cover and frame et as detailed on drawing. | E111: No | F111: 1 | G111: 5000 | H111: =F111*G111 -> 5000
A112: P14 | B112: Sanitary Wares and Fittings | C112: Semi pedestal wash basin | D112: 650 mm and 475 mm vitreous china white wash basin with semi pedestal and center tap hole and overflow and bottle trap including required complete Civil Works. | E112: No | F112: 2 | G112: 85 | H112: =F112*G112 -> 170
A113: P15 | B113: Sanitary Wares and Fittings | C113: Stainless Steel Sink | D113: 1000 mm and 550 mm stainless steel sink single bowl single drainer with drainboard to BS 1244 complete with 2 piece tubular P trap chain and plug and waste and brackets including required complete Civil Works. | E113: No | F113: 1 | G113: 120 | H113: =F113*G113 -> 120
... A150: P52 | B150: Plumbing and Drainage System | C150: Sundries | D150: Allow for OandM Manual | E150: Item | F150: 1 | G150: 0 | H150: =F150*G150 -> 0
A151: P53 | B151: Plumbing and Drainage System | C151: Sundries | D151: Allow for sterilization of all pipes and over head tanks etc. | E151: Item | F151: 1 | G151: 0 | H151: =F151*G151 -> 0 | I151: =SUM(H102:H151) -> 16913
A152: P54 | B152: Plumbing and Drainage System | C152: Sundries | D152: Allow for spare parts for three years as per manufacturers recommendation. | E152: Item | F152: 1 | G152: 0 | H152: =F152*G152 -> 0
A153: P55 | B153: Plumbing and Drainage System | C153: Sundries | D153: Allow for training OandM staff. | E153: Item | F153: 1 | G153: 0 | H153: =F153*G153 -> 0
A154: P56 | B154: Plumbing and Drainage System | C154: Sundries | D154: Allow for any other activity not listed above. | E154: Item | F154: 1 | G154: 0 | H154: =F154*G154 -> 0
A155: F1 | B155: Fire Fighting Installation | C155: Note | D155: Supply and install a complete fire fighting system to the approval of the Civil Defence Authorities and complete with association and fitting as shown in drawings or specified in accordance with BS 530 Part 1 1976 and Part 3 1985 and to approval of the Engineer. | E155: Item | F155: 0 | G155: 0 | H155: =F155*G155 -> 0
A156: F2 | B156: Fire Fighting Installation | C156: Fire Extinguisher | D156: 2 Kg carbon dioxide fire extinguisher | E156: No | F156: 1 | G156: 10 | H156: =F156*G156 -> 10
A157: F3 | B157: Fire Fighting Installation | C157: Fire Extinguisher | D157: 180 and 180 mm fire blanket | E157: No | F157: 1 | G157: 15 | H157: =F157*G157 -> 15
A158: F4 | B158: Fire Fighting Installation | C158: Fire alarm cable and conduits and panel and accessories installation | D158: Automatic Multi detector point | E158: No | F158: 1 | G158: 15 | H158: =F158*G158 -> 15
A159: G1 | B159: Gas supply line | C159: Gas line | D159: Supply and fix 18 mm diameter MS schedule 40 gas pipeline including pickup points and connection to Gas Stove | E159: M | F159: 10 | G159: 50 | H159: =F159*G159 -> 500
A160: M1 | B160: Air Conditioning and Ventilation Installation | C160: High level Wall mounted Split AC with DX unit | D160: 12000 BTU HR capacity high level wall mounted split type air conditioner including connection to electrical outlet and concrete base foundation. | E160: No | F160: 1 | G160: 450 | H160: =F160*G160 -> 450
A161: M2 | B161: Air Conditioning and Ventilation Installation | C161: High level Wall mounted Split AC with DX unit | D161: 18000 BTU HR capacity high level wall mounted split type air conditioner including connection to electrical outlet and concrete base foundation. | E161: No | F161: 4 | G161: 600 | H161: =F161*G161 -> 2400
A162: M3 | B162: Mechanical installation | C162: Sundries | D162: Allow for builders works in connection with sanitary and water services including holes and chases and sleeves and pipe brackets painted casing to exposed pipes and access panels and weather proof flashing to vent pipes passing through roof etc. | E162: Item | F162: 1 | G162: 0 | H162: =F162*G162 -> 0
A163: M4 | B163: Mechanical installation | C163: Sundries | D163: Allow for incidental works such as co ordination with other engineering installations | E163: Item | F163: 1 | G163: 0 | H163: =F163*G163 -> 0
... A200: E32 | B200: Electrical Engineering Installation | C200: Lighting Accessories and cable and conduits installation | D200: 40w fluorescent light fixture for toilet | E200: No | F200: 2 | G200: 12 | H200: =F200*G200 -> 24
A201: E33 | B201: Electrical Engineering Installation | C201: Lighting Accessories and cable and conduits installation | D201: 40w led downlight | E201: No | F201: 7 | G201: 12 | H201: =F201*G201 -> 84 | I201: =SUM(H152:H201) -> 5886
A202: E34 | B202: Electrical Engineering Installation | C202: Lighting Accessories and cable and conduits installation | D202: 25w led wall mounted light fixture | E202: No | F202: 2 | G202: 12 | H202: =F202*G202 -> 24
A203: E35 | B203: Electrical Engineering Installation | C203: Lighting Accessories and cable and conduits installation | D203: 25w led wall mounted light fixture | E203: No | F203: 3 | G203: 12 | H203: =F203*G203 -> 36
A204: E36 | B204: Electrical Engineering Installation | C204: Lighting Accessories and cable and conduits installation | D204: 25w led wall mounted light fixture whether proof IP66 | E204: No | F204: 11 | G204: 12 | H204: =F204*G204 -> 132
A205: E37 | B205: Electrical Engineering Installation | C205: Lighting Accessories and cable and conduits installation | D205: 7w led mirror light | E205: No | F205: 2 | G205: 12 | H205: =F205*G205 -> 24
A206: E38 | B206: Electrical Engineering Installation | C206: Lighting Accessories and cable and conduits installation | D206: 20w compound wall light with whether proof IP65 | E206: No | F206: 13 | G206: 12 | H206: =F206*G206 -> 156
A207: E39 | B207: Electrical Engineering Installation | C207: Lighting Accessories and cable and conduits installation | D207: Ceiling fan | E207: No | F207: 5 | G207: 15 | H207: =F207*G207 -> 75
A208: E40 | B208: Electrical Engineering Installation | C208: Lighting Accessories and cable and conduits installation | D208: Wall mounted exhaust fan | E208: No | F208: 3 | G208: 10 | H208: =F208*G208 -> 30
A209: GN1 | B209: TV System Installation | C209: TV System Installation | D209: Cable and conduit to TV point in concealed installation from satellite | E209: No | F209: 4 | G209: 25 | H209: =F209*G209 -> 100
A210: GN2 | B210: TV System Installation | C210: Outlet | D210: Flush mounted TV Satellite outlet | E210: No | F210: 1 | G210: 25 | H210: =F210*G210 -> 25
A211: GN3 | B211: TV System Installation | C211: TV System Installation | D211: Allow for co axial cable in concealed conduit from dish antenna to satellite switcher with all necessary accessories and trunking and conduits and trays and supports etc. | E211: Item | F211: 1 | G211: 100 | H211: =F211*G211 -> 100
A212: GN4 | B212: Telephone System | C212: TV System Installation | D212: Cable and conduits to telephone outlet points in concealed installation from telephone junction box to IP phone expansion module for reception | E212: No | F212: 4 | G212: 50 | H212: =F212*G212 -> 200
A213: GN5 | B213: Telephone System | C213: Outlet | D213: Cat 6E telephone outlet | E213: No | F213: 4 | G213: 10 | H213: =F213*G213 -> 40
... A229: GN21 | B229: Telephone and Structured Cabling and CCTV System | C229: Sundries | D229: Allow for testing and commissioning of complete electrical installation. | E229: Item | F229: 1 | G229: 0 | H229: =F229*G229 -> 0
A230: GN22 | B230: Telephone and Structured Cabling and CCTV System | C230: Sundries | D230: Allow for documents As Installed drawings Operation and Maintenance manuals. | E230: Item | F230: 1 | G230: 0 | H230: =F230*G230 -> 0 | I230: =SUM(H202:H230) -> 1707
A231: TOTAL 1 NOS HOUSING UNITS | H231: =SUM(H2:H230) -> 79997
A232: TOTAL 3 NOS HOUSING UNITS | H232: =H231*3 -> 239991

Sheet Grand Summary
A1: CONSTRUCTION, COMPLETION AND MAINTENANCE OF PROPOSED (20NOS) HOUSING UNITS AND MAINTENANCE WORKS FOR THE EXISTING (32) HOUSES FOR THE MINISTRY OF HOUSING & URBAN PLANNING AT HALANIYAT ISLAND
A2: GRAND SUMMARY
A3: Priced Bill of Quantities
A4: Transfer the Contract Summary of Contract Value to the Form of Tender
A5: Sl No. | B5: Description | C5: R.O WITH VAT 5%
A6: 1 | B6: BILL NO 01 PRELIMINARIES | C6: ='01 Preliminaries'!G117 -> 227580
A7: 2 | B7: BILL NO 02 DAY WORKS | C7: ='02 Dayworks'!G117 -> 88252.5
A8: 3 | B8: BILL NO 00 PROVISIONAL SUMS | C8: ='[1]BILL NO-3 PROVISIONAL SUM'!H9 -> 200000
A9: 4 | B9: BILL NO 03 NEW HOUSING UNITS 20 NOS | C9: ='03 Housing Units'!G298 -> 1965370.9
A10: 5 | B10: BILL NO 04 EXTERNAL WORKS AND EXTERNAL SERVICES | C10: ='04 External Works'!G13 -> 28455
A11: 6 | B11: BILL NO 05 MAINTENANCE WORKS FOR THE EXISTING HOUSING UNITS - 29 NO. | C11: ='05 Existing Housing Units-29'!H92 -> 1436308.7
A12: 7 | B12: BILL NO 06 PROTECTION AND STORM WATER DRAINAGE | C12: ='06 Storm Water'!H44 -> 265674.67
A13: 8 | B13: BILL NO 07 3 NO. HOUSING UNITS | C13: ='07 Housing Units 3 Nos'!H232 -> 239991
A14: 9 | B14: CONTINGENCIES 10% (Bill No 03 +Bill No 04 + Bill No 05 + Bill No 06 + Bill No 07) | C14: =SUM(C9:C13)*10% -> 393580.03
A15: Total Contract Value | C15: =SUM(C6:C14) -> 4845212.8
A16: The value of VAT must be included in item rates and will not be considered separately as per Ministry of Financial regulations
A17: Total Contract Value | C17: =C15 -> 4845212.8

Sheet Sheet1
E18: 1965370.9
E19: 28455
E20: 1577721.6
E21: 265674.67
E22: =SUM(E18:E21) -> 3837222.2
E23: =E22*0.1 -> 383722.22
