Workbook

Sheet GRANT SUMMARY
B2: CONSTRUCTION, COMPLETION AND MAINTENANCE OF PROPOSED (20NOS) HOUSING UNITS AND MAINTENANCE WORKS FOR THE EXISTING (32) HOUSES FOR THE MINISTRY
B3: GRAND SUMMARY
B4: Priced Bill Of Quantities
B5: Transfer the Contract Summary of Contract Value to the Form of Tender
B7: S/N | C7: BILL NO | D7: DESCRIPTION | E7: BOQ AMOUNT | F7: BOQ AMOUNT | G7: REVISED VALUE AFTER V.O 1 | H7: Addition | I7: Omission | J7: Savings Excluding V.O 1 | K7: EXPECTED REVISED BOQ VALUE AFTER A/O | M7: ADDITION AMOUNT/VARIATION | N7: SAVING AMOUNT | O7: % | R7: CLAUSES | S7: Appendix
B9: 1 | C9: BILL NO 1 | D9: PRELIMINARIES | E9: =F9 -> 227580 | F9: =SUMMARY!D4 -> 227580 | G9: =F9 -> 227580 | H9: 224532 | I9: 124800 | J9: =I9-H9 -> -99732 | K9: =F9-J9 -> 327312 | L9: =K9-F9 -> 99732 | N9: =F9-K9 -> -99732 | O9: =J9/F9*100 -> -43.822832 | P9: =K9/$K$45 -> 0.085451923 | Q9: =P9 -> 0.085451923 | S9: Bill No 1. (PRELIMINARIES)
H10: 0 | I10: 124800 | J10: 124800 | K10: 102780
B12: 2 | C12: BILL NO 2 | D12: DAY WORKS | E12: =F12 -> 88252.5 | F12: =SUMMARY!D6 -> 88252.5 | G12: =F12 -> 88252.5 | I12: 88252.5 | J12: =I12-H12 -> 88252.5 | K12: =F12-J12 -> 0 | L12: =J12-K12 -> 88252.5 | N12: =SUMMARY!G6 -> 88262.5 | O12: =J12/F12*100 -> 100 | P12: =K12/$K$45 -> 0 | Q12: =P12 -> 0 | S12: Bill No 2. (DAY WORK)
B15: 3 | C15: BILL NO 3 | D15: PROVISIONAL SUM | E15: =F15 -> 200000 | F15: 200000 | I15: 200000 | J15: =I15-H15 -> 200000 | L15: =K15-J15 -> -200000 | N15: =F15-K15 -> 200000 | O15: =J15/F15*100 -> 100 | P15: =K15/$K$45 -> 0 | S15: Bill No 3. (PROVISIONAL SUM)
B17: 4 | C17: BILL NO 4 | D17: NEW HOUSING UNIT (20 UNITS) | E17: =F19+F22 -> 1965370.9 | Q17: =SUM(P19,P22) -> 0.42164429
D19: SUBSTRUCTURE WORKS | F19: =SUMMARY!D11 -> 947257 | G19: =F19 -> 947257 | H19: ='20 NHU ADD. QTY'!H33 -> 41896.539 | I19: =SUMMARY!G11 -> 291914.71 | J19: =I19-H19 -> 250018.17 | K19: =F19-J19 -> 697238.83 | L19: =J19-K19 -> -447220.66 | N19: =SUMMARY!G11 -> 291914.71 | O19: =J19/F19*100 -> 26.393911 | P19: =K19/$K$45 -> 0.18202938 | R19: 12.1 | S19: 20 NEW ADD QTY | W19: =G19-635463.746 -> 311793.25
H20: 0 | I20: 311793.25 | J20: 311793.25 | K20: 635463.75
D22: SUPERSTRUCTURE WORKS | F22: =SUMMARY!D21 -> 1018113.9 | G22: =F22 -> 1018113.9 | H22: =SUMMARY!H21 -> 23100 | I22: =SUMMARY!G21 -> 123401.5 | J22: =I22-H22 -> 100301.5 | K22: =F22-J22 -> 917812.44 | L22: =K22-J22 -> 817510.94 | M22: =SUMMARY!H21 -> 23100 | N22: =SUMMARY!G21 -> 123401.5 | O22: =J22/F22*100 -> 9.851697 | P22: =K22/$K$45 -> 0.23961492 | R22: 12.2 | S22: GRAND SUM. ADD. (Bill No. 4 & 7)
H23: 0 | I23: 85157 | J23: 85157 | K23: 932956.94
B25: 5 | C25: BILL NO 4 | D25: EXTERNAL WORKS AND EXTERNAL SERVICES | E25: =F25 -> 28455 | F25: =SUMMARY!D27 -> 28455 | G25: =F25 -> 28455 | H25: 0 | I25: =SUMMARY!G27 -> 2100 | J25: =I25-H25 -> 2100 | K25: =F25-J25 -> 26355 | L25: =K25 -> 26355 | N25: =SUMMARY!G27 -> 2100 | O25: =J25/F25*100 -> 7.3800738 | P25: =K25/$K$45 -> 0.0068805465 | Q25: =P25 -> 0.0068805465 | S25: BIll No 4 (20 NHI EXXTERNAL WORK)
I26: 0 | J26: 0 | K26: 28455
B28: 6 | C28: BILL NO 5 | D28: MAINTENANCE WORKS FOR THE EXISTING HOUSING UNITS (29 NO) | E28: =F28 -> 1436308.6 | F28: =SUMMARY!D13 -> 1436308.6 | G28: =F28 -> 1436308.6 | H28: =SUMMARY!H13 -> 11890 | I28: =SUMMARY!G13 -> 9991.805 | J28: =I28-H28 -> -1898.195 | K28: =F28-J28 -> 1438206.8 | L28: =K28-J28 -> 1440105 | M28: =SUMMARY!H13 -> 11890 | N28: =SUMMARY!G13 -> 9991.805 | O28: =J28/F28*100 -> -0.13215788 | P28: =K28/$K$45 -> 0.37547519 | Q28: =P28 -> 0.37547519 | R28: 12.2 | S28: ADD. WORK (29 - MHU)
H29: 43723 | I29: 9991.8 | J29: -33731.8 | K29: 1470040.4
B32: 7 | C32: BILL NO 6 | D32: PROTECTION AND STORM WATER DRAINAGE | E32: =F32 -> 265674.67 | F32: =SUMMARY!D16 -> 265674.67 | G32: =F32 -> 265674.67 | H32: ='BILL NO 6 (STORM WATER)'!O36 -> 11318 | I32: ='BILL NO 6 (STORM WATER)'!J35 -> 70280.7 | J32: =I32-H32 -> 58962.7 | K32: =F32-J32 -> 206711.97 | L32: =J32-K32 -> -147749.27 | N32: =F32-K32 -> 58962.7 | O32: =J32/F32*100 -> 22.193572 | P32: =K32/$K$45 -> 0.053966661 | Q32: =P32 -> 0.053966661 | S32: ADD. WORK ON CHANNEL
H33: 0 | I33: 103282.2 | J33: 103282.2 | K33: 162392.48
B35: 8 | C35: BILL NO 7 | D35: 3 NUMBER HOUSING UNITS | E35: =F37+F40 -> 239991.02 | Q35: =SUM(P37,P40) -> 0.056581382
D37: SUBSTRUCTURE WORKS | F37: =SUMMARY!D18 -> 36105 | G37: =F37 -> 36105 | H37: ='20 NHU ADD. QTY'!H62 -> 11250 | I37: =SUMMARY!G18 -> 10515.156 | J37: =I37-H37 -> -734.844 | K37: =F37-J37 -> 36839.844 | L37: =K37-J37 -> 37574.688 | N37: =SUMMARY!G18 -> 10515.156 | O37: =J37/F37*100 -> -2.0352971 | P37: =K37/$K$45 -> 0.0096178433 | R37: 12.1 | S37: 20 NHU ADD. QTY/ Bill No 7. (3 NHU)
H38: 0 | I38: 10515.096 | J38: 10515.096 | K38: 25589.904
D40: SUPERSTRUCTURE WORK | F40: =SUMMARY!D23 -> 203886.02 | G40: =F40 -> 203886.02 | H40: ='SUM. OF ADD. WORKS (BILL NO. 4 '!G17 -> 1111.44 | I40: =SUMMARY!G23 -> 25110 | J40: =I40-H40 -> 23998.56 | K40: =F40-J40 -> 179887.46 | L40: =K40-J40 -> 155888.9 | M40: =SUMMARY!H23 -> 1111.44 | N40: =SUMMARY!G23 -> 25110 | O40: =J40/F40*100 -> 11.770576 | P40: =K40/$K$45 -> 0.046963539 | R40: 12.2 | S40: SUM. OF ADD. WORKS (Bill No 4 & 7)
I41: 12000 | J41: 12000 | K41: 204997.44
P42: =SUM(P40,P38,P37,P36,P35,P33,P32,P31,P28,P27,P25,P23,P22,P21,P19,#REF!,P17,P16,P15,P14,P12,P11,P9) -> #REF! | Q42: =SUM(Q40,Q38,Q37,Q36,Q35,Q33,Q32,Q31,Q28,Q27,Q25,Q23,Q22,Q21,Q19,#REF!,Q17,Q16,Q15,Q14,Q12,Q11,Q9) -> #REF!
O43: =N45+M45 -> 746627.81
B45: Total Contract Value | E45: =SUM(E9:E41) -> 4451632.7 | F45: =SUM(F9:F40) -> 4451632.7 | G45: =SUM(G9+G12+G19+G22+G25+G28+G32+G37+G40) -> 4251632.7 | H45: =SUM(H9+H12+H19+H22+H28+H32+H37+H40) -> 325097.98 | I45: =SUM(I9+I12+I19+I22+I25+I28+I32+I37+I40) -> 746366.37 | J45: =SUM(J9+J12+J19+J22+J25+J28+J32+J37+J40+J15) -> 621268.39 | K45: =SUM(K9+K12+K19+K22+K25+K28+K32+K37+K40) -> 3830364.4 | L45: =F45-K45 -> 621268.39 | M45: =SUM(M9:M40) -> 36101.44 | N45: =SUM(N9:N44) -> 710526.37
H48: =I45-H45 -> 421268.39 | K48: =F45-K45 -> 621268.39 | N48: =SUM(N45:N47) -> 710526.37
L49: =I45+J45 -> 1367634.8
F50: CONTRACT PRICE | K50: CLAIMABLE | N50: ADD/OMISSION IMPACT | P50: =328588.41+7678.88 -> 336267.29 | R50: =55*355 -> 19525
P51: =P50-220352 -> 115915.29 | R51: =R50*32 -> 624800 | S51: =R51+K45 -> 4455164.4
D52: PERCENTAGE | F52: AMOUNT | K52: PERCENTAGE | L52: =J45+K48 -> 1242536.8 | N52: =O43-F48 -> 746627.81
C54: Addition/Omission and Change Order Impact | D54: CONTRACT TOTAL VALUE | F54: =F45 -> 4451632.7 | K54: =F54/F54 -> 1 | L54: =H49-J49 -> 0 | S54: =F45-S51 -> -3531.6095
D55: CLAIMABLE TOTAL AMOUNT | F55: =K45 -> 3830364.4 | K55: =F55/F54 -> 0.86044033
D56: ADDITION OMMISSION IMPACT | F56: =N48 -> 710526.37 | K56: =F56/F54 -> 0.15961028
D57: ADDITIONAL WORK BILL NO. 5 | F57: =SUMMARY!H23 -> 1111.44 | K57: =(F57+F58)/F54 -> 0.049748812 | N57: =F57+F58 -> 221463.44
D58: CHANGE ORDER -2 | F58: 220352
D59: NET FINANCIAL IMPACT | F59: =F54*K59 -> 4051827.8 | K59: =K55+K57 -> 0.91018914
C60: Progress Impact | D60: OVERALL FINANCIAL IMPACT | K60: =K54-K59 -> 0.089810857
D61: CLAIMED TO DATE AGAINST CONTRACT | F61: 2193954.4 | K61: =2193954.35/F54 -> 0.49284262 | N61: =(K61+K62)/2 -> 0.53281108
D62: CLAIMED AGAINST CLAIMABLE VALUE | F62: 2193954.4 | K62: =F62/F55 -> 0.57277954
D63: CLAIMABLE AMOUNT - BILL 11 (13-04-26) | F63: 110000 | K63: =F63/F54 -> 0.024710035
K64: =K62-K61+K63 -> 0.10464696 | N64: =69.5%-N61 -> 0.16218892
D65: Progres Against Contract Vs Revised Value | K65: Planned VS Actual Cost | N65: Planned Vs Actual Progress
H71: =SUM(H10+H20+H23+H26+H29+H33+H38+H41) -> 43723 | I71: =SUM(I10+I12+I20+I23+I26+I29+I33+I38+I41) -> 745791.85 | J71: =SUM(J10+J12+J20+J23+J26+J29+J33+J38+J41+J15) -> 902068.25 | K71: =SUM(K10+K20+K23+K26+K29+K33+K38+K41) -> 3562676

Sheet Copy of Copy of GRANT SUMMARY
B2: CONSTRUCTION, COMPLETION AND MAINTENANCE OF PROPOSED (20NOS) HOUSING UNITS AND MAINTENANCE WORKS FOR THE EXISTING (32) HOUSES FOR THE MINISTRY
B3: GRAND SUMMARY
B4: Priced Bill Of Quantities
B5: Transfer the Contract Summary of Contract Value to the Form of Tender
B7: S/N | C7: BILL NO | D7: DESCRIPTION | E7: BOQ AMOUNT | F7: BOQ AMOUNT | G7: REVISED VALUE AFTER V.O 1 | H7: Addition | I7: Omission | J7: Savings Excluding V.O 1 | K7: EXPECTED REVISED BOQ VALUE AFTER A/O | M7: ADDITION AMOUNT/VARIATION | N7: SAVING AMOUNT | O7: % | R7: CLAUSES | S7: Appendix
B9: 1 | C9: BILL NO 1 | D9: PRELIMINARIES | E9: =F9 -> 227580 | F9: =SUMMARY!D4 -> 227580 | G9: =F9 -> 227580 | H9: 0 | I9: 124800 | J9: =I9-H9 -> 124800 | K9: =F9-J9 -> 102780 | L9: =K9-F9 -> -124800 | N9: =F9-K9 -> 124800 | O9: =J9/F9*100 -> 54.837859 | P9: =K9/$K$36 -> 0.028593571 | Q9: =P9 -> 0.028593571 | S9: Bill No 1. (PRELIMINARIES)
B11: 2 | C11: BILL NO 2 | D11: DAY WORKS | E11: =F11 -> 88252.5 | F11: =SUMMARY!D6 -> 88252.5 | G11: =F11 -> 88252.5 | H11: 0 | I11: 88252.5 | J11: =I11-H11 -> 88252.5 | K11: =F11-J11 -> 0 | L11: =J11-K11 -> 88252.5 | N11: =SUMMARY!G6 -> 88262.5 | O11: =J11/F11*100 -> 100 | P11: =K11/$K$36 -> 0 | Q11: =P11 -> 0 | S11: Bill No 2. (DAY WORK)
B14: 3 | C14: BILL NO 3 | D14: PROVISIONAL SUM | E14: =F14 -> 200000 | F14: 200000 | G14: 0 | H14: 0 | I14: 200000 | J14: =I14-H14 -> 200000 | K14: 0 | L14: =K14-J14 -> -200000 | N14: =F14-K14 -> 200000 | O14: =J14/F14*100 -> 100 | P14: =K14/$K$36 -> 0 | S14: Bill No 3. (PROVISIONAL SUM)
B16: 4 | C16: BILL NO 4 | D16: NEW HOUSING UNIT (20 UNITS) | E16: =F18+F20 -> 1965370.9 | Q16: =SUM(P18,P20) -> 0.44931001
D18: SUBSTRUCTURE WORKS | F18: =SUMMARY!D11 -> 947257 | G18: =F18 -> 947257 | H18: ='20 NHU ADD. QTY'!H33 -> 41896.539 | I18: =SUMMARY!G11 -> 291914.71 | J18: =I18-H18 -> 250018.17 | K18: =F18-J18 -> 697238.83 | L18: =J18-K18 -> -447220.66 | N18: =SUMMARY!G11 -> 291914.71 | O18: =J18/F18*100 -> 26.393911 | P18: =K18/$K$36 -> 0.19397303 | R18: 12.1 | S18: 20 NEW ADD QTY
D20: SUPERSTRUCTURE WORKS | F20: =SUMMARY!D21 -> 1018113.9 | G20: =F20 -> 1018113.9 | H20: =SUMMARY!H21 -> 23100 | I20: =SUMMARY!G21 -> 123401.5 | J20: =I20-H20 -> 100301.5 | K20: =F20-J20 -> 917812.44 | L20: =K20-J20 -> 817510.94 | M20: =SUMMARY!H21 -> 23100 | N20: =SUMMARY!G21 -> 123401.5 | O20: =J20/F20*100 -> 9.851697 | P20: =K20/$K$36 -> 0.25533698 | R20: 12.2 | S20: GRAND SUM. ADD. (Bill No. 4 & 7)
B22: 5 | C22: BILL NO 4 | D22: EXTERNAL WORKS AND EXTERNAL SERVICES | E22: =F22 -> 28455 | F22: =SUMMARY!D27 -> 28455 | G22: =F22 -> 28455 | H22: 0 | I22: =SUMMARY!G27 -> 2100 | J22: =I22-H22 -> 2100 | K22: =F22-J22 -> 26355 | L22: =K22 -> 26355 | N22: =SUMMARY!G27 -> 2100 | O22: =J22/F22*100 -> 7.3800738 | P22: =K22/$K$36 -> 0.0073320058 | Q22: =P22 -> 0.0073320058 | S22: BIll No 4 (20 NHI EXXTERNAL WORK)
B24: 6 | C24: BILL NO 5 | D24: MAINTENANCE WORKS FOR THE EXISTING HOUSING UNITS (29 NO) | E24: =F24 -> 1436308.6 | F24: =SUMMARY!D13 -> 1436308.6 | G24: =F24 -> 1436308.6 | H24: =SUMMARY!H13 -> 11890 | I24: =SUMMARY!G13 -> 9991.805 | J24: =I24-H24 -> -1898.195 | K24: =F24-J24 -> 1438206.8 | L24: =K24-J24 -> 1440105 | M24: =SUMMARY!H13 -> 11890 | N24: =SUMMARY!G13 -> 9991.805 | O24: =J24/F24*100 -> -0.13215788 | P24: =K24/$K$36 -> 0.40011158 | Q24: =P24 -> 0.40011158 | R24: 12.2 | S24: ADD. WORK (29 - MHU)
B26: 7 | C26: BILL NO 6 | D26: PROTECTION AND STORM WATER DRAINAGE | E26: =F26 -> 265674.67 | F26: =SUMMARY!D16 -> 265674.67 | G26: =F26 -> 265674.67 | H26: 0 | I26: ='BILL NO 6 (STORM WATER)'!J35 -> 70280.7 | J26: =I26-H26 -> 70280.7 | K26: =F26-J26 -> 195393.97 | L26: =J26-K26 -> -125113.27 | N26: =F26-K26 -> 70280.7 | O26: =J26/F26*100 -> 26.453669 | P26: =K26/$K$36 -> 0.054358936 | Q26: =P26 -> 0.054358936 | S26: ADD. WORK ON CHANNEL
B28: 8 | C28: BILL NO 7 | D28: 3 NUMBER HOUSING UNITS | E28: =F30+F32 -> 239991.02 | Q28: =SUM(P30,P32) -> 0.060293906
D30: SUBSTRUCTURE WORKS | F30: =SUMMARY!D18 -> 36105 | G30: =F30 -> 36105 | H30: ='20 NHU ADD. QTY'!H62 -> 11250 | I30: =SUMMARY!G18 -> 10515.156 | J30: =I30-H30 -> -734.844 | K30: =F30-J30 -> 36839.844 | L30: =K30-J30 -> 37574.688 | N30: =SUMMARY!G18 -> 10515.156 | O30: =J30/F30*100 -> -2.0352971 | P30: =K30/$K$36 -> 0.010248907 | R30: 12.1 | S30: 20 NHU ADD. QTY/ Bill No 7. (3 NHU)
D32: SUPERSTRUCTURE WORK | F32: =SUMMARY!D23 -> 203886.02 | G32: =F32 -> 203886.02 | H32: ='SUM. OF ADD. WORKS (BILL NO. 4 '!G17 -> 1111.44 | I32: =SUMMARY!G23 -> 25110 | J32: =I32-H32 -> 23998.56 | K32: =F32-J32 -> 179887.46 | L32: =K32-J32 -> 155888.9 | M32: =SUMMARY!H23 -> 1111.44 | N32: =SUMMARY!G23 -> 25110 | O32: =J32/F32*100 -> 11.770576 | P32: =K32/$K$36 -> 0.050044998 | R32: 12.2 | S32: SUM. OF ADD. WORKS (Bill No 4 & 7)
P33: =SUM(P32,#REF!,P30,P29,P28,#REF!,P26,P25,P24,P23,P22,#REF!,P20,P19,P18,#REF!,P16,P15,P14,P13,P11,P10,P9) -> #REF! | Q33: =SUM(Q32,#REF!,Q30,Q29,Q28,#REF!,Q26,Q25,Q24,Q23,Q22,#REF!,Q20,Q19,Q18,#REF!,Q16,Q15,Q14,Q13,Q11,Q10,Q9) -> #REF!
O34: =N36+M36 -> 982477.81
B36: Total Contract Value | E36: =SUM(E9:E32) -> 4451632.7 | F36: =SUM(F9:F32) -> 4451632.7 | G36: =SUM(G9+G11+G18+G20+G22+G24+G26+G30+G32) -> 4251632.7 | H36: =SUM(H9+H11+H18+H20+H24+H26+H30+H32+H14) -> 89247.979 | I36: =SUM(I9+I11+I18+I20+I22+I24+I26+I30+I32+I14) -> 946366.37 | J36: =SUM(J9+J11+J18+J20+J22+J24+J26+J30+J32+J14) -> 857118.39 | K36: =SUM(K9+K11+K18+K20+K22+K24+K26+K30+K32) -> 3594514.4 | L36: =F36-K36 -> 857118.39 | M36: =SUM(M9:M32) -> 36101.44 | N36: =SUM(N9:N35) -> 946376.37
H39: =I36-H36 -> 857118.39 | K39: =F36-K36 -> 857118.39 | N39: =SUM(N36:N38) -> 946376.37
L40: =I36+J36 -> 1803484.8
F41: CONTRACT PRICE | K41: CLAIMABLE | N41: ADD/OMISSION IMPACT | P41: =328588.41+7678.88 -> 336267.29 | R41: =55*355 -> 19525
P42: =P41-220352 -> 115915.29 | R42: =R41*32 -> 624800 | S42: =R42+K36 -> 4219314.4
D43: PERCENTAGE | F43: AMOUNT | K43: PERCENTAGE | L43: =J36+K39 -> 1714236.8 | N43: =O34-F39 -> 982477.81
C45: Addition/Omission and Change Order Impact | D45: CONTRACT TOTAL VALUE | F45: =F36 -> 4451632.7 | K45: =F45/F45 -> 1 | L45: =H40-J40 -> 0 | S45: =F36-S42 -> 232318.39
D46: CLAIMABLE TOTAL AMOUNT | F46: =K36 -> 3594514.4 | K46: =F46/F45 -> 0.80745977
D47: ADDITION OMMISSION IMPACT | F47: =N39 -> 946376.37 | K47: =F47/F45 -> 0.21259085
D48: ADDITIONAL WORK BILL NO. 5 | F48: =SUMMARY!H23 -> 1111.44 | K48: =(F48+F49)/F45 -> 0.049748812 | N48: =F48+F49 -> 221463.44
D49: CHANGE ORDER -2 | F49: 220352
D50: NET FINANCIAL IMPACT | F50: =F45*K50 -> 3815977.8 | K50: =K46+K48 -> 0.85720858
C51: Progress Impact | D51: OVERALL FINANCIAL IMPACT | K51: =K45-K50 -> 0.14279142
D52: CLAIMED TO DATE AGAINST CONTRACT | F52: 2193954.4 | K52: =2193954.35/F45 -> 0.49284262 | N52: =(K52+K53)/2 -> 0.55160222
D53: CLAIMED AGAINST CLAIMABLE VALUE | F53: 2193954.4 | K53: =F53/F46 -> 0.61036183
D54: CLAIMABLE AMOUNT - BILL 11 (13-04-26) | F54: 110000 | K54: =F54/F45 -> 0.024710035
K55: =K53-K52+K54 -> 0.14222924 | N55: =69.5%-N52 -> 0.14339778
D56: Progres Against Contract Vs Revised Value | K56: Planned VS Actual Cost | N56: Planned Vs Actual Progress

Sheet 1ST SCENARIOS. BILL 6 ACTUAL
B2: CONSTRUCTION, COMPLETION AND MAINTENANCE OF PROPOSED (20NOS) HOUSING UNITS AND MAINTENANCE WORKS FOR THE EXISTING (32) HOUSES FOR THE MINISTRY
B3: GRAND SUMMARY
B4: Priced Bill Of Quantities
B5: Transfer the Contract Summary of Contract Value to the Form of Tender
B7: S/N | C7: BILL NO | D7: DESCRIPTION | E7: BOQ AMOUNT | F7: BOQ AMOUNT | G7: REVISED VALUE AFTER V.O 1 | H7: Addition | I7: Omission | J7: Savings Excluding V.O 1 | K7: EXPECTED REVISED BOQ VALUE AFTER A/O | L7: AMOUNT CLAIMED AS PER BILL NO. 12 | N7: ADDITION AMOUNT/VARIATION | O7: SAVING AMOUNT | P7: % | S7: CLAUSES | T7: Appendix
B9: 1 | C9: BILL NO 1 | D9: PRELIMINARIES | E9: =F9 -> 227580 | F9: =SUMMARY!D4 -> 227580 | G9: =F9 -> 227580 | H9: 0 | I9: 124800 | J9: =I9-H9 -> 124800 | K9: =F9-J9 -> 102780 | L9: 75255.52 | M9: =K9-F9 -> -124800 | O9: =F9-K9 -> 124800 | P9: =J9/F9*100 -> 54.837859 | Q9: =K9/$K$33 -> 0.030492469 | R9: =Q9 -> 0.030492469 | T9: Bill No 1. (PRELIMINARIES)
B11: 2 | C11: BILL NO 2 | D11: DAY WORKS | E11: =F11 -> 88252.5 | F11: =SUMMARY!D6 -> 88252.5 | G11: =F11 -> 88252.5 | H11: 0 | I11: 88252.5 | J11: =I11-H11 -> 88252.5 | K11: =F11-J11 -> 0 | L11: 0 | M11: =J11-K11 -> 88252.5 | O11: =SUMMARY!G6 -> 88262.5 | P11: =J11/F11*100 -> 100 | Q11: =K11/$K$33 -> 0 | R11: =Q11 -> 0 | T11: Bill No 2. (DAY WORK)
B13: 3 | C13: BILL NO 3 | D13: PROVISIONAL SUM | E13: =F13 -> 200000 | F13: 200000 | G13: 0 | H13: 0 | I13: 200000 | J13: =I13-H13 -> 200000 | K13: 0 | L13: 0 | M13: =K13-J13 -> -200000 | O13: =F13-K13 -> 200000 | P13: =J13/F13*100 -> 100 | Q13: =K13/$K$33 -> 0 | T13: Bill No 3. (PROVISIONAL SUM)
B15: 4 | C15: BILL NO 4 | D15: NEW HOUSING UNIT (20 UNITS) | E15: =F17+F19 -> 1965370.9 | R15: =SUM(Q17,Q19) -> 0.45396819
D17: SUBSTRUCTURE WORKS | F17: =SUMMARY!D11 -> 947257 | G17: =F17 -> 947257 | H17: 0 | I17: =F17-L17 -> 311793.25 | J17: =I17-H17 -> 311793.25 | K17: =F17-J17 -> 635463.75 | L17: 635463.75 | M17: =J17-K17 -> -323670.49 | O17: =SUMMARY!G11 -> 291914.71 | P17: =J17/F17*100 -> 32.915381 | Q17: =K17/$K$33 -> 0.18852752 | S17: 12.1 | T17: 20 NEW ADD QTY
D19: SUPERSTRUCTURE WORKS | F19: =SUMMARY!D21 -> 1018113.9 | G19: =F19 -> 1018113.9 | H19: 0 | I19: =SUMMARY!G21 -> 123401.5 | J19: =I19-H19 -> 123401.5 | K19: =F19-J19 -> 894712.44 | L19: 384919.88 | M19: =K19-J19 -> 771310.94 | N19: =SUMMARY!H21 -> 23100 | O19: =SUMMARY!G21 -> 123401.5 | P19: =J19/F19*100 -> 12.120598 | Q19: =K19/$K$33 -> 0.26544067 | S19: 12.2 | T19: GRAND SUM. ADD. (Bill No. 4 & 7)
B21: 5 | C21: BILL NO 4 | D21: EXTERNAL WORKS AND EXTERNAL SERVICES | E21: =F21 -> 28455 | F21: =SUMMARY!D27 -> 28455 | G21: =F21 -> 28455 | I21: =SUMMARY!G27 -> 2100 | J21: =I21-H21 -> 2100 | K21: =F21-J21 -> 26355 | L21: 0 | M21: =K21 -> 26355 | O21: =SUMMARY!G27 -> 2100 | P21: =J21/F21*100 -> 7.3800738 | Q21: =K21/$K$33 -> 0.0078189242 | R21: =Q21 -> 0.0078189242 | T21: BIll No 4 (20 NHI EXXTERNAL WORK)
B23: 6 | C23: BILL NO 5 | D23: MAINTENANCE WORKS FOR THE EXISTING HOUSING UNITS (29 NO) | E23: =F23 -> 1436308.6 | F23: =SUMMARY!D13 -> 1436308.6 | G23: =F23 -> 1436308.6 | H23: =SUMMARY!H13 -> 11890 | I23: ='SUMMARY OF BILL NO. (4 - 7)'!N75 -> 9991.805 | J23: =I23-H23 -> -1898.195 | K23: =F23-J23 -> 1438206.8 | L23: 1386819.3 | M23: =K23-J23 -> 1440105 | N23: =SUMMARY!H13 -> 11890 | O23: =SUMMARY!G13 -> 9991.805 | P23: =J23/F23*100 -> -0.13215788 | Q23: =K23/$K$33 -> 0.42668298 | R23: =Q23 -> 0.42668298 | S23: 12.2 | T23: ADD. WORK (29 - MHU)
B25: 7 | C25: BILL NO 6 | D25: PROTECTION AND STORM WATER DRAINAGE | E25: =F25 -> 265674.67 | F25: =SUMMARY!D16 -> 265674.67 | G25: =F25 -> 265674.67 | H25: 0 | I25: ='Copy of BILL NO 6 (STORM WATER)'!J52 -> 186375.12 | J25: =I25-H25 -> 186375.12 | K25: =F25-J25 -> 79299.558 | L25: 6120.135 | M25: =J25-K25 -> 107075.56 | O25: =F25-K25 -> 186375.12 | P25: =J25/F25*100 -> 70.151631 | Q25: =K25/$K$33 -> 0.02352636 | R25: =Q25 -> 0.02352636 | T25: ADD. WORK ON CHANNEL
B27: 8 | C27: BILL NO 7 | D27: 3 NUMBER HOUSING UNITS | E27: =F29+F31 -> 239991.02 | R27: =SUM(Q29,Q31) -> 0.057511079
D29: SUBSTRUCTURE WORKS | F29: =SUMMARY!D18 -> 36105 | G29: =F29 -> 36105 | H29: 0 | I29: =F29-L29 -> 10515.096 | J29: =I29-H29 -> 10515.096 | K29: =F29-J29 -> 25589.904 | L29: 25589.904 | M29: =K29-J29 -> 15074.808 | O29: =SUMMARY!G18 -> 10515.156 | P29: =J29/F29*100 -> 29.123656 | Q29: =K29/$K$33 -> 0.0075919377 | S29: 12.1 | T29: 20 NHU ADD. QTY/ Bill No 7. (3 NHU)
D31: SUPERSTRUCTURE WORK | F31: =SUMMARY!D23 -> 203886.02 | G31: =F31 -> 203886.02 | H31: 0 | I31: ='BILL NO 7. (3 NHU)'!M193 -> 35625.156 | J31: =I31-H31 -> 35625.156 | K31: =F31-J31 -> 168260.87 | L31: 28323 | M31: =K31-J31 -> 132635.71 | N31: =SUMMARY!H23 -> 1111.44 | O31: =SUMMARY!G23 -> 25110 | P31: =J31/F31*100 -> 17.473074 | Q31: =K31/$K$33 -> 0.049919142 | S31: 12.2 | T31: SUM. OF ADD. WORKS (Bill No 4 & 7)
B33: Total Contract Value | E33: =SUM(E9:E32) -> 4451632.7 | F33: =SUM(F9:F31) -> 4451632.7 | G33: =SUM(G9+G11+G17+G19+G21+G23+G25+G29+G31+G13) -> 4251632.7 | H33: =SUM(H9+H11+H17+H19+H23+H25+H29+H31) -> 11890 | I33: =SUM(I9+I11+I17+I19+I21+I23+I25+I29+I31+I13) -> 1092854.4 | J33: =SUM(J9+J11+J17+J19+J21+J23+J25+J29+J31+J13) -> 1080964.4 | K33: =SUM(K9+K11+K17+K19+K21+K23+K25+K29+K31+K15+K13) -> 3370668.3 | L33: =SUM(L9+L11+L17+L19+L21+L23+L25+L29+L31+L13) -> 2542491.5 | M33: =F33-K33 -> 1080964.4 | N33: =SUM(N9:N31) -> 36101.44 | O33: =SUM(O9:O32) -> 1062470.8
H36: =I33-H33 -> 1080964.4 | K36: =F33-K33 -> 1080964.4 | O36: =SUM(O33:O35) -> 1062470.8
M37: =I33+J33 -> 2173818.9
F38: CONTRACT PRICE | K38: CLAIMABLE | O38: ADD/OMISSION IMPACT | Q38: =328588.41+7678.88 -> 336267.29 | S38: =55*355 -> 19525
Q39: =Q38-220352 -> 115915.29 | S39: =S38*32 -> 624800 | T39: =S39+K33 -> 3995468.3
D40: PERCENTAGE | F40: AMOUNT | K40: PERCENTAGE | M40: =J33+K36 -> 2161928.9 | O40: =#REF!-F36 -> #REF!
C42: Addition/Omission and Change Order Impact | D42: CONTRACT TOTAL VALUE | F42: =F33 -> 4451632.7 | K42: =F42/F42 -> 1 | M42: =H37-J37 -> 0 | T42: =F33-T39 -> 456164.43
D43: CLAIMABLE TOTAL AMOUNT | F43: =K33 -> 3370668.3 | K43: =F43/F42 -> 0.75717574
D44: ADDITION OMMISSION IMPACT | F44: =O36 -> 1062470.8 | K44: =F44/F42 -> 0.23866991
D45: ADDITIONAL WORK BILL NO. 5 | F45: =SUMMARY!H23 -> 1111.44 | K45: =(F45+F46)/F42 -> 0.049748812 | O45: =F45+F46 -> 221463.44
D46: CHANGE ORDER -2 | F46: 220352
D47: NET FINANCIAL IMPACT | F47: =F42*K47 -> 3592131.8 | K47: =K43+K45 -> 0.80692455
C48: Progress Impact | D48: OVERALL FINANCIAL IMPACT | K48: =K42-K47 -> 0.19307545
D49: CLAIMED TO DATE AGAINST CONTRACT | F49: 2193954.4 | K49: =2193954.35/F42 -> 0.49284262 | O49: =(K49+K50)/2 -> 0.57186928
D50: CLAIMED AGAINST CLAIMABLE VALUE | F50: 2193954.4 | K50: =F50/F43 -> 0.65089595
D51: CLAIMABLE AMOUNT - BILL 11 (13-04-26) | F51: 110000 | K51: =F51/F42 -> 0.024710035
K52: =K50-K49+K51 -> 0.18276336 | O52: =69.5%-O49 -> 0.12313072
D53: Progres Against Contract Vs Revised Value | K53: Planned VS Actual Cost | O53: Planned Vs Actual Progress
K58: =J33+K33 -> 4451632.7
J59: =J33/32 -> 33780.138
J60: =J59/55 -> 614.18433 | K60: =K58-F33 -> 0

Sheet 2ND GRAND SUMMARY (All Addition
B2: CONSTRUCTION, COMPLETION AND MAINTENANCE OF PROPOSED (20NOS) HOUSING UNITS AND MAINTENANCE WORKS FOR THE EXISTING (32) HOUSES FOR THE MINISTRY
B3: GRAND SUMMARY
B4: Priced Bill Of Quantities
B5: Transfer the Contract Summary of Contract Value to the Form of Tender
B7: S/N | C7: BILL NO | D7: DESCRIPTION | E7: BOQ AMOUNT | F7: BOQ AMOUNT | G7: REVISED VALUE AFTER V.O 1 | H7: Addition | I7: Omission | J7: Savings Excluding V.O 1 | K7: EXPECTED REVISED BOQ VALUE AFTER A/O | L7: AMOUNT CLAIMED AS PER BILL NO. 12 | N7: ADDITION AMOUNT/VARIATION | O7: SAVING AMOUNT | P7: % | S7: CLAUSES | T7: Appendix
B9: 1 | C9: BILL NO 1 | D9: PRELIMINARIES | E9: =F9 -> 227580 | F9: =SUMMARY!D4 -> 227580 | G9: =F9 -> 227580 | H9: 0 | I9: 124800 | J9: =I9-H9 -> 124800 | K9: =F9-J9 -> 102780 | L9: 75255.52 | M9: =K9-F9 -> -124800 | O9: =F9-K9 -> 124800 | P9: =J9/F9*100 -> 54.837859 | Q9: =K9/$K$33 -> 0.02758638 | R9: =Q9 -> 0.02758638 | T9: Bill No 1. (PRELIMINARIES)
B11: 2 | C11: BILL NO 2 | D11: DAY WORKS | E11: =F11 -> 88252.5 | F11: =SUMMARY!D6 -> 88252.5 | G11: =F11 -> 88252.5 | H11: 0 | I11: 88252.5 | J11: =I11-H11 -> 88252.5 | K11: =F11-J11 -> 0 | L11: 0 | M11: =J11-K11 -> 88252.5 | O11: =SUMMARY!G6 -> 88262.5 | P11: =J11/F11*100 -> 100 | Q11: =K11/$K$33 -> 0 | R11: =Q11 -> 0 | T11: Bill No 2. (DAY WORK)
B13: 3 | C13: BILL NO 3 | D13: PROVISIONAL SUM | E13: =F13 -> 200000 | F13: 200000 | G13: 0 | H13: 0 | I13: 200000 | J13: =I13-H13 -> 200000 | K13: 0 | L13: 0 | M13: =K13-J13 -> -200000 | O13: =F13-K13 -> 200000 | P13: =J13/F13*100 -> 100 | Q13: =K13/$K$33 -> 0 | T13: Bill No 3. (PROVISIONAL SUM)
B15: 4 | C15: BILL NO 4 | D15: NEW HOUSING UNIT (20 UNITS) | E15: =F17+F19 -> 1965370.9 | R15: =SUM(Q17,Q19) -> 0.4526665
D17: SUBSTRUCTURE WORKS | F17: =SUMMARY!D11 -> 947257 | G17: =F17 -> 947257 | H17: ='20 NHU ADD. QTY'!H33 -> 41896.539 | I17: =F17-L17 -> 311793.25 | J17: =I17-H17 -> 269896.72 | K17: =F17-J17 -> 677360.28 | L17: 635463.75 | M17: =J17-K17 -> -407463.57 | O17: =SUMMARY!G11 -> 291914.71 | P17: =J17/F17*100 -> 28.492449 | Q17: =K17/$K$33 -> 0.181805 | S17: 12.1 | T17: 20 NEW ADD QTY
D19: SUPERSTRUCTURE WORKS | F19: =SUMMARY!D21 -> 1018113.9 | G19: =F19 -> 1018113.9 | H19: ='SUM. OF ADD. WORKS (BILL NO. 4 '!F135 -> 114450.24 | I19: =SUMMARY!G21 -> 123401.5 | J19: =I19-H19 -> 8951.2562 | K19: =F19-J19 -> 1009162.7 | L19: 384919.88 | M19: =K19-J19 -> 1000211.4 | N19: =SUMMARY!H21 -> 23100 | O19: =SUMMARY!G21 -> 123401.5 | P19: =J19/F19*100 -> 0.87919984 | Q19: =K19/$K$33 -> 0.2708615 | S19: 12.2 | T19: GRAND SUM. ADD. (Bill No. 4 & 7) | Y19: =K19-F19 -> -8951.2562
B21: 5 | C21: BILL NO 4 | D21: EXTERNAL WORKS AND EXTERNAL SERVICES | E21: =F21 -> 28455 | F21: =SUMMARY!D27 -> 28455 | G21: =F21 -> 28455 | I21: =SUMMARY!G27 -> 2100 | J21: =I21-H21 -> 2100 | K21: =F21-J21 -> 26355 | L21: 0 | M21: =K21 -> 26355 | O21: =SUMMARY!G27 -> 2100 | P21: =J21/F21*100 -> 7.3800738 | Q21: =K21/$K$33 -> 0.0070737404 | R21: =Q21 -> 0.0070737404 | T21: BIll No 4 (20 NHI EXXTERNAL WORK)
B23: 6 | C23: BILL NO 5 | D23: MAINTENANCE WORKS FOR THE EXISTING HOUSING UNITS (29 NO) | E23: =F23 -> 1436308.6 | F23: =SUMMARY!D13 -> 1436308.6 | G23: =F23 -> 1436308.6 | H23: =SUMMARY!H13 -> 11890 | I23: ='SUMMARY OF BILL NO. (4 - 7)'!N75 -> 9991.805 | J23: =I23-H23 -> -1898.195 | K23: =F23-J23 -> 1438206.8 | L23: 1386819.3 | M23: =K23-J23 -> 1440105 | N23: =SUMMARY!H13 -> 11890 | O23: =SUMMARY!G13 -> 9991.805 | P23: =J23/F23*100 -> -0.13215788 | Q23: =K23/$K$33 -> 0.38601789 | R23: =Q23 -> 0.38601789 | S23: 12.2 | T23: ADD. WORK (29 - MHU)
B25: 7 | C25: BILL NO 6 | D25: PROTECTION AND STORM WATER DRAINAGE | E25: =F25 -> 265674.67 | F25: =SUMMARY!D16 -> 265674.67 | G25: =F25 -> 265674.67 | H25: 0 | I25: ='BILL NO 6 (STORM WATER)'!I36 -> 0 | J25: =I25-H25 -> 0 | K25: =F25-J25 -> 265674.67 | L25: 6120.135 | M25: =J25-K25 -> -265674.67 | O25: =F25-K25 -> 0 | P25: =J25/F25*100 -> 0 | Q25: =K25/$K$33 -> 0.071307671 | R25: =Q25 -> 0.071307671 | T25: ADD. WORK ON CHANNEL
B27: 8 | C27: BILL NO 7 | D27: 3 NUMBER HOUSING UNITS | E27: =F29+F31 -> 239991.02 | R27: =SUM(Q29,Q31) -> 0.055347815
D29: SUBSTRUCTURE WORKS | F29: =SUMMARY!D18 -> 36105 | G29: =F29 -> 36105 | H29: ='20 NHU ADD. QTY'!H62 -> 11250 | I29: =F29-L29 -> 10515.096 | J29: =I29-H29 -> -734.904 | K29: =F29-J29 -> 36839.904 | L29: 25589.904 | M29: =K29-J29 -> 37574.808 | O29: =SUMMARY!G18 -> 10515.156 | P29: =J29/F29*100 -> -2.0354632 | Q29: =K29/$K$33 -> 0.0098879119 | S29: 12.1 | T29: 20 NHU ADD. QTY/ Bill No 7. (3 NHU)
D31: SUPERSTRUCTURE WORK | F31: =SUMMARY!D23 -> 203886.02 | G31: =F31 -> 203886.02 | H31: ='SUM. OF ADD. WORKS (BILL NO. 4 '!G17 -> 1111.44 | I31: ='BILL NO 7. (3 NHU)'!M193 -> 35625.156 | J31: =I31-H31 -> 34513.716 | K31: =F31-J31 -> 169372.31 | L31: 28323 | M31: =K31-J31 -> 134858.59 | N31: =SUMMARY!H23 -> 1111.44 | O31: =SUMMARY!G23 -> 25110 | P31: =J31/F31*100 -> 16.927946 | Q31: =K31/$K$33 -> 0.045459903 | S31: 12.2 | T31: SUM. OF ADD. WORKS (Bill No 4 & 7)
B33: Total Contract Value | E33: =SUM(E9:E32) -> 4451632.7 | F33: =SUM(F9:F31) -> 4451632.7 | G33: =SUM(G9+G11+G17+G19+G21+G23+G25+G29+G31+G13) -> 4251632.7 | H33: =SUM(H9+H11+H17+H19+H23+H25+H29+H31) -> 180598.22 | I33: =SUM(I9+I11+I17+I19+I21+I23+I25+I29+I31+I13) -> 906479.31 | J33: =SUM(J9+J11+J17+J19+J21+J23+J25+J29+J31+J13) -> 725881.09 | K33: =SUM(K9+K11+K17+K19+K21+K23+K25+K29+K31+K15+K13) -> 3725751.7 | L33: =SUM(L9+L11+L17+L19+L21+L23+L25+L29+L31+L13) -> 2542491.5 | M33: =F33-K33 -> 725881.09 | N33: =SUM(N9:N31) -> 36101.44 | O33: =SUM(O9:O32) -> 876095.67
H36: =I33-H33 -> 725881.09 | K36: =F33-K33 -> 725881.09 | O36: =SUM(O33:O35) -> 876095.67
M37: =I33+J33 -> 1632360.4
F38: CONTRACT PRICE | K38: CLAIMABLE | O38: ADD/OMISSION IMPACT | Q38: =328588.41+7678.88 -> 336267.29 | S38: =55*355 -> 19525
Q39: =Q38-220352 -> 115915.29 | S39: =S38*32 -> 624800 | T39: =S39+K33 -> 4350551.7
D40: PERCENTAGE | F40: AMOUNT | K40: PERCENTAGE | M40: =J33+K36 -> 1451762.2 | O40: =#REF!-F36 -> #REF!
C42: Addition/Omission and Change Order Impact | D42: CONTRACT TOTAL VALUE | F42: =F33 -> 4451632.7 | K42: =F42/F42 -> 1 | M42: =H37-J37 -> 0 | T42: =F33-T39 -> 101081.09
D43: CLAIMABLE TOTAL AMOUNT | F43: =K33 -> 3725751.7 | K43: =F43/F42 -> 0.83694048
D44: ADDITION OMMISSION IMPACT | F44: =O36 -> 876095.67 | K44: =F44/F42 -> 0.19680322
D45: ADDITIONAL WORK BILL NO. 5 | F45: =SUMMARY!H23 -> 1111.44 | K45: =(F45+F46)/F42 -> 0.049748812 | O45: =F45+F46 -> 221463.44
D46: CHANGE ORDER -2 | F46: 220352
D47: NET FINANCIAL IMPACT | F47: =F42*K47 -> 3947215.1 | K47: =K43+K45 -> 0.88668929
C48: Progress Impact | D48: OVERALL FINANCIAL IMPACT | K48: =K42-K47 -> 0.11331071
D49: CLAIMED TO DATE AGAINST CONTRACT | F49: 2193954.4 | K49: =2193954.35/F42 -> 0.49284262 | O49: =(K49+K50)/2 -> 0.54085241
D50: CLAIMED AGAINST CLAIMABLE VALUE | F50: 2193954.4 | K50: =F50/F43 -> 0.58886221
D51: CLAIMABLE AMOUNT - BILL 11 (13-04-26) | F51: 110000 | K51: =F51/F42 -> 0.024710035
K52: =K50-K49+K51 -> 0.12072962 | O52: =69.5%-O49 -> 0.15414759
D53: Progres Against Contract Vs Revised Value | K53: Planned VS Actual Cost | O53: Planned Vs Actual Progress
K58: =J33+K33 -> 4451632.7
J59: =J33/32 -> 22683.784
J60: =J59/55 -> 412.43244 | K60: =K58-F33 -> 0

Sheet 3RD GRAND SUMMARY (Consultant S
B2: CONSTRUCTION, COMPLETION AND MAINTENANCE OF PROPOSED (20NOS) HOUSING UNITS AND MAINTENANCE WORKS FOR THE EXISTING (32) HOUSES FOR THE MINISTRY
B3: GRAND SUMMARY
B4: Priced Bill Of Quantities
B5: Transfer the Contract Summary of Contract Value to the Form of Tender
B7: S/N | C7: BILL NO | D7: DESCRIPTION | E7: BOQ AMOUNT | F7: BOQ AMOUNT | G7: REVISED VALUE AFTER V.O 1 | H7: Addition | I7: Omission | J7: Savings Excluding V.O 1 | K7: EXPECTED REVISED BOQ VALUE AFTER A/O | L7: AMOUNT CLAIMED AS PER BILL NO. 12 | N7: ADDITION AMOUNT/VARIATION | O7: SAVING AMOUNT | P7: % | S7: CLAUSES | T7: Appendix
B9: 1 | C9: BILL NO 1 | D9: PRELIMINARIES | E9: =F9 -> 227580 | F9: =SUMMARY!D4 -> 227580 | G9: =F9 -> 227580 | H9: 0 | I9: 124800 | J9: =I9-H9 -> 124800 | K9: =F9-J9 -> 102780 | L9: 75255.52 | M9: =K9-F9 -> -124800 | O9: =F9-K9 -> 124800 | P9: =J9/F9*100 -> 54.837859 | Q9: =K9/$K$33 -> 0.028894784 | R9: =Q9 -> 0.028894784 | T9: Bill No 1. (PRELIMINARIES)
B11: 2 | C11: BILL NO 2 | D11: DAY WORKS | E11: =F11 -> 88252.5 | F11: =SUMMARY!D6 -> 88252.5 | G11: =F11 -> 88252.5 | H11: 0 | I11: 88252.5 | J11: =I11-H11 -> 88252.5 | K11: =F11-J11 -> 0 | L11: 0 | M11: =J11-K11 -> 88252.5 | O11: =SUMMARY!G6 -> 88262.5 | P11: =J11/F11*100 -> 100 | Q11: =K11/$K$33 -> 0 | R11: =Q11 -> 0 | T11: Bill No 2. (DAY WORK)
B13: 3 | C13: BILL NO 3 | D13: PROVISIONAL SUM | E13: =F13 -> 200000 | F13: 200000 | G13: 0 | H13: 0 | I13: 200000 | J13: =I13-H13 -> 200000 | K13: 0 | L13: 0 | M13: =K13-J13 -> -200000 | O13: =F13-K13 -> 200000 | P13: =J13/F13*100 -> 100 | Q13: =K13/$K$33 -> 0 | T13: Bill No 3. (PROVISIONAL SUM)
B15: 4 | C15: BILL NO 4 | D15: NEW HOUSING UNIT (20 UNITS) | E15: =F17+F19 -> 1965370.9 | R15: =SUM(Q17,Q19) -> 0.43018204
D17: SUBSTRUCTURE WORKS | F17: =SUMMARY!D11 -> 947257 | G17: =F17 -> 947257 | H17: 0 | I17: =F17-L17 -> 311793.25 | J17: =I17-H17 -> 311793.25 | K17: =F17-J17 -> 635463.75 | L17: 635463.75 | M17: =J17-K17 -> -323670.49 | O17: =SUMMARY!G11 -> 291914.71 | P17: =J17/F17*100 -> 32.915381 | Q17: =K17/$K$33 -> 0.17864942 | S17: 12.1 | T17: 20 NEW ADD QTY
D19: SUPERSTRUCTURE WORKS | F19: =SUMMARY!D21 -> 1018113.9 | G19: =F19 -> 1018113.9 | H19: 0 | I19: =SUMMARY!G21 -> 123401.5 | J19: =I19-H19 -> 123401.5 | K19: =F19-J19 -> 894712.44 | L19: 384919.88 | M19: =K19-J19 -> 771310.94 | N19: =SUMMARY!H21 -> 23100 | O19: =SUMMARY!G21 -> 123401.5 | P19: =J19/F19*100 -> 12.120598 | Q19: =K19/$K$33 -> 0.25153262 | S19: 12.2 | T19: GRAND SUM. ADD. (Bill No. 4 & 7)
B21: 5 | C21: BILL NO 4 | D21: EXTERNAL WORKS AND EXTERNAL SERVICES | E21: =F21 -> 28455 | F21: =SUMMARY!D27 -> 28455 | G21: =F21 -> 28455 | I21: =SUMMARY!G27 -> 2100 | J21: =I21-H21 -> 2100 | K21: =F21-J21 -> 26355 | L21: 0 | M21: =K21 -> 26355 | O21: =SUMMARY!G27 -> 2100 | P21: =J21/F21*100 -> 7.3800738 | Q21: =K21/$K$33 -> 0.0074092432 | R21: =Q21 -> 0.0074092432 | T21: BIll No 4 (20 NHI EXXTERNAL WORK)
B23: 6 | C23: BILL NO 5 | D23: MAINTENANCE WORKS FOR THE EXISTING HOUSING UNITS (29 NO) | E23: =F23 -> 1436308.6 | F23: =SUMMARY!D13 -> 1436308.6 | G23: =F23 -> 1436308.6 | H23: =SUMMARY!H13 -> 11890 | I23: ='SUMMARY OF BILL NO. (4 - 7)'!N75 -> 9991.805 | J23: =I23-H23 -> -1898.195 | K23: =F23-J23 -> 1438206.8 | L23: 1386819.3 | M23: =K23-J23 -> 1440105 | N23: =SUMMARY!H13 -> 11890 | O23: =SUMMARY!G13 -> 9991.805 | P23: =J23/F23*100 -> -0.13215788 | Q23: =K23/$K$33 -> 0.40432647 | R23: =Q23 -> 0.40432647 | S23: 12.2 | T23: ADD. WORK (29 - MHU)
B25: 7 | C25: BILL NO 6 | D25: PROTECTION AND STORM WATER DRAINAGE | E25: =F25 -> 265674.67 | F25: =SUMMARY!D16 -> 265674.67 | G25: =F25 -> 265674.67 | H25: 0 | I25: ='BILL NO 6 (STORM WATER)'!I36 -> 0 | J25: =I25-H25 -> 0 | K25: =F25-J25 -> 265674.67 | L25: 6120.135 | M25: =J25-K25 -> -265674.67 | O25: =F25-K25 -> 0 | P25: =J25/F25*100 -> 0 | Q25: =K25/$K$33 -> 0.074689747 | R25: =Q25 -> 0.074689747 | T25: ADD. WORK ON CHANNEL
B27: 8 | C27: BILL NO 7 | D27: 3 NUMBER HOUSING UNITS | E27: =F29+F31 -> 239991.02 | R27: =SUM(Q29,Q31) -> 0.054497724
D29: SUBSTRUCTURE WORKS | F29: =SUMMARY!D18 -> 36105 | G29: =F29 -> 36105 | H29: 0 | I29: =F29-L29 -> 10515.096 | J29: =I29-H29 -> 10515.096 | K29: =F29-J29 -> 25589.904 | L29: 25589.904 | M29: =K29-J29 -> 15074.808 | O29: =SUMMARY!G18 -> 10515.156 | P29: =J29/F29*100 -> 29.123656 | Q29: =K29/$K$33 -> 0.00719415 | S29: 12.1 | T29: 20 NHU ADD. QTY/ Bill No 7. (3 NHU)
D31: SUPERSTRUCTURE WORK | F31: =SUMMARY!D23 -> 203886.02 | G31: =F31 -> 203886.02 | H31: 0 | I31: ='BILL NO 7. (3 NHU)'!M193 -> 35625.156 | J31: =I31-H31 -> 35625.156 | K31: =F31-J31 -> 168260.87 | L31: 28323 | M31: =K31-J31 -> 132635.71 | N31: =SUMMARY!H23 -> 1111.44 | O31: =SUMMARY!G23 -> 25110 | P31: =J31/F31*100 -> 17.473074 | Q31: =K31/$K$33 -> 0.047303574 | S31: 12.2 | T31: SUM. OF ADD. WORKS (Bill No 4 & 7)
B33: Total Contract Value | E33: =SUM(E9:E32) -> 4451632.7 | F33: =SUM(F9:F31) -> 4451632.7 | G33: =SUM(G9+G11+G17+G19+G21+G23+G25+G29+G31+G13) -> 4251632.7 | H33: =SUM(H9+H11+H17+H19+H23+H25+H29+H31) -> 11890 | I33: =SUM(I9+I11+I17+I19+I21+I23+I25+I29+I31+I13) -> 906479.31 | J33: =SUM(J9+J11+J17+J19+J21+J23+J25+J29+J31+J13) -> 894589.31 | K33: =SUM(K9+K11+K17+K19+K21+K23+K25+K29+K31+K15+K13) -> 3557043.4 | L33: =SUM(L9+L11+L17+L19+L21+L23+L25+L29+L31+L13) -> 2542491.5 | M33: =F33-K33 -> 894589.31 | N33: =SUM(N9:N31) -> 36101.44 | O33: =SUM(O9:O32) -> 876095.67
H36: =I33-H33 -> 894589.31 | K36: =F33-K33 -> 894589.31 | O36: =SUM(O33:O35) -> 876095.67
M37: =I33+J33 -> 1801068.6
F38: CONTRACT PRICE | K38: CLAIMABLE | O38: ADD/OMISSION IMPACT | Q38: =328588.41+7678.88 -> 336267.29 | S38: =55*355 -> 19525
Q39: =Q38-220352 -> 115915.29 | S39: =S38*32 -> 624800 | T39: =S39+K33 -> 4181843.4
D40: PERCENTAGE | F40: AMOUNT | K40: PERCENTAGE | M40: =J33+K36 -> 1789178.6 | O40: =#REF!-F36 -> #REF!
C42: Addition/Omission and Change Order Impact | D42: CONTRACT TOTAL VALUE | F42: =F33 -> 4451632.7 | K42: =F42/F42 -> 1 | M42: =H37-J37 -> 0 | T42: =F33-T39 -> 269789.31
D43: CLAIMABLE TOTAL AMOUNT | F43: =K33 -> 3557043.4 | K43: =F43/F42 -> 0.79904243
D44: ADDITION OMMISSION IMPACT | F44: =O36 -> 876095.67 | K44: =F44/F42 -> 0.19680322
D45: ADDITIONAL WORK BILL NO. 5 | F45: =SUMMARY!H23 -> 1111.44 | K45: =(F45+F46)/F42 -> 0.049748812 | O45: =F45+F46 -> 221463.44
D46: CHANGE ORDER -2 | F46: 220352
D47: NET FINANCIAL IMPACT | F47: =F42*K47 -> 3778506.9 | K47: =K43+K45 -> 0.84879124
C48: Progress Impact | D48: OVERALL FINANCIAL IMPACT | K48: =K42-K47 -> 0.15120876
D49: CLAIMED TO DATE AGAINST CONTRACT | F49: 2193954.4 | K49: =2193954.35/F42 -> 0.49284262 | O49: =(K49+K50)/2 -> 0.55481709
D50: CLAIMED AGAINST CLAIMABLE VALUE | F50: 2193954.4 | K50: =F50/F43 -> 0.61679155
D51: CLAIMABLE AMOUNT - BILL 11 (13-04-26) | F51: 110000 | K51: =F51/F42 -> 0.024710035
K52: =K50-K49+K51 -> 0.14865897 | O52: =69.5%-O49 -> 0.14018291
D53: Progres Against Contract Vs Revised Value | K53: Planned VS Actual Cost | O53: Planned Vs Actual Progress
K58: =J33+K33 -> 4451632.7
J59: =J33/32 -> 27955.916
J60: =J59/55 -> 508.28938 | K60: =K58-F33 -> 0

Sheet Sheet38
B2: S/N | C2: DESCRIPTION OF WORK | D2: UOM | E2: QTY | F2: RATE | G2: AMOUNT
B3: 1 | C3: MAINTENANCE EXTENSION | D3: SQM | E3: 1760 | F3: 447.71 | G3: =E3*F3 -> 787969.6
B5: 2 | C5: REVISED DOORS
C6: D1 - ALUM. DOOR | D6: NR | E6: 20 | F6: 1300 | G6: =E6*F6 -> 26000
C7: D2 - ALUM. DOOR | D7: NR | E7: 20 | F7: 400 | G7: =E7*F7 -> 8000
G10: =SUM(G3:G9) -> 821969.6

Sheet SUMMARY
B2: S/N | C2: DESCRIPTION | D2: BOQ AMOUNT | E2: REVISED AMOUNT (CLAIMABLE) | G2: OMISSION AMOUNT (SAVINGS) | H2: ADDITION AMOUNT | I2: ENQUIRY ON ITEM OF WORK (AMOUNT)
B4: BILL NO 1 | C4: PRELIMINARIES | D4: ='BILL NO 1. (PRELIMINARIES)'!I146 -> 227580 | E4: ='BILL NO 1. (PRELIMINARIES)'!J146 -> 102780 | G4: ='BILL NO 1. (PRELIMINARIES)'!L146 -> 124800 | I4: -------------
B6: BILL NO 2 | C6: DAY WORK | D6: ='BILL NO 2. (DAY WORK)'!H120 -> 88252.5 | E6: ='BILL NO 2. (DAY WORK)'!J120 -> 0 | G6: ='BILL NO 2. (DAY WORK)'!K120 -> 88262.5 | I6: -------------
B8: BILL NO 3 | C8: PROVISIONAL SUM | D8: ='BILL NO 3. (PROVISIONAL SUM)'!I11 -> 200000 | E8: 0 | G8: ='BILL NO 3. (PROVISIONAL SUM)'!K11 -> 200000 | I8: -------------
C10: SUBSTRUCTURE WORK
B11: BILL NO 4 | C11: 20 NEW HOUSING UNIT | D11: ='BILL NO4. (20 NHU)'!I34 -> 947257 | E11: ='BILL NO4. (20 NHU)'!K34 -> 656066.04 | G11: ='BILL NO4. (20 NHU)'!M34 -> 291914.71 | I11: -------------
B13: BILL NO 5 | C13: MAINTENANCE HOUSING UNIT - 29 UNIT | D13: ='BILL NO 5. (MAINTENANCE HOUSING'!I116 -> 1436308.6 | E13: ='BILL NO 5. (MAINTENANCE HOUSING'!K116 -> 1426316.8 | G13: ='SUMMARY OF BILL NO. (4 - 7)'!N75 -> 9991.805 | H13: ='APPENDIX - B'!G24 -> 11890 | I13: -------------
B16: BILL NO 6 | C16: PROTECTION AND STORM WATER DRAINAGE | D16: ='BILL NO 6 (STORM WATER)'!I35 -> 265674.67 | G16: ='Copy of BILL NO 6 (STORM WATER)'!K51 -> 265674.67 | I16: -------------
B18: BILL NO 7 | C18: 3 NEW HOUSING UNIT | D18: ='BILL NO 7. (3 NHU)'!I33*3 -> 36105 | E18: ='BILL NO 7. (3 NHU)'!K33*3 -> 25589.844 | G18: ='BILL NO 7. (3 NHU)'!M33*3 -> 10515.156 | I18: -------------
C20: SUPERSTRUCTURE WORK
B21: BILL NO 4 | C21: 20 NEW HOUSING UNIT | D21: ='BILL NO4. (20 NHU)'!I371-D11 -> 1018113.9 | E21: ='BILL NO4. (20 NHU)'!K371-E11 -> 894712.44 | G21: ='BILL NO4. (20 NHU)'!M371-G11 -> 123401.5 | H21: ='BILL NO4. (20 NHU)'!O371 -> 23100
B23: BILL NO 7 | C23: 3 NEW HOUSING UNIT | D23: =SUM('BILL NO 7. (3 NHU)'!I194+'BILL NO 7. (3 NHU)'!I115+'BILL NO 7. (3 NHU)'!I52+'BILL NO 7. (3 NHU)'!I46+'BILL NO 7. (3 NHU)'!I41+'BILL NO 7. (3 NHU)'!I36)*3+0.025 -> 203886.02 | E23: =SUM('BILL NO 7. (3 NHU)'!K194+'BILL NO 7. (3 NHU)'!K115+'BILL NO 7. (3 NHU)'!K52+'BILL NO 7. (3 NHU)'!K46+'BILL NO 7. (3 NHU)'!K41+'BILL NO 7. (3 NHU)'!K36)*3 -> 181521 | G23: ='BILL NO 7. (3 NHU)'!M193-G18 -> 25110 | H23: ='SUM. OF ADD. WORKS (BILL NO. 4 '!G17 -> 1111.44 | I23: -------------
B27: BILL NO 4 | C27: EXTERNAL WORK (20 NEW HOUSING UNIT) | D27: ='BILL NO 4 (20 NHU EXTERNAL WORK'!I15 -> 28455 | E27: ='BILL NO 4 (20 NHU EXTERNAL WORK'!K15 -> 26355 | G27: ='BILL NO 4 (20 NHU EXTERNAL WORK'!M14 -> 2100 | I27: -------------
D29: =SUM(D4:D28) -> 4451632.7 | E29: =SUM(E4:E28)+I21 -> 3313341.1 | F29: =D29-E29 -> 1138291.6 | G29: =SUM(G4:G28) -> 1141770.3

Sheet SUMMARY OF BILL NO. (4 - 7)
B2: BILL NO 4 (20 NEW HOUSING UNIT)
B3: #REF! | C3: #REF! | D3: #REF! | E3: #REF! | F3: #REF! | G3: #REF! | H3: #REF! | I3: #REF! | J3: #REF! | K3: #REF! | L3: #REF! | M3: ADDITION AMOUNT | N3: ='[1]BILL NO 4 (20'!M2 -> #REF!
B6: #REF! | C6: #REF! | D6: #REF! | E6: #REF! | F6: #REF! | G6: #REF! | H6: #REF! | I6: #REF! | J6: #REF! | K6: #REF! | L6: #REF! | N6: #REF!
B7: #REF! | C7: #REF! | D7: #REF! | E7: #REF! | F7: #REF! | G7: #REF! | H7: #REF! | I7: #REF! | J7: #REF! | K7: #REF! | L7: #REF! | N7: #REF!
B8: #REF! | C8: #REF! | D8: #REF! | E8: #REF! | F8: #REF! | G8: #REF! | H8: #REF! | I8: #REF! | J8: #REF! | K8: #REF! | L8: #REF! | N8: #REF!
B9: #REF! | C9: #REF! | D9: #REF! | E9: #REF! | F9: #REF! | G9: #REF! | H9: #REF! | I9: #REF! | J9: #REF! | K9: #REF! | L9: #REF! | N9: #REF!
B10: #REF! | C10: #REF! | D10: #REF! | E10: #REF! | F10: #REF! | G10: #REF! | H10: #REF! | I10: #REF! | J10: #REF! | K10: #REF! | L10: #REF! | N10: #REF!
B11: #REF! | C11: #REF! | D11: #REF! | E11: #REF! | F11: #REF! | G11: #REF! | H11: #REF! | I11: #REF! | J11: #REF! | K11: #REF! | L11: #REF! | M11: =L11*G11 -> #VALUE! | N11: #REF!
B12: #REF! | C12: #REF! | D12: #REF! | E12: #REF! | F12: #REF! | G12: #REF! | H12: #REF! | I12: #REF! | J12: #REF! | K12: #REF! | L12: #REF! | N12: #REF!
B13: #REF! | C13: #REF! | D13: #REF! | E13: #REF! | F13: #REF! | G13: #REF! | H13: #REF! | I13: #REF! | J13: #REF! | K13: #REF! | L13: #REF! | N13: #REF!
B14: #REF! | C14: #REF! | D14: #REF! | E14: #REF! | F14: #REF! | G14: #REF! | H14: #REF! | I14: #REF! | J14: #REF! | K14: #REF! | L14: #REF! | N14: ='[1]BILL NO 4 (20'!M13 -> #REF!
B15: #REF! | C15: #REF! | D15: #REF! | E15: #REF! | F15: #REF! | G15: #REF! | H15: #REF! | I15: #REF! | J15: #REF! | K15: #REF! | L15: #REF! | N15: ='[1]BILL NO 4 (20'!M15 -> #REF!
B16: #REF! | C16: #REF! | D16: #REF! | E16: #REF! | F16: #REF! | G16: #REF! | H16: #REF! | I16: #REF! | J16: #REF! | K16: #REF! | L16: #REF! | N16: ='[1]BILL NO 4 (20'!M17 -> #REF!
B17: #REF! | C17: #REF! | D17: #REF! | E17: #REF! | F17: #REF! | G17: #REF! | H17: #REF! | I17: #REF! | J17: #REF! | K17: #REF! | L17: #REF! | N17: ='[1]BILL NO 4 (20'!M19 -> #REF!
B18: #REF! | C18: #REF! | D18: #REF! | E18: #REF! | F18: #REF! | G18: #REF! | H18: #REF! | I18: #REF! | J18: #REF! | K18: #REF! | L18: #REF! | N18: #REF!
B19: #REF! | C19: #REF! | D19: #REF! | E19: #REF! | F19: #REF! | G19: #REF! | H19: #REF! | I19: #REF! | J19: #REF! | K19: #REF! | L19: #REF! | N19: #REF!
B20: #REF! | C20: #REF! | D20: #REF! | E20: #REF! | F20: #REF! | G20: #REF! | H20: #REF! | I20: #REF! | J20: #REF! | K20: #REF! | L20: #REF! | N20: #REF!
B21: #REF! | C21: #REF! | D21: #REF! | E21: #REF! | F21: #REF! | G21: #REF! | H21: #REF! | I21: #REF! | J21: #REF! | K21: #REF! | L21: #REF! | N21: #REF!
B22: #REF! | C22: #REF! | D22: #REF! | E22: #REF! | F22: ='[1]BILL NO 4 (20'!F25 -> #REF! | G22: #REF! | H22: #REF! | I22: #REF! | J22: #REF! | K22: #REF! | L22: #REF! | N22: #REF!
B23: #REF! | C23: #REF! | D23: #REF! | E23: #REF! | F23: #REF! | G23: #REF! | H23: #REF! | I23: #REF! | J23: #REF! | K23: #REF! | L23: #REF! | N23: #REF!
C25: SUBSTRUCTURE WORKS | I25: =SUM(I6:I24) -> 0 | K25: =SUM(K6:K24) -> 0 | M25: =SUM(M6:M24) -> #VALUE! | N25: =SUM(N6:N24) -> #REF!
B26: #REF! | C26: #REF! | D26: #REF! | E26: #REF! | F26: #REF! | G26: #REF! | H26: #REF! | I26: #REF! | J26: #REF! | K26: #REF! | L26: #REF! | N26: #REF!
B27: #REF! | C27: #REF! | D27: #REF! | E27: #REF! | F27: #REF! | G27: #REF! | H27: #REF! | I27: #REF! | J27: #REF! | K27: #REF! | L27: #REF! | N27: #REF!
B28: #REF! | C28: #REF! | D28: #REF! | E28: #REF! | F28: #REF! | G28: #REF! | H28: #REF! | I28: #REF! | J28: #REF! | K28: #REF! | L28: #REF! | N28: #REF!
B29: #REF! | C29: #REF! | D29: #REF! | E29: #REF! | F29: #REF! | G29: #REF! | H29: #REF! | I29: #REF! | J29: #REF! | L29: ='[1]BILL NO 4 (20'!L211 -> #REF! | N29: =H29*G29 -> #VALUE!
B30: #REF! | C30: #REF! | D30: #REF! | E30: #REF! | F30: #REF! | G30: #REF! | H30: #REF! | I30: #REF! | J30: #REF! | K30: #REF! | L30: #REF! | N30: #REF!
B31: #REF! | C31: #REF! | D31: #REF! | E31: #REF! | F31: #REF! | G31: #REF! | H31: #REF! | I31: #REF! | J31: #REF! | K31: #REF! | L31: #REF! | N31: #REF!
B32: #REF! | C32: #REF! | D32: #REF! | E32: #REF! | F32: #REF! | G32: #REF! | H32: #REF! | I32: #REF! | J32: #REF! | K32: #REF! | L32: #REF! | N32: #REF!
B33: #REF! | C33: #REF! | D33: #REF! | E33: #REF! | F33: #REF! | G33: #REF! | H33: #REF! | I33: #REF! | J33: #REF! | K33: #REF! | L33: #REF! | N33: #REF!
B34: #REF! | C34: #REF! | D34: #REF! | E34: #REF! | F34: #REF! | G34: #REF! | H34: #REF! | I34: #REF! | J34: #REF! | L34: #REF! | N34: #REF!
B35: #REF! | C35: #REF! | D35: #REF! | E35: #REF! | F35: #REF! | G35: #REF! | H35: #REF! | I35: #REF! | J35: #REF! | L35: #REF! | N35: =G35*H35 -> #VALUE!
B36: #REF! | C36: #REF! | D36: #REF! | E36: #REF! | F36: #REF! | G36: #REF! | H36: #REF! | I36: #REF! | J36: #REF! | L36: #REF! | N36: =G36*H36 -> #VALUE!
B37: #REF! | C37: #REF! | D37: #REF! | E37: #REF! | F37: #REF! | G37: #REF! | H37: #REF! | I37: #REF! | J37: #REF! | N37: =H37*G37 -> #VALUE!
B38: #REF! | C38: #REF! | D38: #REF! | E38: #REF! | F38: #REF! | G38: #REF! | H38: #REF! | I38: #REF! | J38: #REF! | N38: =H38*G38 -> #VALUE!
B41: SUPERSTRUCTURE WORK | I41: =SUM(I26:I40) -> 0 | K41: =SUM(K26:K40) -> 0 | N41: =SUM(N26:N40) -> #VALUE!
B42: SUB - TOTAL
C43: SUBSTRUCTURE | I43: =I25 -> 0 | J43: =J25 -> 0 | K43: =K25 -> 0 | M43: =M25 -> #VALUE! | N43: =N25 -> #REF!
C44: SUPERSTRUCTURE | I44: =I41 -> 0 | K44: =K41 -> 0 | M44: =M41 -> 0 | N44: =N41 -> #VALUE!
B47: 20 NEW HOUSING UNITS | I47: =SUM(I43:I46) -> 0 | J47: =SUM(J43:J46) -> 0 | K47: =SUM(K43:K46) -> 0 | M47: =SUM(M43:M46) -> #VALUE! | N47: =SUM(N43:N46) -> #REF!
B51: BILLL NO 4 (EXTERNAL WORKS)
B52: ='BILL NO 4 (20 NHU EXTERNAL WORK'!B3 -> Item Code | C52: ='BILL NO 4 (20 NHU EXTERNAL WORK'!C3 -> Item Name | D52: ='BILL NO 4 (20 NHU EXTERNAL WORK'!D3 -> Item Details | E52: ='BILL NO 4 (20 NHU EXTERNAL WORK'!E3 -> Additional Information | F52: ='BILL NO 4 (20 NHU EXTERNAL WORK'!F3 -> UOM | G52: ='BILL NO 4 (20 NHU EXTERNAL WORK'!G3 -> Unit Price In Figure | H52: ='BILL NO 4 (20 NHU EXTERNAL WORK'!H3 -> BOQ QTY | I52: ='BILL NO 4 (20 NHU EXTERNAL WORK'!I3 -> BOQ Amount | ... L52: ='BILL NO 4 (20 NHU EXTERNAL WORK'!L3 -> Addition/Omission Quantity | M52: ADDITION AMOUNT | N52: ='BILL NO 4 (20 NHU EXTERNAL WORK'!M3 -> OMISSION
B54: ='BILL NO 4 (20 NHU EXTERNAL WORK'!B14 -> EW11 | C54: ='BILL NO 4 (20 NHU EXTERNAL WORK'!C14 -> External Works General Site Works | D54: ='BILL NO 4 (20 NHU EXTERNAL WORK'!D14 -> Design and Build Shaded Car Parking of 20 numbers with Solar Panel Canopy | E54: ='BILL NO 4 (20 NHU EXTERNAL WORK'!E14 -> Allow for the Contractor to design and build the Shaded Car Park for houses with Solar Panel Canopy as per Engineer Employer Instruction. | F54: ='BILL NO 4 (20 NHU EXTERNAL WORK'!F14 -> no | G54: ='BILL NO 4 (20 NHU EXTERNAL WORK'!G14 -> 105 | H54: ='BILL NO 4 (20 NHU EXTERNAL WORK'!H14 -> 20 | I54: ='BILL NO 4 (20 NHU EXTERNAL WORK'!I14 -> 2100 | ... L54: ='BILL NO 4 (20 NHU EXTERNAL WORK'!L14 -> 20 | N54: ='BILL NO 4 (20 NHU EXTERNAL WORK'!M14 -> 2100
B58: EXTERNAL WORK (20 NEW HOUSING UNIT) | I58: =SUM(I54:I57) -> 2100 | K58: 0 | M58: 0 | N58: =SUM(N54:N57) -> 2100
B62: BILL NO 5 (MAINTENANCE OF 29 HOUSING UNITS)
B63: Item Code | C63: Item Name | D63: Item Details | E63: Additional Information | F63: UOM | G63: BOQ Qty | H63: Revised QTY | I63: Unit Price In Figure-OMR | J63: BOQ Total Amount-OMR | K63: Revised Amount (Claimable) | L63: Saving Quantities | M63: ADDITION AMOUNT | N63: Savings Amount
B66: ='BILL NO 5. (MAINTENANCE HOUSING'!B12 -> EX7 | C66: ='BILL NO 5. (MAINTENANCE HOUSING'!C12 -> External Works Lump sum | D66: ='BILL NO 5. (MAINTENANCE HOUSING'!D12 -> Dewatering | E66: ='BILL NO 5. (MAINTENANCE HOUSING'!E12 -> Allow for keeping excavations free from underground surface or running water from whatever source | F66: ='BILL NO 5. (MAINTENANCE HOUSING'!F12 -> Item | G66: ='BILL NO 5. (MAINTENANCE HOUSING'!G12 -> 29 | H66: ='BILL NO 5. (MAINTENANCE HOUSING'!J12 -> 29 | I66: ='BILL NO 5. (MAINTENANCE HOUSING'!H12 -> 252 | J66: ='BILL NO 5. (MAINTENANCE HOUSING'!I12 -> 7308 | K66: ='BILL NO 5. (MAINTENANCE HOUSING'!K12 -> 0 | L66: ='BILL NO 5. (MAINTENANCE HOUSING'!L12 -> 29 | N66: =G66*I66 -> 7308
B67: ='BILL NO 5. (MAINTENANCE HOUSING'!B58 -> P8 | C67: ='BILL NO 5. (MAINTENANCE HOUSING'!C58 -> Sanitary Wares and Fittings | D67: ='BILL NO 5. (MAINTENANCE HOUSING'!D58 -> shower tray | E67: ='BILL NO 5. (MAINTENANCE HOUSING'!E58 -> Supply and install white glazed shower tray size 70x70 with the necessary fittings and plumbing darins including all UPVC and PVC pipes for water supply and drain with fittings and flexible pipes | F67: ='BILL NO 5. (MAINTENANCE HOUSING'!F58 -> Item | G67: ='BILL NO 5. (MAINTENANCE HOUSING'!G58 -> 29 | H67: ='BILL NO 5. (MAINTENANCE HOUSING'!J58 -> 29 | I67: ='BILL NO 5. (MAINTENANCE HOUSING'!H58 -> 12.6 | J67: ='BILL NO 5. (MAINTENANCE HOUSING'!I58 -> 365.4 | K67: ='BILL NO 5. (MAINTENANCE HOUSING'!K58 -> 0 | L67: ='BILL NO 5. (MAINTENANCE HOUSING'!L58 -> 29 | N67: =H67*I67 -> 365.4
B68: ='BILL NO 5. (MAINTENANCE HOUSING'!B83 -> E2 | C68: ='BILL NO 5. (MAINTENANCE HOUSING'!C83 -> Electrical Engineering Installation | D68: ='BILL NO 5. (MAINTENANCE HOUSING'!D83 -> Contractor to provide full Solar system | E68: ='BILL NO 5. (MAINTENANCE HOUSING'!E83 -> The contractor to Design and Provide the solar system including all materials and supply and fix it to be compatible with the MCCP and DBs at the houses and get the approvals from the ClientEngineer before executing any work | F68: ='BILL NO 5. (MAINTENANCE HOUSING'!F83 -> Item | G68: ='BILL NO 5. (MAINTENANCE HOUSING'!G83 -> 29 | H68: ='BILL NO 5. (MAINTENANCE HOUSING'!J83 -> 0 | I68: ='BILL NO 5. (MAINTENANCE HOUSING'!H83 -> 0 | J68: ='BILL NO 5. (MAINTENANCE HOUSING'!I83 -> - | K68: ='BILL NO 5. (MAINTENANCE HOUSING'!K83 -> 0 | L68: ='BILL NO 5. (MAINTENANCE HOUSING'!L83 -> 29 | N68: ='BILL NO 5. (MAINTENANCE HOUSING'!M83 -> 0
B69: ='BILL NO 5. (MAINTENANCE HOUSING'!B86 -> E5 | C69: ='BILL NO 5. (MAINTENANCE HOUSING'!C86 -> Electrical Engineering Installation | D69: ='BILL NO 5. (MAINTENANCE HOUSING'!D86 -> Sub Main Distribution Board | E69: ='BILL NO 5. (MAINTENANCE HOUSING'!E86 -> The contractor to add a new DB for the New Caravans to be weatherproof GRP IP 65 . | F69: ='BILL NO 5. (MAINTENANCE HOUSING'!F86 -> Item | G69: ='BILL NO 5. (MAINTENANCE HOUSING'!G86 -> 29 | H69: ='BILL NO 5. (MAINTENANCE HOUSING'!J86 -> 29 | I69: ='BILL NO 5. (MAINTENANCE HOUSING'!H86 -> 62.566 | J69: ='BILL NO 5. (MAINTENANCE HOUSING'!I86 -> 1814.414 | K69: ='BILL NO 5. (MAINTENANCE HOUSING'!K86 -> 0 | L69: ='BILL NO 5. (MAINTENANCE HOUSING'!L86 -> 29 | N69: =H69*I69 -> 1814.414
B70: ='BILL NO 5. (MAINTENANCE HOUSING'!B108 -> E25 | C70: ='BILL NO 5. (MAINTENANCE HOUSING'!C108 -> Electrical Engineering Installation | D70: ='BILL NO 5. (MAINTENANCE HOUSING'!D108 -> Lighting Fixture | E70: ='BILL NO 5. (MAINTENANCE HOUSING'!E108 -> Supply install connect test and commission of the following lighting fixtures Emergency light | F70: ='BILL NO 5. (MAINTENANCE HOUSING'!F108 -> Item | G70: ='BILL NO 5. (MAINTENANCE HOUSING'!G108 -> 29 | H70: ='BILL NO 5. (MAINTENANCE HOUSING'!J108 -> 29 | I70: ='BILL NO 5. (MAINTENANCE HOUSING'!H108 -> 17.379 | J70: ='BILL NO 5. (MAINTENANCE HOUSING'!I108 -> 503.991 | K70: ='BILL NO 5. (MAINTENANCE HOUSING'!K108 -> 0 | L70: ='BILL NO 5. (MAINTENANCE HOUSING'!L108 -> 29 | N70: =H70*I70 -> 503.991
B71: ='BILL NO 5. (MAINTENANCE HOUSING'!B113 -> G1 | C71: ='BILL NO 5. (MAINTENANCE HOUSING'!C113 -> Sundrie | D71: ='BILL NO 5. (MAINTENANCE HOUSING'!D113 -> Sundrie Items | E71: ='BILL NO 5. (MAINTENANCE HOUSING'!E113 -> Any other works not specifically enumerated under the works in this bill but indicated in the drawings or required to complete the work in manner of respect to handover the project in working and safe conditions to the residents specification or needed to complete the work. | F71: ='BILL NO 5. (MAINTENANCE HOUSING'!F113 -> Item | G71: ='BILL NO 5. (MAINTENANCE HOUSING'!G113 -> 29 | H71: ='BILL NO 5. (MAINTENANCE HOUSING'!J113 -> 29 | I71: ='BILL NO 5. (MAINTENANCE HOUSING'!H113 -> 52.138 | J71: ='BILL NO 5. (MAINTENANCE HOUSING'!I113 -> 1512.002 | K71: ='BILL NO 5. (MAINTENANCE HOUSING'!K113 -> 1512.002 | L71: ='BILL NO 5. (MAINTENANCE HOUSING'!L113 -> 0
B75: BIL NO 5 - MAINTENANCE WORK | J75: =SUM(J66:J74) -> 11503.807 | K75: =SUM(K66:K74) -> 1512.002 | M75: 0 | N75: =SUM(N66:N74) -> 9991.805
B79: BILL NO 6 (STORM WATER AND PROTECTION)
B80: Item Code | C80: Item Name | D80: Item Details | E80: Additional Information | F80: Unit | G80: Qty | H80: Unit Price in Figure | I80: Omission work | J80: Total Price in Figure
B82: ='BILL NO 6 (STORM WATER)'!B6 -> PSW9 | C82: ='BILL NO 6 (STORM WATER)'!C6 -> Earthwork | D82: ='BILL NO 6 (STORM WATER)'!D6 -> Earthwork for pipe Trenches | E82: ='BILL NO 6 (STORM WATER)'!E6 -> Trench excavation and backfilling Depth 0 to 2m | F82: ='BILL NO 6 (STORM WATER)'!F6 -> m3 | G82: ='BILL NO 6 (STORM WATER)'!G6 -> 9180 | H82: ='BILL NO 6 (STORM WATER)'!H6 -> 0.7 | I82: ='BILL NO 6 (STORM WATER)'!I6 -> 6426 | J82: ='BILL NO 6 (STORM WATER)'!J6 -> 6426
B83: ='BILL NO 6 (STORM WATER)'!B7 -> PSW10 | C83: ='BILL NO 6 (STORM WATER)'!C7 -> Earthwork | D83: ='BILL NO 6 (STORM WATER)'!D7 -> Earthwork for pipe Trenches | E83: ='BILL NO 6 (STORM WATER)'!E7 -> Trench excavation and backfilling Depth 2m to 2m | F83: ='BILL NO 6 (STORM WATER)'!F7 -> m3 | G83: ='BILL NO 6 (STORM WATER)'!G7 -> 12615 | H83: ='BILL NO 6 (STORM WATER)'!H7 -> 1.575 | I83: ='BILL NO 6 (STORM WATER)'!I7 -> 19868.625 | J83: ='BILL NO 6 (STORM WATER)'!J7 -> 19868.625
B84: ='BILL NO 6 (STORM WATER)'!B8 -> PSW11 | C84: ='BILL NO 6 (STORM WATER)'!C8 -> Earthwork | D84: ='BILL NO 6 (STORM WATER)'!D8 -> Earthwork for pipe Trenches | E84: ='BILL NO 6 (STORM WATER)'!E8 -> Trench excavation and backfilling Depth 3m to 4m | F84: ='BILL NO 6 (STORM WATER)'!F8 -> m3 | G84: ='BILL NO 6 (STORM WATER)'!G8 -> 3090 | H84: ='BILL NO 6 (STORM WATER)'!H8 -> 2.1 | I84: ='BILL NO 6 (STORM WATER)'!I8 -> 6489 | J84: ='BILL NO 6 (STORM WATER)'!J8 -> 6489
B85: ='BILL NO 6 (STORM WATER)'!B9 -> PSW12 | C85: ='BILL NO 6 (STORM WATER)'!C9 -> Earthwork | D85: ='BILL NO 6 (STORM WATER)'!D9 -> Earthwork for pipe Trenches | E85: ='BILL NO 6 (STORM WATER)'!E9 -> Trench excavation and backfilling Depth more than 4m | F85: ='BILL NO 6 (STORM WATER)'!F9 -> m3 | G85: ='BILL NO 6 (STORM WATER)'!G9 -> 4080 | H85: ='BILL NO 6 (STORM WATER)'!H9 -> 4.2 | I85: ='BILL NO 6 (STORM WATER)'!I9 -> 17136 | J85: ='BILL NO 6 (STORM WATER)'!J9 -> 17136
B86: ='BILL NO 6 (STORM WATER)'!B10 -> PSW13 | C86: ='BILL NO 6 (STORM WATER)'!C10 -> 3 Granular Subbase Aggregate Base Course and Stabilized Base Courses. | D86: ='BILL NO 6 (STORM WATER)'!D10 -> Redesign and Construction of Asphalt Road to be suitable for Erection of Culvert with all necessary drawings details… | E86: ='BILL NO 6 (STORM WATER)'!E10 -> Aggregate Base Course Class B | F86: ='BILL NO 6 (STORM WATER)'!F10 -> m3 | G86: ='BILL NO 6 (STORM WATER)'!G10 -> 1500 | H86: ='BILL NO 6 (STORM WATER)'!H10 -> 2.1 | I86: ='BILL NO 6 (STORM WATER)'!I10 -> 3150 | J86: ='BILL NO 6 (STORM WATER)'!J10 -> 0
B87: ='BILL NO 6 (STORM WATER)'!B11 -> PSW14 | C87: ='BILL NO 6 (STORM WATER)'!C11 -> 4 Bituminous Pavement | D87: ='BILL NO 6 (STORM WATER)'!D11 -> Redesign and Construction of Asphalt Road to be suitable for Erection of Culvert with all necessary drawings details… | E87: ='BILL NO 6 (STORM WATER)'!E11 -> Bituminous Prime Coat Application rate 1.5 KgSq.m | F87: ='BILL NO 6 (STORM WATER)'!F11 -> m3 | G87: ='BILL NO 6 (STORM WATER)'!G11 -> 4050 | H87: ='BILL NO 6 (STORM WATER)'!H11 -> 2.1 | I87: ='BILL NO 6 (STORM WATER)'!I11 -> 8505 | J87: ='BILL NO 6 (STORM WATER)'!J11 -> 0
B88: ='BILL NO 6 (STORM WATER)'!B12 -> PSW15 | C88: ='BILL NO 6 (STORM WATER)'!C12 -> Asphalt Road | D88: ='BILL NO 6 (STORM WATER)'!D12 -> Redesign and Construction of Asphalt Road to be suitable for Erection of Culvert with all necessary drawings details… | E88: ='BILL NO 6 (STORM WATER)'!E12 -> Bituminous Wearing Course Class B | F88: ='BILL NO 6 (STORM WATER)'!F12 -> m3 | G88: ='BILL NO 6 (STORM WATER)'!G12 -> 280 | H88: ='BILL NO 6 (STORM WATER)'!H12 -> 12.6 | I88: ='BILL NO 6 (STORM WATER)'!I12 -> 3528 | J88: ='BILL NO 6 (STORM WATER)'!J12 -> 0
B89: ='BILL NO 6 (STORM WATER)'!B14 -> PSW18 | C89: ='BILL NO 6 (STORM WATER)'!C14 -> Concrete and Concrete Structures | D89: ='BILL NO 6 (STORM WATER)'!D14 -> Construction of Box culvert N2 Size 2x1.5m concrete class 30 with reinforcement as per HDS 2017 including wing wall foundations bituminous paint excavation backfilling and as directed by Engineer | E89: ='BILL NO 6 (STORM WATER)'!E14 -> Concrete Class 35 in box culverts wing walls apron slab retaining walls and debris foundations. | F89: ='BILL NO 6 (STORM WATER)'!F14 -> m3 | G89: ='BILL NO 6 (STORM WATER)'!G14 -> 375 | H89: ='BILL NO 6 (STORM WATER)'!H14 -> 12.6 | I89: ='BILL NO 6 (STORM WATER)'!I14 -> 4725 | J89: ='BILL NO 6 (STORM WATER)'!J14 -> 0
B90: ='BILL NO 6 (STORM WATER)'!B16 -> PSW20 | C90: ='BILL NO 6 (STORM WATER)'!C16 -> Concrete and Concrete structure | D90: ='BILL NO 6 (STORM WATER)'!D16 -> Construction of Box culvert N2 Size 2x1.5m concrete class 30 with reinforcement as per HDS 2017 including wing wall foundations bituminous paint excavation backfilling and as directed by Engineer | E90: ='BILL NO 6 (STORM WATER)'!E16 -> High tensile steel bar factory epoxy coated reinforcement of any diameter | F90: ='BILL NO 6 (STORM WATER)'!F16 -> Ton | G90: ='BILL NO 6 (STORM WATER)'!G16 -> 55 | H90: ='BILL NO 6 (STORM WATER)'!H16 -> 94.5 | I90: ='BILL NO 6 (STORM WATER)'!I16 -> 5197.5 | J90: ='BILL NO 6 (STORM WATER)'!J16 -> 0
B91: ='BILL NO 6 (STORM WATER)'!B17 -> PSW22 | C91: ='BILL NO 6 (STORM WATER)'!C17 -> Concrete and Concrete structure | D91: ='BILL NO 6 (STORM WATER)'!D17 -> Construction of Box culvert N2 Size 2x1.5m concrete class 30 with reinforcement as per HDS 2017 including wing wall foundations bituminous paint excavation backfilling and as directed by Engineer | E91: ='BILL NO 6 (STORM WATER)'!E17 -> Tar or bituminous paint Type II 2 coats for surfaces in contact with earth in all structures | F91: ='BILL NO 6 (STORM WATER)'!F17 -> m2 | G91: ='BILL NO 6 (STORM WATER)'!G17 -> 1420 | H91: ='BILL NO 6 (STORM WATER)'!H17 -> 1.05 | I91: ='BILL NO 6 (STORM WATER)'!I17 -> 1491 | J91: ='BILL NO 6 (STORM WATER)'!J17 -> 0
B92: ='BILL NO 6 (STORM WATER)'!B18 -> PSW23 | C92: ='BILL NO 6 (STORM WATER)'!C18 -> Concrete and Concrete structure | D92: ='BILL NO 6 (STORM WATER)'!D18 -> Construction of Box culvert N2 Size 2x1.5m concrete class 30 with reinforcement as per HDS 2017 including wing wall foundations bituminous paint excavation backfilling and as directed by Engineer | E92: ='BILL NO 6 (STORM WATER)'!E18 -> Membrane Waterproofing Geotextile 4mm thickness | F92: ='BILL NO 6 (STORM WATER)'!F18 -> m2 | G92: ='BILL NO 6 (STORM WATER)'!G18 -> 15500 | H92: ='BILL NO 6 (STORM WATER)'!H18 -> 1.05 | I92: ='BILL NO 6 (STORM WATER)'!I18 -> 16275 | J92: ='BILL NO 6 (STORM WATER)'!J18 -> 0
B93: ='BILL NO 6 (STORM WATER)'!B19 -> PSW25 | C93: ='BILL NO 6 (STORM WATER)'!C19 -> Drainage | D93: ='BILL NO 6 (STORM WATER)'!D19 -> Storm Sewer | E93: ='BILL NO 6 (STORM WATER)'!E19 -> Storm Sewer GRP Diamter 300mm | F93: ='BILL NO 6 (STORM WATER)'!F19 -> m | G93: ='BILL NO 6 (STORM WATER)'!G19 -> 315 | H93: ='BILL NO 6 (STORM WATER)'!H19 -> 3.15 | I93: ='BILL NO 6 (STORM WATER)'!I19 -> 992.25 | J93: ='BILL NO 6 (STORM WATER)'!J19 -> 992.25
B94: ='BILL NO 6 (STORM WATER)'!B20 -> PSW26 | C94: ='BILL NO 6 (STORM WATER)'!C20 -> Drainage | D94: ='BILL NO 6 (STORM WATER)'!D20 -> Storm Sewer | E94: ='BILL NO 6 (STORM WATER)'!E20 -> Storm Sewer GRP Diamter 400mm | F94: ='BILL NO 6 (STORM WATER)'!F20 -> m | G94: ='BILL NO 6 (STORM WATER)'!G20 -> 1270 | H94: ='BILL NO 6 (STORM WATER)'!H20 -> 2.1 | I94: ='BILL NO 6 (STORM WATER)'!I20 -> 2667 | J94: ='BILL NO 6 (STORM WATER)'!J20 -> 2667
B95: ='BILL NO 6 (STORM WATER)'!B21 -> PSW27 | C95: ='BILL NO 6 (STORM WATER)'!C21 -> Drainage | D95: ='BILL NO 6 (STORM WATER)'!D21 -> Storm Sewer | E95: ='BILL NO 6 (STORM WATER)'!E21 -> Storm Sewer GRP Diamter 500mm | F95: ='BILL NO 6 (STORM WATER)'!F21 -> m | G95: ='BILL NO 6 (STORM WATER)'!G21 -> 345 | H95: ='BILL NO 6 (STORM WATER)'!H21 -> 1.575 | I95: ='BILL NO 6 (STORM WATER)'!I21 -> 543.375 | J95: ='BILL NO 6 (STORM WATER)'!J21 -> 543.375
B96: ='BILL NO 6 (STORM WATER)'!B22 -> PSW28 | C96: ='BILL NO 6 (STORM WATER)'!C22 -> Drainage | D96: ='BILL NO 6 (STORM WATER)'!D22 -> Storm Sewer | E96: ='BILL NO 6 (STORM WATER)'!E22 -> Storm Sewer R.C Diamter 600mm | F96: ='BILL NO 6 (STORM WATER)'!F22 -> m | G96: ='BILL NO 6 (STORM WATER)'!G22 -> 865 | H96: ='BILL NO 6 (STORM WATER)'!H22 -> 1.575 | I96: ='BILL NO 6 (STORM WATER)'!I22 -> 1362.375 | J96: ='BILL NO 6 (STORM WATER)'!J22 -> 1362.375
B97: ='BILL NO 6 (STORM WATER)'!B23 -> PSW29 | C97: ='BILL NO 6 (STORM WATER)'!C23 -> Drainage | D97: ='BILL NO 6 (STORM WATER)'!D23 -> Storm Sewer | E97: ='BILL NO 6 (STORM WATER)'!E23 -> Storm Sewer R.C Diamter 700mm | F97: ='BILL NO 6 (STORM WATER)'!F23 -> m | G97: ='BILL NO 6 (STORM WATER)'!G23 -> 1090 | H97: ='BILL NO 6 (STORM WATER)'!H23 -> 2.1 | I97: ='BILL NO 6 (STORM WATER)'!I23 -> 2289 | J97: ='BILL NO 6 (STORM WATER)'!J23 -> 2289
B98: ='BILL NO 6 (STORM WATER)'!B24 -> PSW30 | C98: ='BILL NO 6 (STORM WATER)'!C24 -> Drainage | D98: ='BILL NO 6 (STORM WATER)'!D24 -> Storm Sewer | E98: ='BILL NO 6 (STORM WATER)'!E24 -> Storm Sewer R.C Diamter 800mm | F98: ='BILL NO 6 (STORM WATER)'!F24 -> m | G98: ='BILL NO 6 (STORM WATER)'!G24 -> 460 | H98: ='BILL NO 6 (STORM WATER)'!H24 -> 2.1 | I98: ='BILL NO 6 (STORM WATER)'!I24 -> 966 | J98: ='BILL NO 6 (STORM WATER)'!J24 -> 966
B99: ='BILL NO 6 (STORM WATER)'!B25 -> PSW31 | C99: ='BILL NO 6 (STORM WATER)'!C25 -> Drainage | D99: ='BILL NO 6 (STORM WATER)'!D25 -> Storm Sewer | E99: ='BILL NO 6 (STORM WATER)'!E25 -> Storm Sewer R.C Diamter 900mm | F99: ='BILL NO 6 (STORM WATER)'!F25 -> m | G99: ='BILL NO 6 (STORM WATER)'!G25 -> 130 | H99: ='BILL NO 6 (STORM WATER)'!H25 -> 3.15 | I99: ='BILL NO 6 (STORM WATER)'!I25 -> 409.5 | J99: ='BILL NO 6 (STORM WATER)'!J25 -> 409.5
B100: ='BILL NO 6 (STORM WATER)'!B26 -> PSW32 | C100: ='BILL NO 6 (STORM WATER)'!C26 -> Drainage | D100: ='BILL NO 6 (STORM WATER)'!D26 -> Storm Sewer | E100: ='BILL NO 6 (STORM WATER)'!E26 -> Storm Sewer R.C Diamter 1200mm | F100: ='BILL NO 6 (STORM WATER)'!F26 -> m | G100: ='BILL NO 6 (STORM WATER)'!G26 -> 490 | H100: ='BILL NO 6 (STORM WATER)'!H26 -> 3.15 | I100: ='BILL NO 6 (STORM WATER)'!I26 -> 1543.5 | J100: ='BILL NO 6 (STORM WATER)'!J26 -> 1543.5
B101: ='BILL NO 6 (STORM WATER)'!B27 -> PSW34 | C101: ='BILL NO 6 (STORM WATER)'!C27 -> Drainage | D101: ='BILL NO 6 (STORM WATER)'!D27 -> Manholes Inlets and Chambers | E101: ='BILL NO 6 (STORM WATER)'!E27 -> R.C Manholes Chamber Ring Dia. 1200mm Type A | F101: ='BILL NO 6 (STORM WATER)'!F27 -> No | G101: ='BILL NO 6 (STORM WATER)'!G27 -> 48 | H101: ='BILL NO 6 (STORM WATER)'!H27 -> 3.15 | I101: ='BILL NO 6 (STORM WATER)'!I27 -> 151.2 | J101: ='BILL NO 6 (STORM WATER)'!J27 -> 151.2
... B106: ='BILL NO 6 (STORM WATER)'!B32 -> PSW39 | C106: ='BILL NO 6 (STORM WATER)'!C32 -> Drainage | D106: ='BILL NO 6 (STORM WATER)'!D32 -> Manholes Inlets and Chambers | E106: ='BILL NO 6 (STORM WATER)'!E32 -> UPVC Drainage pipe to drain gully to manhole 200mm Diamter | F106: ='BILL NO 6 (STORM WATER)'!F32 -> No | G106: ='BILL NO 6 (STORM WATER)'!G32 -> 2010 | H106: ='BILL NO 6 (STORM WATER)'!H32 -> 4.305 | I106: ='BILL NO 6 (STORM WATER)'!I32 -> 8653.05 | J106: ='BILL NO 6 (STORM WATER)'!J32 -> 8653.05
B109: TOTAL OMISSION BILL NO 6 | J109: =SUM(J81:J106) -> 70280.7
B113: BILL NO 7 ( 3 NEW HOUSING UNITS)
B114: ='BILL NO 7. (3 NHU)'!B3 -> Item Code | C114: ='BILL NO 7. (3 NHU)'!C3 -> Item Name | D114: ='BILL NO 7. (3 NHU)'!D3 -> Item Details | E114: ='BILL NO 7. (3 NHU)'!E3 -> Additional Information | F114: ='BILL NO 7. (3 NHU)'!F3 -> UOM | G114: ='BILL NO 7. (3 NHU)'!G3 -> BOQ-Quantity | H114: ='BILL NO 7. (3 NHU)'!H3 -> Unit Price In Figure | I114: ='BILL NO 7. (3 NHU)'!I3 -> BOQ Total Amount-OMR | ... L114: ='BILL NO 7. (3 NHU)'!L3 -> QUANTITIES | M114: ADDITION AMOUNT | N114: ='BILL NO 7. (3 NHU)'!M3 -> Amount
B117: ='BILL NO 7. (3 NHU)'!B5 -> C1 | C117: ='BILL NO 7. (3 NHU)'!C5 -> General Works | D117: ='BILL NO 7. (3 NHU)'!D5 -> Demolishing and Clearing the Construction Area. | E117: ='BILL NO 7. (3 NHU)'!E5 -> Demolishing the complete buildings up to foundations and removing the debris from the Construction Site as per Engineer/Employer Instruction (including cart-away from the Project Site) | F117: ='BILL NO 7. (3 NHU)'!F5 -> LS | G117: ='BILL NO 7. (3 NHU)'!G5 -> 1 | H117: ='BILL NO 7. (3 NHU)'!H5 -> 2000 | I117: ='BILL NO 7. (3 NHU)'!I5 -> 2000 | ... L117: ='BILL NO 7. (3 NHU)'!L5 -> 0 | N117: ='BILL NO 7. (3 NHU)'!M5 -> 0
B118: ='BILL NO 7. (3 NHU)'!B6 -> C2 | C118: ='BILL NO 7. (3 NHU)'!C6 -> Substructure Works | D118: ='BILL NO 7. (3 NHU)'!D6 -> Site Clearance | E118: ='BILL NO 7. (3 NHU)'!E6 -> This shall include removing vegetation, undergrowth, bushes, hedges, trees, other temporary buildings, structures,... or the like all complete to clean the full plot. | F118: ='BILL NO 7. (3 NHU)'!F6 -> LS | G118: ='BILL NO 7. (3 NHU)'!G6 -> 1 | H118: ='BILL NO 7. (3 NHU)'!H6 -> 1000 | I118: ='BILL NO 7. (3 NHU)'!I6 -> 1000 | ... L118: ='BILL NO 7. (3 NHU)'!L6 -> 0 | N118: ='BILL NO 7. (3 NHU)'!M6 -> 0
B119: ='BILL NO 7. (3 NHU)'!B7 -> C3 | C119: ='BILL NO 7. (3 NHU)'!C7 -> Substructure Works | D119: ='BILL NO 7. (3 NHU)'!D7 -> Earth work and Excavation | E119: ='BILL NO 7. (3 NHU)'!E7 -> Bulk Excavation to receive foundations in any kind of soil including hard soil and rock, earth sport, underground, surface or running water from whatever source if any, for the new foundation building area including removal of old buildings' foundations, cleaning the site, and removing all debris (not suitable for backfilling) from the project area to the damp yard, contractor to prepare all areas to receive new foundation safely as per drawings and soil report | F119: ='BILL NO 7. (3 NHU)'!F7 -> M3 | G119: ='BILL NO 7. (3 NHU)'!G7 -> 350 | H119: ='BILL NO 7. (3 NHU)'!H7 -> 0.8 | I119: ='BILL NO 7. (3 NHU)'!I7 -> 280 | ... L119: ='BILL NO 7. (3 NHU)'!L7 -> 70 | N119: ='BILL NO 7. (3 NHU)'!M7 -> 56
B120: ='BILL NO 7. (3 NHU)'!B8 -> C4 | C120: ='BILL NO 7. (3 NHU)'!C8 -> Substructure Works | D120: ='BILL NO 7. (3 NHU)'!D8 -> Filling | E120: ='BILL NO 7. (3 NHU)'!E8 -> Approved imported granular fill material compacted in layers in making up levels in the excavation area of the demolished buildings from foundation level up to levels on site plan. | F120: ='BILL NO 7. (3 NHU)'!F8 -> M3 | G120: ='BILL NO 7. (3 NHU)'!G8 -> 400 | H120: ='BILL NO 7. (3 NHU)'!H8 -> 0.5 | I120: ='BILL NO 7. (3 NHU)'!I8 -> 200 | ... L120: ='BILL NO 7. (3 NHU)'!L8 -> 400 | N120: ='BILL NO 7. (3 NHU)'!M8 -> 200
B121: ='BILL NO 7. (3 NHU)'!B9 -> C5 | C121: ='BILL NO 7. (3 NHU)'!C9 -> Substructure Works | D121: ='BILL NO 7. (3 NHU)'!D9 -> Filling | E121: ='BILL NO 7. (3 NHU)'!E9 -> Approved imported fill material compacted in layers to raise the levels | F121: ='BILL NO 7. (3 NHU)'!F9 -> M3 | G121: ='BILL NO 7. (3 NHU)'!G9 -> 200 | H121: ='BILL NO 7. (3 NHU)'!H9 -> 0.5 | I121: ='BILL NO 7. (3 NHU)'!I9 -> 100 | ... L121: ='BILL NO 7. (3 NHU)'!L9 -> 200 | N121: ='BILL NO 7. (3 NHU)'!M9 -> 100
B122: ='BILL NO 7. (3 NHU)'!B10 -> C6 | C122: ='BILL NO 7. (3 NHU)'!C10 -> Substructure Works | D122: ='BILL NO 7. (3 NHU)'!D10 -> Filling | E122: ='BILL NO 7. (3 NHU)'!E10 -> Approved, selected excavated material backfilled into excavations | F122: ='BILL NO 7. (3 NHU)'!F10 -> M3 | G122: ='BILL NO 7. (3 NHU)'!G10 -> 350 | H122: ='BILL NO 7. (3 NHU)'!H10 -> 0.5 | I122: ='BILL NO 7. (3 NHU)'!I10 -> 175 | ... L122: ='BILL NO 7. (3 NHU)'!L10 -> 130.148 | N122: ='BILL NO 7. (3 NHU)'!M10 -> 65.074
B123: ='BILL NO 7. (3 NHU)'!B11 -> C7 | C123: ='BILL NO 7. (3 NHU)'!C11 -> Substructure Works | D123: ='BILL NO 7. (3 NHU)'!D11 -> Filling | E123: ='BILL NO 7. (3 NHU)'!E11 -> 200 mm thick well compacted hardcore filling under floors | F123: ='BILL NO 7. (3 NHU)'!F11 -> M3 | G123: ='BILL NO 7. (3 NHU)'!G11 -> 35 | H123: ='BILL NO 7. (3 NHU)'!H11 -> 0.5 | I123: ='BILL NO 7. (3 NHU)'!I11 -> 17.5 | ... L123: ='BILL NO 7. (3 NHU)'!L11 -> 35 | N123: ='BILL NO 7. (3 NHU)'!M11 -> 17.5
B124: ='BILL NO 7. (3 NHU)'!B13 -> C8 | C124: ='BILL NO 7. (3 NHU)'!C13 -> Substructure Works | D124: ='BILL NO 7. (3 NHU)'!D13 -> Anti-termite treatment | E124: ='BILL NO 7. (3 NHU)'!E13 -> Anti-termite treatment to surfaces of ground or filling applied strictly in accordance with the manufacturers printed instructions including digging trenches, backfilling, etc. as required by the manufacturer and the provision of guarantee valid for 10 years | F124: ='BILL NO 7. (3 NHU)'!F13 -> M2 | G124: ='BILL NO 7. (3 NHU)'!G13 -> 150 | H124: ='BILL NO 7. (3 NHU)'!H13 -> 1.5 | I124: ='BILL NO 7. (3 NHU)'!I13 -> 225 | ... L124: ='BILL NO 7. (3 NHU)'!L13 -> 52.24 | N124: ='BILL NO 7. (3 NHU)'!M13 -> 78.36
B125: ='BILL NO 7. (3 NHU)'!B14 -> C9 | C125: ='BILL NO 7. (3 NHU)'!C14 -> Substructure Works | D125: ='BILL NO 7. (3 NHU)'!D14 -> Poured Concrete - Plain insitu concrete, poured ordinary Portland Cement (OPC), concrete grade (C15), all in accordance with Drawings and Specifications and including Formwork to give (as struck) finish - Providing and erecting formwork including all necessary staging, centering, shuttering, supports, cross bracing, de-shuttering carefully, making good the damaged surfaces wherever necessary, all complete as specified and as directed by the Engineer all in accordance with the Drawings and Specifications | E125: ='BILL NO 7. (3 NHU)'!E14 -> Blinding upto 100 mm thickness for the full area under the boundary of foundation. | F125: ='BILL NO 7. (3 NHU)'!F14 -> M3 | G125: ='BILL NO 7. (3 NHU)'!G14 -> 17.5 | H125: ='BILL NO 7. (3 NHU)'!H14 -> 45 | I125: ='BILL NO 7. (3 NHU)'!I14 -> 787.5 | ... L125: ='BILL NO 7. (3 NHU)'!L14 -> 5.316 | N125: ='BILL NO 7. (3 NHU)'!M14 -> 239.22
B126: ='BILL NO 7. (3 NHU)'!B16 -> C10 | C126: ='BILL NO 7. (3 NHU)'!C16 -> Substructure Works | D126: ='BILL NO 7. (3 NHU)'!D16 -> Reinforced insitu concrete, poured vibrated Sulphate Resistent Cement (OPC), concrete grade (C30), all in accordance with Drawings and Specifications and including Reinforcement - High yield strength deformed bars, conforming to BS 4449 (grade 460) including cutting, bending, binding, binding wire, cover blocks, tests and all necessary fixing accessories, all in accordance with the Drawings and Specifications and including Formwork to give (as struck) finish - Providing and erecting formwork including all necessary staging, centering, shuttering, supports, cross bracing, de-shuttering carefully, making good the damaged surfaces wherever necessary, all complete as specified and as directed by the Engineer all in accordance with the Drawings and Specifications | E126: ='BILL NO 7. (3 NHU)'!E16 -> Footings | F126: ='BILL NO 7. (3 NHU)'!F16 -> M3 | G126: ='BILL NO 7. (3 NHU)'!G16 -> 45 | H126: ='BILL NO 7. (3 NHU)'!H16 -> 50 | I126: ='BILL NO 7. (3 NHU)'!I16 -> 2250 | ... L126: ='BILL NO 7. (3 NHU)'!L16 -> 3.746 | N126: ='BILL NO 7. (3 NHU)'!M16 -> 187.3
B127: ='BILL NO 7. (3 NHU)'!B17 -> C11 | C127: ='BILL NO 7. (3 NHU)'!C17 -> Substructure Works | D127: ='BILL NO 7. (3 NHU)'!D17 -> Plinth Beam | E127: ='BILL NO 7. (3 NHU)'!E17 -> Plinth Beam | F127: ='BILL NO 7. (3 NHU)'!F17 -> M3 | G127: ='BILL NO 7. (3 NHU)'!G17 -> 14 | H127: ='BILL NO 7. (3 NHU)'!H17 -> 50 | I127: ='BILL NO 7. (3 NHU)'!I17 -> 700 | ... L127: ='BILL NO 7. (3 NHU)'!L17 -> 3.171 | N127: ='BILL NO 7. (3 NHU)'!M17 -> 158.55
B128: ='BILL NO 7. (3 NHU)'!B20 -> C12 | C128: ='BILL NO 7. (3 NHU)'!C20 -> Substructure Works | D128: ='BILL NO 7. (3 NHU)'!D20 -> Reinforced insitu concrete, poured vibrated Sulphate Resistent Cement (OPC), concrete grade (C30), all in accordance with Drawings and Specifications and including Reinforcement - High yield strength deformed bars, conforming to BS 4449 (grade 460) including cutting, bending, binding, binding wire, cover blocks, tests and all necessary fixing accessories, all in accordance with the Drawings and Specifications and including Steel fabric reinforcement, A-393 BRC mesh in two layers. All complete in accordance with the Drawings and Specifications and including Formwork to give (as struck) finish - Providing and erecting formwork including all necessary staging, centering, shuttering, supports, cross bracing, de-shuttering carefully, making good the damaged surfaces wherever necessary, all complete as specified and as directed by the Engineer all in accordance with the Drawings and Specifications | E128: ='BILL NO 7. (3 NHU)'!E20 -> Beds (Slabs, Grade slabs) upto 200 mm thickness | F128: ='BILL NO 7. (3 NHU)'!F20 -> M3 | G128: ='BILL NO 7. (3 NHU)'!G20 -> 30 | H128: ='BILL NO 7. (3 NHU)'!H20 -> 50 | I128: ='BILL NO 7. (3 NHU)'!I20 -> 1500 | ... L128: ='BILL NO 7. (3 NHU)'!L20 -> 9.888 | N128: ='BILL NO 7. (3 NHU)'!M20 -> 494.4
B129: ='BILL NO 7. (3 NHU)'!B22 -> C13 | C129: ='BILL NO 7. (3 NHU)'!C22 -> Substructure Works | D129: ='BILL NO 7. (3 NHU)'!D22 -> Reinforced insitu concrete, poured vibrated ordinary Portland Cement (OPC), concrete grade (C40), all in accordance with Drawings and Specifications and including Reinforcement - High yield strength deformed bars, conforming to BS 4449 (grade 460) including cutting, bending, binding, binding wire, cover blocks, tests and all necessary fixing accessories, all in accordance with the Drawings and Specifications and including Formwork to give (as struck) finish - Providing and erecting formwork including all necessary staging, centering, shuttering, supports, cross bracing, de-shuttering carefully, making good the damaged surfaces wherever necessary, all complete as specified and as directed by the Engineer all in accordance with the Drawings and Specifications | E129: ='BILL NO 7. (3 NHU)'!E22 -> Substructure columns | F129: ='BILL NO 7. (3 NHU)'!F22 -> M3 | G129: ='BILL NO 7. (3 NHU)'!G22 -> 4 | H129: ='BILL NO 7. (3 NHU)'!H22 -> 50 | I129: ='BILL NO 7. (3 NHU)'!I22 -> 200 | ... L129: ='BILL NO 7. (3 NHU)'!L22 -> 0.537 | N129: ='BILL NO 7. (3 NHU)'!M22 -> 26.85
B130: ='BILL NO 7. (3 NHU)'!B23 -> C14 | C130: ='BILL NO 7. (3 NHU)'!C23 -> Substructure Works | D130: ='BILL NO 7. (3 NHU)'!D23 -> Concrete / Block work Protection | E130: ='BILL NO 7. (3 NHU)'!E23 -> Polythene sheet, gauge 1200, all in accordance with Drawings and Specifications - to surfaces of structural members in contact with soil | F130: ='BILL NO 7. (3 NHU)'!F23 -> M2 | G130: ='BILL NO 7. (3 NHU)'!G23 -> 115 | H130: ='BILL NO 7. (3 NHU)'!H23 -> 0.5 | I130: ='BILL NO 7. (3 NHU)'!I23 -> 57.5 | ... L130: ='BILL NO 7. (3 NHU)'!L23 -> 29.66 | N130: ='BILL NO 7. (3 NHU)'!M23 -> 14.83
B131: ='BILL NO 7. (3 NHU)'!B24 -> C15 | C131: ='BILL NO 7. (3 NHU)'!C24 -> Substructure Works | D131: ='BILL NO 7. (3 NHU)'!D24 -> Bitumenous Sheet | E131: ='BILL NO 7. (3 NHU)'!E24 -> Bitumenous Paint base coat and 4mm membrane to the surfaces of concrete and block work( foundation + solid block work + short columns ) | F131: ='BILL NO 7. (3 NHU)'!F24 -> M2 | G131: ='BILL NO 7. (3 NHU)'!G24 -> 300 | H131: ='BILL NO 7. (3 NHU)'!H24 -> 5 | I131: ='BILL NO 7. (3 NHU)'!I24 -> 1500 | ... L131: ='BILL NO 7. (3 NHU)'!L24 -> 300 | N131: ='BILL NO 7. (3 NHU)'!M24 -> 1500
B132: ='BILL NO 7. (3 NHU)'!B25 -> C16 | C132: ='BILL NO 7. (3 NHU)'!C25 -> Substructure Works | D132: ='BILL NO 7. (3 NHU)'!D25 -> Bitumenous Paint | E132: ='BILL NO 7. (3 NHU)'!E25 -> Bitumenous paint 3 coats to the surfaces of concrete ( plinth beams ) | F132: ='BILL NO 7. (3 NHU)'!F25 -> M2 | G132: ='BILL NO 7. (3 NHU)'!G25 -> 145 | H132: ='BILL NO 7. (3 NHU)'!H25 -> 0.5 | I132: ='BILL NO 7. (3 NHU)'!I25 -> 72.5 | ... L132: ='BILL NO 7. (3 NHU)'!L25 -> 145 | N132: ='BILL NO 7. (3 NHU)'!M25 -> 72.5
B133: ='BILL NO 7. (3 NHU)'!B27 -> C17 | C133: ='BILL NO 7. (3 NHU)'!C27 -> Substructure Works | D133: ='BILL NO 7. (3 NHU)'!D27 -> Concrete solid block work, 10.5N/mm2 compressive strength, cement and sand mortar (1:3), with and including stiffener columns and stiffener beams, as required, all in accordance with Drawings and Specifications | E133: ='BILL NO 7. (3 NHU)'!E27 -> 200mm thick walls | F133: ='BILL NO 7. (3 NHU)'!F27 -> M2 | G133: ='BILL NO 7. (3 NHU)'!G27 -> 120 | H133: ='BILL NO 7. (3 NHU)'!H27 -> 6 | I133: ='BILL NO 7. (3 NHU)'!I27 -> 720 | ... L133: ='BILL NO 7. (3 NHU)'!L27 -> 49.078 | N133: ='BILL NO 7. (3 NHU)'!M27 -> 294.468
B134: ='BILL NO 7. (3 NHU)'!B28 -> C18 | C134: ='BILL NO 7. (3 NHU)'!C28 -> Substructure Works | D134: ='BILL NO 7. (3 NHU)'!D28 -> Block work Protection including Bitumenous Paint and Bitumenous Sheet | E134: ='BILL NO 7. (3 NHU)'!E28 -> Protection to concrete and excavated area, masonry/block work in contact with soil, Bitumenous Paint base coat of approved bituminous paint, 4mm bituminous sheet, and including flexible board all in accordance with Drawings and Specifications - to surfaces of block work in contact with soil.up to bottom of plinth beams | F134: ='BILL NO 7. (3 NHU)'!F28 -> M2 | G134: ='BILL NO 7. (3 NHU)'!G28 -> 250 | H134: ='BILL NO 7. (3 NHU)'!H28 -> 1 | I134: ='BILL NO 7. (3 NHU)'!I28 -> 250 | ... L134: ='BILL NO 7. (3 NHU)'!L28 -> 0 | N134: ='BILL NO 7. (3 NHU)'!M28 -> 0
C136: BILL NO 7. (3 NEW HOUSING UNIT) - SUBSTRUCTURE WORKS | H136: 1 UNIT | I136: =SUM(I117:I135) -> 12035 | K136: =SUM(K117:K135) -> 8529.948 | M136: 0 | N136: =SUM(N117:N135) -> 3505.052
H137: 3 UNITS | I137: =I136*3 -> 36105 | K137: =K136*3 -> 25589.844 | M137: 0 | N137: =N136*3 -> 10515.156

Sheet MAS 
B2: PROVISIONAL SUM
B3: ='BILL NO 3. (PROVISIONAL SUM)'!B3 -> Item Code | C3: ='BILL NO 3. (PROVISIONAL SUM)'!C3 -> Item Name | D3: ='BILL NO 3. (PROVISIONAL SUM)'!D3 -> Item Details | E3: ='BILL NO 3. (PROVISIONAL SUM)'!E3 -> Additional Information | F3: ='BILL NO 3. (PROVISIONAL SUM)'!F3 -> UOM | G3: ='BILL NO 3. (PROVISIONAL SUM)'!G3 -> Quantity | H3: ='BILL NO 3. (PROVISIONAL SUM)'!H3 -> Unit Price | I3: ='BILL NO 3. (PROVISIONAL SUM)'!I3 -> Total Price In Figure | J3: STATUS
B15: BILL NO. 4 (20 - NEW HOUSING UNITS)
B16: =B3 -> Item Code | C16: =C3 -> Item Name | D16: =D3 -> Item Details | E16: =E3 -> Additional Information | F16: =F3 -> UOM | G16: =G3 -> Quantity | H16: =H3 -> Unit Price | I16: =I3 -> Total Price In Figure
B17: ='BILL NO4. (20 NHU)'!B133 -> C91 | C17: ='BILL NO4. (20 NHU)'!C133 -> Superstructure Works Finishes | D17: ='BILL NO4. (20 NHU)'!D133 -> Allow for supply fabricate and installation of water point protection as per the specifications drawings and to approval of the Engineer. | E17: ='BILL NO4. (20 NHU)'!E133 -> Water point protection | F17: ='BILL NO4. (20 NHU)'!F133 -> No | G17: ='BILL NO4. (20 NHU)'!G133 -> 20 | H17: ='BILL NO4. (20 NHU)'!H133 -> 47.25 | I17: ='BILL NO4. (20 NHU)'!I133 -> 945 | J17: Pending | K17: Reason
B18: ='BILL NO4. (20 NHU)'!B134 -> C92 | C18: ='BILL NO4. (20 NHU)'!C134 -> Superstructure Works Finishes | D18: ='BILL NO4. (20 NHU)'!D134 -> Allow for supply fabricate and installation of Meter Panel protection as per the specifications drawings and to approval of the Engineer. | E18: ='BILL NO4. (20 NHU)'!E134 -> Meter Panel protection | F18: ='BILL NO4. (20 NHU)'!F134 -> No | G18: ='BILL NO4. (20 NHU)'!G134 -> 20 | H18: ='BILL NO4. (20 NHU)'!H134 -> 47.25 | I18: ='BILL NO4. (20 NHU)'!I134 -> 945 | J18: Pending | K18: Design Issue
B19: ='BILL NO4. (20 NHU)'!B211 -> F1 | C19: ='BILL NO4. (20 NHU)'!C211 -> Fire Fighting Installation | D19: ='BILL NO4. (20 NHU)'!D211 -> Fire Fighting Installation | E19: ='BILL NO4. (20 NHU)'!E211 -> Supply and install a complete fire fighting system to the approval of the Civil Defence Authorities and complete with association and fitting as shown in drawings or specified in accordance with BS 530 Part 1 1976 and Part 3 1985 and to approval of the Engineer. | F19: ='BILL NO4. (20 NHU)'!F211 -> Item | G19: ='BILL NO4. (20 NHU)'!G211 -> 1 | H19: ='BILL NO4. (20 NHU)'!H211 -> 0 | I19: ='BILL NO4. (20 NHU)'!I211 -> 0 | J19: Cancelled
B20: ='BILL NO4. (20 NHU)'!B212 -> F2 | C20: ='BILL NO4. (20 NHU)'!C212 -> Fire Fighting Installation | D20: ='BILL NO4. (20 NHU)'!D212 -> Fire hose reel | E20: ='BILL NO4. (20 NHU)'!E212 -> 1.5 mm thick Electro static powder coated painted stainless steel recessed type fire hose reel cabinet with 25 mm diameter hose reel and 45 meter long including 1 No. 9 litter foam type fire extinguisher and 1 No 5Kg carbon dioxide type fire extinguisher with civil defence final approval certificate. | F20: ='BILL NO4. (20 NHU)'!F212 -> No | G20: ='BILL NO4. (20 NHU)'!G212 -> 3 | H20: ='BILL NO4. (20 NHU)'!H212 -> 0 | I20: ='BILL NO4. (20 NHU)'!I212 -> 0
B21: ='BILL NO4. (20 NHU)'!B213 -> F3 | C21: ='BILL NO4. (20 NHU)'!C213 -> Fire Fighting Installation | D21: ='BILL NO4. (20 NHU)'!D213 -> outlet | E21: ='BILL NO4. (20 NHU)'!E213 -> Wet riser outlet with valve assembly | F21: ='BILL NO4. (20 NHU)'!F213 -> NO | G21: ='BILL NO4. (20 NHU)'!G213 -> 3 | H21: ='BILL NO4. (20 NHU)'!H213 -> 80 | I21: ='BILL NO4. (20 NHU)'!I213 -> 240 | J21: Pending | K21: Reason
B22: ='BILL NO4. (20 NHU)'!B214 -> F4 | C22: ='BILL NO4. (20 NHU)'!C214 -> Fire Fighting Installation | D22: ='BILL NO4. (20 NHU)'!D214 -> valve | E22: ='BILL NO4. (20 NHU)'!E214 -> Zonal control valve assembly | F22: ='BILL NO4. (20 NHU)'!F214 -> NO | G22: ='BILL NO4. (20 NHU)'!G214 -> 1 | H22: ='BILL NO4. (20 NHU)'!H214 -> 120 | I22: ='BILL NO4. (20 NHU)'!I214 -> 120 | J22: Pending | K22: Reason
B23: ='BILL NO4. (20 NHU)'!B215 -> F5 | C23: ='BILL NO4. (20 NHU)'!C215 -> Fire Fighting Installation | D23: ='BILL NO4. (20 NHU)'!D215 -> inlet | E23: ='BILL NO4. (20 NHU)'!E215 -> Breaching inlet | F23: ='BILL NO4. (20 NHU)'!F215 -> NO | G23: ='BILL NO4. (20 NHU)'!G215 -> 1 | H23: ='BILL NO4. (20 NHU)'!H215 -> 200 | I23: ='BILL NO4. (20 NHU)'!I215 -> 200 | J23: Cancelled | K23: Not possible
B24: ='BILL NO4. (20 NHU)'!B339 -> GN4 | C24: ='BILL NO4. (20 NHU)'!C339 -> Telephone System | D24: ='BILL NO4. (20 NHU)'!D339 -> Cable | E24: ='BILL NO4. (20 NHU)'!E339 -> Cable and conduits to telephone outlet points in concealed installation from telephone junction box to IP phone expansion module for reception | F24: ='BILL NO4. (20 NHU)'!F339 -> No | G24: ='BILL NO4. (20 NHU)'!G339 -> 120 | H24: ='BILL NO4. (20 NHU)'!H339 -> 2.45 | I24: ='BILL NO4. (20 NHU)'!I339 -> 294 | J24: Cancelled
B25: ='BILL NO4. (20 NHU)'!B340 -> GN5 | C25: ='BILL NO4. (20 NHU)'!C340 -> Telephone System | D25: ='BILL NO4. (20 NHU)'!D340 -> Outlet | E25: ='BILL NO4. (20 NHU)'!E340 -> Cat 6E telephone outlet | F25: ='BILL NO4. (20 NHU)'!F340 -> No | G25: ='BILL NO4. (20 NHU)'!G340 -> 120 | H25: ='BILL NO4. (20 NHU)'!H340 -> 2.45 | I25: ='BILL NO4. (20 NHU)'!I340 -> 294 | J25: Cancelled
B26: ='BILL NO4. (20 NHU)'!B341 -> GN6 | C26: ='BILL NO4. (20 NHU)'!C341 -> Telephone System | D26: ='BILL NO4. (20 NHU)'!D341 -> Junction box | E26: ='BILL NO4. (20 NHU)'!E341 -> Telephone junction box | F26: ='BILL NO4. (20 NHU)'!F341 -> No | G26: ='BILL NO4. (20 NHU)'!G341 -> 20 | H26: ='BILL NO4. (20 NHU)'!H341 -> 2.1 | I26: ='BILL NO4. (20 NHU)'!I341 -> 42 | J26: Cancelled
B27: ='BILL NO4. (20 NHU)'!B352 -> GN16 | C27: ='BILL NO4. (20 NHU)'!C352 -> Structured Cabling system | D27: ='BILL NO4. (20 NHU)'!D352 -> patch panel | E27: ='BILL NO4. (20 NHU)'!E352 -> 16 Port Cat 6A Patch panel | F27: ='BILL NO4. (20 NHU)'!F352 -> No | G27: ='BILL NO4. (20 NHU)'!G352 -> 20 | H27: ='BILL NO4. (20 NHU)'!H352 -> 8.4 | I27: ='BILL NO4. (20 NHU)'!I352 -> 168 | J27: Cancelled
B28: ='BILL NO4. (20 NHU)'!B353 -> GN17 | C28: ='BILL NO4. (20 NHU)'!C353 -> Structured Cabling system | D28: ='BILL NO4. (20 NHU)'!D353 -> Structured Cabling system | E28: ='BILL NO4. (20 NHU)'!E353 -> 500mm single mode fiber LC SC Patch cords | F28: ='BILL NO4. (20 NHU)'!F353 -> No | G28: ='BILL NO4. (20 NHU)'!G353 -> 20 | H28: ='BILL NO4. (20 NHU)'!H353 -> 9.45 | I28: ='BILL NO4. (20 NHU)'!I353 -> 189 | J28: Pending
B29: ='BILL NO4. (20 NHU)'!B355 -> GN18 | C29: ='BILL NO4. (20 NHU)'!C355 -> Structured Cabling system | D29: ='BILL NO4. (20 NHU)'!D355 -> Accessories | E29: ='BILL NO4. (20 NHU)'!E355 -> Accessories and stacking kits and cable management and cable organizer and cable channels and supports all types of cords and pig tail connectors including termination etc complete | F29: ='BILL NO4. (20 NHU)'!F355 -> Item | G29: ='BILL NO4. (20 NHU)'!G355 -> 1 | H29: ='BILL NO4. (20 NHU)'!H355 -> 1050 | I29: ='BILL NO4. (20 NHU)'!I355 -> 1050 | J29: Under Review
B30: ='BILL NO4. (20 NHU)'!B356 -> GN19 | C30: ='BILL NO4. (20 NHU)'!C356 -> CCTV System | D30: ='BILL NO4. (20 NHU)'!D356 -> PTZ Camera | E30: ='BILL NO4. (20 NHU)'!E356 -> PTZ Vandal proof with weather proof Bullet type Day and Night vision CCTV IP camera Outdoor as specified. | F30: ='BILL NO4. (20 NHU)'!F356 -> No | G30: ='BILL NO4. (20 NHU)'!G356 -> 40 | H30: ='BILL NO4. (20 NHU)'!H356 -> 26.25 | I30: ='BILL NO4. (20 NHU)'!I356 -> 1050 | J30: Under Review
B31: ='BILL NO4. (20 NHU)'!B357 -> GN20 | C31: ='BILL NO4. (20 NHU)'!C357 -> CCTV System | D31: ='BILL NO4. (20 NHU)'!D357 -> pulling box | E31: ='BILL NO4. (20 NHU)'!E357 -> Allow for cable pulling boxes | F31: ='BILL NO4. (20 NHU)'!F357 -> Item | G31: ='BILL NO4. (20 NHU)'!G357 -> 1 | H31: ='BILL NO4. (20 NHU)'!H357 -> 1575 | I31: ='BILL NO4. (20 NHU)'!I357 -> 1575 | J31: Under Review | K31: Basic Structure not available
B32: ='BILL NO4. (20 NHU)'!B259 -> E25 | C32: ='BILL NO4. (20 NHU)'!C259 -> MAIN DISTRIBUTION BOARD Electrical Engineering Installation | D32: ='BILL NO4. (20 NHU)'!D259 -> Main Distribution Board | E32: ='BILL NO4. (20 NHU)'!E259 -> Main Distribution panel board in weather proof Stainless steel enclosure IP 65 including 2 nos 600A and 4 nos 400A and 1NOS spare100 A and 1 NOS spare 200A Incoming MCCB Breaker and 4nos 200A and 2nos spare 100 A Outgoing MCCB Breakers and supports and Busbar and earthing and cable glands and Ammeters and Voltmeters and internal wiring interconnection 1PH 3PH KWH series meters and labels as per approved MHEW drawings | F32: ='BILL NO4. (20 NHU)'!F259 -> NO | G32: ='BILL NO4. (20 NHU)'!G259 -> 6 | H32: ='BILL NO4. (20 NHU)'!H259 -> 14 | I32: ='BILL NO4. (20 NHU)'!I259 -> 84 | J32: Under Review
I36: =SUM(I17:I35) -> 7196
B38: 20 NEW HOUSING UNITS - EXTERNAL WORKS
B40: ='BILL NO 4 (20 NHU EXTERNAL WORK'!B14 -> EW11 | C40: ='BILL NO 4 (20 NHU EXTERNAL WORK'!C14 -> External Works General Site Works | D40: ='BILL NO 4 (20 NHU EXTERNAL WORK'!D14 -> Design and Build Shaded Car Parking of 20 numbers with Solar Panel Canopy | E40: ='BILL NO 4 (20 NHU EXTERNAL WORK'!E14 -> Allow for the Contractor to design and build the Shaded Car Park for houses with Solar Panel Canopy as per Engineer Employer Instruction. | F40: ='BILL NO 4 (20 NHU EXTERNAL WORK'!F14 -> no | G40: ='BILL NO 4 (20 NHU EXTERNAL WORK'!G14 -> 105 | H40: ='BILL NO 4 (20 NHU EXTERNAL WORK'!H14 -> 20 | I40: ='BILL NO 4 (20 NHU EXTERNAL WORK'!I14 -> 2100 | J40: Under Review
B41: ='BILL NO 4 (20 NHU EXTERNAL WORK'!B6 -> EW3 | C41: ='BILL NO 4 (20 NHU EXTERNAL WORK'!C6 -> External Works General Site Works | D41: ='BILL NO 4 (20 NHU EXTERNAL WORK'!D6 -> Wicket Gate | E41: ='BILL NO 4 (20 NHU EXTERNAL WORK'!E6 -> Allow for the Contractor to supply fabricate and installation of single leaf Wicket Gate as per the Architectural Drawing and follow as per Engineer Employer Instructions including anti corrotion epoxy paint. | F41: ='BILL NO 4 (20 NHU EXTERNAL WORK'!F6 -> no | G41: ='BILL NO 4 (20 NHU EXTERNAL WORK'!G6 -> 105 | H41: ='BILL NO 4 (20 NHU EXTERNAL WORK'!H6 -> 20 | I41: ='BILL NO 4 (20 NHU EXTERNAL WORK'!I6 -> 2100 | J41: Pending
B42: ='BILL NO 4 (20 NHU EXTERNAL WORK'!B7 -> EW4 | C42: ='BILL NO 4 (20 NHU EXTERNAL WORK'!C7 -> External Works General Site Works | D42: ='BILL NO 4 (20 NHU EXTERNAL WORK'!D7 -> Car Entrance Gate | E42: ='BILL NO 4 (20 NHU EXTERNAL WORK'!E7 -> Allow for the Contractor to supply fabricate and installation of single leaf Car Entrance Gate as per the Architectural Drawing and follow as per Engineer Employer Instructions including anti corrotion epoxy paint | F42: ='BILL NO 4 (20 NHU EXTERNAL WORK'!F7 -> no | G42: ='BILL NO 4 (20 NHU EXTERNAL WORK'!G7 -> 141.75 | H42: ='BILL NO 4 (20 NHU EXTERNAL WORK'!H7 -> 20 | I42: ='BILL NO 4 (20 NHU EXTERNAL WORK'!I7 -> 2835 | J42: Pending
I44: =SUM(I40:I43) -> 7035
B46: BILL NO. 5 - (29 MAINTENANCE HOUSING UNITS)
B48: ='BILL NO 5. (MAINTENANCE HOUSING'!B27 -> C11 | C48: ='BILL NO 5. (MAINTENANCE HOUSING'!C27 -> Superstructure Works Metal Works | D48: ='BILL NO 5. (MAINTENANCE HOUSING'!D27 -> galvanized steel cat Ladder | E48: ='BILL NO 5. (MAINTENANCE HOUSING'!E27 -> Supply and install galvanized steel cat Ladder as specified and detailed on the drawingas per exixting desin hand rail in new houses drawings. | F48: ='BILL NO 5. (MAINTENANCE HOUSING'!F27 -> Item | G48: ='BILL NO 5. (MAINTENANCE HOUSING'!G27 -> 29 | H48: ='BILL NO 5. (MAINTENANCE HOUSING'!H27 -> 262.5 | I48: =G48*H48 -> 7612.5 | J48: Pending
B49: ='BILL NO 5. (MAINTENANCE HOUSING'!B108 -> E25 | C49: ='BILL NO 5. (MAINTENANCE HOUSING'!C108 -> Electrical Engineering Installation | D49: ='BILL NO 5. (MAINTENANCE HOUSING'!D108 -> Lighting Fixture | E49: ='BILL NO 5. (MAINTENANCE HOUSING'!E108 -> Supply install connect test and commission of the following lighting fixtures Emergency light | F49: ='BILL NO 5. (MAINTENANCE HOUSING'!F108 -> Item | G49: ='BILL NO 5. (MAINTENANCE HOUSING'!G108 -> 29 | H49: ='BILL NO 5. (MAINTENANCE HOUSING'!H108 -> 17.379 | I49: =G49*H49 -> 503.991 | J49: Under Review
I51: =SUM(I48:I50) -> 8116.491
B53: BILL NO. 6 (STORM WATER PROTECTION)
B54: ='BILL NO 6 (STORM WATER)'!B6 -> PSW9 | C54: ='BILL NO 6 (STORM WATER)'!C6 -> Earthwork | D54: ='BILL NO 6 (STORM WATER)'!D6 -> Earthwork for pipe Trenches | E54: ='BILL NO 6 (STORM WATER)'!E6 -> Trench excavation and backfilling Depth 0 to 2m | F54: ='BILL NO 6 (STORM WATER)'!F6 -> m3 | G54: ='BILL NO 6 (STORM WATER)'!G6 -> 9180 | H54: ='BILL NO 6 (STORM WATER)'!H6 -> 0.7 | I54: =G54*H54 -> 6426 | J54: Cancelled
B55: ='BILL NO 6 (STORM WATER)'!B7 -> PSW10 | C55: ='BILL NO 6 (STORM WATER)'!C7 -> Earthwork | D55: ='BILL NO 6 (STORM WATER)'!D7 -> Earthwork for pipe Trenches | E55: ='BILL NO 6 (STORM WATER)'!E7 -> Trench excavation and backfilling Depth 2m to 2m | F55: ='BILL NO 6 (STORM WATER)'!F7 -> m3 | G55: ='BILL NO 6 (STORM WATER)'!G7 -> 12615 | H55: ='BILL NO 6 (STORM WATER)'!H7 -> 1.575 | I55: =G55*H55 -> 19868.625 | J55: Cancelled
B56: ='BILL NO 6 (STORM WATER)'!B8 -> PSW11 | C56: ='BILL NO 6 (STORM WATER)'!C8 -> Earthwork | D56: ='BILL NO 6 (STORM WATER)'!D8 -> Earthwork for pipe Trenches | E56: ='BILL NO 6 (STORM WATER)'!E8 -> Trench excavation and backfilling Depth 3m to 4m | F56: ='BILL NO 6 (STORM WATER)'!F8 -> m3 | G56: ='BILL NO 6 (STORM WATER)'!G8 -> 3090 | H56: ='BILL NO 6 (STORM WATER)'!H8 -> 2.1 | I56: =G56*H56 -> 6489 | J56: Cancelled
B57: ='BILL NO 6 (STORM WATER)'!B9 -> PSW12 | C57: ='BILL NO 6 (STORM WATER)'!C9 -> Earthwork | D57: ='BILL NO 6 (STORM WATER)'!D9 -> Earthwork for pipe Trenches | E57: ='BILL NO 6 (STORM WATER)'!E9 -> Trench excavation and backfilling Depth more than 4m | F57: ='BILL NO 6 (STORM WATER)'!F9 -> m3 | G57: ='BILL NO 6 (STORM WATER)'!G9 -> 4080 | H57: ='BILL NO 6 (STORM WATER)'!H9 -> 4.2 | I57: =G57*H57 -> 17136 | J57: Cancelled
B58: ='BILL NO 6 (STORM WATER)'!B10 -> PSW13 | C58: ='BILL NO 6 (STORM WATER)'!C10 -> 3 Granular Subbase Aggregate Base Course and Stabilized Base Courses. | D58: ='BILL NO 6 (STORM WATER)'!D10 -> Redesign and Construction of Asphalt Road to be suitable for Erection of Culvert with all necessary drawings details… | E58: ='BILL NO 6 (STORM WATER)'!E10 -> Aggregate Base Course Class B | F58: ='BILL NO 6 (STORM WATER)'!F10 -> m3 | G58: ='BILL NO 6 (STORM WATER)'!G10 -> 1500 | H58: ='BILL NO 6 (STORM WATER)'!H10 -> 2.1 | I58: =G58*H58 -> 3150 | J58: Cancelled
B59: ='BILL NO 6 (STORM WATER)'!B11 -> PSW14 | C59: ='BILL NO 6 (STORM WATER)'!C11 -> 4 Bituminous Pavement | D59: ='BILL NO 6 (STORM WATER)'!D11 -> Redesign and Construction of Asphalt Road to be suitable for Erection of Culvert with all necessary drawings details… | E59: ='BILL NO 6 (STORM WATER)'!E11 -> Bituminous Prime Coat Application rate 1.5 KgSq.m | F59: ='BILL NO 6 (STORM WATER)'!F11 -> m3 | G59: ='BILL NO 6 (STORM WATER)'!G11 -> 4050 | H59: ='BILL NO 6 (STORM WATER)'!H11 -> 2.1 | I59: =G59*H59 -> 8505 | J59: Cancelled
B60: ='BILL NO 6 (STORM WATER)'!B12 -> PSW15 | C60: ='BILL NO 6 (STORM WATER)'!C12 -> Asphalt Road | D60: ='BILL NO 6 (STORM WATER)'!D12 -> Redesign and Construction of Asphalt Road to be suitable for Erection of Culvert with all necessary drawings details… | E60: ='BILL NO 6 (STORM WATER)'!E12 -> Bituminous Wearing Course Class B | F60: ='BILL NO 6 (STORM WATER)'!F12 -> m3 | G60: ='BILL NO 6 (STORM WATER)'!G12 -> 280 | H60: ='BILL NO 6 (STORM WATER)'!H12 -> 12.6 | I60: =G60*H60 -> 3528 | J60: Cancelled
B61: ='BILL NO 6 (STORM WATER)'!B13 -> PSW17 | C61: ='BILL NO 6 (STORM WATER)'!C13 -> Concrete and Concrete Structures | D61: ='BILL NO 6 (STORM WATER)'!D13 -> Construction of Box culvert N2 Size 2x1.5m concrete class 30 with reinforcement as per HDS 2017 including wing wall foundations bituminous paint excavation backfilling and as directed by Engineer | E61: ='BILL NO 6 (STORM WATER)'!E13 -> Concrete Class 15 in foundations. | F61: ='BILL NO 6 (STORM WATER)'!F13 -> m3 | G61: ='BILL NO 6 (STORM WATER)'!G13 -> 130 | H61: ='BILL NO 6 (STORM WATER)'!H13 -> 13.65 | I61: =G61*H61 -> 1774.5 | J61: Cancelled
B62: ='BILL NO 6 (STORM WATER)'!B14 -> PSW18 | C62: ='BILL NO 6 (STORM WATER)'!C14 -> Concrete and Concrete Structures | D62: ='BILL NO 6 (STORM WATER)'!D14 -> Construction of Box culvert N2 Size 2x1.5m concrete class 30 with reinforcement as per HDS 2017 including wing wall foundations bituminous paint excavation backfilling and as directed by Engineer | E62: ='BILL NO 6 (STORM WATER)'!E14 -> Concrete Class 35 in box culverts wing walls apron slab retaining walls and debris foundations. | F62: ='BILL NO 6 (STORM WATER)'!F14 -> m3 | G62: ='BILL NO 6 (STORM WATER)'!G14 -> 375 | H62: ='BILL NO 6 (STORM WATER)'!H14 -> 12.6 | I62: =G62*H62 -> 4725 | J62: Cancelled
B63: ='BILL NO 6 (STORM WATER)'!B16 -> PSW20 | C63: ='BILL NO 6 (STORM WATER)'!C16 -> Concrete and Concrete structure | D63: ='BILL NO 6 (STORM WATER)'!D16 -> Construction of Box culvert N2 Size 2x1.5m concrete class 30 with reinforcement as per HDS 2017 including wing wall foundations bituminous paint excavation backfilling and as directed by Engineer | E63: ='BILL NO 6 (STORM WATER)'!E16 -> High tensile steel bar factory epoxy coated reinforcement of any diameter | F63: ='BILL NO 6 (STORM WATER)'!F16 -> Ton | G63: ='BILL NO 6 (STORM WATER)'!G16 -> 55 | H63: ='BILL NO 6 (STORM WATER)'!H16 -> 94.5 | I63: =G63*H63 -> 5197.5 | J63: Cancelled
B64: ='BILL NO 6 (STORM WATER)'!B17 -> PSW22 | C64: ='BILL NO 6 (STORM WATER)'!C17 -> Concrete and Concrete structure | D64: ='BILL NO 6 (STORM WATER)'!D17 -> Construction of Box culvert N2 Size 2x1.5m concrete class 30 with reinforcement as per HDS 2017 including wing wall foundations bituminous paint excavation backfilling and as directed by Engineer | E64: ='BILL NO 6 (STORM WATER)'!E17 -> Tar or bituminous paint Type II 2 coats for surfaces in contact with earth in all structures | F64: ='BILL NO 6 (STORM WATER)'!F17 -> m2 | G64: ='BILL NO 6 (STORM WATER)'!G17 -> 1420 | H64: ='BILL NO 6 (STORM WATER)'!H17 -> 1.05 | I64: =G64*H64 -> 1491 | J64: Cancelled
B65: ='BILL NO 6 (STORM WATER)'!B18 -> PSW23 | C65: ='BILL NO 6 (STORM WATER)'!C18 -> Concrete and Concrete structure | D65: ='BILL NO 6 (STORM WATER)'!D18 -> Construction of Box culvert N2 Size 2x1.5m concrete class 30 with reinforcement as per HDS 2017 including wing wall foundations bituminous paint excavation backfilling and as directed by Engineer | E65: ='BILL NO 6 (STORM WATER)'!E18 -> Membrane Waterproofing Geotextile 4mm thickness | F65: ='BILL NO 6 (STORM WATER)'!F18 -> m2 | G65: ='BILL NO 6 (STORM WATER)'!G18 -> 15500 | H65: ='BILL NO 6 (STORM WATER)'!H18 -> 1.05 | I65: =G65*H65 -> 16275 | J65: Cancelled
B66: ='BILL NO 6 (STORM WATER)'!B19 -> PSW25 | C66: ='BILL NO 6 (STORM WATER)'!C19 -> Drainage | D66: ='BILL NO 6 (STORM WATER)'!D19 -> Storm Sewer | E66: ='BILL NO 6 (STORM WATER)'!E19 -> Storm Sewer GRP Diamter 300mm | F66: ='BILL NO 6 (STORM WATER)'!F19 -> m | G66: ='BILL NO 6 (STORM WATER)'!G19 -> 315 | H66: ='BILL NO 6 (STORM WATER)'!H19 -> 3.15 | I66: =G66*H66 -> 992.25 | J66: Cancelled
B67: ='BILL NO 6 (STORM WATER)'!B20 -> PSW26 | C67: ='BILL NO 6 (STORM WATER)'!C20 -> Drainage | D67: ='BILL NO 6 (STORM WATER)'!D20 -> Storm Sewer | E67: ='BILL NO 6 (STORM WATER)'!E20 -> Storm Sewer GRP Diamter 400mm | F67: ='BILL NO 6 (STORM WATER)'!F20 -> m | G67: ='BILL NO 6 (STORM WATER)'!G20 -> 1270 | H67: ='BILL NO 6 (STORM WATER)'!H20 -> 2.1 | I67: =G67*H67 -> 2667 | J67: Cancelled
B68: ='BILL NO 6 (STORM WATER)'!B21 -> PSW27 | C68: ='BILL NO 6 (STORM WATER)'!C21 -> Drainage | D68: ='BILL NO 6 (STORM WATER)'!D21 -> Storm Sewer | E68: ='BILL NO 6 (STORM WATER)'!E21 -> Storm Sewer GRP Diamter 500mm | F68: ='BILL NO 6 (STORM WATER)'!F21 -> m | G68: ='BILL NO 6 (STORM WATER)'!G21 -> 345 | H68: ='BILL NO 6 (STORM WATER)'!H21 -> 1.575 | I68: =G68*H68 -> 543.375 | J68: Cancelled
B69: ='BILL NO 6 (STORM WATER)'!B22 -> PSW28 | C69: ='BILL NO 6 (STORM WATER)'!C22 -> Drainage | D69: ='BILL NO 6 (STORM WATER)'!D22 -> Storm Sewer | E69: ='BILL NO 6 (STORM WATER)'!E22 -> Storm Sewer R.C Diamter 600mm | F69: ='BILL NO 6 (STORM WATER)'!F22 -> m | G69: ='BILL NO 6 (STORM WATER)'!G22 -> 865 | H69: ='BILL NO 6 (STORM WATER)'!H22 -> 1.575 | I69: =G69*H69 -> 1362.375 | J69: Cancelled
B70: ='BILL NO 6 (STORM WATER)'!B23 -> PSW29 | C70: ='BILL NO 6 (STORM WATER)'!C23 -> Drainage | D70: ='BILL NO 6 (STORM WATER)'!D23 -> Storm Sewer | E70: ='BILL NO 6 (STORM WATER)'!E23 -> Storm Sewer R.C Diamter 700mm | F70: ='BILL NO 6 (STORM WATER)'!F23 -> m | G70: ='BILL NO 6 (STORM WATER)'!G23 -> 1090 | H70: ='BILL NO 6 (STORM WATER)'!H23 -> 2.1 | I70: =G70*H70 -> 2289 | J70: Cancelled
B71: ='BILL NO 6 (STORM WATER)'!B24 -> PSW30 | C71: ='BILL NO 6 (STORM WATER)'!C24 -> Drainage | D71: ='BILL NO 6 (STORM WATER)'!D24 -> Storm Sewer | E71: ='BILL NO 6 (STORM WATER)'!E24 -> Storm Sewer R.C Diamter 800mm | F71: ='BILL NO 6 (STORM WATER)'!F24 -> m | G71: ='BILL NO 6 (STORM WATER)'!G24 -> 460 | H71: ='BILL NO 6 (STORM WATER)'!H24 -> 2.1 | I71: =G71*H71 -> 966 | J71: Cancelled
B72: ='BILL NO 6 (STORM WATER)'!B25 -> PSW31 | C72: ='BILL NO 6 (STORM WATER)'!C25 -> Drainage | D72: ='BILL NO 6 (STORM WATER)'!D25 -> Storm Sewer | E72: ='BILL NO 6 (STORM WATER)'!E25 -> Storm Sewer R.C Diamter 900mm | F72: ='BILL NO 6 (STORM WATER)'!F25 -> m | G72: ='BILL NO 6 (STORM WATER)'!G25 -> 130 | H72: ='BILL NO 6 (STORM WATER)'!H25 -> 3.15 | I72: =G72*H72 -> 409.5 | J72: Cancelled
B73: ='BILL NO 6 (STORM WATER)'!B26 -> PSW32 | C73: ='BILL NO 6 (STORM WATER)'!C26 -> Drainage | D73: ='BILL NO 6 (STORM WATER)'!D26 -> Storm Sewer | E73: ='BILL NO 6 (STORM WATER)'!E26 -> Storm Sewer R.C Diamter 1200mm | F73: ='BILL NO 6 (STORM WATER)'!F26 -> m | G73: ='BILL NO 6 (STORM WATER)'!G26 -> 490 | H73: ='BILL NO 6 (STORM WATER)'!H26 -> 3.15 | I73: =G73*H73 -> 1543.5 | J73: Cancelled
B74: ='BILL NO 6 (STORM WATER)'!B27 -> PSW34 | C74: ='BILL NO 6 (STORM WATER)'!C27 -> Drainage | D74: ='BILL NO 6 (STORM WATER)'!D27 -> Manholes Inlets and Chambers | E74: ='BILL NO 6 (STORM WATER)'!E27 -> R.C Manholes Chamber Ring Dia. 1200mm Type A | F74: ='BILL NO 6 (STORM WATER)'!F27 -> No | G74: ='BILL NO 6 (STORM WATER)'!G27 -> 48 | H74: ='BILL NO 6 (STORM WATER)'!H27 -> 3.15 | I74: =G74*H74 -> 151.2 | J74: Cancelled
... B79: ='BILL NO 6 (STORM WATER)'!B32 -> PSW39 | C79: ='BILL NO 6 (STORM WATER)'!C32 -> Drainage | D79: ='BILL NO 6 (STORM WATER)'!D32 -> Manholes Inlets and Chambers | E79: ='BILL NO 6 (STORM WATER)'!E32 -> UPVC Drainage pipe to drain gully to manhole 200mm Diamter | F79: ='BILL NO 6 (STORM WATER)'!F32 -> No | G79: ='BILL NO 6 (STORM WATER)'!G32 -> 2010 | H79: ='BILL NO 6 (STORM WATER)'!H32 -> 4.305 | I79: =G79*H79 -> 8653.05 | J79: Cancelled
B80: ='BILL NO 6 (STORM WATER)'!B34 -> PSW41 | C80: ='BILL NO 6 (STORM WATER)'!C34 -> Slope protection and Stablization | D80: ='BILL NO 6 (STORM WATER)'!D34 -> Existing Dyke Improvement | E80: ='BILL NO 6 (STORM WATER)'!E34 -> Remove the existing dyke use the suitable backfilling and compact in the new place in layers as per Oman specifications shift not suitable existing backfilling materials to damp yard etc. | F80: ='BILL NO 6 (STORM WATER)'!F34 -> Item | G80: ='BILL NO 6 (STORM WATER)'!G34 -> 1 | H80: ='BILL NO 6 (STORM WATER)'!H34 -> 52.5 | I80: =G80*H80 -> 52.5 | J80: Cancelled
I83: =SUM(I54:I81) -> 114979.2
B85: BILL NO. 7 (3 NEW HOUSING UNITS )
B86: ='BILL NO 7. (3 NHU)'!B51 -> C37 | C86: ='BILL NO 7. (3 NHU)'!C51 -> Superstructure Works Metal Works | D86: ='BILL NO 7. (3 NHU)'!D51 -> CAT Ladder | E86: ='BILL NO 7. (3 NHU)'!E51 -> Supply and install a 3800mm high CAT steel Ladder as specified and detailed on the drawing, with anti-correlation epoxy pain. | F86: ='BILL NO 7. (3 NHU)'!F51 -> No | G86: ='BILL NO 7. (3 NHU)'!G51 -> 1 | H86: ='BILL NO 7. (3 NHU)'!H51 -> 100 | I86: ='BILL NO 7. (3 NHU)'!I51 -> 100 | J86: Pending
B87: ='BILL NO 7. (3 NHU)'!B92 -> C82 | C87: ='BILL NO 7. (3 NHU)'!C92 -> Superstructure Works Finishes | D87: ='BILL NO 7. (3 NHU)'!D92 -> Allow for supply, fabricate and installation of Meter Panel protection as per the specifications, drawings and to approval of the Engineer. | E87: ='BILL NO 7. (3 NHU)'!E92 -> Meter Panel protection | F87: ='BILL NO 7. (3 NHU)'!F92 -> Item | G87: ='BILL NO 7. (3 NHU)'!G92 -> 1 | H87: ='BILL NO 7. (3 NHU)'!H92 -> 100 | I87: ='BILL NO 7. (3 NHU)'!I92 -> 100 | J87: Pending
B88: ='BILL NO 7. (3 NHU)'!B147 -> G1 | C88: ='BILL NO 7. (3 NHU)'!C147 -> Gas supply line | D88: ='BILL NO 7. (3 NHU)'!D147 -> Gas line | E88: ='BILL NO 7. (3 NHU)'!E147 -> Supply and fix 18 mm diameter MS schedule 40 gas pipeline including pickup points and connection to Gas Stove | F88: ='BILL NO 7. (3 NHU)'!F147 -> M | G88: ='BILL NO 7. (3 NHU)'!G147 -> 10 | H88: ='BILL NO 7. (3 NHU)'!H147 -> 50 | I88: ='BILL NO 7. (3 NHU)'!I147 -> 500 | J88: Under Review
B89: ='BILL NO 7. (3 NHU)'!B180 -> GN4 | C89: ='BILL NO 7. (3 NHU)'!C180 -> Telephone System | D89: ='BILL NO 7. (3 NHU)'!D180 -> TV System Installation | E89: ='BILL NO 7. (3 NHU)'!E180 -> Cable and conduits to telephone outlet points in concealed installation from telephone junction box to IP phone expansion module for reception | F89: ='BILL NO 7. (3 NHU)'!F180 -> No | G89: ='BILL NO 7. (3 NHU)'!G180 -> 4 | H89: ='BILL NO 7. (3 NHU)'!H180 -> 50 | I89: ='BILL NO 7. (3 NHU)'!I180 -> 200 | J89: Under Review
B90: ='BILL NO 7. (3 NHU)'!B181 -> GN5 | C90: ='BILL NO 7. (3 NHU)'!C181 -> Telephone System | D90: ='BILL NO 7. (3 NHU)'!D181 -> Outlet | E90: ='BILL NO 7. (3 NHU)'!E181 -> Cat 6E telephone outlet | F90: ='BILL NO 7. (3 NHU)'!F181 -> No | G90: ='BILL NO 7. (3 NHU)'!G181 -> 4 | H90: ='BILL NO 7. (3 NHU)'!H181 -> 10 | I90: ='BILL NO 7. (3 NHU)'!I181 -> 40 | J90: Under Review
B91: ='BILL NO 7. (3 NHU)'!B182 -> GN6 | C91: ='BILL NO 7. (3 NHU)'!C182 -> Telephone System | D91: ='BILL NO 7. (3 NHU)'!D182 -> Junction box | E91: ='BILL NO 7. (3 NHU)'!E182 -> Telephone junction box | F91: ='BILL NO 7. (3 NHU)'!F182 -> No | G91: ='BILL NO 7. (3 NHU)'!G182 -> 1 | H91: ='BILL NO 7. (3 NHU)'!H182 -> 50 | I91: ='BILL NO 7. (3 NHU)'!I182 -> 50 | J91: Under Review
B92: ='BILL NO 7. (3 NHU)'!B102 -> EW10 | C92: ='BILL NO 7. (3 NHU)'!C102 -> External Works - General Site Works | D92: ='BILL NO 7. (3 NHU)'!D102 -> Design and Build Shaded Car Parking of 20 numbers with Solar Panel Canopy | E92: ='BILL NO 7. (3 NHU)'!E102 -> Allow for the Contractor to design and build the Shaded Car Park for houses with Solar Panel Canopy, as per Engineer / Employer Instruction. | F92: ='BILL NO 7. (3 NHU)'!F102 -> Item | G92: ='BILL NO 7. (3 NHU)'!G102 -> 1 | H92: ='BILL NO 7. (3 NHU)'!H102 -> 1300 | I92: ='BILL NO 7. (3 NHU)'!I102 -> 1300 | J92: Cancelled
B93: ='BILL NO 7. (3 NHU)'!B140 -> P42 | C93: ='BILL NO 7. (3 NHU)'!C140 -> Water Supply installation | D93: ='BILL NO 7. (3 NHU)'!D140 -> Booster pump | E93: ='BILL NO 7. (3 NHU)'!E140 -> Cold water pressurised booster pump set 1No Working pump and 1No standby pump for domestic water supply delivering 2 l per sec at 2.5 bar with Gate valve and Non return valve and float switch and pressue guage and pressure vessel 30 to 50 lit PN10 and water low level cut off relay etc with pump room all complete as detailed in the drawing to approval. | F93: ='BILL NO 7. (3 NHU)'!F140 -> No | G93: ='BILL NO 7. (3 NHU)'!G140 -> 1 | H93: ='BILL NO 7. (3 NHU)'!H140 -> 1500 | I93: ='BILL NO 7. (3 NHU)'!I140 -> 1500 | J93: Pending
B94: ='BILL NO 7. (3 NHU)'!B97 -> EW5 | C94: ='BILL NO 7. (3 NHU)'!C97 -> External Works - General Site Works | D94: ='BILL NO 7. (3 NHU)'!D97 -> Wicket Gate | E94: ='BILL NO 7. (3 NHU)'!E97 -> Single leaf Wicket Gate solid WPC | F94: ='BILL NO 7. (3 NHU)'!F97 -> Item | G94: ='BILL NO 7. (3 NHU)'!G97 -> 1 | H94: ='BILL NO 7. (3 NHU)'!H97 -> 900 | I94: ='BILL NO 7. (3 NHU)'!I97 -> 900 | J94: Pending
B95: ='BILL NO 7. (3 NHU)'!B98 -> EW6 | C95: ='BILL NO 7. (3 NHU)'!C98 -> External Works - General Site Works | D95: ='BILL NO 7. (3 NHU)'!D98 -> Car Entrance Gate | E95: ='BILL NO 7. (3 NHU)'!E98 -> Single leaf Car Entrance Gate soild WPC | F95: ='BILL NO 7. (3 NHU)'!F98 -> Item | G95: ='BILL NO 7. (3 NHU)'!G98 -> 1 | H95: ='BILL NO 7. (3 NHU)'!H98 -> 1200 | I95: ='BILL NO 7. (3 NHU)'!I98 -> 1200 | J95: Pending
H97: 1 UNIT | I97: =SUM(I86:I96) -> 5890
H98: 3 UNIT | I98: =I97*3 -> 17670

Sheet Copy of GRANT SUMMARY
B2: CONSTRUCTION, COMPLETION AND MAINTENANCE OF PROPOSED (20NOS) HOUSING UNITS AND MAINTENANCE WORKS FOR THE EXISTING (32) HOUSES FOR THE MINISTRY
B3: GRAND SUMMARY
B4: Priced Bill Of Quantities
B5: Transfer the Contract Summary of Contract Value to the Form of Tender
B7: S/N | C7: BILL NO | D7: DESCRIPTION | E7: BOQ AMOUNT | F7: BOQ AMOUNT | G7: REVISED VALUE AFTER V.O 1 | H7: Addition | I7: Omission | J7: Savings Excluding V.O 1 | K7: EXPECTED REVISED BOQ VALUE AFTER A/O | M7: ADDITION AMOUNT/VARIATION | N7: SAVING AMOUNT | O7: % | R7: CLAUSES | S7: Appendix
B9: 1 | C9: BILL NO 1 | D9: PRELIMINARIES | E9: =F9 -> 227580 | F9: =SUMMARY!D4 -> 227580 | G9: =F9 -> 227580 | H9: 0 | I9: 124800 | J9: =I9-H9 -> 124800 | K9: =F9-J9 -> 102780 | L9: =K9-F9 -> -124800 | N9: =F9-K9 -> 124800 | O9: =J9/F9*100 -> 54.837859 | P9: =K9/$K$36 -> 0.029012987 | Q9: =P9 -> 0.029012987 | S9: Bill No 1. (PRELIMINARIES)
B11: 2 | C11: BILL NO 2 | D11: DAY WORKS | E11: =F11 -> 88252.5 | F11: =SUMMARY!D6 -> 88252.5 | G11: =F11 -> 88252.5 | H11: 0 | I11: 88252.5 | J11: =I11-H11 -> 88252.5 | K11: =F11-J11 -> 0 | L11: =J11-K11 -> 88252.5 | N11: =SUMMARY!G6 -> 88262.5 | O11: =J11/F11*100 -> 100 | P11: =K11/$K$36 -> 0 | Q11: =P11 -> 0 | S11: Bill No 2. (DAY WORK)
B14: 3 | C14: BILL NO 3 | D14: PROVISIONAL SUM | E14: =F14 -> 200000 | F14: 200000 | G14: 0 | H14: 0 | K14: =J14 -> 0 | L14: =K14-J14 -> 0 | N14: =F14-K14 -> 200000 | O14: =J14/F14*100 -> 0 | P14: =K14/$K$36 -> 0 | S14: Bill No 3. (PROVISIONAL SUM)
B16: 4 | C16: BILL NO 4 | D16: NEW HOUSING UNIT (20 UNITS) | E16: =F18+F20 -> 1965370.9 | Q16: =SUM(P18,P20) -> 0.44407393
D18: SUBSTRUCTURE WORKS | F18: =SUMMARY!D11 -> 947257 | G18: =F18 -> 947257 | H18: 0 | I18: =SUMMARY!G11 -> 291914.71 | J18: =I18-H18 -> 291914.71 | K18: =F18-J18 -> 655342.29 | L18: =J18-K18 -> -363427.58 | N18: =SUMMARY!G11 -> 291914.71 | O18: =J18/F18*100 -> 30.816844 | P18: =K18/$K$36 -> 0.18499161 | R18: 12.1 | S18: 20 NEW ADD QTY
D20: SUPERSTRUCTURE WORKS | F20: =SUMMARY!D21 -> 1018113.9 | G20: =F20 -> 1018113.9 | H20: =SUMMARY!H21 -> 23100 | I20: =SUMMARY!G21 -> 123401.5 | J20: =I20-H20 -> 100301.5 | K20: =F20-J20 -> 917812.44 | L20: =K20-J20 -> 817510.94 | M20: =SUMMARY!H21 -> 23100 | N20: =SUMMARY!G21 -> 123401.5 | O20: =J20/F20*100 -> 9.851697 | P20: =K20/$K$36 -> 0.25908232 | R20: 12.2 | S20: GRAND SUM. ADD. (Bill No. 4 & 7)
B22: 5 | C22: BILL NO 4 | D22: EXTERNAL WORKS AND EXTERNAL SERVICES | E22: =F22 -> 28455 | F22: =SUMMARY!D27 -> 28455 | G22: =F22 -> 28455 | H22: 0 | I22: =SUMMARY!G27 -> 2100 | J22: =I22-H22 -> 2100 | K22: =F22-J22 -> 26355 | L22: =K22 -> 26355 | N22: =SUMMARY!G27 -> 2100 | O22: =J22/F22*100 -> 7.3800738 | P22: =K22/$K$36 -> 0.0074395532 | Q22: =P22 -> 0.0074395532 | S22: BIll No 4 (20 NHI EXXTERNAL WORK)
B24: 6 | C24: BILL NO 5 | D24: MAINTENANCE WORKS FOR THE EXISTING HOUSING UNITS (29 NO) | E24: =F24 -> 1436308.6 | F24: =SUMMARY!D13 -> 1436308.6 | G24: =F24 -> 1436308.6 | H24: ='BILL NO 5. (MAINTENANCE HOUSING'!O116 -> 11890 | I24: =SUMMARY!G13 -> 9991.805 | J24: =I24-H24 -> -1898.195 | K24: =F24-J24 -> 1438206.8 | L24: =K24-J24 -> 1440105 | M24: =SUMMARY!H13 -> 11890 | N24: =SUMMARY!G13 -> 9991.805 | O24: =J24/F24*100 -> -0.13215788 | P24: =K24/$K$36 -> 0.4059805 | Q24: =P24 -> 0.4059805 | R24: 12.2 | S24: ADD. WORK (29 - MHU)
B26: 7 | C26: BILL NO 6 | D26: PROTECTION AND STORM WATER DRAINAGE | E26: =F26 -> 265674.67 | F26: =SUMMARY!D16 -> 265674.67 | G26: =F26 -> 265674.67 | H26: 0 | I26: ='BILL NO 6 (STORM WATER)'!J35 -> 70280.7 | J26: =I26-H26 -> 70280.7 | K26: =F26-J26 -> 195393.97 | L26: =J26-K26 -> -125113.27 | N26: =F26-K26 -> 70280.7 | O26: =J26/F26*100 -> 26.453669 | P26: =K26/$K$36 -> 0.055156285 | Q26: =P26 -> 0.055156285 | S26: ADD. WORK ON CHANNEL
B28: 8 | C28: BILL NO 7 | D28: 3 NUMBER HOUSING UNITS | E28: =F30+F32 -> 239991.02 | Q28: =SUM(P30,P32) -> 0.058336748
D30: SUBSTRUCTURE WORKS | F30: =SUMMARY!D18 -> 36105 | G30: =F30 -> 36105 | H30: 0 | I30: =F30-K30 -> 10515.096 | J30: =I30-H30 -> 10515.096 | K30: 25589.904 | L30: =K30-J30 -> 15074.808 | N30: =SUMMARY!G18 -> 10515.156 | O30: =J30/F30*100 -> 29.123656 | P30: =K30/$K$36 -> 0.0072235801 | R30: 12.1 | S30: 20 NHU ADD. QTY/ Bill No 7. (3 NHU)
D32: SUPERSTRUCTURE WORK | F32: =SUMMARY!D23 -> 203886.02 | G32: =F32 -> 203886.02 | H32: ='BILL NO 7. (3 NHU)'!O193 -> 2295 | I32: =SUMMARY!G23 -> 25110 | J32: =I32-H32 -> 22815 | K32: =F32-J32 -> 181071.02 | L32: =K32-J32 -> 158256.02 | M32: =SUMMARY!H23 -> 1111.44 | N32: =SUMMARY!G23 -> 25110 | O32: =J32/F32*100 -> 11.190075 | P32: =K32/$K$36 -> 0.051113167 | R32: 12.2 | S32: SUM. OF ADD. WORKS (Bill No 4 & 7)
P33: =SUM(P32,#REF!,P30,P29,P28,#REF!,P26,P25,P24,P23,P22,#REF!,P20,P19,P18,#REF!,P16,P15,P14,P13,P11,P10,P9) -> #REF! | Q33: =SUM(Q32,#REF!,Q30,Q29,Q28,#REF!,Q26,Q25,Q24,Q23,Q22,#REF!,Q20,Q19,Q18,#REF!,Q16,Q15,Q14,Q13,Q11,Q10,Q9) -> #REF!
K34: =F34-J34 -> 0 | O34: =N36+M36 -> 982477.81
K35: =F35-J35 -> 0
B36: Total Contract Value | E36: =SUM(E9:E32) -> 4451632.7 | F36: =SUM(F9:F32) -> 4451632.7 | G36: =SUM(G9+G11+G18+G20+G22+G24+G26+G30+G32) -> 4251632.7 | H36: =SUM(H9+H11+H18+H20+H24+H26+H30+H32+H14) -> 37285 | I36: =SUM(I9+I11+I18+I20+I22+I24+I26+I30+I32+I14) -> 746366.31 | J36: =SUM(J9+J11+J18+J20+J22+J24+J26+J30+J32+J14) -> 709081.31 | K36: =SUM(K9+K11+K18+K20+K22+K24+K26+K30+K32) -> 3542551.4 | L36: =F36-K36 -> 909081.31 | M36: =SUM(M9:M32) -> 36101.44 | N36: =SUM(N9:N35) -> 946376.37
H39: =I36-H36 -> 709081.31 | K39: =F36-K36 -> 909081.31 | N39: =SUM(N36:N38) -> 946376.37
L40: =I36+J36 -> 1455447.6
F41: CONTRACT PRICE | K41: CLAIMABLE | N41: ADD/OMISSION IMPACT | P41: =328588.41+7678.88 -> 336267.29 | R41: =55*355 -> 19525
P42: =P41-220352 -> 115915.29 | R42: =R41*32 -> 624800 | S42: =R42+K36 -> 4167351.4
D43: PERCENTAGE | F43: AMOUNT | K43: PERCENTAGE | L43: =J36+K39 -> 1618162.6 | N43: =O34-F39 -> 982477.81
C45: Addition/Omission and Change Order Impact | D45: CONTRACT TOTAL VALUE | F45: =F36 -> 4451632.7 | K45: =F45/F45 -> 1 | L45: =H40-J40 -> 0 | S45: =F36-S42 -> 284281.31
D46: CLAIMABLE TOTAL AMOUNT | F46: =K36 -> 3542551.4 | K46: =F46/F45 -> 0.79578699
D47: ADDITION OMMISSION IMPACT | F47: =N39 -> 946376.37 | K47: =F47/F45 -> 0.21259085
D48: ADDITIONAL WORK BILL NO. 5 | F48: =SUMMARY!H23 -> 1111.44 | K48: =(F48+F49)/F45 -> 0.049748812 | N48: =F48+F49 -> 221463.44
D49: CHANGE ORDER -2 | F49: 220352
D50: NET FINANCIAL IMPACT | F50: =F45*K50 -> 3764014.9 | K50: =K46+K48 -> 0.8455358
C51: Progress Impact | D51: OVERALL FINANCIAL IMPACT | K51: =K45-K50 -> 0.1544642
D52: CLAIMED TO DATE AGAINST CONTRACT | F52: 2193954.4 | K52: =2193954.35/F45 -> 0.49284262 | N52: =(K52+K53)/2 -> 0.55607868
D53: CLAIMED AGAINST CLAIMABLE VALUE | F53: 2193954.4 | K53: =F53/F46 -> 0.61931475
D54: CLAIMABLE AMOUNT - BILL 11 (13-04-26) | F54: 110000 | K54: =F54/F45 -> 0.024710035
K55: =K53-K52+K54 -> 0.15118216 | N55: =69.5%-N52 -> 0.13892132
D56: Progres Against Contract Vs Revised Value | K56: Planned VS Actual Cost | N56: Planned Vs Actual Progress

Sheet BILL NO 1. (PRELIMINARIES)
B2: BILL NO 1. (PRELIMINARIES)
B3: Item Code | C3: Item Name | D3: Item Details | E3: Additional Information | F3: UOM | G3: BOQ-Quantity | H3: Unit Price | I3: BOQ Total Amount | J3: Claimable Amount | K3: Addition & Omission Quantity | L3: Omission | M3: Addition | O3: Overall Prelim. Excluding P111 | R3: =R11+R23 -> 102780
O4: Fixed Preliminaries
B6: P1 | C6: Preliminary and General Requirements Tender Drawings | D6: Notes | E6: All items will be priced individually. Any item not priced hereunder will be deemed to be included in the Contractors Tender. | F6: Item | G6: 0 | H6: 0 | I6: 0 | J6: =G6*H6 -> 0 | P6: =B13 -> P8 | R6: =I13 -> 10500
B7: P2 | C7: Preliminary and General Requirements Tender Drawings | D7: Tender Drawings | E7: The Tender Drawings are listed in Volume 4 Tender Drawings. | F7: Item | G7: 1 | H7: 0 | I7: 0 | J7: =G7*H7 -> 0 | P7: =B14 -> P9 | R7: =J14 -> 10500
B8: P3 | C8: Preliminary and General Requirements Conditions of Contract | D8: Conditions of Contract | E8: The Conditions of Contract shall be those contained within the Sultanate of Oman Standard Documents for Building and Civil Engineering Works prepared and issued by the Ministry of Finance Muscat. | F8: Item | G8: 1 | H8: 0 | I8: 0 | J8: =G8*H8 -> 0 | P8: =B43 -> P32 | R8: =I43 -> 1575
B9: P4 | C9: Preliminary and General Requirements Conditions of Contract | D9: Conditions of Contract | E9: The Contractor shall allow for complying in all respect with the Conditions of Contract. | F9: Item | G9: 1 | H9: 0 | I9: 0 | J9: =G9*H9 -> 0 | P9: =B44 -> P33 | R9: =I44 -> 1575
B10: P5 | C10: Preliminary and General Requirements Contractors Administration Arrangements | D10: Drawings | E10: The Contractor shall be responsible for checking all drawings and schedule etc. supplied by the Engineer. In the event of any discrepancy being found between such drawings and schedules etc. or if the Contractor considers that additional detail drawings are required then in either case the Contractor shall report such discrepancy to the Engineer for instruction or apply in writing for such detail drawings at least 28 days before the materials and components necessary for the works are to be placed on order by the Contractor. | F10: Item | G10: 1 | H10: 0 | I10: 0 | J10: =G10*H10 -> 0 | P10: =B89 -> P70 | R10: =I89 -> 1575
B11: P6 | C11: Preliminary and General Requirements Contractors Administration Arrangements | D11: Drawings | E11: The Contractor shall ascertain from the drawings or otherwise any holes recesses plugs etc. which may be required in time to form these as the work proceeds. No extra payments will be allowed for cuttings or forming such holes subsequently. | F11: Item | G11: 1 | H11: 0 | I11: 0 | J11: =G11*H11 -> 0 | R11: =SUM(R6:R10) -> 25725
B12: P7 | C12: Preliminary and General Requirements Contractors Administration Arrangements | D12: Drawings | E12: The Contractor will prepare at his own cost detailed working and shop drawings that may require supplementary to the construction drawings furnished by the Engineer. | F12: Item | G12: 1 | H12: 0 | I12: 0 | J12: =G12*H12 -> 0 | O12: Time based Preliminaries
B13: P8 | C13: Preliminary and General Requirements Contractors Administration Arrangements | D13: Drawings | E13: The detail and working drawing for civil and building works shall be prepared by the contractor supplement the construction drawings furnished by the Engineer will include Reinforcement details and Other drawings. | F13: Item | G13: 1 | H13: 10500 | I13: =G13*H13 -> 10500 | J13: =G13*H13 -> 10500 | P13: =B69 -> P54 | R13: =H69 -> 1050
B14: P9 | C14: Preliminary and General Requirements Contractors Administration Arrangements | D14: Drawings | E14: The detail and working drawing for civil and building works shall be prepared by the contractor supplement the construction drawings furnished by the Engineer will include the Drawings and details of foundation for equipment machinery and technical installation. | F14: Item | G14: 1 | H14: 10500 | I14: =G14*H14 -> 10500 | J14: =G14*H14 -> 10500 | P14: =B71 -> P56 | R14: =I71 -> 1575
B15: P10 | C15: Preliminary and General Requirements Contractors Administration Arrangements | D15: Drawings | E15: Such drawing and detail will depend on the type and make of the equipment offered and will include in particular foundations etc. for the standby power generators chiller and radiators transformers ventilation and airconditioning equipment etc. Construction details as required. | F15: Item | G15: 1 | H15: 0 | I15: 0 | P15: =B85 -> P66 | R15: =I85 -> 15750
B16: A | E16: SUM FOR PAGE1/13 | I16: =SUM(I6:I15) -> 21000 | J16: =SUM(J6:J15) -> 21000 | P16: =B86 -> P67 | R16: =I86 -> 7560
P17: =B87 -> P68 | R17: =I87 -> 15120
B18: P11 | C18: Preliminary and General Requirements Contractors Administration Arrangements | D18: Drawings | E18: No drawing etc. prepared by the Contractor shall be used in the works before the Engineer has approved it. | F18: Item | G18: 1 | H18: 0 | I18: 0 | J18: =G18*H18 -> 0 | P18: =B91 -> P72 | R18: =I91 -> 525
B19: P12 | C19: Preliminary and General Requirements Contractors Administration Arrangements | D19: Drawings | E19: The Contractor shall submit to the Engineer for his approval two copies of all his detail working or shop drawings and related documents produced by him for use in construction work. Any changes or modifications considered necessary by the Engineer shall be made at no extra cost to the Employer. | F19: Item | G19: 1 | H19: 0 | I19: 0 | J19: =G19*H19 -> 0 | P19: =B92 -> P73 | R19: =I91 -> 525
B20: P13 | C20: Preliminary and General Requirements Contractors Administration Arrangements | D20: Drawings | E20: Drawings and other documentation submitted to the Engineer for approval during the construction period should in no case be submitted later than two weeks before the date when the drawings or documents will be required on site for construction purpose. | F20: Item | G20: 1 | H20: 0 | I20: 0 | J20: =G20*H20 -> 0 | P20: =B123 -> P98 | R20: =I123 -> 1050
B21: P14 | C21: Preliminary and General Requirements General Instruction | D21: DESCRIPTION OF THE WORKS | E21: The work under this Contract comprises the provision of all materials plant and labour of whatever kind necessary and the proper performance of every operation required for the complete and proper construction completion commissioning and maintenance of Proposed 20 Nos Housing Units at Halaniyat Island including civil structural mechanical and electrical services and external works. The exact scope of work is indicated in the Tender Drawings. | F21: Item | G21: 1 | H21: 0 | I21: 0 | J21: =G21*H21 -> 0 | P21: =B143 -> P114 | R21: =J143 -> 25200
B22: P15 | C22: Preliminary and General Requirements General Instruction | D22: GENERAL INSTRUCTIONS | E22: The Tenderer shall insert a lumpsum or rate to each individual item Clause or SubClause in this Bill which he considers has a financial implication or is of financial value. Where the Contractor considers that an item Clause or SubClause has no financial value he shall insert the word Nil. Lump Sums shall not be inserted covering more than one item Clause or SubClause. | F22: Item | G22: 1 | H22: 0 | I22: 0 | J22: =G22*H22 -> 0 | P22: =B144 -> P115 | R22: =J144 -> 8700
B23: P16 | C23: Preliminary and General Requirements General Instruction | D23: GENERAL INSTRUCTIONS | E23: The value of services and obligations involved in all the items Clauses and SubClauses in this Bill shall not be included in rates or prices in other Bills of Quantities but shall be priced in their totality in this Bill. | F23: Item | G23: 1 | H23: 0 | I23: 0 | J23: =G23*H23 -> 0 | R23: =SUM(R13:R22) -> 77055
B24: P17 | C24: Preliminary and General Requirements Contractors Administration Arrangements | D24: Contractors Administrative Arrangements | E24: No examination or approval by the Engineer of any drawing or order documents submitted by the Contractor shall relieve the Contractor of any of his responsibilities under the Contract. | F24: Item | G24: 1 | H24: 0 | I24: 0 | J24: =G24*H24 -> 0
B25: P18 | C25: Preliminary and General Requirements Contractors Administration Arrangements | D25: Site Administration | E25: The Contractor shall allow for providing all that is required for the proper administration of the Contract at site level and in particular for complying in all respects with the relevant Clauses in the Standard Conditions of Contract. | F25: Item | G25: 1 | H25: 0 | I25: 0 | J25: =G25*H25 -> 0 | O25: Vessel | R25: 40000
B26: P19 | C26: Preliminary and General Requirements Contractors Administration Arrangements | D26: Site Inspection | E26: The Contractor is advised to visit and inspect the site during tendering at his own cost and hire own boat and to satisfy himself as to the accessibility and full extent and character of the site and of all local conditions and restrictions including the provision of and any matter referred to in Clause 11 of the Conditions of Contract.. | F26: Item | G26: 1 | H26: 0 | I26: 0 | J26: =G26*H26 -> 0 | O26: Head Office Exp | R26: 13232
B27: B | E27: SUM FOR PAGE2/13 | I27: =SUM(I18:I26) -> 0 | J27: =SUM(J18:J26) -> 0 | O27: OPC/SRC self life | R27: 5935
O28: Warehouse Taqa | R28: 2200
B29: P20 | C29: Preliminary and General Requirements Contractors Administration Arrangements | D29: Access to the site | E29: Access to the site will be from existing roads adjacent to the site.Access to the site may be obtained by prior arrangement with Engineer. During the construction and maintenance stages the Contractor will be responsible for complying with all of the Employers security and safety requirements. | F29: Item | G29: 1 | H29: 0 | I29: 0 | J29: =G29*H29 -> 0 | O29: Logistics | R29: 2700
B30: P21 | C30: Preliminary and General Requirements Contractors Administration Arrangements | D30: Access to the site | E30: During construction the Contractor will afford access to the site to any persons or Company employed directly by the Employer for the purpose of carrying out work at the site and will liaise with that person or company to agree a work procedure to ensure a mutually beneficial programme of work and to provide such services as are required in accordance with Clause 31 of the Conditions of Contract. | F30: Item | G30: 1 | H30: 0 | I30: 0 | J30: =G30*H30 -> 0 | O30: Eng. Accomodations | R30: 1260
B31: P22 | C31: Preliminary and General Requirements Contractors Administration Arrangements | D31: Access for Plant | E31: The Contractor should allow for all costs involved in making access arrangements for any items of plant etc. without risk of damage to roads leading to the site and such like and for reinstatement thereto. | F31: Item | G31: 1 | H31: 0 | I31: 0 | J31: =G31*H31 -> 0 | O31: Prolongation Overhead Cost | R31: =SUM(R25:R30) -> 65327
B32: P23 | C32: Preliminary and General Requirements Contractors Administration Arrangements | D32: Limitations of Working Space | E32: The Contractor shall confine his apparatus the storage of materials and the operations of the workman to the site and shall not be unreasonably encumber the area with his materials. | F32: Item | G32: 1 | H32: 0 | I32: 0 | J32: =G32*H32 -> 0
B33: P24 | C33: Preliminary and General Requirements Contractors Administration Arrangements | D33: Limitations of Working Space | E33: The Contractor shall be entirely responsible for complying with municipality regulations regarding fencing the site storage of materials and spoil heaps unloading of materials temporary building sanitary arrangements etc. No claims for delay or costs will be entertained in the event of work being stopped for breach of regulations. | F33: Item | G33: 1 | H33: 0 | I33: 0 | J33: =G33*H33 -> 0
B34: P25 | C34: Preliminary and General Requirements Contractors Administration Arrangements | D34: Limitation of Working Hours | E34: Any work which in accordance with Clause 45 of the Conditions of Contract or by agreement with the Engineer executed outside of normal working hours or on Fridays or Public Holidays shall be carried out in such a way as to cause the absolute minimum of disturbance or inconvenience to the Residents or users of the buildings near or adjacent to the works. | F34: Item | G34: 1 | H34: 0 | I34: 0 | J34: =G34*H34 -> 0
B35: P26 | C35: Preliminary and General Requirements Contractors Administration Arrangements | D35: Limitation of Working Hours | E35: The Contractors specific attention is drawn to the clauses in the specification relating to restriction of placement of certain items of work in certain weatherstemperature conditions and he is to allow for complying with these requirements. | F35: Item | G35: 1 | H35: 0 | I35: 0 | J35: =G35*H35 -> 0 | O35: Time Based Claim/Day | R35: =R23/730 -> 105.55479
B36: P27 | C36: Preliminary and General Requirements Contractors Administration Arrangements | D36: Restrictions | E36: The site shall not be used for any purpose other than the execution of the Contract. | F36: Item | G36: 1 | H36: 0 | I36: 0 | J36: =G36*H36 -> 0 | O36: Claim for 128 Days | R36: =R35*128 -> 13511.014
B37: P28 | C37: Preliminary and General Requirements Contractors Administration Arrangements | D37: Restrictions | E37: The Contractor will be required to make good any damage to the surrounding properties caused during the execution of the work and to restore to their original condition after the completion of the works. | F37: Item | G37: 1 | H37: 0 | I37: 0 | J37: =G37*H37 -> 0 | O37: Prolongation Cost Indirect | R37: =R31 -> 65327
B38: P29 | C38: Preliminary and General Requirements Contractors Administration Arrangements | D38: Restrictions | E38: Vegetation and trees are not to be cut down or in any way interfered with even if shown on the drawings to be removed or breached until the Engineers permission has been obtained. | F38: Item | G38: 1 | H38: 0 | I38: 0 | J38: =G38*H38 -> 0 | O38: Total Times Based Prelim. Claim | R38: =R37+R36 -> 78838.014
B39: C | E39: SUM FOR PAGE3/13 | I39: =SUM(I29:I38) -> 0 | J39: =SUM(J29:J38) -> 0
O40: Overall Prelim Excluding P111/Day | R40: =R3/730 -> 140.79452
B41: P30 | C41: Preliminary and General Requirements Contractors Administration Arrangements | D41: Vegetation and Trees | E41: Prevent damage to vegetation and trees and provide protection for them in accordance with the Specification. Pay all costs and charges incurred in complying with statutes and regulations regarding trees | F41: Item | G41: 1 | H41: 0 | I41: 0 | J41: =G41*H41 -> 0 | O41: Claim for 128 Days | R41: =R40*128 -> 18021.699
B42: P31 | C42: Preliminary and General Requirements Contractors Administration Arrangements | D42: Vegetation and Trees | E42: The Contractor shall ascertain for himself the location of existing services on under or over the site. He shall take precautions to protect all such services within the confines of the site temporarily divert as required reinstate on completion and immediately make good any damage at his own expense all to the satisfaction of the Engineer. | F42: Item | G42: 1 | H42: 0 | I42: 0 | J42: =G42*H42 -> 0 | O42: Prolongation Cost Indirect | R42: =R31 -> 65327
B43: P32 | C43: Preliminary and General Requirements Contractors Administration Arrangements | D43: Existing Services | E43: The Contractor shall ascertain for himself the location of existing services on under or over the site. He shall take precautions to protect all such services within the confines of the site temporarily divert as required reinstate on completion and immediately make good any damage at his own expense all to the satisfaction of the Engineer. | F43: Item | G43: 1 | H43: 1575 | I43: 1575 | J43: =G43*H43 -> 1575 | O43: Total Overall Prelim Based Claim | R43: =R41+R42 -> 83348.699
B44: P33 | C44: Preliminary and General Requirements Contractors Administration Arrangements | D44: Existing Services | E44: Allow for locate protect uphold temporarily divert if necessary and maintain all pipes ducts drains sewers service mains overhead or underground electrical telephone cables etc. during execution of the Works. The Contractor shall make good any damage to existing services andor property however caused at his own expense or pay any costs or charges in connection. Approval shall be obtained a minimum of two weeks in advance of any planned interruption of services. | F44: Item | G44: 1 | H44: 1575 | I44: 1575 | J44: =G44*H44 -> 1575
B45: P34 | C45: Preliminary and General Requirements Contractors Administration Arrangements | D45: Existing Services | E45: Existing services and their locations may not be fully shown on the drawings and the Contractor shall liaise with the relevant authorities to determine the exact nature and full extent of such services which require protection and maintenance. | F45: Item | G45: 1 | H45: 0 | I45: 0 | J45: =G45*H45 -> 0
B46: P35 | C46: Preliminary and General Requirements Contractors Administration Arrangements | D46: Supervision | E46: Detailed Curriculum Vitae of the Contractors Supervisory staff together with those of his SubContractors Supervisors must be submitted for the Engineers approval prior to commencement of the Works. | F46: Item | G46: 1 | H46: 0 | I46: 0 | J46: =G46*H46 -> 0
B47: P36 | C47: Preliminary and General Requirements Contractors Administration Arrangements | D47: Supervision | E47: The Project Manager Project Engineer shall not be changed without one months written notice to the Engineer. | F47: Item | G47: 1 | H47: 0 | I47: 0 | J47: =G47*H47 -> 0
B48: P37 | C48: Preliminary and General Requirements Contractors Administration Arrangements | D48: Security | E48: Allow for providing security to the site. Only those staff and workpeople directly employed on this project will be allowed on site. | F48: Item | G48: 1 | H48: 0 | I48: 0 | J48: =G48*H48 -> 0
B49: P38 | C49: Preliminary and General Requirements Contractors Administration Arrangements | D49: Safety Health and Welfare of Workpeople | E49: Provide for all costs and charges incurred by complying with all safety health and welfare regulations appertaining to staff and workpeople employed on the site including those employed by all SubContractors. | F49: Item | G49: 1 | H49: 0 | I49: 0 | J49: =G49*H49 -> 0
B50: D | E50: SUM FOR PAGE4/13 | I50: =SUM(I41:I49) -> 3150 | J50: =SUM(J41:J49) -> 3150
B52: P39 | C52: Preliminary and General Requirements Contractors Administration Arrangements | D52: Safety Health and Welfare of Workpeople | E52: The Contractor shall be responsible for and shall allow for providing medical facilities including emergency medical facilities for his staff and shall make these available to the Engineers staff. | F52: Item | G52: 1 | H52: 0 | I52: 0 | J52: =G52*H52 -> 0
B53: P40 | C53: Preliminary and General Requirements Contractors Administration Arrangements | D53: Safety Health and Welfare of Workpeople | E53: Allow for all costs for providing protective clothing and accessories for all workmen and supervisory staff on site. | F53: Item | G53: 1 | H53: 0 | I53: 0 | J53: =G53*H53 -> 0
B54: P41 | C54: Preliminary and General Requirements Contractors Administration Arrangements | D54: Safety Health and Welfare of Workpeople | E54: Contractors and Subcontractors operatives will not be allowed to eat and sleep on site at any time. Proper shaded areas are to be provided within the site establishment for Contractors and Subcontractors operatives to ensure they do not move outside the site premises. | F54: Item | G54: 1 | H54: 0 | I54: 0 | J54: =G54*H54 -> 0
B55: P42 | C55: Preliminary and General Requirements Contractors Administration Arrangements | D55: Transport of Workpeople | E55: Allow for the cost of all transport to and from site of the workpeople engaged on the site in approved vehicles. | F55: Item | G55: 1 | H55: 0 | I55: 0 | J55: =G55*H55 -> 0
B56: P43 | C56: Preliminary and General Requirements Contractors Administration Arrangements | D56: Constructional PlantSmall Plant and Tools | E56: Provide for all necessary small plant and tools for the proper execution and completion of the Contract. | F56: Item | G56: 1 | H56: 0 | I56: 0 | J56: =G56*H56 -> 0
B57: P44 | C57: Preliminary and General Requirements Contractors Administration Arrangements | D57: Constructional PlantScaffoldingworking platforms | E57: Provide all necessary temporary scaffolding and working platforms for the proper execution and completion of the Contract. Alter relocate and adapt from time to time as necessary. The Contractor is to ascertain whether any scaffolding or platform is required by any SubContractor before striking. If the Contractor should strike any of his scaffolding or working platform and it is so required it shall be reerected at his own expenses. | F57: Item | G57: 1 | H57: 0 | I57: 0 | J57: =G57*H57 -> 0
B58: P45 | C58: Preliminary and General Requirements Contractors Administration Arrangements | D58: Constructional PlantPlant required for Specific Trades | E58: Provide all necessary plant required for specific trades for the proper execution and completion of the Contract. | F58: Item | G58: 1 | H58: 0 | I58: 0 | J58: =G58*H58 -> 0
B59: P46 | C59: Preliminary and General Requirements Contractors Administration Arrangements | D59: Constructional PlantCranes and Lifting Plant | E59: Allow for all cranes and lifting plant necessary for the safe and efficient execution of the works to the satisfaction of the Engineer. | F59: Item | G59: 1 | H59: 0 | I59: 0 | J59: =G59*H59 -> 0
B60: P47 | C60: Preliminary and General Requirements Contractors Administration Arrangements | D60: Constructional PlantPlant generally | E60: Allow for all other plant necessary for the safe and efficient execution of the Works. | F60: Item | G60: 1 | H60: 0 | I60: 0 | J60: =G60*H60 -> 0
B61: P48 | C61: Preliminary and General Requirements Contractors Administration Arrangements | D61: Transport for Work People | E61: The Contractor is to allow for obtaining an adequate labour force for the Works and is to include for transport men to and from the Site as is necessary. | F61: Item | G61: 1 | H61: 0 | I61: 0 | J61: =G61*H61 -> 0
B62: P49 | C62: Preliminary and General Requirements Contractors Administration Arrangements | D62: Site Transportation | E62: Provide all necessary vehicles and other site transport etc. with all consumables store etc. as described for small plant and tools etc. | F62: Item | G62: 1 | H62: 0 | I62: 0 | J62: =G62*H62 -> 0
B63: E | E63: SUM FOR PAGE5/13 | I63: =SUM(I52:I62) -> 0 | J63: =SUM(J52:J62) -> 0
B65: P50 | C65: Preliminary and General Requirements Employer Facilities | D65: Temporary Office | E65: Provide erect furnish equip maintain and remove three month after completion of the Contract fully serviced furnished and equipped airconditioned offices and a conference room for the exclusive use of the Engineer all as described in General Requirement of the Architectural Specification. | F65: Item | G65: 1 | H65: 0 | I65: 0 | J65: =G65*H65 -> 0
B66: P51 | C66: Preliminary and General Requirements Employer Facilities | D66: Temporary Office | E66: The offices shall be provided and maintained throughout the period of the Contract. | F66: Item | G66: 1 | H66: 0 | I66: 0 | J66: =G66*H66 -> 0
B67: P52 | C67: Preliminary and General Requirements Employer Facilities | D67: Temporary Office | E67: The Contractor shall be responsible for providing security power water drainage safety helmets safety boots daily cleaning car parking and other facilities to the Engineers offices. | F67: Item | G67: 1 | H67: 0 | I67: 0 | J67: =G67*H67 -> 0
B68: P53 | C68: Preliminary and General Requirements Employer Facilities | D68: Temporary Office | E68: The Contractor shall be responsible during the continuance of the Contract for satisfactorily maintain and security of the offices and for all plans documents and paper and other articles contained there in. | F68: Item | G68: 1 | H68: 0 | I68: 0 | J68: =G68*H68 -> 0
B69: P54 | C69: Preliminary and General Requirements Employer Facilities | D69: Telephone for the Engineer and Employer | E69: Allow for providing the Engineers site office with an independent telephone service until removal of office and for paying all charges incurred by the Engineers staff for business calls concerning the project within the Sultanate of Oman. | F69: Item | G69: 1 | H69: 1050 | I69: 1050 | J69: =G69*H69 -> 1050
B70: P55 | C70: Preliminary and General Requirements Employer Facilities | D70: Attendance on the Engineer | E70: Provide attendance and assistance to the Engineer all as described in the Specification. | F70: Item | G70: 1 | H70: 0 | I70: 0 | J70: =G70*H70 -> 0
B71: P56 | C71: Preliminary and General Requirements Employer Facilities | D71: Surveying and other equipment | E71: The Contractor shall provide to the Engineer for his exclusive use all survey equipment and electrical test equipment as described in the Specification. | F71: Item | G71: 1 | H71: 1575 | I71: 1575 | J71: =G71*H71 -> 1575
B72: P57 | C72: Preliminary and General Requirements Employer Facilities | D72: Mobilisation | E72: The Engineer may issue the notice to proceed at any time within the period of validity of the tender. After the date of the notice to proceed the Contractor shall have a period of 120 days to complete mobilisation and to be completely prepared for the work. After the mobilisation is complete the work shall be carried out in accordance with the requirements of this Contract. | F72: Item | G72: 1 | H72: 0 | I72: 0 | J72: =G72*H72 -> 0
B73: P58 | C73: Preliminary and General Requirements Employer Facilities | D73: Programme and Order of Works | E73: Within 14 days of receipt of an order to commence the Works the Contractor shall submit to the Engineer a detailed programme in respect of all works contained in the scope of works including temporary works and services. | F73: Item | G73: 1 | H73: 0 | I73: 0 | J73: =G73*H73 -> 0
B74: P59 | C74: Preliminary and General Requirements Employer Facilities | D74: Programme and Order of Works | E74: Within 21 days of receipt of an order to commence the Works the Contractor shall submit to the Engineer a detailed programme in respect of all trades separately for each building section and external works and services together with the target dates for receipt of information required to enable the Contractor to comply with this programme. | F74: Item | G74: 1 | H74: 0 | I74: 0 | J74: =G74*H74 -> 0
B75: F | E75: SUM FOR PAGE6/13 | I75: =SUM(I65:I74) -> 2625 | J75: =SUM(J65:J74) -> 2625
B77: P60 | C77: Preliminary and General Requirements Employer Facilities | D77: Programme and Order of Works | E77: In addition the Contractor shall at the same time submit to the Engineer a detailed schedule of items and information that he requires instruction upon for early ordering schedules. | F77: Item | G77: 1 | H77: 0 | I77: 0 | J77: =G77*H77 -> 0
B78: P61 | C78: Preliminary and General Requirements Employer Facilities | D78: Coordination | E78: The Contractors attention is drawn to the fact that he shall be entirely responsible for the coordination of all works carried out by both his own workmen and the workmen of SubContractors and shall be responsible for ensuring that all SubContractors shop andor working drawings are submitted to the Engineer for approval in such time as not to prejudice the expeditious execution of the Works in accordance with the Contractors programme. | F78: Item | G78: 1 | H78: 0 | I78: 0 | J78: =G78*H78 -> 0
B79: P62 | C79: Preliminary and General Requirements Employer Facilities | D79: Reports | E79: Provide and maintain daily reports and delivery records for inspection by the Engineer. Such reports must give details of number and category of labour force list of plant list of material deliveries work planned and work carried out climatic conditions high and low temperature and any other information required by the Engineer. | F79: Item | G79: 1 | H79: 0 | I79: 0 | J79: =G79*H79 -> 0
B80: P63 | C80: Preliminary and General Requirements Employer Facilities | D80: Progress Reports | E80: Provide progress reports at intervals and in a format as required by the Engineer. | F80: Item | G80: 1 | H80: 0 | I80: 0 | J80: =G80*H80 -> 0
B81: P64 | C81: Preliminary and General Requirements Employer Facilities | D81: Progress Reports | E81: Provide a camera on site for use by the Engineer and arrange each month to print in duplicate colour progress photographs of the works taken by the Engineer. All photographs shall be subject to the Employers security precautions and shall not be used for promotional commercial purposes without written permission of the Employer. The Contractor shall provide suitable albums for the correct storage of the above photographs. The copy rights of all photographs rests with the Employer. | F81: Item | G81: 1 | H81: 0 | I81: 0 | J81: =G81*H81 -> 0
B82: P65 | C82: Preliminary and General Requirements Employer Facilities | D82: Site Sign Boards | E82: The Contractor shall allow for the provision erection and maintenance of two site sign board to display the project name the names of all Consultants associated with the Works and the Contractors name all as specified and to the approval of the Engineer.The sign board shall be complete with all necessary foundations supports framing painting and sign writing in Arabic and English denoting the title of the Project name of the Employer and names of Consultants and Contractor with their respective addresses and logos. The Contractor shall provide all details of the sign board to the Engineer for his approval before any work is put in hand and to enable erection to commence in the early stages of the Contract.The Contractor shall at the completion of the Contract remove the sign board supports and foundations. | F82: Item | G82: 1 | H82: 0 | I82: 0 | J82: =G82*H82 -> 0
B83: G | E83: SUM FOR PAGE7/13 | I83: =SUM(I77:I82) -> 0 | J83: =SUM(J77:J82) -> 0
B85: P66 | C85: Preliminary and General Requirements Employer Facilities | D85: Site Offices Stores and Other Facilities | E85: The Contractor shall provide erect maintain and remove on completion all necessary site offices stores messrooms sanitary accommodation and other facilities as may be required by the Contractor for his own and his SubContractors use together with all associated water drainage electrical lighting and power airconditioning telephoneradio facilities furniture equipment and attendance. | F85: Item | G85: 1 | H85: 15750 | I85: 15750 | J85: =G85*H85 -> 15750
B86: P67 | C86: Preliminary and General Requirements Employer Facilities | D86: Site Offices Stores and Other Facilities | E86: The position of all site offices stores etc. shall be to the approval of the Engineer and the Contractor must allow for all other facilities he may require to fulfil his contractual obligations additional to the area allocated to him. | F86: Item | G86: 1 | H86: 7560 | I86: 7560 | J86: =G86*H86 -> 7560
B87: P68 | C87: Preliminary and General Requirements Contractor Facilities | D87: Accommodation for Workmen | E87: The Contractor will not be allowed to accommodate workpeople on the site and arrangements must be made for such accommodation elsewhere at the Contractors expense and for transporting the workforce to the site. | F87: Item | G87: 1 | H87: 15120 | I87: 15120 | J87: =G87*H87 -> 15120
B88: P69 | C88: Preliminary and General Requirements Contractor Facilities | D88: Communications | E88: Provide a telephone for both his own and his SubContractors use including paying all charges in connection therewith. Radio telephone will only be permitted at the discretion of the Engineer if in his opinion it is not feasible to obtain a conventional telephone connection. | F88: Item | G88: 1 | H88: 0 | I88: 0 | J88: =G88*H88 -> 0
B89: P70 | C89: Preliminary and General Requirements | D89: Temporary worksTemporary Fencing | E89: Allow for all temporary fencing hoardings screens gantries etc. necessary for the execution of the Works. The Contractors particular attention is drawn to the neatness and approval of the hoardings by the Authorities and the Engineer. | F89: Item | G89: 1 | H89: 1575 | I89: 1575 | J89: =G89*H89 -> 1575
B90: P71 | C90: Preliminary and General Requirements | D90: Temporary worksTemporary Roads | E90: Provide maintain and alter as necessary temporary roads paths hardstandings pavement crossings and the like to and within the site. Remove and reinstate all ground and work disturbed when required. | F90: Item | G90: 1 | H90: 0 | I90: 0 | J90: =G90*H90 -> 0
B91: P72 | C91: Preliminary and General Requirements | D91: Temporary worksWater for the Works | E91: Provide all water required for the Works and provide and remove on completion all requisite temporary pipework pumps storage tanks etc. The Contractor must include for obtaining water from an independent source. | F91: Item | G91: 1 | H91: 525 | I91: 525 | J91: =G91*H91 -> 525
B92: P73 | C92: Preliminary and General Requirements | D92: Temporary worksElectricity for the Works | E92: Provide all electric light and power required for the Works including all temporary installations maintaining altering and adapting as necessary and remove all temporary installations on completion. | F92: Item | G92: 1 | H92: 525 | I92: 525 | J92: =G92*H92 -> 525
B93: P74 | C93: Preliminary and General Requirements | D93: Temporary worksTraffic Diversions | E93: The Contractor is to maintain at all times the flow of traffic on the existing roads and is to provide suitable signs lights and flag men at all times during the currency of the Contract all to the approval of the Authorities and the Engineer. | F93: Item | G93: 1 | H93: 0 | I93: 0 | J93: =G93*H93 -> 0
B94: P75 | C94: Preliminary and General Requirements | D94: Temporary worksPumping and Dewatering | E94: Provide here for all equipment and labour necessary to comply with the requirements for keeping the excavations and area of site free from surface underground running or standing water to the complete satisfaction of the Engineer to cover all such work wherever such work is not specifically measured in the relevant sections of the Bills of Quantities. | F94: Item | G94: 1 | H94: 0 | I94: 0 | J94: =G94*H94 -> 0
B95: H | E95: SUM FOR PAGE8/13 | I95: =SUM(I85:I94) -> 41055 | J95: =SUM(J85:J94) -> 41055
B97: P76 | C97: Preliminary and General Requirements | D97: Temporary worksTemporary Lighting | E97: Allow for installation maintenance and operation during hours of darkness a system of sufficient artificial lighting of roads paths access routes working platforms and areas where the works are in operation on site and that may be used or approached by any persons authorised to be on site and final removal from site on completion of the works. | F97: Item | G97: 1 | H97: 0 | I97: 0 | J97: =G97*H97 -> 0
B98: P77 | C98: Preliminary and General Requirements | D98: Sundry ItemsTesting of Materials and the Works | E98: Allow for all tests required by the Specification to be carried out including providing all necessary equipment materials and samples | F98: Item | G98: 1 | H98: 0 | I98: 0 | J98: =G98*H98 -> 0
B99: P78 | C99: Preliminary and General Requirements | D99: Sundry ItemsSingle Sources of Supply | E99: Where a choice of manufacturer or source of supply is allowed for any particular product of material the whole quantity required to complete the work must be of the same type manufacturer andor source. Changes will not be allowed without prior approval of the Engineer and at no cost to the Client. Written evidence of sources of supply must be produced when requested by Engineer. | F99: Item | G99: 1 | H99: 0 | I99: 0 | J99: =G99*H99 -> 0
B100: P79 | C100: Preliminary and General Requirements | D100: Sundry ItemsSamples; generally | E100: Allow for providing and submitting to the Engineer as he may require samples of all materials and goods which the Contractor proposes to incorporate in the Works. | F100: Item | G100: 1 | H100: 0 | I100: 0 | J100: =G100*H100 -> 0
B101: P80 | C101: Preliminary and General Requirements | D101: Sundry ItemsSamples; generally | E101: Allow for providing sample panels of materials workmanship and mockups as required by the Specification. | F101: Item | G101: 1 | H101: 0 | I101: 0 | J101: =G101*H101 -> 0
B102: P81 | C102: Preliminary and General Requirements | D102: Sundry ItemsSamples Marble | E102: The contractor shall submit three samples 300 x 300 mm of each marble specified layout of slabs and detailed shop drawings showing dimensions to the Engineer and obtain his approval prior to placing order. One of the samples should be the type of marble proposed to be incorporated in the works. | F102: Item | G102: 1 | H102: 0 | I102: 0 | J102: =G102*H102 -> 0
B103: P82 | C103: Preliminary and General Requirements | D103: Sundry ItemsSamples Marble | E103: The other two shall indicate the closest natural variation in colour and grain of the proposed marble. All marble slabs shall be delivered on site polished and ready for installation. | F103: Item | G103: 1 | H103: 0 | I103: 0 | J103: =G103*H103 -> 0
B104: P83 | C104: Preliminary and General Requirements | D104: Sundry ItemsSource of Marble | E104: Tenderers are required to name the proposed suppliers of marble to be incorporated in the works this information is to be submitted with the Tender. | F104: Item | G104: 1 | H104: 0 | I104: 0 | J104: =G104*H104 -> 0
B105: P84 | C105: Preliminary and General Requirements | D105: Sundry ItemsProtection of the Works | E105: Allow for protecting the Works from damage from any source including inclement weather. | F105: Item | G105: 1 | H105: 0 | I105: 0 | J105: =G105*H105 -> 0
B106: P85 | C106: Preliminary and General Requirements | D106: Sundry ItemsDisposal of refuse | E106: Keep the site free from debris arising from the Works during the construction period and leave the site free from debris and large loose stones on completion to the satisfaction of the Engineer. | F106: Item | G106: 1 | H106: 0 | I106: 0 | J106: =G106*H106 -> 0
B107: P86 | C107: Preliminary and General Requirements | D107: Sundry ItemsSite Clearance | E107: Clear the site of all scrub debris rubbish etc. in accordance with the Specification. | F107: Item | G107: 1 | H107: 0 | I107: 0 | J107: =G107*H107 -> 0
...

Sheet BILL NO 2. (DAY WORK)
B2: BILL NO 2. (DAY WORK)
B3: Item Code | C3: Item Name | D3: Item Details | E3: Additional Information | F3: UOM | G3: Quantity | H3: Unit Price | I3: Total Price In Figure | J3: CLAIMABLE AMOUNT | K3: Omission | L3: Addition
B5: D1 | C5: Daywork Schedule | D5: Day Work | E5: The Contractor may be required to execute certain works on the basis of day works. | F5: Item | G5: 1 | H5: 0 | I5: =G5*H5 -> 0
B6: D2 | C6: Daywork Schedule | D6: Day Work | E6: The Contractor shall keep an accurate record of time spent and materials and plant and used on each separate instruction given. Day work sheets are to be numbered and are to describe fully the instructions to which they refer and they are to be fully summarized fully priced and submitted to the Engineer for signature. The submission of such day work sheets does not necessarily mean that the work will be valued under Clause 13.5 of the Conditions of Contract or that any payment is in fact due. | F6: Item | G6: 1 | H6: 0 | I6: =G6*H6 -> 0
B7: D3 | C7: Daywork Schedule | D7: Labour 1. The Tenderer shall give the rates herein required for labourers and craftsmen against each item stated. 2.The rates are to be comprehensive and include | E7: Wages and all costs payments and charges including pensions annual and public holidays traveling time expenses fares and transport guaranteed time nonproductive time and other expenses in connection with overtime incentive and bonus payments dirty money and danger money and other disbursements arising from employment of labour including redundancy payment reduced working hours during Ramadhan all associated costs if labourers imported form other countries and workmens compensation insurance gratuity and all terminal benefits as per Oman labour Laws. | F7: Item | G7: 1 | H7: 0 | I7: =G7*H7 -> 0
B8: D4 | C8: Daywork Schedule | D8: Labour 1. The Tenderer shall give the rates herein required for labourers and craftsmen against each item stated. 2.The rates are to be comprehensive and include | E8: Charges incurred in respect of site and office supervision including foreman�s time and extra emoluments paid to foreman and leading craftsmen and gangers. | F8: Item | G8: 1 | H8: 0 | I8: =G8*H8 -> 0
B9: D5 | C9: Daywork Schedule | D9: Labour 1. The Tenderer shall give the rates herein required for labourers and craftsmen against each item stated. 2.The rates are to be comprehensive and include | E9: Site and Head Office overhead charges such as rent rates insurances electricity fuel water printing stationery postage telephone charges motor car expenses renewals maintenance and depreciation of premises machinery plant and the like. | F9: Item | G9: 1 | H9: 0 | I9: =G9*H9 -> 0
B10: D6 | C10: Daywork Schedule | D10: Labour 1. The Tenderer shall give the rates herein required for labourers and craftsmen against each item stated. 2.The rates are to be comprehensive and include | E10: Profit | F10: Item | G10: 1 | H10: 0 | I10: =G10*H10 -> 0
B11: D7 | C11: Daywork Schedule | D11: Materials | E11: Materials used in day works to be charged at invoice cost. All discounts are to be allowed to the Ministry of Health. Invoices are to be made available to the Engineer at the time the relevant day work sheets are submitted. | F11: Item | G11: 1 | H11: 0 | I11: =G11*H11 -> 0
B12: D8 | C12: Daywork Schedule | D12: Materials | E12: The Contractor is to allow for additional percentage he requires to be added to the invoice cost of materials to cover for ordering taking delivery paying all insurances in transit landing charges dues custom duties Municipality tax and all other charges loading and transporting to the site taking into store storing as may be required and all other charges and profit. | F12: Item | G12: 1 | H12: 0 | I12: =G12*H12 -> 0
B13: D9 | C13: Daywork Schedule | D13: Plant 1. The Contractor shall give here the rates he requires for plant and machinery 2. The rates are to be comprehensive and include | E13: Mobilization and demobilization costs | F13: Item | G13: 1 | H13: 0 | I13: =G13*H13 -> 0
B14: D10 | C14: Daywork Schedule | D14: Plant 1. The Contractor shall give here the rates he requires for plant and machinery 2. The rates are to be comprehensive and include | E14: Fuel oil lubricants and all other consumable stores. | F14: Item | G14: 1 | H14: 0 | I14: =G14*H14 -> 0
B15: D11 | C15: Daywork Schedule | D15: Plant 1. The Contractor shall give here the rates he requires for plant and machinery 2. The rates are to be comprehensive and include | E15: Servicing repairs and replacements. | F15: Item | G15: 1 | H15: 0 | I15: =G15*H15 -> 0
B16: D12 | C16: Daywork Schedule | D16: Plant 1. The Contractor shall give here the rates he requires for plant and machinery 2. The rates are to be comprehensive and include | E16: Site and Head Office overhead charges as previously defined. | F16: Item | G16: 1 | H16: 0 | I16: =G16*H16 -> 0
... B24: D20 | C24: Daywork Schedule | D24: Labour | E24: Tile Layers | F24: Hr | G24: 50 | H24: 0 | I24: =G24*H24 -> 0
B25: D21 | C25: Daywork Schedule | D25: Labour | E25: Masons | F25: Hr | G25: 50 | H25: 10.6 | I25: =G25*H25 -> 530 | K25: =G25*H25 -> 530
B26: D22 | C26: Daywork Schedule | D26: Labour | E26: Painters | F26: Hr | G26: 50 | H26: 10.5 | I26: =G26*H26 -> 525 | K26: =G26*H26 -> 525
B27: D23 | C27: Daywork Schedule | D27: Labour | E27: Scaffolders | F27: Hr | G27: 50 | H27: 10.5 | I27: =G27*H27 -> 525 | K27: =G27*H27 -> 525
B28: D24 | C28: Daywork Schedule | D28: Labour | E28: Drainlayers | F28: Hr | G28: 50 | H28: 10.6 | I28: =G28*H28 -> 530 | K28: =G28*H28 -> 530
B29: D25 | C29: Daywork Schedule | D29: Labour | E29: Plumbers | F29: Hr | G29: 50 | H29: 10.5 | I29: =G29*H29 -> 525 | K29: =G29*H29 -> 525
B30: D26 | C30: Daywork Schedule | D30: Labour | E30: ElectriciansA.C. Mechanics | F30: Hr | G30: 50 | H30: 10.5 | I30: =G30*H30 -> 525 | K30: =G30*H30 -> 525
B31: D27 | C31: Daywork Schedule | D31: Labour | E31: Welders | F31: Hr | G31: 50 | H31: 10.5 | I31: =G31*H31 -> 525 | K31: =G31*H31 -> 525
B32: D28 | C32: Daywork Schedule | D32: Labour | E32: FabricatorsFitters | F32: Hr | G32: 50 | H32: 10.5 | I32: =G32*H32 -> 525 | K32: =G32*H32 -> 525
B33: D29 | C33: Daywork Schedule | D33: Labour | E33: Plant and Machinery Operators and Drivers | F33: Hr | G33: 80 | H33: 10.5 | I33: =G33*H33 -> 840 | K33: =G33*H33 -> 840
B34: D30 | C34: Daywork Schedule | D34: Materials | E34: Include the Provisional Sum of Rials Omani Ten Thousand RO. 10000.000 for the cost of Local Materials expended on Dayworks. These costs shall be charged at the nett price paid by the Contractor for the materials exsupplier as substantiated by the suppliers invoices. | F34: Item | G34: 1 | H34: 0 | I34: =G34*H34 -> 0
B35: D31 | C35: Daywork Schedule | D35: Materials | E35: Include the Provisional Sum of Rials Omani Ten Thousand R.O. 10000.000 for the cost of Imported Materials expended on daywork. These costs shall be charged at the nett price paid by the Contractor for the materials delivered C.I.F. Oman as substantiated by the suppliers invoices. | F35: Item | G35: 1 | H35: 0 | I35: =G35*H35 -> 0
B36: D32 | C36: Daywork Schedule | D36: Materials | E36: Contractors percentage on net cost of material 5 percent | F36: Item | G36: 1 | H36: 0 | I36: =G36*H36 -> 0
B37: D33 | C37: Daywork Schedule | D37: Plant | E37: Portable compressors Complete with hoses Delivery of free air Up to 4.6 Cumper minute | F37: Hr | G37: 50 | H37: 52.5 | I37: =G37*H37 -> 2625 | K37: =G37*H37 -> 2625
B38: D34 | C38: Daywork Schedule | D38: Plant | E38: Pneumatic hammer including steels | F38: Hr | G38: 20 | H38: 31.5 | I38: =G38*H38 -> 630 | K38: =G38*H38 -> 630
B39: D35 | C39: Daywork Schedule | D39: Plant | E39: Concrete Mixers | F39: Hr | G39: 50 | H39: 21 | I39: =G39*H39 -> 1050 | K39: =G39*H39 -> 1050
B40: D36 | C40: Daywork Schedule | D40: Plant | E40: Dumper up to 0.5 Cum bucket capacity | F40: Hr | G40: 30 | H40: 21 | I40: =G40*H40 -> 630 | K40: =G40*H40 -> 630
B41: D37 | C41: Daywork Schedule | D41: Plant | E41: Concrete vibrator poker 50mm diameter | F41: Hr | G41: 30 | H41: 10.5 | I41: =G41*H41 -> 315 | K41: =G41*H41 -> 315
B42: D38 | C42: Daywork Schedule | D42: Plant | E42: Excavators up to 0.5 Cum bucket capacity | F42: Hr | G42: 30 | H42: 10.5 | I42: =G42*H42 -> 315 | K42: =G42*H42 -> 315
B43: D39 | C43: Daywork Schedule | D43: Plant | E43: Generator sets 50 KVA | F43: Hr | G43: 50 | H43: 31.5 | I43: =G43*H43 -> 1575 | K43: =G43*H43 -> 1575
B44: D40 | C44: Daywork Schedule | D44: Plant | E44: Tipper truck 10 tonne | F44: Hr | G44: 40 | H44: 52.5 | I44: =G44*H44 -> 2100 | K44: =G44*H44 -> 2100
B45: D41 | C45: Daywork Schedule | D45: Plant | E45: Van or utility vehicle | F45: Hr | G45: 40 | H45: 21 | I45: =G45*H45 -> 840 | K45: =G45*H45 -> 840
B46: D42 | C46: Daywork Schedule | D46: Plant | E46: Three tonne pickup | F46: Hr | G46: 40 | H46: 31.5 | I46: =G46*H46 -> 1260 | K46: =G46*H46 -> 1260
B47: D43 | C47: Daywork Schedule | D47: Plant | E47: Water tanker 2000 gallon | F47: Hr | G47: 20 | H47: 31.5 | I47: =G47*H47 -> 630 | K47: =G47*H47 -> 630
B48: D44 | C48: Daywork Schedule | D48: Plant | E48: Excavator hydraulic full circle slew 1m3 | F48: Hr | G48: 20 | H48: 42 | I48: =G48*H48 -> 840 | K48: =G48*H48 -> 840
... B69: D65 | C69: Daywork Schedule | D69: Employee Staff | E69: Assistant to Cook | F69: Hr | G69: 200 | H69: 10.5 | I69: =G69*H69 -> 2100 | K69: =G69*H69 -> 2100
B70: P66 | C70: Preliminary and General Requirements Employer Facilities | D70: Site Offices Stores and Other Facilities | E70: The Contractor shall provide erect maintain and remove on completion all necessary site offices stores messrooms sanitary accommodation and other facilities as may be required by the Contractor for his own and his SubContractors use together with all associated water drainage electrical lighting and power airconditioning telephoneradio facilities furniture equipment and attendance. | F70: Item | G70: 1 | H70: 0 | I70: =G70*H70 -> 0
B71: P67 | C71: Preliminary and General Requirements Employer Facilities | D71: Site Offices Stores and Other Facilities | E71: The position of all site offices stores etc. shall be to the approval of the Engineer and the Contractor must allow for all other facilities he may require to fulfil his contractual obligations additional to the area allocated to him. | F71: Item | G71: 1 | H71: 0 | I71: =G71*H71 -> 0
B72: P68 | C72: Preliminary and General Requirements Contractor Facilities | D72: Accommodation for Workmen | E72: The Contractor will not be allowed to accommodate workpeople on the site and arrangements must be made for such accommodation elsewhere at the Contractors expense and for transporting the workforce to the site. | F72: Item | G72: 1 | H72: 0 | I72: =G72*H72 -> 0
B73: P69 | C73: Preliminary and General Requirements Contractor Facilities | D73: Communications | E73: Provide a telephone for both his own and his SubContractors use including paying all charges in connection therewith. Radio telephone will only be permitted at the discretion of the Engineer if in his opinion it is not feasible to obtain a conventional telephone connection. | F73: Item | G73: 1 | H73: 0 | I73: =G73*H73 -> 0
B74: P70 | C74: Preliminary and General Requirements | D74: Temporary worksTemporary Fencing | E74: Allow for all temporary fencing hoardings screens gantries etc. necessary for the execution of the Works. The Contractors particular attention is drawn to the neatness and approval of the hoardings by the Authorities and the Engineer. | F74: Item | G74: 1 | H74: 0 | I74: =G74*H74 -> 0
B75: P71 | C75: Preliminary and General Requirements | D75: Temporary worksTemporary Roads | E75: Provide maintain and alter as necessary temporary roads paths hardstandings pavement crossings and the like to and within the site. Remove and reinstate all ground and work disturbed when required. | F75: Item | G75: 1 | H75: 0 | I75: =G75*H75 -> 0
B76: P72 | C76: Preliminary and General Requirements | D76: Temporary worksWater for the Works | E76: Provide all water required for the Works and provide and remove on completion all requisite temporary pipework pumps storage tanks etc. The Contractor must include for obtaining water from an independent source. | F76: Item | G76: 1 | H76: 0 | I76: =G76*H76 -> 0
B77: P73 | C77: Preliminary and General Requirements | D77: Temporary worksElectricity for the Works | E77: Provide all electric light and power required for the Works including all temporary installations maintaining altering and adapting as necessary and remove all temporary installations on completion. | F77: Item | G77: 1 | H77: 0 | I77: =G77*H77 -> 0
B78: P74 | C78: Preliminary and General Requirements | D78: Temporary worksTraffic Diversions | E78: The Contractor is to maintain at all times the flow of traffic on the existing roads and is to provide suitable signs lights and flag men at all times during the currency of the Contract all to the approval of the Authorities and the Engineer. | F78: Item | G78: 1 | H78: 0 | I78: =G78*H78 -> 0
B79: P75 | C79: Preliminary and General Requirements | D79: Temporary worksPumping and Dewatering | E79: Provide here for all equipment and labour necessary to comply with the requirements for keeping the excavations and area of site free from surface underground running or standing water to the complete satisfaction of the Engineer to cover all such work wherever such work is not specifically measured in the relevant sections of the Bills of Quantities. | F79: Item | G79: 1 | H79: 0 | I79: =G79*H79 -> 0
B80: P76 | C80: Preliminary and General Requirements | D80: Temporary worksTemporary Lighting | E80: Allow for installation maintenance and operation during hours of darkness a system of sufficient artificial lighting of roads paths access routes working platforms and areas where the works are in operation on site and that may be used or approached by any persons authorised to be on site and final removal from site on completion of the works. | F80: Item | G80: 1 | H80: 0 | I80: =G80*H80 -> 0
B81: P77 | C81: Preliminary and General Requirements | D81: Sundry ItemsTesting of Materials and the Works | E81: Allow for all tests required by the Specification to be carried out including providing all necessary equipment materials and samples | F81: Item | G81: 1 | H81: 0 | I81: =G81*H81 -> 0
... B119: P115 | C119: Preliminary and General Requirements Contractors Administration Arrangements | D119: Site Transportation for EngineersEmployers | E119: Provide necessary 4x4 vehicles 2nos in excellent condition for consultantclient staff transportation and pickup vehicle 2nos for site transport etc. with all consumables fuel etc. as described for small plant and tools for regular maintenance etc as per details in prim documents. | F119: Item | G119: 1 | H119: 0 | I119: =G119*H119 -> 0
B120: TOTAL DAYWORKS | H120: 88252.5 | J120: 0 | K120: =SUM(K6:K119) -> 88262.5 | L120: =SUM(L5:L119) -> 0

Sheet BILL NO 3. (PROVISIONAL SUM)
B2: BILL NO. 3 (PROVISIONAL SUM)
B3: Item Code | C3: Item Name | D3: Item Details | E3: Additional Information | F3: UOM | G3: Quantity | H3: Unit Price | I3: Total Price In Figure | J3: REVISED BOQ AMOUNT | K3: Omission | L3: Addition
B5: PV1 | C5: Allow for the provisional sums to be expended as directed by the Engineer or deducted in whole or in part if not required - Soft landscaping and Irrigation System | D5: 1 | E5: Item | F5: Item | G5: 1 | H5: 20000 | I5: =G5*H5 -> 20000 | K5: =G5*H5 -> 20000
B6: PV2 | C6: Allow for the provisional sums to be expended as directed by the Engineer or deducted in whole or in part if not - 2000 KVA Sub Station | D6: 1 | E6: Item | F6: Item | G6: 1 | H6: 40000 | I6: =G6*H6 -> 40000 | K6: =G6*H6 -> 40000
B7: PV3 | C7: Allow for the provisional sums to be expended as directed by the Engineer or deducted in whole or in part if not - 11 KV extension & tapping | D7: 1 | E7: Item | F7: Item | G7: 1 | H7: 60000 | I7: =G7*H7 -> 60000 | K7: =G7*H7 -> 60000
B8: PV4 | C8: Allow for the provisional sums to be expended as directed by the Engineer or deducted in whole or in part if not - Water and Power Main Connection from the Authority for Electricity line and Water line. | D8: 1 | E8: Item | F8: Item | G8: 1 | H8: 40000 | I8: =G8*H8 -> 40000 | K8: =G8*H8 -> 40000
B9: PV5 | C9: Allow for the provisional sums to be expended as directed by the Engineer or deducted in whole or in part if not - Relocation of Halaniyat Resident to the Temporary Houses in Salalah, Two Bed Room, Two Toilet, One Kitchen for 28 months. | D9: 1 | E9: Item | F9: Item | G9: 1 | H9: --------------- | I9: Covered in Preliminaries P111 | K9: -------------------
B10: PV6 | C10: Allow for the provisional sums to be expended as directed by the Engineer or deducted in whole or in part if not - Add for overhead and profit (7.5 percent) | D10: 1 | E10: Item | F10: Item | G10: 1 | H10: 40000 | I10: =G10*H10 -> 40000 | K10: =G10*H10 -> 40000
B11: TOTAL PROVISIONAL SUM | I11: =SUM(I5:I10) -> 200000 | J11: ---------------- | K11: =SUM(K5:K10) -> 200000 | L11: =SUM(L5:L10) -> 0

Sheet BILL NO4. (20 NHU)
B2: BILL NO 4. (20 NEW HOUSING UNITS) | J2: REVISED AMOUNT | L2: OMISSION | N2: ADDITION
B3: Item Code | C3: Item Name | D3: Item Details | E3: Additional Information | F3: UOM | G3: BOQ-Quantity | H3: Unit Price | I3: Total Price In Figure | J3: Actual-Quantity | K3: Actual Amount | L3: QUANTITIES | M3: AMOUNT | N3: QUANTITIES | O3: AMOUNT | P3: APPENDIX
B5: C1 | C5: General Works | D5: Demolishing and Clearing the Construction Area | E5: Demolishing the complete building and removing the debris from the Construction Site as per EngineerEmployer Instruction including cart away from the Project Site up to OGL | F5: NO | G5: 20 | H5: 2520 | I5: =G5*H5 -> 50400 | J5: 20 | K5: =J5*H5 -> 50400
B6: C2 | C6: Substructure Works | D6: Site Clearance | E6: This shall include removing vegetation undergrowth bushes hedges trees other temporary buildings structures or the like all complete to clean the full plot. | F6: NO | G6: 20 | H6: 52.5 | I6: =G6*H6 -> 1050 | J6: 20 | K6: =J6*H6 -> 1050
B7: C3 | C7: Substructure Works | D7: Earth work and Excavation | E7: Bulk Excavation to receive foundations in any kind of soil including hard soil and rock earth sport underground surface or running water from whatever source if any for the new foundation building area including removal of old buildings foundations cleaning the site and removing all debris not suitable for backfilling from the project area to the damp yard contractor to prepare all areas to receive new foundation safely as per drawings and soil report. | F7: M3 | G7: 15000 | H7: 0.77 | I7: =G7*H7 -> 11550 | J7: 12726.72 | K7: =J7*H7 -> 9799.5744 | L7: =G7-J7 -> 2273.28 | M7: =L7*H7 -> 1750.4256
B8: C4 | C8: Substructure Works | D8: Filling | E8: Approved imported granular fill material compacted in layers in making up levels under floors | F8: M3 | G8: 4000 | H8: 0.525 | I8: =G8*H8 -> 2100 | L8: =G8-J8 -> 4000 | M8: =L8*H8 -> 2100
B9: C5 | C9: Substructure Works | D9: Filling | E9: Approved imported fill material compacted in layers to raise the levels | F9: M3 | G9: 15000 | H9: 0.525 | I9: =G9*H9 -> 7875 | J9: =5018.54+542.81 -> 5561.35 | K9: =J9*H9 -> 2919.7088 | L9: =G9-J9 -> 9438.65 | M9: =L9*H9 -> 4955.2913
B10: C6 | C10: Substructure Works | D10: Filling | E10: Approved selected excavated material backfilled into excavations | F10: M3 | G10: 6000 | H10: 0.525 | I10: =G10*H10 -> 3150 | J10: 6000 | K10: =J10*H10 -> 3150 | L10: =G10-J10 -> 0 | M10: =L10*H10 -> 0
B11: C7 | C11: Substructure Works | D11: Filling | E11: 200 mm thick well compacted hardcore filling under floors | F11: M3 | G11: 1040 | H11: 0.455 | I11: =G11*H11 -> 473.2 | K11: =J11*H11 -> 0 | L11: =G11-J11 -> 1040 | M11: =L11*H11 -> 473.2
B12: C8 | C12: Substructure Works | D12: Anti termite treatment | E12: Anti termite treatment to surfaces of ground or filling applied strictly in accordance with the manufacturers printed instructions including digging trenches backfilling etc. as required by the manufacturer and the provision of guarantee valid for 10 years | F12: M2 | G12: 6200 | H12: 1.524 | I12: =G12*H12 -> 9448.8 | J12: =(260.53*20)+723.75 -> 5934.35 | K12: =J12*H12 -> 9043.9494 | L12: =G12-J12 -> 265.65 | M12: =L12*H12 -> 404.8506
B13: A | C13: SUM FOR PAGE-1/68 | I13: 86047 | K13: =SUM(K5:K12) -> 76363.233 | L13: =G13-J13 -> 0 | M13: =SUM(M7:M12) -> 9683.7675
B14: C9 | C14: Substructure Works | D14: Poured Concrete Plain insitu concrete poured Ordinary Portland Cement OPC Concrete Grade C15 all in accordance with Drawings and Specifications and including Formwork to give as struck finish. Providing and erecting formwork including all necessary staging centering shuttering supports cross bracing deshuttering carefully making good the damaged surfaces wherever necessary all complete as specified and as directed by the Engineer all in accordance with the Drawings and Specifications | E14: Blinding upto 100 mm thickness | F14: M3 | G14: 300 | H14: 63 | I14: 18900 | J14: 284.36 | K14: =J14*H14 -> 17914.68 | L14: =G14-J14 -> 15.64 | M14: =L14*H14 -> 985.32
B15: B | C15: SUM FOR PAGE-2/68 | I15: 18900 | K15: =K14 -> 17914.68 | L15: =G15-J15 -> 0 | M15: =M14 -> 985.32
B16: C10 | C16: Substructure Works | D16: Reinforced insitu concrete poured vibrated Sulphate Resistent Cement OPC Concrete Grade C30 all in accordance with Drawings and Specifications and including Reinforcement High yield strength deformed bars conforming to BS 4449 Grade 460 including cutting bending binding binding wire cover blocks tests and all necessary fixing accessories all in accordance with the Drawings and Specifications and including Formwork to give as struck finish. Providing and erecting formwork including all necessary staging centering shuttering supports cross bracing deshuttering carefully making good the damaged surfaces wherever necessary all complete as specified and as directed by the Engineer all in accordance with the Drawings and Specifications | E16: Footings | F16: M3 | G16: 800 | H16: 94.5 | I16: 75600 | J16: 734.32 | K16: =J16*H16 -> 69393.24 | L16: =G16-J16 -> 65.68 | M16: =L16*H16 -> 6206.76
B17: C | C17: SUM FOR PAGE-3/68 | I17: 75600 | K17: =K16 -> 69393.24 | L17: =G17-J17 -> 0 | M17: =M16 -> 6206.76
B18: C11 | C18: Substructure Works | D18: Reinforced insitu concrete poured vibrated Sulphate Resistent Cement OPC Concrete Grade C30 all in accordance with Drawings and Specifications and including Reinforcement High yield strength deformed bars conforming to BS 4449 Grade 460 including cutting bending binding binding wire cover blocks tests and all necessary fixing accessories all in accordance with the Drawings and Specifications and including Formwork to give as struck finish. Providing and erecting formwork including all necessary staging centering shuttering supports cross bracing deshuttering carefully making good the damaged surfaces wherever necessary all complete as specified and as directed by the Engineer all in accordance with the Drawings and Specifications | E18: Plinth beams | F18: M3 | G18: 600 | H18: 94.5 | I18: 56700 | J18: =22.23*20 -> 444.6 | K18: =J18*H18 -> 42014.7 | L18: =G18-J18 -> 155.4 | M18: =L18*H18 -> 14685.3
B19: D | C19: SUM FOR PAGE-4/68 | I19: 56700 | K19: =K18 -> 42014.7 | L19: =G19-J19 -> 0 | M19: =M18 -> 14685.3
B20: C12 | C20: Substructure Works | D20: Reinforced insitu concrete poured vibrated Sulphate Resistent Cement OPC Concrete Grade C30 all in accordance with Drawings and Specifications and including Reinforcement High yield strength deformed bars conforming to BS 4449 Grade 460 including cutting bending binding binding wire cover blocks tests and all necessary fixing accessories all in accordance with the Drawings and Specifications and including Steel fabric reinforcement A 393 BRC mesh in two layers. All complete in accordance with the Drawings and Specifications and including Formwork to give as struck finish. Providing and erecting formwork including all necessary staging centering shuttering supports cross bracing deshuttering carefully making good the damaged surfaces wherever necessary all complete as specified and as directed by the Engineer all in accordance with the Drawings and Specifications | E20: Beds Slabs Grade slabs upto 120 mm thickness | F20: M3 | G20: 800 | H20: 94.5 | I20: 75600 | J20: =606.192+86.85 -> 693.042 | K20: =(J20*H20) -> 65492.469 | L20: =G20-J20 -> 106.958 | M20: =L20*H20 -> 10107.531
B21: E | C21: SUM FOR PAGE-5/68 | I21: 75600 | K21: =K20 -> 65492.469 | L21: =G21-J21 -> 0 | M21: =M20 -> 10107.531
B22: C13 | C22: Substructure Works | D22: Reinforced insitu concrete poured vibrated ordinary Portland Cement OPC Concrete Grade C40 all in accordance with Drawings and Specifications and including Reinforcement High yield strength deformed bars conforming to BS 4449 Grade 460 including cutting bending binding binding wire cover blocks tests and all necessary fixing accessories all in accordance with the Drawings and Specifications and including Formwork to give as struck finish. Providing and erecting formwork including all necessary staging centering shuttering supports cross bracing deshuttering carefully making good the damaged surfaces wherever necessary all complete as specified and as directed by the Engineer all in accordance with the Drawings and Specifications | E22: Substructure columns | F22: M3 | G22: 200 | H22: 94.5 | I22: 18900 | J22: 113.54 | K22: =J22*H22 -> 10729.53 | L22: =G22-J22 -> 86.46 | M22: =L22*H22 -> 8170.47
B23: C14 | C23: Substructure Works | D23: Sundries Concrete and Block work Protection | E23: Polythene sheet gauge 1200 all in accordance with Drawings and Specifications to surfaces of structural members in contact with soil | F23: M2 | G23: 8400 | H23: 2 | I23: 16800 | J23: =(394.76*20)+723.75 -> 8618.95 | K23: =(J23*H23)+723.75 -> 17961.65 | L23: =G23-J23 -> -218.95 | M23: =L23*H23 -> -437.9
B24: C15 | C24: Substructure Works | D24: Sundries Bitumenous Paint | E24: Bitumenous Paint 3 coat to the surfaces of concrete | F24: M2 | G24: 10000 | H24: 0.546 | I24: 5460 | K24: =J24*H24 -> 0 | L24: =G24-J24 -> 10000 | M24: =L24*H24 -> 5460
B25: C16 | C25: Substructure Works | D25: Sundries Bitumenous Sheet | E25: Bitumenous Sheet to the surfaces of concrete | F25: M2 | G25: 5200 | H25: 5.25 | I25: 27300 | K25: =J25*H25 -> 0 | L25: =G25-J25 -> 5200 | M25: =L25*H25 -> 27300
B26: F | C26: SUM FOR PAGE-6/68 | I26: 68460 | K26: =SUM(K22:K25) -> 28691.18 | L26: =G26-J26 -> 0 | M26: =SUM(M22:M25) -> 40492.57
B27: C17 | C27: Substructure Works | D27: Sundries Block work Protection including Bitumenous Paint and Bitumenous Sheet | E27: Protection to concrete masonryblock work in contact with soil 3 coats of approved bituminous paint bituminous sheet and including flexible board all in accordance with Drawings and Specifications to surfaces of block work in contact with soil. | F27: M2 | G27: 22000 | H27: 21 | I27: 462000 | J27: =14861.5+420.75 -> 15282.25 | K27: =J27*H27 -> 320927.25 | L27: =G27-J27 -> 6717.75 | M27: =L27*H27 -> 141072.75
B28: C18 | C28: Substructure Works | D28: Concrete solid block work 10.5N per mm2 compressive strength cement and sand mortar 1to3 with and including stiffener columns and stiffener beams as required all in accordance with Drawings and Specifications | E28: 200mm thick walls | F28: M2 | G28: 11000 | H28: 9.45 | I28: 103950 | J28: 3732.2 | K28: =J28*H28 -> 35269.29 | L28: =G28-J28 -> 7267.8 | M28: =L28*H28 -> 68680.71
B29: C19 | C29: Substructure Works | D29: The Contractor should read and quote as per the supply laying and all works are included and required approval and commissioning as per contract standards should be under the Contractor scope of work including required charges also including DNP scope and guarantees for material. | E29: Important Note | F29: Item | G29: 0 | H29: 0 | I29: 0 | J29: - | K29: -
B30: G | C30: SUM FOR PAGE-7/68 | I30: 565950 | K30: =SUM(K27:K29) -> 356196.54 | M30: =SUM(M27:M29) -> 209753.46
B31: C20 | C31: Substructure Works | D31: The Contractor is adviced to complete the project as per the drawing boq and specification also need to complete if anything missing in the drawing but mentioned in the boq and specification and viceversa. Should the Tenderer fail to insert any item here it will be deemed that this lump sum price for the tender includes all items and no subsequent claim for any additional items will be entertained | E31: Important Note | F31: Item | G31: 0 | H31: 0 | I31: 0 | J31: - | K31: -
B32: H | C32: SUM FOR PAGE-8/68 | I32: 0 | K32: -
B33: C21 | C33: Substructure Works | D33: The Contractor is to detail below any additional items with quantities and rates not previously included to complete the build up of the lump sum tender price for this section of the works. Should the Tenderer fail to insert any item here it will be deemed that this lump sum price for the tender includes all items and no subsequent claim for any additional items will be entertained | E33: Important Note | F33: Item | G33: 0 | H33: 0 | I33: 0 | J33: - | K33: -
B34: I | C34: SUM FOR PAGE-9/68 | I34: =I30+I26+I21+I19+I17+I15+I13 -> 947257 | K34: =K30+K26+K21+K19+K17+K15+K13 -> 656066.04 | M34: =M30+M26+M21+M19+M17+M15+M13 -> 291914.71
B35: C22 | C35: Superstructure Works Concrete Works | D35: Poured Concrete Reinforced insitu concrete poured vibrated Ordinary Portland Cement OPC concrete grade C30 all in accordance with the Drawings and Specifications and including Reinforcement High yield strength deformed bars conforming to BS 4449 Grade 460 including cutting bending binding binding wire cover blocks tests and all necessary fixing accessories all in accordance with the Drawings and Specifications and including Formwork to give as struck finish. Providing and erecting formwork including all necessary staging centering shuttering supports cross bracing deshuttering carefully making good the damaged surfaces wherever necessary all complete as specified and as directed by the Engineer all in accordance with the Drawings and Specifications | E35: Suspended slabs waist slabs landingsstair etc. not exceeding 200 mm thickness | F35: M3 | G35: 1400 | H35: 10.08 | I35: 14112 | J35: 1400 | K35: =J35*H35 -> 14112
B36: J | C36: SUM FOR PAGE-10/68 | I36: 14112 | K36: =K35 -> 14112
B37: C23 | C37: Superstructure Works Concrete Works | D37: Poured Concrete Reinforced insitu concrete poured vibrated Ordinary Portland Cement OPC Concrete Grade C30 all in accordance with the Drawings and Specifications and including Reinforcement High yield strength deformed bars conforming to BS 4449 Grade 460 including cutting bending binding binding wire cover blocks tests and all necessary fixing accessories all in accordance with the Drawings and Specifications and including Formwork to give as struck finish. Providing and erecting formwork including all necessary staging centering shuttering supports cross bracing deshuttering carefully making good the damaged surfaces wherever necessary all complete as specified and as directed by the Engineer all in accordance with the Drawings and Specifications | E37: Columns | F37: M3 | G37: 380 | H37: 13.153 | I37: 4998.14 | J37: 380 | K37: =J37*H37 -> 4998.14
B38: K | C38: SUM FOR PAGE-11/68 | I38: 4998.14 | K38: =K37 -> 4998.14
B39: C24 | C39: Superstructure Works Concrete Works | D39: Poured Concrete Reinforced insitu concrete poured vibrated Ordinary Portland Cement OPC Concrete Grade C30 all in accordance with the Drawings and Specifications and including Reinforcement High yield strength deformed bars conforming to BS 4449 Grade 460 including cutting bending binding binding wire cover blocks tests and all necessary fixing accessories all in accordance with the Drawings and Specifications and including Formwork to give as struck finish. Providing and erecting formwork including all necessary staging centering shuttering supports cross bracing deshuttering carefully making good the damaged surfaces wherever necessary all complete as specified and as directed by the Engineer all in accordance with the Drawings and Specifications | E39: Beams | F39: M3 | G39: 650 | H39: 8.53 | I39: 5544.5 | J39: 650 | K39: =J39*H39 -> 5544.5
B40: L | C40: SUM FOR PAGE-12/68 | I40: 5544.5 | K40: =K39 -> 5544.5
B41: C25 | C41: Superstructure Works Concrete Works | D41: Poured Concrete Reinforced insitu concrete poured vibrated Ordinary Portland Cement OPC Concrete Grade C30 all in accordance with the Drawings and Specifications and including Reinforcement High yield strength deformed bars conforming to BS 4449 Grade 460 including cutting bending binding binding wire cover blocks tests and all necessary fixing accessories all in accordance with the Drawings and Specifications and including Formwork to give as struck finish. Providing and erecting formwork including all necessary staging centering shuttering supports cross bracing deshuttering carefully making good the damaged surfaces wherever necessary all complete as specified and as directed by the Engineer all in accordance with the Drawings and Specifications | E41: Ramp | F41: M3 | G41: 200 | H41: 1.26 | I41: 252 | J41: 200 | K41: =J41*H41 -> 252
B42: C26 | C42: Superstructure Works Concrete Works | D42: Sundries | E42: GRC Mesh in the Duct 300 X 400 refer to the Architectural Drawing. | F42: NO | G42: 20 | H42: 21 | I42: 420 | J42: 20 | K42: =J42*H42 -> 420
B43: M | C43: SUM FOR PAGE-13/68 | I43: 672 | K43: =SUM(K41:K42) -> 672
B44: C27 | C44: Superstructure Works Concrete Works | D44: Sundries | E44: GRC Mesh in the Duct 300 X 500 refer to the Architectural Drawing. | F44: NO | G44: 20 | H44: 21 | I44: 420 | J44: 20 | K44: =J44*H44 -> 420
B45: C28 | C45: Superstructure Works Concrete Works | D45: Sundries | E45: GRC Mesh in the Duct 300 X 1000 refer to the Architectural Drawing. | F45: NO | G45: 20 | H45: 21 | I45: 420 | J45: 20 | K45: =J45*H45 -> 420
B46: C29 | C46: Superstructure Works Concrete Works | D46: Sundries | E46: Planter box including excavation backfilling disposals blinding solid blockwork waterproofing plaster all complete of various size | F46: No | G46: 100 | H46: 47.25 | I46: 4725 | J46: 100 | K46: =J46*H46 -> 4725
B47: C30 | C47: Superstructure Works Masonry | D47: Internal Walls Ordinary Portland cement concrete blocks 7.5N per mm2 compressive strength cement and sand mortar 1to3 with and including stiffener columns and stiffener beams as required all in accordance with the Drawings and Specifications | E47: 200mm thick walls | F47: M2 | G47: 17400 | H47: 15 | I47: 261000 | J47: 17400 | K47: =J47*H47 -> 261000
B48: C31 | C48: Superstructure Works Masonry | D48: Sunken Slab Waterproofing | E48: Providing and applying Sunken Slab Waterproof course with bituminous paint and bituminous membrane conforming to BSto6398 in horizontal joints laid strictly in compliance with approved manufacturers printed instructions and as directed by Engineer. | F48: M2 | G48: 700 | H48: 3.6 | I48: 2520 | J48: 700 | K48: =J48*H48 -> 2520
B49: N | C49: SUM FOR PAGE-14/68 | I49: 269085 | K49: =SUM(K44:K48) -> 269085
C50: Superstructure Works Masonry | D50: Roof Slab Waterproofing THERMAL AND MOISTURE PROTECTION COVERINGS AND LININGS | E50: Combo roof treatment for thermal and moisture protection for open terraces by an approved expert agency complete with thermal and moisture resistant layers UV protection layer leveling course separation layers top finishes skirting with 250mm high etc. ensuring smooth runoff and with minimum 25 years of warranty. | F50: Item | G50: 1 | H50: 15750 | I50: 15750 | J50: 1 | K50: =J50*H50 -> 15750
B51: C33 | C51: Superstructure Works Thermal and Moisture Protection | D51: Backgrounds and Finishes Roof screed light weight concrete screed 1000 kg per m3 minimum 50 mm thick to a maximum of 125 mm thick | E51: 50 mm minimum bed laid on concrete to falls and cross falls | F51: M2 | G51: 5600 | H51: 1.05 | I51: 5880 | J51: 5600 | K51: =J51*H51 -> 5880
B52: C34 | C52: Superstructure Works Thermal and Moisture Protection | D52: 4 mm thick torch applied acrylic polypropylene modified bitumen membrane with non woven polyester reinforcement and polyethylene film waterproof membrane including primer to roofs as per the manufacturer printed instructions complete as specified. Contractor to allow for 10 years guarantee and 24 hours flood test. | E52: To roof decks 4mm thick on flat surface laid to falls and cross falls | F52: M2 | G52: 5600 | H52: 1.05 | I52: 5880 | J52: 5600 | K52: =J52*H52 -> 5880
B53: O | C53: SUM FOR PAGE-15/68 | I53: 27510 | K53: =SUM(K50:K52) -> 27510
B54: C35 | C54: Superstructure Works Thermal and Moisture Protection | D54: Skirting 300 mm girth including turning into groove | E54: In up standsdrops and around plinths minimum 300 mm high including dressing over fillet grooves sealant tantalized batten etc. complete to roof deck | F54: M | G54: 1900 | H54: 1.05 | I54: 1995 | J54: 1900 | K54: =H54*J54 -> 1995
B55: C36 | C55: Superstructure Works Thermal and Moisture Protection | D55: Insulation Extruded high density polystyrene foam board insulation with rigid closed cell structure all in accordance with the specifications and drawings in external | E55: to roof decks 50 mm thick laid on concrete spot bonded to waterproofing | F55: M2 | G55: 5600 | H55: 1.05 | I55: 5880 | J55: 5600 | K55: =H55*J55 -> 5880
B56: C37 | C56: Superstructure Works Thermal and Moisture Protection | D56: Roof Finishes | E56: 300 x 300 x 30 mm white cement tiles bedded on and including cement mortar screed to falls and cross falls jointed in cement mortar movements joints etc. complete to roof | F56: M2 | G56: 5600 | H56: 4.2 | I56: 23520 | J56: 5600 | K56: =H56*J56 -> 23520
B57: C38 | C57: Superstructure Works Thermal and Moisture Protection | D57: Roof Finishes | E57: 100 x 30 mm white cement skirting to upstands | F57: M | G57: 1900 | H57: 3.15 | I57: 5985 | J57: 1900 | K57: =H57*J57 -> 5985
B58: C39 | C58: Superstructure Works Thermal and Moisture Protection | D58: Roof Sundries | E58: Allow for Providing dressing around 110mm 83mm UPVC rainwater outlets roof duct gargoyle extract fan soil and vent pipe | F58: NO | G58: 20 | H58: 78.75 | I58: 1575 | J58: 20 | K58: =H58*J58 -> 1575
B59: P | C59: SUM FOR PAGE-16/68 | I59: 38955 | K59: =SUM(K54:K58) -> 38955
B60: C40 | C60: Superstructure Works Thermal and Moisture Protection | D60: Roof Sundries | E60: Allow for gun applied sealant to seal the joints and groove as applicable and as specified. | F60: NO | G60: 20 | H60: 26.25 | I60: 525 | J60: 20 | K60: =J60*H60 -> 525
B61: C41 | C61: Superstructure Works Metal Works | D61: WPC Pergola | E61: Supply fabricate and install of WPC Pergola as per the approved Construction Drawing and refer to the Architectural Drawing for a highquality WPC Pergola waterproof and antimoisture. The Contractor should submit a detailed drawing of pergola approval 10 years guarantee.. | F61: NO | G61: 19 | H61: 210 | I61: 3990 | J61: 19 | K61: =J61*H61 -> 3990
B62: C42 | C62: Superstructure Works Metal Works | D62: Staircase hand rail | E62: Stainless steel handrail as shown in the Architectural drawing shop drawings with full sections details to be approved before supply. Note to all stainless steel material shall be of 316 grade. | F62: M | G62: 200 | H62: 26.25 | I62: 5250 | J62: 200 | K62: =J62*H62 -> 5250
B63: C43 | C63: Superstructure Works Metal Works | D63: CAT Ladder | E63: Supply and install a 3800mm high CAT steel Ladder as specified and detailed on the drawing with anticorrelation epoxy pain. | F63: No | G63: 20 | H63: 152.25 | I63: 3045 | J63: 20 | K63: =J63*H63 -> 3045
B64: C44 | C64: Superstructure Works Doors and Windows | D64: Wood Doors Note | E64: 1 All timber and veneers shall be well conditioned seasoned dried vacuum treated and preservative treated all as specified | F64: Item | G64: 1 | H64: 0 | I64: 0 | J64: 1 | K64: =J64*H64 -> 0
B65: C45 | C65: Superstructure Works Doors and Windows | D65: Wood Doors Note | E65: 2 Prepare the surface prime and apply two under coats and two finishing coats of high gloss enamel paint of approved quality make and shade for shutter and frame | F65: Item | G65: 1 | H65: 0 | I65: 0 | J65: 1 | K65: =J65*H65 -> 0
B66: C46 | C66: Superstructure Works Doors and Windows | D66: Wood Doors Note | E66: 3 All hardwood timber shall be best quality Meranti | F66: Item | G66: 0 | H66: 0 | I66: 0 | J66: 1 | K66: =J66*H66 -> 0
B67: Q | C67: SUM FOR PAGE-17/68 | I67: 12810 | J67: 1 | K67: =SUM(K60:K66) -> 12810
B68: C47 | C68: Superstructure Works Doors and Windows | D68: Wood Doors Note | E68: 4 Sizes stated are structural opening sizes | F68: Item | G68: 0 | H68: 0 | I68: 0 | J68: 0 | K68: =J68*H68 -> 0
B69: C48 | C69: Superstructure Works Doors and Windows | D69: Wood Doors Door comprising profiled heads jambs frames subframes architraves beadings mouldings plinth block ply linings infill panels mastic and other pointing fixings neoprene seal master lining and all ancillary items including fixing of ironmongery and final decoration for a complete installation all as specified and as detailed on drawing including required reinforcement cement concrete lintels and including Supply and fix ironmongery as specified in schedule and approved fixed to hardwood including paint All locks shall be under master key system as detailed on drawing Note All stainless steel fittings shall be of 316 grade | E69: Type D1 double leaf overall size 1800x2400mm high | F69: No | G69: 20 | H69: 892.5 | I69: 17850 | L69: =G69 -> 20 | M69: =L69*H69 -> 17850 | N69: =G69 -> 20 | O69: =N69*H69 -> 17850 | P69: Replaced with Aluminium Door - Check Appendix A
B70: R | C70: SUM FOR PAGE-18/68 | I70: 17850 | L70: =G70 -> 0 | M70: =L70*H70 -> 0 | N70: =G70 -> 0 | O70: =N70*H70 -> 0 | P70: Replaced with Aluminium Door - Check Appendix A
B71: C49 | C71: Superstructure Works Doors and Windows | D71: Wood Doors Door comprising profiled heads jambs frames subframes architraves beadings mouldings plinth block ply linings infill panels mastic and other pointing fixings neoprene seal master lining and all ancillary items including fixing of ironmongery and final decoration for a complete installation all as specified and as detailed on drawing including required reinforcement cement concrete lintels and including Supply and fix ironmongery as specified in schedule and approved fixed to hardwood including paint All locks shall be under master key system as detailed on drawing Note All stainless steel fittings shall be of 316 grade | E71: Type D2 single leaf overall size 1000x2400mm high | F71: No | G71: 20 | H71: 262.5 | I71: 5250 | L71: =G71 -> 20 | M71: =L71*H71 -> 5250 | N71: =G71 -> 20 | O71: =N71*H71 -> 5250 | P71: Replaced with Aluminium Door - Check Appendix A
B72: S | C72: SUM FOR PAGE-19/68 | I72: 5250 | K72: =K71 -> 0
B73: C50 | C73: Superstructure Works Doors and Windows | D73: Wood Doors Door comprising profiled heads jambs frames subframes architraves beadings mouldings plinth block ply linings infill panels mastic and other pointing fixings neoprene seal master lining and all ancillary items including fixing of ironmongery and final decoration for a complete installation all as specified and as detailed on drawing including required reinforcement cement concrete lintels and including Supply and fix ironmongery as specified in schedule and approved fixed to hardwood including paint All locks shall be under master key system as detailed on drawing Note All stainless steel fittings shall be of 316 grade | E73: Type D3 single leaf overall size 1000x2100mm high | F73: No | G73: 160 | H73: 229.7 | I73: 36752 | K73: =J73*H73 -> 0 | L73: =G73 -> 160 | M73: =L73*H73 -> 36752
B74: T | C74: SUM FOR PAGE-20/68 | I74: 36752 | K74: =K73 -> 0
B75: C51 | C75: Superstructure Works Doors and Windows | D75: Wood Doors Door comprising profiled heads jambs frames subframes architraves beadings mouldings plinth block ply linings infill panels mastic and other pointing fixings neoprene seal master lining and all ancillary items including fixing of ironmongery and final decoration for a complete installation all as specified and as detailed on drawing including required reinforcement cement concrete lintels and including Supply and fix ironmongery as specified in schedule and approved fixed to hardwood including paint All locks shall be under master key system as detailed on drawing Note All stainless steel fittings shall be of 316 grade | E75: Type D4 single leaf overall size 800x2100mm high | F75: No | G75: 100 | H75: 220.5 | I75: 22050 | K75: =J75*H75 -> 0 | L75: =G75 -> 100 | M75: =L75*H75 -> 22050
B76: U | C76: SUM FOR PAGE-21/68 | I76: 22050 | K76: =K75 -> 0
B77: C52 | C77: Superstructure Works Doors and Windows | D77: Wood Doors Door comprising profiled heads jambs frames subframes architraves beadings mouldings plinth block ply linings infill panels mastic and other pointing fixings neoprene seal master lining and all ancillary items including fixing of ironmongery and final decoration for a complete installation all as specified and as detailed on drawing including required reinforcement cement concrete lintels and including Supply and fix ironmongery as specified in schedule and approved fixed to hardwood including paint All locks shall be under master key system as detailed on drawing Note All stainless steel fittings shall be of 316 grade | E77: Type D5 single leaf overall size 1000x2100mm high | F77: No | G77: 40 | H77: 262.5 | I77: 10500 | J77: 40 | K77: =J77*H77 -> 10500
B78: V | C78: SUM FOR PAGE-22/68 | I78: 10500 | K78: =K77 -> 10500
B79: C53 | C79: Superstructure Works Doors and Windows | D79: Wood Doors Door comprising profiled heads jambs frames subframes architraves beadings mouldings plinth block ply linings infill panels mastic and other pointing fixings neoprene seal master lining and all ancillary items including fixing of ironmongery and final decoration for a complete installation all as specified and as detailed on drawing including required reinforcement cement concrete lintels and including Supply and fix ironmongery as specified in schedule and approved fixed to hardwood including paint All locks shall be under master key system as detailed on drawing Note All stainless steel fittings shall be of 316 grade | E79: Type D6 single leaf overall size 1000x2400mm high | F79: No | G79: 40 | H79: 131.25 | I79: 5250 | J79: 40 | K79: =J79*H79 -> 5250
B80: W | C80: SUM FOR PAGE-23/68 | I80: 5250 | K80: =K79 -> 5250
B81: C54 | C81: Superstructure Works Doors and Windows | D81: WPC Solid Core Doors Door comprising profiled heads jambs frames subframes architraves beadings mouldings plinth block ply linings infill panels mastic and other pointing fixings neoprene seal master lining and all ancillary items including fixing of ironmongery and final decoration for a complete installation all as specified and as detailed on drawing including required reinforcement cement concrete lintels and including Supply and fix ironmongery as specified in schedule and approved fixed to hardwood including paint All locks shall be under master key system as detailed on drawing Note All stainless steel fittings shall be of 316 grade. | E81: Type D1 double leaf overall size 1800x2400mm high | F81: Item | G81: 1 | H81: 9135 | I81: 9135 | K81: =J81*H81 -> 0 | L81: =G81 -> 1 | M81: =L81*H81 -> 9135
B82: X | C82: SUM FOR PAGE-24/68 | I82: 9135 | K82: =J82*H82 -> 0 | L82: =G82 -> 0 | M82: =L82*H82 -> 0
B83: C55 | C83: Superstructure Works Doors and Windows | D83: WPC Solid Core Doors Door comprising profiled heads jambs frames subframes architraves beadings mouldings plinth block ply linings infill panels mastic and other pointing fixings neoprene seal master lining and all ancillary items including fixing of ironmongery and final decoration for a complete installation all as specified and as detailed on drawing including required reinforcement cement concrete lintels and including Supply and fix ironmongery as specified in schedule and approved fixed to hardwood including paint All locks shall be under master key system as detailed on drawing Note All stainless steel fittings shall be of 316 grade. | E83: Type D2 single leaf overall size 1000x2400mm high | F83: Item | G83: 1 | H83: 4410 | I83: 4410 | K83: =J83*H83 -> 0 | L83: =G83 -> 1 | M83: =L83*H83 -> 4410
B84: Y | C84: SUM FOR PAGE-25/68 | I84: 4410 | K84: =K83 -> 0
